Workbook
Name _._IMPUESTOS_SOBRE_COMBUSTIBLES_Y_GAS_NATURAL: [1]C!$B$27:$N$27
Name _._IMPUESTOS_SOBRE_ENERGIA_ELECTRICA: [1]C!$B$28:$N$28
Name __r: #REF!
Name __r: #REF!
Name __r: #REF!
Name __r: #REF!
Name __r: #REF!
Name __r: #REF!
Name __r: #REF!
Name __r: #REF!
Name __r: #REF!
Name __r: #REF!
Name __r: #REF!
Name __r: #REF!
Name __r: #REF!
Name __r: #REF!
Name __r: #REF!
Name __r: #REF!
Name __r: #REF!
Name _r: #REF!
Name _r: #REF!
Name _r: #REF!
Name _r: #REF!
Name _r: #REF!
Name _r: #REF!
Name _r: #REF!
Name _r: #REF!
Name _r: #REF!
Name _r: #REF!
Name _r: #REF!
Name _r: #REF!
Name _r: #REF!
Name _r: #REF!
Name _r: #REF!
Name _r: #REF!
Name _r: #REF!
Name A_impresión_IM: '[2]03-08'!#REF!
Name ACC: '[3]CARTERA FONDO'!#REF!
Name ACP: '[3]CARTERA FONDO'!#REF!
Name AMPO5: "Gráfico 8"
Name AÑO: #REF!
Name AÑO: #REF!
Name año2003: #REF!
Name año2003: #REF!
Name cacho: [4]GRAFPROM!#REF!
Name cacho: [4]GRAFPROM!#REF!
Name cacho: [4]GRAFPROM!#REF!
Name carajo: #REF!
Name carajo: #REF!
Name CDF: '[3]CARTERA FONDO'!#REF!
Name CDF: '[3]CARTERA FONDO'!#REF!
Name CFA: '[3]CARTERA FONDO'!#REF!
Name CFD: '[3]CARTERA FONDO'!#REF!
Name CLH: '[3]CARTERA FONDO'!#REF!
Name Coef: [5]CoefStocks!$A$4:$AT$260
Name Coef: [5]CoefStocks!$A$4:$AT$260
Name Coef: [5]CoefStocks!$A$4:$AT$260
Name COPA: #N/A
Name COPARTICIPACION_FEDERAL__LEY_N__23548: [1]C!$B$13:$N$13
Name CUADRO_10.3.1: '[6]fondo promedio'!$A$36:$L$74

Sheet INDICE
B2: MINISTERIO DE ECONOMÍA
B3: SECRETARÍA DE FINANZAS
B5: DEUDA DE LA ADMINISTRACIÓN CENTRAL
B8: ÍNDICE
B10: HOJA | C10: CONTENIDO
B11: Deuda al 31/12/2021: nivel y composición
B12: A.1.1 | C12: Deuda de la Administración Central - Por instrumento y tipo de plazo
B13: A.1.2 | C13: Deuda Bruta de la Administración Central - Por Deuda Directa o Indirecta
B14: A.1.3 | C14: Deuda Bruta de la Administración Central - Por legislación, situación e instrumento
B15: A.1.4 | C15: Deuda Bruta de la Administración Central - Por tipo de moneda y tasa
B16: A.1.5 | C16: Tasa promedio ponderada por moneda e instrumento
B17: A.1.6 | C17: Vida promedio por instrumento
B18: A.1.7 | C18: Títulos públicos y letras del tesoro emitidos en moneda nacional
B19: A.1.8 | C19: Títulos públicos, letras del tesoro, pagarés y préstamos garantizados emitidos en moneda nacional y ajustables por CER
B20: A.1.9 | C20: Títulos públicos, letras del tesoro y pagarés emitidos en moneda extranjera
B21: A.1.10 | C21: Deuda elegible pendiente de reestructuración, desagregada por instrumento
B23: Evolución reciente de la deuda
B24: A.2.1 | C24: Deuda Bruta de la Administración Central - Serie de saldos trimestrales - 4to. Trimestre 2020/4to. Trimestre 2021
B25: A.2.2 | C25: Deuda Bruta de la Administración Central - Flujos y variaciones 4to. Trimestre 2021
B26: A.2.3 | C26: Deuda Bruta de la Administración Central - Flujos y variaciones acumulados 2021
B27: A.2.4 | C27: Serie de Tipos de Cambio y Coeficiente de Estabilización de Referencia (CER)
B28: A.2.5 | C28: Serie de la Deuda del Sector Público Nacional por año - 1992/2021
B30: Vencimientos de capital e interés de la deuda al 31-12-2021 proyectados
B31: A.3.1 | C31: Perfil mensual de vencimientos de capital e interés de la Deuda Bruta de la Administración Central - 01/2022 a 12/2022
B32: A.3.2 | C32: Perfil mensual de vencimientos de capital de la Deuda Bruta de la Administración Central, desagregado por instrumento - 2022
B33: A.3.3 | C33: Perfil mensual de vencimientos de interés de la Deuda Bruta de la Administración Central, desagregado por instrumento - 2022
B34: A.3.4 | C34: Perfil mensual de vencimientos de capital de la Deuda Bruta de la Administración Central, desagregado por instrumento - 2023
B35: A.3.5 | C35: Perfil mensual de vencimientos de interés de la Deuda Bruta de la Administración Central, desagregado por instrumento - 2023
B36: A.3.6 | C36: Perfil anual de vencimientos de capital e interés de la Deuda Bruta de la Administración Central
B37: A.3.7 | C37: Perfil anual de vencimientos de capital de la Deuda Bruta de la Administración Central, desagregado por instrumento
B38: A.3.8 | C38: Perfil anual de vencimientos de interés de la Deuda Bruta de la Administración Central, desagregado por instrumento
B40: Otros Cuadros
B41: A.4.1 | C41: Valores Negociables Vinculados al PBI
B42: A.4.2 | C42: Activos financieros de la Administración Central
B43: A.4.3 | C43: Activos financieros con cargo a provincias
B44: A.4.4 | C44: Flujos netos anuales con Organismos Internacionales
B45: A.4.5 | C45: Deuda Bruta de la Administración Central - Por residencia del tenedor
B46: A.4.6 | C46: Deuda Bruta Externa de la Administración Central - Perfil de vencimientos de capital
B47: A.4.7 | C47: Indicadores de sostenibilidad de la Deuda Bruta de la Administración Central

Sheet A.1.1
A1: Indice
B2: MINISTERIO DE ECONOMÍA
B3: SECRETARÍA DE FINANZAS
B6: DEUDA DE LA ADMINISTRACIÓN CENTRAL
B7: POR INSTRUMENTO Y POR TIPO DE PLAZO
B10: Datos al 31/12/2021
C11: Miles de u$s | D11: Miles de $
B13: I- DEUDA BRUTA + VALORES NEGOCIABLES VINCULADOS AL PBI (II + VI) | C13: =+C16+C84 -> 3.7621495e+08 | D13: =+D16+D84 -> 3.8656086e+10
B16: II- DEUDA BRUTA (III + IV + V) | C16: =+C19+C61+C66 -> 3.6323261e+08 | D16: =+D19+D61+D66 -> 3.7322151e+10
B19: III- DEUDA EN SITUACIÓN DE PAGO NORMAL | C19: =+C21+C54 -> 3.6068874e+08 | D19: =+D21+D54 -> 3.7060768e+10
B21: MEDIANO Y LARGO PLAZO | C21: =+C23+C27+C29+C52 -> 3.2576771e+08 | D21: =+D23+D27+D29+D52 -> 3.3472632e+10
B23: TÍTULOS PÚBLICOS | C23: =+C24+C25 -> 2.3036901e+08 | D23: =+D24+D25 -> 2.3670416e+10
B24: - Moneda nacional | C24: 60334299 | D24: 6.1993492e+09
B25: - Moneda extranjera | C25: 1.7003471e+08 | D25: 1.7471066e+10
B27: LETRAS DEL TESORO (1) | C27: 9432983.6 | D27: 9.6923906e+08
B29: PRÉSTAMOS | C29: =+C31+C33+C44+C46+C48+C50 -> 78101973 | D29: =+D31+D33+D44+D46+D48+D50 -> 8.0249777e+09
B31: PRÉSTAMOS GARANTIZADOS | C31: 751015.37 | D31: 77166829
B33: ORGANISMOS INTERNACIONALES | C33: =SUM(C34:C42) -> 68065416 | D33: =SUM(D34:D42) -> 6.9937215e+09
B34: - BCIE | C34: 79285.845 | D34: 8146620.6
B35: - BIRF | C35: 8517393 | D35: 8.7516213e+08
B36: - BID | C36: 14051577 | D36: 1.4437995e+09
B37: - FONPLATA | C37: 404331.3 | D37: 41545041
B38: - FIDA | C38: 33561.959 | D38: 3448491.3
B39: - CAF | C39: 3781438.9 | D39: 3.8854285e+08
B40: - OFID | C40: 123824.5 | D40: 12722967
B41: - FMI | C41: 40952110 | D41: 4.2078293e+09
B42: - BEI | C42: 121894.5 | D42: 12524660
B44: ORGANISMOS OFICIALES | C44: 4709868.6 | D44: 4.83939e+08
B46: BANCA COMERCIAL | C46: 2530002 | D46: 2.5995771e+08
B48: AVALES | C48: 1667070.6 | D48: 1.7129151e+08
... B52: ADELANTOS TRANSITORIOS BCRA | C52: 7863747 | D52: 808000000
B54: CORTO PLAZO (2) | C54: =SUM(C55:C59) -> 34921032 | D54: =SUM(D55:D59) -> 3.588136e+09
B56: ADELANTOS TRANSITORIOS BCRA | C56: 13285152 | D56: 1.3650493e+09
B57: LETRAS DEL TESORO | C57: 20687534 | D57: 2.1256442e+09
B58: AVALES | C58: 121095.08 | D58: 12442519
B59: PAGARES | C59: 827250.61 | D59: 85000000
B61: IV- DEUDA EN SITUACIÓN DE PAGO DIFERIDO (3) | C61: =+C63+C64 -> 104561.86 | D61: =+D63+D64 -> 10743731
B63: CAPITAL | C63: 96201.236 | D63: 9884677
B64: INTERÉS (4) | C64: 8360.6238 | D64: 859054.09
B66: V- DEUDA ELEGIBLE PENDIENTE DE REESTRUCTURACIÓN (5) | C66: =+C68+C73+C78 -> 2439303.2 | D66: =+D68+D73+D78 -> 2.506384e+08
B68: CAPITAL | C68: =+C70+C71 -> 1059021 | D68: =+D70+D71 -> 1.0881441e+08
B70: - Moneda nacional | C70: 48187.354 | D70: 4951250.6
B71: - Moneda extranjera | C71: 1010833.7 | D71: 1.0386316e+08
B73: ATRASOS DE INTERÉS | C73: =+C75+C76 -> 865683.32 | D73: =+D75+D76 -> 88948961
B75: - Moneda nacional | C75: 1436.1103 | D75: 147560.33
B76: - Moneda extranjera | C76: 864247.21 | D76: 88801401
B78: INTERESES COMPENSATORIOS (6) | C78: =+C80+C81 -> 514598.8 | D78: =+D80+D81 -> 52875027
B80: - Moneda nacional | C80: 6744.3311 | D80: 692980.02
B81: - Moneda extranjera | C81: 507854.47 | D81: 52182047
B84: VI- VALORES NEGOCIABLES VINCULADOS AL PBI (7) | C84: 12982343 | D84: 1.3339358e+09
B87: VII- ACTIVOS FINANCIEROS (8) | C87: 1764372.5 | D87: 1.8128928e+08
B89: VIII- DEUDA NETA (II - VII) | C89: =+C16-C87 -> 3.6146824e+08 | D89: =+D16-D87 -> 3.7140861e+10
B92: (1) Incluye las Letras en Garantía.
B93: (2) Incluye operaciones de hasta un año de plazo.
B94: (3) Deuda en situacion de pago diferido, no elegible para canjes de Dtos. 1735/04 y 563/10.
B95: (4) No incluye intereses moratorios ni punitorios.
B96: (5) Se trata de la deuda elegible y no presentada al canje (Dtos. 1735/04 y 563/10) y no cancelada a la fecha en el marco de los acuerdos contemplados en la Ley n° 27.249.
B97: (6) Intereses compensatorios estimados, devengados e impagos con posterioridad a la fecha de vencimiento de cada bono.
B98: (7) Valor remanente total. Es la diferencia entre el máximo a pagar de 48 unidades por cada 100 de valor nocional y la suma de los montos pagados hasta la actualidad, de acuerdo con las condiciones establecidas en las respectivas normas de emisión.
B99: (8) Activos Financieros son créditos a favor del Estado Nacional que se originan en operaciones de Crédito Público. Dato provisorio.

Sheet A.1.2
A1: Indice
B2: MINISTERIO DE ECONOMÍA
B3: SECRETARÍA DE FINANZAS
B6: DEUDA BRUTA DE LA ADMINISTRACIÓN CENTRAL
B7: POR DEUDA DIRECTA E INDIRECTA
B10: Datos al 31/12/2021
C11: Miles de u$s
B13: I- DEUDA BRUTA (II + III) | C13: =+C16+C46 -> 3.6323261e+08
B16: II- DEUDA DIRECTA | C16: =+C18+C29+C35+C40 -> 3.5287356e+08
B18: LARGO PLAZO | C18: =SUM(C20:C27) -> 3.1552975e+08
B20: Títulos Públicos | C20: 2.3036901e+08
B21: Préstamos Garantizados | C21: 751015.37
B22: Organismos Intenacionales | C22: 66162458
B23: Organismos Oficiales | C23: 4603546.1
B24: Banca Comercial | C24: 2378790
B25: Adelantos Transitorios | C25: 7863747
B26: Letras del Tesoro | C26: 3022590
B27: Pagarés del Tesoro | C27: 378599.56
B29: CORTO PLAZO (1) | C29: =SUM(C31:C33) -> 34799937
B31: Adelantos Transitorios | C31: 13285152
B32: Letras del Tesoro | C32: 20687534
B33: Pagarés del Tesoro | C33: 827250.61
B35: DEUDA EN SITUACIÓN DE PAGO DIFERIDO (2) | C35: =+C37+C38 -> 104561.86
B37: Capital | C37: 96201.236
B38: Interés (3) | C38: 8360.6238
B40: DEUDA ELEGIBLE PENDIENTE DE REESTRUCTURACIÓN (4) | C40: =+C42+C43+C44 -> 2439303.2
B42: Capital | C42: 1059021
B43: Atrasos de Interés | C43: 865683.32
B44: Intereses compensatorios (5) | C44: 514598.8
B46: III- DEUDA INDIRECTA | C46: =SUM(C48:C51) -> 10359053
B48: Avales | C48: 1788165.7
B49: Garantías a las provincias | C49: 2160493.4
B50: Letras en garantía | C50: 6410393.5
B53: (1) Incluye operaciones de hasta un año de plazo.
B54: (2) Deuda en situacion de pago diferido, no elegible para canjes de Dtos. 1735/04 y 563/10.
B55: (3) No incluye intereses moratorios ni punitorios.
B56: (4) Se trata de la deuda elegible y no presentada al canje (Dtos. 1735/04 y 563/10) y no cancelada a la fecha en el marco de los acuerdos contemplados en la Ley n° 27.249.
B57: (5) Intereses compensatorios estimados, devengados e impagos con posterioridad a la fecha de vencimiento de cada título.

Sheet A.1.3
A1: Indice
B2: MINISTERIO DE ECONOMÍA
B3: SECRETARÍA DE FINANZAS
B6: DEUDA BRUTA DE LA ADMINISTRACIÓN CENTRAL
B7: POR LEGISLACIÓN, INSTRUMENTO Y SITUACIÓN
B10: Datos al 31/12/2021
C11: Saldo Bruto | D11: %
C12: Miles de u$s
B14: DEUDA BRUTA + VALORES NEGOCIABLES VINCULADOS AL PBI | C14: =+C17+C64 -> 3.7621495e+08
B17: - DEUDA BRUTA | C17: =+C19+C21+C23 -> 3.6323261e+08 | D17: =+D19+D21+D23 -> 1
B19: - EN SITUACIÓN DE PAGO NORMAL | C19: =+C28+C48 -> 3.6068874e+08 | D19: =+C19/$C$17 -> 0.9929966
B21: - EN SITUACIÓN DE PAGO DIFERIDO (1) | C21: =+C36+C54 -> 104561.86 | D21: =+C21/$C$17 -> 0.00028786474
B23: - ELEGIBLE PENDIENTE DE REESTRUCTURACIÓN (2) | C23: =+C41+C58 -> 2439303.2 | D23: =+C23/$C$17 -> 0.0067155401
B26: I- LEGISLACIÓN ARGENTINA | C26: =+C28+C36+C41 -> 2.1870022e+08 | D26: =+D28+D36+D41 -> 0.60209412
B28: - EN SITUACIÓN DE PAGO NORMAL | C28: =SUM(C29:C34) -> 2.1858068e+08 | D28: =+C28/$C$17 -> 0.60176503
B29: TÍTULOS PÚBLICOS Y LETRAS DEL TESORO | C29: 1.9159429e+08 | D29: =+C29/$C$17 -> 0.52746997
B30: PRÉSTAMOS GARANTIZADOS | C30: 751015.37 | D30: =+C30/$C$17 -> 0.002067588
B31: ADELANTOS TRANSITORIOS BCRA | C31: 21148899 | D31: =+C31/$C$17 -> 0.058224119
B32: AVALES | C32: 1788165.7 | D32: =+C32/$C$17 -> 0.0049229218
B33: BANCA COMERCIAL | C33: 2092457.4 | D33: =+C33/$C$17 -> 0.0057606541
B34: PAGARÉS DEL TESORO | C34: 1205850.2 | D34: =+C34/$C$17 -> 0.003319774
B36: - EN SITUACIÓN DE PAGO DIFERIDO (1) | C36: =+SUM(C37:C39) -> 62298.482 | D36: =+C36/$C$17 -> 0.00017151126
B37: BANCA COMERCIAL | C37: 172.73352 | D37: =+C37/$C$17 -> 4.7554519e-07
B38: AVALES | C38: 60464.16 | D38: =+C38/$C$17 -> 0.00016646127
B39: OTROS | C39: 1661.5893 | D39: =+C39/$C$17 -> 4.5744496e-06
B41: - ELEGIBLE PENDIENTE DE REESTRUCTURACIÓN (2) | C41: =SUM(C42:C44) -> 57237.907 | D41: =+C41/$C$17 -> 0.00015757921
B42: CAPITAL | C42: 48187.361 | D42: =+C42/$C$17 -> 0.00013266254
B43: ATRASOS DE INTERÉS | C43: 2306.2045 | D43: =+C43/$C$17 -> 6.3491121e-06
B44: INTERESES COMPENSATORIOS (3) | C44: 6744.3415 | D44: =+C44/$C$17 -> 1.8567555e-05
B46: II- LEGISLACIÓN EXTRANJERA | C46: =+C48+C54+C58 -> 1.4453239e+08 | D46: =+D48+D54+D58 -> 0.39790588
B48: - EN SITUACIÓN DE PAGO NORMAL | C48: =SUM(C49:C52) -> 1.4210806e+08 | D48: =+C48/$C$17 -> 0.39123157
B49: TÍTULOS PÚBLICOS Y LETRAS DEL TESORO | C49: 68895234 | D49: =+C49/$C$17 -> 0.18967249
B50: ORGANISMOS INTERNACIONALES | C50: 68065416 | D50: =+C50/$C$17 -> 0.18738796
B51: ORGANISMOS OFICIALES | C51: 4709868.6 | D51: =+C51/$C$17 -> 0.012966536
B52: BANCA COMERCIAL | C52: 437544.62 | D52: =+C52/$C$17 -> 0.0012045852
B54: - EN SITUACIÓN DE PAGO DIFERIDO (1) | C54: =SUM(C55:C56) -> 42263.377 | D54: =+C54/$C$17 -> 0.00011635348
B55: BANCA COMERCIAL | C55: 33578.545 | D55: =+C55/$C$17 -> 9.2443641e-05
B56: OTROS | C56: 8684.8322 | D56: =+C56/$C$17 -> 2.3909836e-05
B58: - ELEGIBLE PENDIENTE DE REESTRUCTURACIÓN (2) | C58: =SUM(C59:C61) -> 2382065.3 | D58: =+C58/$C$17 -> 0.0065579609
B59: CAPITAL | C59: 1010833.7 | D59: =+C59/$C$17 -> 0.0027828825
B60: ATRASOS DE INTERÉS | C60: 863377.12 | D60: =+C60/$C$17 -> 0.0023769262
B61: INTERESES COMPENSATORIOS (3) | C61: 507854.46 | D61: =+C61/$C$17 -> 0.0013981522
B64: - VALORES NEGOCIABLES VINCULADOS AL PBI (4) | C64: =+C66+C71 -> 12982343 | D64: =+D66+D71 -> 1
B66: I- LEGISLACIÓN ARGENTINA | C66: =+C68+C69 -> 1021098.6 | D66: =SUM(D68:D69) -> 0.078652874
B68: U$S-LEY ARG (TVPA) | C68: 929780.55 | D68: =+C68/$C$64 -> 0.071618856
B69: ARG-LEY ARG (TVPP) | C69: 91318.041 | D69: =+C69/$C$64 -> 0.0070340184
B71: II- LEGISLACIÓN EXTRANJERA | C71: =+C73+C74+C75 -> 11961244 | D71: =SUM(D73:D75) -> 0.92134713
B73: U$S-LEY NY (TVPY-TVYO) | C73: 5151027.2 | D73: =+C73/$C$64 -> 0.39677177
B74: EUR- LEY INGLESA (TVPE) | C74: 6678041.8 | D74: =+C74/$C$64 -> 0.51439418
B75: YEN- LEY JAPONESA | C75: 132175.51 | D75: =+C75/$C$64 -> 0.010181176
B78: (1) Deuda en situacion de pago diferido, no elegible para canjes de Dtos. 1735/04 y 563/10.
B79: (2) Se trata de la deuda elegible y no presentada al canje (Dtos. 1735/04 y 563/10) y no cancelada a la fecha en el marco de los acuerdos contemplados en la Ley n° 27.249.
B80: (3) Intereses compensatorios estimados, devengados e impagos con posterioridad a la fecha de vencimiento de cada título.
B81: (4) Valor remanente total. Es la diferencia entre el máximo a pagar de 48 unidades por cada 100 de valor nocional y la suma de los montos pagados hasta la actualidad, de acuerdo con las condiciones establecidas en las respectivas normas de emisión.

Sheet A.1.4
A1: Indice
B2: MINISTERIO DE ECONOMÍA
B3: SECRETARÍA DE FINANZAS
B6: DEUDA BRUTA DE LA ADMINISTRACIÓN CENTRAL
B7: POR MONEDA Y TASA
C10: AL 31/12/2021
C11: Deuda Bruta de la Administración Central (Excluida la elegible pendiente de reestructuración) | E11: Deuda elegible pendiente de reestructuración | G11: Total Deuda Bruta
C13: Miles de u$s | D13: % | E13: Miles de u$s | F13: % | G13: Miles de u$s | H13: %
B15: TOTAL | C15: =+C17+C28 -> 3.6079331e+08 | D15: =+D17+D28 -> 0.99328446 | E15: =+E17+E28 -> 2439303.2 | F15: =+F17+F28 -> 0.0067155401 | G15: =+G17+G28 -> 3.6323261e+08 | H15: =+H17+H28 -> 1
B17: Moneda local (1) | C17: =+C19+C24 -> 1.0780948e+08 | D17: =+D19+D24 -> 0.29680562 | E17: =+E19+E24 -> 56367.796 | F17: =+F19+F24 -> 0.00015518374 | G17: =+G19+G24 -> 1.0786585e+08 | H17: =+H19+H24 -> 0.2969608
B19: Deuda no ajustable por CER | C19: =SUM(C20:C22) -> 45604684 | D19: =SUM(D20:D22) -> 0.12555229 | E19: =SUM(E20:E22) -> 307.62682 | F19: =SUM(F20:F22) -> 8.469141e-07 | G19: =SUM(G20:G22) -> 45604992 | H19: =SUM(H20:H22) -> 0.12555313
B20: Tasa fija | C20: 11432824 | D20: =+C20/$G$15 -> 0.031475213 | E20: 8.7822256 | F20: =+E20/$G$15 -> 2.4177966e-08 | G20: =+C20+E20 -> 11432833 | H20: =+F20+D20 -> 0.031475237
B21: Tasa Cero | C21: 32020353 | D21: =+C21/$G$15 -> 0.088153851 | E21: 0 | F21: =+E21/$G$15 -> 0 | G21: =+C21+E21 -> 32020353 | H21: =+F21+D21 -> 0.088153851
B22: Tasas Variables | C22: 2151507.3 | D22: =+C22/$G$15 -> 0.0059232217 | E22: 298.84459 | F22: =+E22/$G$15 -> 8.2273614e-07 | G22: =+C22+E22 -> 2151806.1 | H22: =+F22+D22 -> 0.0059240444
B24: Deuda ajustable por CER | C24: =SUM(C25:C26) -> 62204794 | D24: =SUM(D25:D26) -> 0.17125333 | E24: =SUM(E25:E26) -> 56060.169 | F24: =SUM(F25:F26) -> 0.00015433683 | G24: =SUM(G25:G26) -> 62260854 | H24: =SUM(H25:H26) -> 0.17140767
B25: Tasa fija | C25: 48569033 | D25: =+C25/$G$15 -> 0.13371331 | E25: 46516.861 | F25: =+E25/$G$15 -> 0.00012806356 | G25: =+C25+E25 -> 48615550 | H25: =+F25+D25 -> 0.13384137
B26: Tasa cero | C26: 13635761 | D26: =+C26/$G$15 -> 0.037540024 | E26: 9543.3076 | F26: =+E26/$G$15 -> 2.6273268e-05 | G26: =+C26+E26 -> 13645304 | H26: =+F26+D26 -> 0.037566297
B28: Moneda extranjera | C28: =+C30+C37+C47+C50+C44 -> 2.5298383e+08 | D28: =+D30+D37+D47+D50+D44 -> 0.69647884 | E28: =+E30+E37+E47+E50+E44 -> 2382935.4 | F28: =+F30+F37+F47+F50+F44 -> 0.0065603564 | G28: =+G30+G37+G47+G50+G44 -> 2.5536676e+08 | H28: =+H30+H37+H47+H50+H44 -> 0.7030392
B30: Deuda en dólares estadounidenses | C30: =SUM(C31:C33) -> 2.0440555e+08 | D30: =SUM(D31:D33) -> 0.56274009 | E30: =SUM(E31:E33) -> 1467106.6 | F30: =SUM(F31:F33) -> 0.0040390278 | G30: =SUM(G31:G33) -> 2.0587266e+08 | H30: =SUM(H31:H33) -> 0.56677911
B31: Tasa fija | C31: 1.1408708e+08 | D31: =+C31/$G$15 -> 0.3140882 | E31: 1379175.2 | F31: =+E31/$G$15 -> 0.0037969476 | G31: =+C31+E31 -> 1.1546625e+08 | H31: =+F31+D31 -> 0.31788515
B32: Tasa Cero | C32: 9459313.5 | D32: =+C32/$G$15 -> 0.026042027 | E32: 63 | F32: =+E32/$G$15 -> 1.7344258e-07 | G32: =+C32+E32 -> 9459376.5 | H32: =+F32+D32 -> 0.026042201
B33: Tasas Variables | C33: =+C34+C35 -> 80859159 | D33: =+D34+D35 -> 0.22260986 | E33: =+E34+E35 -> 87868.416 | F33: =+F34+F35 -> 0.00024190674 | G33: =+C33+E33 -> 80947028 | H33: =+H34+H35 -> 0.22285176
B34: Tasa Libo | C34: 23265131 | D34: =+C34/$G$15 -> 0.064050227 | E34: 80677.426 | F34: =+E34/$G$15 -> 0.00022210954 | G34: =+C34+E34 -> 23345808 | H34: =+F34+D34 -> 0.064272336
B35: Otras tasas variables | C35: 57594028 | D35: =+C35/$G$15 -> 0.15855963 | E35: 7190.9894 | F35: =+E35/$G$15 -> 1.9797202e-05 | G35: =+C35+E35 -> 57601219 | H35: =+F35+D35 -> 0.15857943
B37: Deuda en Euros | C37: =SUM(C38:C40) -> 6741175.2 | D37: =SUM(D38:D40) -> 0.018558838 | E37: =SUM(E38:E40) -> 868087.84 | F37: =SUM(F38:F40) -> 0.0023898951 | G37: =SUM(G38:G40) -> 7609263 | H37: =SUM(H38:H40) -> 0.020948733
B38: Tasa fija | C38: 6417180.6 | D38: =+C38/$G$15 -> 0.017666863 | E38: 852805.15 | F38: =+E38/$G$15 -> 0.002347821 | G38: =+C38+E38 -> 7269985.8 | H38: =+F38+D38 -> 0.020014684
B39: Tasa Cero | C39: 0 | D39: =+C39/$G$15 -> 0 | E39: 0 | F39: =+E39/$G$15 -> 0 | G39: =+C39+E39 -> 0 | H39: =+F39+D39 -> 0
B40: Tasas Variables | C40: =+C41+C42 -> 323994.58 | D40: =+D41+D42 -> 0.00089197548 | E40: =+E41+E42 -> 15282.684 | F40: =+F41+F42 -> 4.2074096e-05 | G40: =+C40+E40 -> 339277.26 | H40: =+H41+H42 -> 0.00093404957
B41: Tasa Libo | C41: 323994.58 | D41: =+C41/$G$15 -> 0.00089197548 | E41: 15282.684 | F41: =+E41/$G$15 -> 4.2074096e-05 | G41: =+C41+E41 -> 339277.26 | H41: =+F41+D41 -> 0.00093404957
B42: Otras tasas variables | C42: 0 | D42: =+C42/$G$15 -> 0 | E42: 0 | F42: =+E42/$G$15 -> 0 | G42: =+C42+E42 -> 0 | H42: =+F42+D42 -> 0
B44: Deuda en Derechos especiales de giro | C44: =+C45 -> 40959532 | D44: =+SUM(D45:D46) -> 0.11276392 | E44: =+SUM(E45:E46) -> 0 | F44: =+SUM(F45:F46) -> 0 | G44: =+SUM(G45:G46) -> 40959532 | H44: =+SUM(H45:H46) -> 0.11276392
B45: Tasas Variables | C45: 40959532 | D45: =+C45/$G$15 -> 0.11276392 | E45: 0 | F45: =+E45/$G$15 -> 0 | G45: =+C45+E45 -> 40959532 | H45: =+F45+D45 -> 0.11276392
B47: Deuda en Yenes | C47: =+SUM(C48:C48) -> 646850.79 | D47: =+SUM(D48:D48) -> 0.0017808169 | E47: =+SUM(E48:E48) -> 27848.314 | F47: =+SUM(F48:F48) -> 7.6667989e-05 | G47: =+SUM(G48:G48) -> 674699.1 | H47: =+SUM(H48:H48) -> 0.0018574849
B48: Tasa fija | C48: 646850.79 | D48: =+C48/$G$15 -> 0.0017808169 | E48: 27848.314 | F48: =+E48/$G$15 -> 7.6667989e-05 | G48: =+C48+E48 -> 674699.1 | H48: =+F48+D48 -> 0.0018574849
B50: Deuda en otras monedas extranjeras (2) | C50: =SUM(C51:C52) -> 230720.58 | D50: =SUM(D51:D52) -> 0.00063518687 | E50: =SUM(E51:E52) -> 19892.615 | F50: =SUM(F51:F52) -> 5.4765499e-05 | G50: =SUM(G51:G52) -> 250613.2 | H50: =SUM(H51:H52) -> 0.00068995236
B51: Tasa fija | C51: 227212.59 | D51: =+C51/$G$15 -> 0.00062552915 | E51: 19892.615 | F51: =+E51/$G$15 -> 5.4765499e-05 | G51: =+C51+E51 -> 247105.2 | H51: =+F51+D51 -> 0.00068029465
B52: Tasa Cero | C52: 3507.9967 | D52: =+C52/$G$15 -> 9.657714e-06 | E52: 0 | G52: =+C52+E52 -> 3507.9967 | H52: =+F52+D52 -> 9.657714e-06
B55: (1) La deuda emitida en dólares, pero cuyo pago de capital e interés es en pesos, se clasifica como deuda en Moneda Local.
B56: (2) Incluye: Libras esterlinas, Franco Suizo, Corona Danesa, Corona Sueca, Dólar Canadiense, Dinar Kuwaiti, Dólar Australiano y Dirham de Emiratos Árabes Unidos.

Sheet A.1.5
A1: Indice
B2: MINISTERIO DE ECONOMÍA
B3: SECRETARÍA DE FINANZAS
B6: TASA PROMEDIO PONDERADA (1)
B7: POR MONEDA E INSTRUMENTO
B10: Datos al 31/12/2021
B11: TASA PROMEDIO PONDERADA TOTAL | C11: 0.027491311
B13: Deuda en pesos no ajustables por CER | C13: 0.1263699
B15: Títulos Públicos | C15: 0.23275718
B16: Letras del Tesoro | C16: 0.4097057
B17: Otros préstamos | C17: 0.010337207
B18: Adelantos Transitorios BCRA | C18: 0
B20: Deuda en pesos ajustables por CER | C20: 0.022150716
B22: Títulos Públicos | C22: 0.023690148
B23: Letras del Tesoro | C23: 0.015385005
B24: Préstamos garantizados | C24: 0.05
B25: Otros préstamos | C25: 0.0177
B27: Deuda en dólares estadounidenses | C27: 0.0097681731
... B55: Otros préstamos | C55: 0.0025312926
B58: (1) Nota Metodológica: Cálculo realizado sobre la deuda en situación de pago normal. Se aplican las tasas de referencia vigentes al 31/12/2021, incluyendo la tasa "plena" en aquellos instrumentos que capitalizan parte de los intereses que devengan.

Sheet A.1.6
A1: Indice
B2: MINISTERIO DE ECONOMÍA
B3: SECRETARÍA DE FINANZAS
B6: VIDA PROMEDIO (1)
B7: POR INSTRUMENTO
B10: Datos al 31/12/2021 | C10: - En años -
B12: VIDA PROMEDIO TOTAL | C12: 6.139862
B14: Títulos Públicos | C14: 7.5259365
B16: Letras en Garantía | C16: 9.6494218
B18: Letras del Tesoro | C18: 1.022718
B20: Total Préstamos | C20: 4.666415
B22: - Organismos Internacionales | C22: 4.774985
B24: - Organismos Oficiales | C24: 3.5266285
B26: - Préstamos Garantizados (Canje Noviembre 2001) | C26: 9.1349647
B28: - Pagarés del Tesoro | C28: 4.7519294
B30: - Banca Comercial | C30: 1.504075
B32: - Avales | C32: 6.0757054
B34: Adelantos Transitorios | C34: 1.2222683
B37: (1) Nota Metodológica: Cálculo realizado sobre la deuda en situación de pago normal.

Sheet A.1.7
A1: Indice
B2: MINISTERIO DE ECONOMÍA
B3: SECRETARÍA DE FINANZAS
B6: TÍTULOS PÚBLICOS Y LETRAS DEL TESORO
B7: EMITIDOS EN MONEDA NACIONAL
B8: DATOS AL 31/12/2021
H11: En miles de u$s
B12: Fecha de emisión | C12: Denominación | D12: Tasa vigente | E12: Vencimiento | F12: Valor nominal original en circulación | G12: Valor nominal residual en circulación (1) | H12: Valor nominal actualizado en circulación (2)
C18: TÍTULOS PÚBLICOS | F18: =+F20+F23+F40 -> 13099058 | G18: =+G20+G23+G40 -> 12844151 | H18: =+H20+H23+H40 -> 12896542
C20: BONOS DE CONSOLIDACIÓN | F20: =+F21 -> 204171.41 | G20: =+G21 -> 69418.279 | H20: =+H21 -> 121807.7
B21: 40182 | C21: PR15/$/BADLAR/04-10-2022 | D21: Badlar Bancos Privados | E21: 2022 | F21: 204171.41 | G21: 69418.279 | H21: 121807.7
C23: BONOS | F23: =+SUM(F24:F38) -> 12894887 | G23: =+SUM(G24:G38) -> 12774733 | H23: =+SUM(H24:H38) -> 12774733
B24: 43294 | C24: BONAR/DLK/4,50%U$S-2,35%$/13-02-2020 (3) | D24: 4,50% U$S | E24: 2022 | F24: 739.069 | G24: 739.069 | H24: 739.069
B25: 43193 | C25: BONAR/$/6,72763943919512%/31-12-2028 | D25: 0.067276394 | E25: 2028 | F25: 456295.89 | G25: 340044.6 | H25: 340044.6
B26: 42828 | C26: BONAR/$/BADLAR+200PB/03-04-2022 | D26: Badlar Bancos Privados + 2,00% | E26: 2022 | F26: 675524.8 | G26: 675524.8 | H26: 675524.8
B27: 32875 | C27: BONO CONSOLIDADO/$/02-01-2089 | D27: Tasa Cero | E27: 2089 | F27: 8578.722 | G27: 7549.2754 | H27: 7549.2754
B28: 42660 | C28: BONTE/$/15,50%/17-10-2026 | D28: 0.155 | E28: 2026 | F28: 939851.23 | G28: 939851.23 | H28: 939851.23
B29: 42660 | C29: BONTE/$/16,00%/17-10-2023 | D29: 0.16 | E29: 2023 | F29: 624334.34 | G29: 624334.34 | H29: 624334.34
B30: 43866 | C30: BONTE/DLK/4,00%/05-08-2021 (3) | D30: 0.04 | E30: 2022 | F30: 4.84 | G30: 4.84 | H30: 4.84
B31: 44133 | C31: BONTE/DLK/0,10%/29-04-2022 (3) | D31: 0.001 | E31: 2022 | F31: 1952375 | G31: 1952375 | H31: 1952375
B32: 43972 | C32: BONTE/$/22,00%/21-05-2022 | D32: 0.22 | E32: 2022 | F32: 3595049.4 | G32: 3595049.4 | H32: 3595049.4
B33: 44232 | C33: BONTE/$/BADLAR+525PB/06-02-2023 | D33: Badlar Bancos Privados + 5,25% | E33: 2023 | F33: 565750.26 | G33: 565750.26 | H33: 565750.26
B34: 44337 | C34: BONTE/DLK/0,20%/30-11-2022 (3) | D34: 0.002 | E34: 2022 | F34: 1613635.6 | G34: 1613635.6 | H34: 1613635.6
B35: 44382 | C35: BONTE/$/BADLAR/05-07-2030 | D35: Badlar Bancos Privados | E35: 2030 | F35: 78788.665 | G35: 78788.665 | H35: 78788.665
B36: 44425 | C36: BONTE/$/BADLAR+400PB/17-08-2031 | D36: Badlar Bancos Privados + 4,00% | E36: 2031 | F36: 114908.35 | G36: 112035.64 | H36: 112035.64
B37: 44452 | C37: BONTE/DLK/0,30%/28-04-2023 (3) | D37: 0.003 | E37: 2023 | F37: 2221751.6 | G37: 2221751.6 | H37: 2221751.6
B38: 44552 | C38: BONTE /$/ BADLAR/22-12-2026 | D38: Badlar Bancos Privados | E38: 2026 | F38: 47298.711 | G38: 47298.711 | H38: 47298.711
C40: AMPAROS Y EXCEPCIONES | H40: 1.4664214
C42: LETRAS DEL TESORO | F42: =+SUM(F43:F54) -> 8266750.2 | G42: =+SUM(G43:G54) -> 8266748.2 | H42: =+SUM(H43:H54) -> 8266748.2
B43: 44095 | C43: LETRA/DLK/CMEA/21-09-2022 (3) | D43: Tasa Cero | E43: 2022 | F43: 124646.08 | G43: 124646.08 | H43: 124646.08
B44: 44399 | C44: LETES/$/31-01-2022 | D44: Tasa Cero | E44: 2022 | F44: 2075544.3 | G44: 2075544.3 | H44: 2075544.3
B45: 44469 | C45: LETES/$/28-02-2022 | D45: Tasa Cero | E45: 2022 | F45: 1307245.2 | G45: 1307245.2 | H45: 1307245.2
B46: 44498 | C46: LETES/$/31-03-2022 | D46: Tasa Cero | E46: 2022 | F46: 1319530.3 | G46: 1319530.3 | H46: 1319530.3
B47: 44530 | C47: LETES/$/29-04-2022 | D47: Tasa Cero | E47: 2022 | F47: 488597.7 | G47: 488597.7 | H47: 488597.7
B48: 44545 | C48: LELITE/30 DIAS/$/14-01-2022 | D48: Tasa Cero | E48: 2022 | F48: 210024.33 | G48: 210024.33 | H48: 210024.33
B49: 44545 | C49: LETES/$/31-05-2022 | D49: Tasa Cero | E49: 2022 | F49: 103858.64 | G49: 103858.64 | H49: 103858.64
B50: 44384 | C50: LETRA/$/INTRA SP/03-01-2022 | D50: Tasa Badlar Pública | E50: 2022 | F50: 235247 | G50: 235247 | H50: 235247
B51: 44473 | C51: LETRA/$/INTRA SP/01-04-2022 | D51: Tasa Badlar Pública | E51: 2022 | F51: 315053.03 | G51: 315053.03 | H51: 315053.03
B52: 43608 | C52: LELINKS/DLK/4,25%/04-12-2019 (3) | D52: 0.0425 | E52: 2022 | F52: 4.857 | G52: 2.9142 | H52: 2.9142
B53: 44377 | C53: LETES/$/31-12-2021 | D53: Tasa Cero | E53: 2021 | F53: 2077779.8 | G53: 2077779.8 | H53: 2077779.8
B54: 44545 | C54: LELITE/16 DIAS/$/31-12-2021 | D54: Tasa Cero | E54: 2021 | F54: 9218.9781 | G54: 9218.9781 | H54: 9218.9781
C56: PAGARÉS DEL TESORO | F56: =+SUM(F57:F60) -> 827250.61 | G56: =+SUM(G57:G60) -> 827250.61 | H56: =+SUM(H57:H60) -> 827250.61
B57: 44525 | C57: PAG.CUT 2021-M. INT. | D57: Tasa Cero | E57: 2022 | F57: 291970.8 | G57: 291970.8 | H57: 291970.8
B58: 44525 | C58: PAG.CUT 2021-S.SEGUR | D58: Tasa Cero | E58: 2022 | F58: 58394.161 | G58: 58394.161 | H58: 58394.161
B59: 44525 | C59: PAG.CUT 2021-INTA | D59: Tasa Cero | E59: 2022 | F59: 418491.48 | G59: 418491.48 | H59: 418491.48
B60: 44525 | C60: PAG.CUT 2021-ENACOM | D60: Tasa Cero | E60: 2022 | F60: 58394.161 | G60: 58394.161 | H60: 58394.161
B62: TOTAL | F62: =+F42+F18+F56 -> 22193059 | G62: =+G42+G18+G56 -> 21938150 | H62: =+H42+H18+H56 -> 21990541
B64: (1) Valor nominal original (VNO) menos amortizaciones vencidas. Surge de multiplicar el VNO por el valor residual al 31-12-2021.
B65: (2) Surge de multiplicar el valor nominal residual por el coeficiente de capitalización al 31-12-2021.
B66: (3) DLK: Instrumentos emitidos en u$s que se pagan en Pesos de acuerdo a la normativa de emisión.

Sheet A.1.8
A1: Indice
B2: MINISTERIO DE ECONOMÍA
B3: SECRETARÍA DE FINANZAS
B6: TÍTULOS PÚBLICOS, LETRAS DEL TESORO, PRÉSTAMOS GARANTIZADOS Y PAGARÉS
B7: EMITIDOS EN MONEDA NACIONAL AJUSTABLES POR CER
B8: DATOS AL 31/12/2021
H11: En miles de u$s
B12: Fecha de emisión | C12: Denominación | D12: Tasa Vigente | E12: Vencimiento | F12: Valor nominal original en circulación (1) | G12: Valor nominal residual en circulación (2) | H12: Valor nominal actualizado en circulación (3)
C17: TÍTULOS PÚBLICOS | F17: =+F22+F19+F35+F42 -> 18503479 | G17: =+G22+G19+G35+G42 -> 18488958 | H17: =+H22+H19+H35+H42 -> 47437757
C19: BONOS DE CONSOLIDACIÓN | F19: =+F20 -> 18811.97 | G19: =+G20 -> 4291.0103 | H19: =+H20 -> 138012.37
B20: 38061 | C20: PR13/$+CER/2,00%/15-03-2024 | D20: 0.02 | E20: 2024 | F20: 18811.97 | G20: 4291.0103 | H20: 138012.37
C22: BONOS | F22: =+SUM(F23:F33) -> 18126131 | G22: =+SUM(G23:G33) -> 18126131 | H22: =+SUM(H23:H33) -> 34701204
B23: 43165 | C23: BONCER/$+CER/4,00%/06-03-2023 | D23: 0.04 | E23: 2023 | F23: 275352.68 | G23: 275352.68 | H23: 1207485.6
B24: 43217 | C24: BONCER/$+CER/4,00%/27-04-2025 | D24: 0.04 | E24: 2025 | F24: 283190.25 | G24: 283190.25 | H24: 1194791.9
B25: 43908 | C25: BONCER/$+CER/1,20%/18-03-2022 | D25: 0.012 | E25: 2022 | F25: 2558863.4 | G25: 2558863.4 | H25: 4874251.9
B26: 43915 | C26: BONCER/$+CER/1,40%/25-03-2023 | D26: 0.014 | E26: 2023 | F26: 2997791.9 | G26: 2997791.9 | H26: 5684871.4
B27: 43915 | C27: BONCER/$+CER/1,50%/25-03-2024 | D27: 0.015 | E27: 2024 | F27: 3365285 | G27: 3365285 | H27: 6381768.2
B28: 43433 | C28: BONCER/$+CER/8,50%/29-11-2022 | D28: 0.085 | E28: 2022 | F28: 330552.51 | G28: 330552.51 | H28: 1082102.9
B29: 43971 | C29: BONCER/$+CER/1,30%/20-09-2022 | D29: 0.013 | E29: 2022 | F29: 3566194.1 | G29: 3566194.1 | H29: 6443992.6
B30: 44056 | C30: BONCER/$+CER//1,45%/13-08-2023 | D30: 0.0145 | E30: 2023 | F30: 2934639.6 | G30: 2934639.6 | H30: 5055604.7
B31: 44078 | C31: BONCER/$+CER/2%/09-11-2026 | D31: 0.02 | E31: 2026 | F31: 651003.01 | G31: 651003.01 | H31: 1106416.3
B32: 44078 | C32: BONCER/$+CER/2,25%/09-11-2028 | D32: 0.0225 | E32: 2028 | F32: 89993.209 | G32: 89993.209 | H32: 152948.54
B33: 44253 | C33: BONCER/$+CER/1,55%/26-07-2024 | D33: 0.0155 | E33: 2024 | F33: 1073265.3 | G33: 1073265.3 | H33: 1516970
C35: BONOS DE LA REESTRUCTURACIÓN - DTO. 1735/04 y 563/10 | F35: =SUM(F36:F40) -> 358536.27 | G35: =SUM(G36:G40) -> 358536.27 | H35: =SUM(H36:H40) -> 12597355
B36: 37986 | C36: PAR/$+CER/TASA FIJA/31-12-2038/DTO. 1735-04 | D36: 0.0177 | E36: 2038 | F36: 27519.58 | G36: 27519.58 | H36: 729960.16
B37: 37986 | C37: PAR/$+CER/TASA FIJA/31-12-2038/DTO. 563-10 | D37: 0.0177 | E37: 2038 | F37: 109.44543 | G37: 109.44543 | H37: 2903.0532
B38: 37986 | C38: DISCOUNT/$+CER/5,83%/31-12-2033/DTO. 1735-04 | D38: 0.0583 | E38: 2033 | F38: 101617.11 | G38: 101617.11 | H38: 3422993.9
B39: 37986 | C39: DISCOUNT/$+CER/5,83%/31-12-2033/DTO. 563-10 | D39: 0.0583 | E39: 2033 | F39: 1221.5135 | G39: 1221.5135 | H39: 41146.923
B40: 37986 | C40: CUASIPAR/$+CER/3,31%/31-12-2045/DTO. 1735-04 | D40: 0.0331 | E40: 2045 | F40: 228068.62 | G40: 228068.62 | H40: 8400350.8
C42: AMPAROS Y EXCEPCIONES | H42: 1185.6692
C44: LETRAS DEL TESORO | F44: =+SUM(F45:F52) -> 10872357 | G44: =+SUM(G45:G52) -> 10872357 | H44: =+SUM(H45:H52) -> 13635761
B45: 44273 | C45: LETES/$+CER/28-02-2022 | D45: Tasa Cero | E45: 2022 | F45: 1926290 | G45: 1926290 | H45: 2649499.5
B46: 44286 | C46: LETES/$+CER/31-03-2022 | D46: Tasa Cero | E46: 2022 | F46: 1100979.3 | G46: 1100979.3 | H46: 1492037.7
B47: 44305 | C47: LETES/$+CER/18-04-2022 | D47: Tasa Cero | E47: 2022 | F47: 1339148.5 | G47: 1339148.5 | H47: 1772889.6
B48: 44337 | C48: LETES/$+CER/23-05-2022 | D48: Tasa Cero | E48: 2022 | F48: 1733516.7 | G48: 1733516.7 | H48: 2186540.4
B49: 44377 | C49: LETES/$+CER/30-06-2022 | D49: Tasa Cero | E49: 2022 | F49: 2146315.9 | G49: 2146315.9 | H49: 2578693.8
B50: 44413 | C50: LETES/$+CER/29-07-2022 | D50: Tasa Cero | E50: 2022 | F50: 1479318.7 | G50: 1479318.7 | H50: 1711790.5
B51: 44530 | C51: LETES/$+CER/16-08-2022 | D51: Tasa Cero | E51: 2022 | F51: 780450.96 | G51: 780450.96 | H51: 804173.27
B52: 44377 | C52: LETES/$+CER/31-12-2021 | D52: Tasa Cero | E52: 2021 | F52: 366337.09 | G52: 366337.09 | H52: 440136.14
C54: PRÉSTAMOS GARANTIZADOS | F54: =SUM(F55:F62) -> 16339.094 | G54: =SUM(G55:G62) -> 16339.094 | H54: =SUM(H55:H62) -> 751015.37
B55: 37201 | C55: PTMO. GAR. TASA FIJA GL 31 | D55: 0.05 | E55: 2031 | F55: 28.122624 | G55: 28.122624 | H55: 1113.9944
B56: 37201 | C56: PTMO. GAR. TASA FIJA GL 30 | D56: 0.05 | E56: 2030 | F56: 122.78561 | G56: 122.78561 | H56: 4863.7882
B57: 37201 | C57: PTMO. GAR. TASA FIJA BONTE 27 | D57: 0.05 | E57: 2027 | F57: 569.9464 | G57: 569.9464 | H57: 22574.378
B58: 37201 | C58: PTMO. GAR. TASA VAR. GL 30 | D58: 0.05 | E58: 2030 | F58: 922.39358 | G58: 922.39358 | H58: 36388.42
B59: 37201 | C59: PTMO. GAR. TASA FIJA GL 27 | D59: 0.05 | E59: 2027 | F59: 1619.4615 | G59: 1619.4615 | H59: 64123.492
B60: 37201 | C60: PTMO. GAR. TASA VAR. GL 27 | D60: 0.05 | E60: 2027 | F60: 1658.3878 | G60: 1658.3878 | H60: 65402.784
B61: 37201 | C61: PTMO. GAR. TASA VAR. GL 31 MEGA | D61: 0.05 | E61: 2031 | F61: 2231.4899 | G61: 2231.4899 | H61: 108411.44
B62: 37201 | C62: PTMO. GAR. TASA FIJA GL 31 MEGA | D62: 0.05 | E62: 2031 | F62: 9186.5061 | G62: 9186.5061 | H62: 448137.07
C64: PAGARÉS DEL TESORO | F64: =+F65 -> 14273.246 | G64: =+G65 -> 14273.246 | H64: =+H65 -> 378599.56
B65: 37986 | C65: PAGARÉ 2038-BNA | D65: 0.0177 | E65: 2038 | F65: 14273.246 | G65: 14273.246 | H65: 378599.56
B67: TOTAL | F67: =+F64+F54+F44+F17 -> 29406449 | G67: =+G64+G54+G44+G17 -> 29391928 | H67: =+H64+H54+H44+H17 -> 62203133
B69: (1) En el caso de los préstamos garantizados, el monto surge de multiplicar por 1,40 el VNO en circulación.
B70: (2) Valor nominal original (VNO) menos amortizaciones vencidas. Surge de multiplicar el VNO por el valor residual al 31-12-2021.
B71: (3) Surge de multiplicar el valor nominal residual por el coeficiente de capitalización y el coeficiente de estabilización de referencia al 31-12-2021.

Sheet A.1.9
A1: Indice
B2: MINISTERIO DE ECONOMÍA
B3: SECRETARÍA DE FINANZAS
B6: TÍTULOS PÚBLICOS, LETRAS DEL TESORO Y PAGARÉS
B7: EMITIDOS EN MONEDA EXTRANJERA
B8: DATOS AL 31/12/2021
H11: En miles de u$s
B12: Fecha de emisión | C12: Denominación | D12: Tasa vigente | E12: Vencimiento | F12: Valor nominal original en circulación | G12: Valor nominal residual en circulación (1) | H12: Valor nominal actualizado en circulación (2)
C18: TÍTULOS PÚBLICOS | F18: =+F20+F44+F56 -> 1.124989e+08 | G18: =+G20+G44+G56 -> 1.1249369e+08 | H18: =+H20+H44+H56 -> 1.1252526e+08
C20: BONOS | F20: =SUM(F21:F42) -> 1.1154389e+08 | G20: =SUM(G21:G42) -> 1.1153868e+08 | H20: =SUM(H21:H42) -> 1.1153868e+08
B21: 41766 | C21: BONAR/U$S/8,75%/07-05-2024 | D21: 0.0875 | E21: 2024 | F21: 31240.452 | G21: 26035.793 | H21: 26035.793
B22: 42285 | C22: BONAR/U$S/8,00%/08-10-2020 | D22: 0.08 | E22: 2022 | F22: 7924.43 | G22: 7924.43 | H22: 7924.43
B23: 42587 | C23: BONAR/U$S/1,00%/05-08-2023 | D23: 0.01 | E23: 2023 | F23: 24998.895 | G23: 24998.895 | H23: 24998.895
B24: 42843 | C24: BONAR/U$S/5,75%/18-04-2025 | D24: 0.0575 | E24: 2025 | F24: 1960.808 | G24: 1960.808 | H24: 1960.808
B25: 42843 | C25: BONAR/U$S/7,625%/18-04-2037 | D25: 0.07625 | E25: 2037 | F25: 4021.279 | G25: 4021.279 | H25: 4021.279
B26: 44078 | C26: BONO GLOBAL/U$S/STEP UP/09-07-2030 | D26: 0.005 | E26: 2030 | F26: 16090612 | G26: 16090612 | H26: 16090612
B27: 44078 | C27: BONO GLOBAL/U$S/STEP UP/09-07-2035 | D27: 0.01125 | E27: 2035 | F27: 20501718 | G27: 20501718 | H27: 20501718
B28: 44078 | C28: BONO GLOBAL/U$S/STEP UP/09-01-2038 | D28: 0.02 | E28: 2038 | F28: 11405065 | G28: 11405065 | H28: 11405065
B29: 44078 | C29: BONO GLOBAL/U$S/STEP UP/09-07-2041 | D29: 0.025 | E29: 2041 | F29: 10482111 | G29: 10482111 | H29: 10482111
B30: 44078 | C30: BONO GLOBAL/U$S/1,00%/09-07-2029 | D30: 0.01 | E30: 2029 | F30: 2635028.7 | G30: 2635028.7 | H30: 2635028.7
B31: 44078 | C31: BONO GLOBAL/U$S/STEP UP/09-07-2046 | D31: 0.01125 | E31: 2046 | F31: 2091997.1 | G31: 2091997.1 | H31: 2091997.1
B32: 44078 | C32: BONO R.A./U$S/STEP UP/09-07-2030 | D32: 0.005 | E32: 2030 | F32: 13524104 | G32: 13524104 | H32: 13524104
... B42: 44078 | C42: BONO GLOBAL/EUR/STEP UP/09-07-2046 | D42: 0.0075 | E42: 2046 | F42: 282057.62 | G42: 282057.62 | H42: 282057.62
C44: BONOS DE LA REESTRUCTURACIÓN - DTO. 1735/04 y 563/10 | F44: =SUM(F45:F54) -> 955010.31 | G44: =SUM(G45:G54) -> 955010.31 | H44: =SUM(H45:H54) -> 972909.79
B45: 37986 | C45: PAR/U$S/TASA FIJA/31-12-2038/DTO. 1735-04/LEY ARG | D45: 0.0375 | E45: 2038 | F45: 28985.612 | G45: 28985.612 | H45: 28985.612
B46: 37986 | C46: PAR/U$S/TASA FIJA/31-12-2038/DTO. 563-10/LEY NY | D46: 0.0375 | E46: 2038 | F46: 35819.56 | G46: 35819.56 | H46: 35819.56
B47: 37986 | C47: PAR/U$S/TASA FIJA/31-12-2038/DTO. 563-10/LEY ARG | D47: 0.0375 | E47: 2038 | F47: 5563.179 | G47: 5563.179 | H47: 5563.179
B48: 37986 | C48: PAR/EUR/TASA FIJA/31-12-2038/DTO. 563-10 | D48: 0.0338 | E48: 2038 | F48: 645884.06 | G48: 645884.06 | H48: 645884.06
B49: 37986 | C49: PAR/JPY/TASA FIJA/31-12-2038/DTO. 1735-04 | D49: 0.0067 | E49: 2038 | F49: 150022.97 | G49: 150022.97 | H49: 150022.97
B50: 37986 | C50: PAR/JPY/TASA FIJA/31-12-2038/DTO. 563-10 | D50: 0.0067 | E50: 2038 | F50: 7419.9079 | G50: 7419.9079 | H50: 7419.9079
B51: 37986 | C51: DISCOUNT/USD/8,28%/31-12-2033/DTO. 1735-04/LEY ARG | D51: 0.0828 | E51: 2033 | F51: 7017.752 | G51: 7017.752 | H51: 9839.155
B52: 37986 | C52: DISCOUNT/USD/8,28%/31-12-2033/DTO. 563-10/LEY ARG | D52: 0.0828 | E52: 2033 | F52: 2855.245 | G52: 2855.245 | H52: 4003.162
B53: 37986 | C53: DISCOUNT/JPY/4,33%/31-12-2033/DTO. 1735-04 | D53: 0.0433 | E53: 2033 | F53: 49292.57 | G53: 49292.57 | H53: 58903.907
B54: 37986 | C54: DISCOUNT/JPY/4,33%/31-12-2033/DTO. 563-10 | D54: 0.0433 | E54: 2033 | F54: 22149.461 | G54: 22149.461 | H54: 26468.285
C56: AMPAROS | H56: 13664.388
C58: LETRAS DEL TESORO | F58: =SUM(F59:F74) -> 9159067.1 | G58: =SUM(G59:G74) -> 8218008.9 | H58: =SUM(H59:H74) -> 8218008.9
B59: 43630 | C59: LETES/U$S/17-01-2020 (R) | D59: Tasa Cero | E59: 2022 | F59: 5.536 | G59: 5.536 | H59: 5.536
B60: 43644 | C60: LETES/U$S/31-01-2020 (R) | D60: Tasa Cero | E60: 2022 | F60: 15.803 | G60: 15.803 | H60: 15.803
B61: 43665 | C61: LETES/U$S/14-02-2020 (R) | D61: Tasa Cero | E61: 2022 | F61: 11.736 | G61: 11.736 | H61: 11.736
B62: 43672 | C62: LETES/U$S/28-02-2020 (R) | D62: Tasa Cero | E62: 2022 | F62: 7.22 | G62: 7.22 | H62: 7.22
B63: 43693 | C63: LETRA/U$S/MENDOZA/28-10-2024 | D63: Tasa Cero | E63: 2024 | F63: 1023362.9 | G63: 704559.59 | H63: 704559.59
B64: 43490 | C64: LETES/U$S/30-08-2019 (R) | D64: Tasa Cero | E64: 2022 | F64: 222.829 | G64: 133.6974 | H64: 133.69725
B65: 43504 | C65: LETES/U$S/13-09-2019 (R) | D65: Tasa Cero | E65: 2022 | F65: 2088.821 | G65: 1253.2926 | H65: 1253.2926
B66: 43518 | C66: LETES/U$S/27-09-2019 (R) | D66: Tasa Cero | E66: 2022 | F66: 996.259 | G66: 846.82015 | H66: 846.8201
B67: 43539 | C67: LETES/U$S/11-10-2019 (R) | D67: Tasa Cero | E67: 2022 | F67: 2339.838 | G67: 1988.8623 | H67: 1988.8623
B68: 43553 | C68: LETES/U$S/25-10-2019 (R) | D68: Tasa Cero | E68: 2022 | F68: 2575.409 | G68: 2189.0976 | H68: 2189.0976
B69: 43567 | C69: LETES/U$S/15-11-2019 (R) | D69: Tasa Cero | E69: 2022 | F69: 354.976 | G69: 301.7296 | H69: 301.72955
B70: 43581 | C70: LETES/U$S/29-11-2019 (R) | D70: Tasa Cero | E70: 2022 | F70: 55.263 | G70: 46.97355 | H70: 46.9735
... B74: 43455 | C74: LETRAS EN GARANTIA | D74: Tasa Cero | E74: 2041 | F74: 2769576.5 | G74: 2599116.5 | H74: 2599116.5
C76: LETRAS ADQUIRIDAS POR EL BCRA | F76: =SUM(F77:F88) -> 57509452 | G76: =SUM(G77:G88) -> 57509452 | H76: =SUM(H77:H88) -> 57509452
B77: 41019 | C77: LETRA/U$S/FDA/TITULOS/20-04-2022 | D77: Libor-1,00% | E77: 2022 | F77: 5674000 | G77: 5674000 | H77: 5674000
B78: 41290 | C78: LETRA/U$S/FDA/TITULOS/16-01-2023 | D78: Libor-1,00% | E78: 2023 | F78: 7132655 | G78: 7132655 | H78: 7132655
B79: 41669 | C79: LETRA/U$S/FDA/TITULOS/30-01-2024 | D79: Libor-1,00% | E79: 2024 | F79: 7896764.9 | G79: 7896764.9 | H79: 7896764.9
B80: 42156 | C80: LETRA/U$S/FDA/TITULOS/01-06-2025 | D80: Libor-1,00% | E80: 2025 | F80: 10562540 | G80: 10562540 | H80: 10562540
B81: 41088 | C81: LETRA/U$S/FOI/28-06-2022 | D81: Libor-1,00% | E81: 2022 | F81: 2083648 | G81: 2083648 | H81: 2083648
B82: 41502 | C82: LETRA/U$S/FOI/16-08-2023 | D82: Libor-1,00% | E82: 2023 | F82: 2292296.8 | G82: 2292296.8 | H82: 2292296.8
B83: 41876 | C83: LETRA/U$S/FOI/25-08-2024 | D83: Libor-1,00% | E83: 2024 | F83: 3043000 | G83: 3043000 | H83: 3043000
B84: 42489 | C84: LETRA/U$S/BCRA/29-04-2026 | D84: Libor-1,00% | E84: 2026 | F84: 376299.93 | G84: 376299.93 | H84: 376299.93
B85: 43829 | C85: LETRA/U$S/BCRA/30-12-2029 | D85: Libor-1,00% | E85: 2029 | F85: 4571000 | G85: 4571000 | H85: 4571000
B86: 43941 | C86: LETRA/U$S/BCRA/20-04-2030 | D86: Libor-1,00% | E86: 2030 | F86: 118678.58 | G86: 118678.58 | H86: 118678.58
B87: 44203 | C87: LETRA/U$S/BCRA/07-01-2031 | D87: Libor-1,00% | E87: 2031 | F87: 9627595.8 | G87: 9627595.8 | H87: 9627595.8
B88: 44460 | C88: LETRA/U$S/BCRA/21-09-2031 | D88: Libor-1,00% | E88: 2031 | F88: 4130973.5 | G88: 4130973.5 | H88: 4130973.5
B90: TOTAL | F90: =+F76+F58+F18 -> 1.7916742e+08 | G90: =+G76+G58+G18 -> 1.7822115e+08 | H90: =+H76+H58+H18 -> 1.7825272e+08
B92: (1) Valor nominal original (VNO) menos amortizaciones vencidas. Surge de multiplicar el VNO por el valor residual al 31-12-2021.
B93: (2) Surge de multiplicar el valor nominal residual por el coeficiente de capitalización al 31-12-2021.

Sheet A.1.10
A1: Indice
B2: MINISTERIO DE ECONOMÍA
B3: SECRETARÍA DE FINANZAS
B6: DEUDA ELEGIBLE PENDIENTE DE REESTRUCTURACIÓN
B7: DATOS AL 31/12/2021
G10: En miles de u$s
B11: Denominación | C11: Moneda de origen | D11: Capital | E11: Atrasos de Interés (1) | F11: Intereses Compensatorios (2) | G11: Total
B17: EN MONEDA NACIONAL | D17: =SUM(D19:D31) -> 271.06328 | E17: =SUM(E19:E31) -> 25.794632 | F17: =SUM(F19:F31) -> 10.768909 | G17: =SUM(G19:G31) -> 307.62682
B19: BOCON PRE.2ºS./$/C.A./02/PRE3 | C19: Pesos | D19: 4.8625341 | E19: 0.04260279 | F19: 0.48572208 | G19: =SUM(D19:F19) -> 5.390859
B20: BOCON PRO.1ºS./$/C.A./07/PRO1 | C20: Pesos | D20: 86.884254 | E20: 5.7582359 | F20: 2.8201797 | G20: =SUM(D20:F20) -> 95.46267
B21: BOCON PRO.2ºS./$/C.A./10/PRO3 | C21: Pesos | D21: 1.3892201 | E21: 0.13964269 | F21: 0.019556726 | G21: =SUM(D21:F21) -> 1.5484196
B22: BOCON PRO.3ºS./$/C.A./07/PRO5 | C22: Pesos | D22: 58.600058 | E22: 4.4594311 | F22: 1.9622833 | G22: =SUM(D22:F22) -> 65.021773
B23: BOCON PRO.5°S./$/C.A./07/PRO9 | C23: Pesos | D23: 59.904717 | E23: 6.2588491 | F23: 1.9630773 | G23: =SUM(D23:F23) -> 68.126643
B24: EUROLETRA/$/11,75%/2007 | C24: Pesos | D24: 3.1143552 | E24: 2.0126521 | F24: 3.364585 | G24: =SUM(D24:F24) -> 8.4915923
B25: EUROLETRA/$/8,75%/2002 | C25: Pesos | D25: 0.12727981 | E25: 0.0098487307 | F25: 0.15350475 | G25: =SUM(D25:F25) -> 0.29063328
B26: Dto.1023/7-7-95/CHACO | C26: Pesos | D26: 0.024356496 | E26: 0.0044815572 | F26: 0 | G26: =SUM(D26:F26) -> 0.028838054
B27: Dto.1023/7-7-95/CHUBUT | C27: Pesos | D27: 10.528855 | E27: 0.48846365 | F27: 0 | G27: =SUM(D27:F27) -> 11.017318
B28: Dto.1023/7-7-95/RIO NEGRO | C28: Pesos | D28: 1.5010794 | E28: 0.12004487 | F28: 0 | G28: =SUM(D28:F28) -> 1.6211243
B29: Dto.1023/7-7-95/SALTA | C29: Pesos | D29: 1.9043081 | E29: 0.15229178 | F29: 0 | G29: =SUM(D29:F29) -> 2.0565999
B30: Dto.1023/7-7-95/SANT. ESTERO | C30: Pesos | D30: 0.17753353 | E30: 0.014198248 | F30: 0 | G30: =SUM(D30:F30) -> 0.19173178
B31: Dto.1023/7-7-95/M.C.B.A. | C31: Pesos | D31: 42.044728 | E31: 6.3338895 | F31: 0 | G31: =SUM(D31:F31) -> 48.378618
B33: EN MONEDA NACIONAL AJUSTABLE POR CER | D33: =SUM(D35:D58) -> 47916.291 | E33: =SUM(E35:E58) -> 1410.3157 | F33: =SUM(F35:F58) -> 6733.5622 | G33: =SUM(G35:G58) -> 56060.169
B35: LETES/U$S/15-3-2002(P) | C35: Pesos Ajustados por CER | D35: 4968.0902 | E35: 0 | F35: 0 | G35: =SUM(D35:F35) -> 4968.0902
B36: LETES/U$S/15-2-2002(P) | C36: Pesos Ajustados por CER | D36: 1840.6118 | E36: 0 | F36: 0 | G36: =SUM(D36:F36) -> 1840.6118
B37: LETES/U$S/8-3-2002(P) | C37: Pesos Ajustados por CER | D37: 1864.1487 | E37: 0 | F37: 0 | G37: =SUM(D37:F37) -> 1864.1487
B38: LETES/U$S/22-2-2002(P) | C38: Pesos Ajustados por CER | D38: 415.79685 | E38: 0 | F38: 0 | G38: =SUM(D38:F38) -> 415.79685
B39: LETES/U$S/22-3-2002(P) | C39: Pesos Ajustados por CER | D39: 454.66003 | E39: 0 | F39: 0 | G39: =SUM(D39:F39) -> 454.66003
B40: BONEX/1992(P) | C40: Pesos Ajustados por CER | D40: 3800.1623 | E40: 29.157149 | F40: 1010.4381 | G40: =SUM(D40:F40) -> 4839.7576
B41: FERROBONOS(P) | C41: Pesos Ajustados por CER | D41: 3.3838554 | E41: 0.98738341 | F41: 0 | G41: =SUM(D41:F41) -> 4.3712388
B42: PRE4(P) | C42: Pesos Ajustados por CER | D42: 1200.9179 | E42: 20.886499 | F42: 276.17618 | G42: =SUM(D42:F42) -> 1497.9806
B43: PRO2(P) | C43: Pesos Ajustados por CER | D43: 6821.9169 | E43: 364.67605 | F43: 1236.4717 | G43: =SUM(D43:F43) -> 8423.0646
B44: PRO4(P) | C44: Pesos Ajustados por CER | D44: 2500.2668 | E44: 253.26482 | F44: 265.8617 | G44: =SUM(D44:F44) -> 3019.3933
B45: PRO6(P) | C45: Pesos Ajustados por CER | D45: 4327.4731 | E45: 125.11924 | F45: 357.91176 | G45: =SUM(D45:F45) -> 4810.5041
B46: PRO8(P) | C46: Pesos Ajustados por CER | D46: 122.26251 | E46: 12.136732 | F46: 0.76074453 | G46: =SUM(D46:F46) -> 135.15999
... B58: BONO/U$S/ENC.+4.35%/2004(P) | C58: Pesos Ajustados por CER | D58: 52.65062 | E58: 2.4279456 | F58: 12.842224 | G58: =SUM(D58:F58) -> 67.920789
B60: EN MONEDA EXTRANJERA | D60: =SUM(D62:D81,D102:D176) -> 1010833.7 | E60: =SUM(E62:E81,E102:E176) -> 864247.21 | F60: =SUM(F62:F81,F102:F176) -> 507854.47 | G60: =SUM(G62:G81,G102:G176) -> 2382935.4
B62: EUROLETRA/CHF/7%/2003 | C62: CHF | D62: 8216.3999 | E62: 1150.296 | F62: 7127.0422 | G62: =SUM(D62:F62) -> 16493.738
B63: DISCOUNT/DEM/L.+0,8125%/2023 | C63: EUR | D63: 284.7937 | E63: 92.071827 | F63: 32.663935 | G63: =SUM(D63:F63) -> 409.52946
B64: PAR BONDS/DEM/5,87%/2023 | C64: EUR | D64: 3818.5605 | E64: 2913.9435 | F64: 1086.8536 | G64: =SUM(D64:F64) -> 7819.3576
B65: EUROLETRA/EUR/8,75%/2003 | C65: EUR | D65: 4262.1291 | E65: 745.8726 | F65: 4928.9748 | G65: =SUM(D65:F65) -> 9936.9765
B66: EUROLETRA/DEM/7%/2004 | C66: EUR | D66: 27172.225 | E66: 5706.1673 | F66: 23004.308 | G66: =SUM(D66:F66) -> 55882.701
B67: EUROLETRA/DEM/8%/2009 | C67: EUR | D67: 922.57644 | E67: 590.44892 | F67: 478.30463 | G67: =SUM(D67:F67) -> 1991.33
B68: EUROLETRA/EUR/11%-8%/2008 | C68: EUR | D68: 2632.1219 | E68: 1473.9883 | F68: 1717.3133 | G68: =SUM(D68:F68) -> 5823.4235
B69: EUROLETRA/EUR/T.FIJA/2010 | C69: EUR | D69: 1344.5424 | E69: 1035.2977 | F69: 701.51502 | G69: =SUM(D69:F69) -> 3081.3551
B70: EUROLETRA/DEM/7,875%/2005 | C70: EUR | D70: 303.97368 | E70: 95.75171 | F70: 256.86726 | G70: =SUM(D70:F70) -> 656.59266
B71: EUROLETRA/DEM/14%-9%/2008 | C71: EUR | D71: 173.20106 | E71: 109.11666 | F71: 115.74161 | G71: =SUM(D71:F71) -> 398.05933
B72: BONO R.A./EUR/9%/2003 | C72: EUR | D72: 1979.6522 | E72: 356.33738 | F72: 2288.9728 | G72: =SUM(D72:F72) -> 4624.9623
B73: BONO R.A./EUR/10%/2007 | C73: EUR | D73: 929.86245 | E73: 557.91747 | F73: 802.00637 | G73: =SUM(D73:F73) -> 2289.7863
... B81: EUROLETRA/EUR/8,125%/2004 | C81: EUR | D81: 6758.3654 | E81: 1647.3516 | F81: 6342.6796 | G81: =SUM(D81:F81) -> 14748.397
B85: MINISTERIO DE FINANZAS
B86: SECRETARÍA DE FINANZAS
B89: =+B6 -> DEUDA ELEGIBLE PENDIENTE DE REESTRUCTURACIÓN
B90: =+B7 -> DATOS AL 31/12/2021
G93: En miles de u$s
B94: Denominación | C94: Moneda de origen | D94: Capital | E94: Atrasos de Interés (1) | F94: Intereses Compensatorios (2) | G94: Total
B100: (Continuación)
B102: BOCON PRO.1ºS./U$S/L./07/PRO2 | C102: U$S | D102: 1e-05 | E102: 1.26446 | F102: 0 | G102: =SUM(D102:F102) -> 1.26447
B103: BONO/U$S/ENCUESTA+4.35%/2004 | C103: U$S | D103: 1e-05 | E103: 1.87 | F103: 0 | G103: =SUM(D103:F103) -> 1.87001
B104: BONO/U$S/ENCUESTA+4%/2002 | C104: U$S | D104: 1e-05 | E104: 14.02309 | F104: 0 | G104: =SUM(D104:F104) -> 14.0231
B105: BONTES/U$S/ENCUESTA+3,2%/2003 | C105: U$S | D105: 1e-05 | E105: 15.68152 | F105: 0 | G105: =SUM(D105:F105) -> 15.68153
B106: BOCON PRO.5ºS./U$S/L./07/PRO10 | C106: U$S | D106: 1e-05 | E106: 25.04966 | F106: 0 | G106: =SUM(D106:F106) -> 25.04967
B107: BOCON PRO.2ºS./U$S/L./10/PRO4 | C107: U$S | D107: 1e-05 | E107: 27.7379 | F107: 0 | G107: =SUM(D107:F107) -> 27.73791
B108: BONO/U$S/ENCUESTA+3,3%/2002 | C108: U$S | D108: 1e-05 | E108: 41.03004 | F108: 0 | G108: =SUM(D108:F108) -> 41.03005
B109: EUROLETRA/U$S/ENC.+4,95%/2004 | C109: U$S | D109: 1e-05 | E109: 501.22017 | F109: 0 | G109: =SUM(D109:F109) -> 501.22018
B110: EUROLETRA/U$S/BAD.+2,98%/2004 | C110: U$S | D110: 0.007 | E110: 242.21741 | F110: 0.010390558 | G110: =SUM(D110:F110) -> 242.2348
B111: GLOBAL BOND/$/10%-12%/2008 | C111: U$S | D111: 0.356 | E111: 0.27767533 | F111: 0.32443467 | G111: =SUM(D111:F111) -> 0.95811
B112: GLOBAL BOND/U$S/8,875%/2029 | C112: U$S | D112: 2 | E112: 2.14881 | F112: 0 | G112: =SUM(D112:F112) -> 4.14881
B113: GLOBAL BOND/U$S/T.CERO/2004 | C113: U$S | D113: 63 | E113: 0 | F113: 0 | G113: =SUM(D113:F113) -> 63
... B176: GLOBAL BOND/U$S/11,375%/2017 | C176: U$S | D176: 181636.8 | E176: 297405.42 | F176: 0 | G176: =SUM(D176:F176) -> 479042.22
B178: TOTAL | D178: =+D60+D33+D17 -> 1059021 | E178: =+E60+E33+E17 -> 865683.32 | F178: =+F60+F33+F17 -> 514598.8 | G178: =+G60+G33+G17 -> 2439303.2
B180: (1) No incluye intereses moratorios ni punitorios.
B181: (2) Intereses compensatorios estimados, devengados e impagos con posterioridad a la fecha de vencimiento de cada título.

Sheet A.2.1
A1: Indice
B2: MINISTERIO DE ECONOMÍA
B3: SECRETARÍA DE FINANZAS
B6: DEUDA BRUTA DE LA ADMINISTRACIÓN CENTRAL
B7: SERIE POR TRIMESTRE Y POR INSTRUMENTO
B10: En miles de u$s - TC del trimestre
B11: INSTRUMENTO | C11: 2020 | D11: 2021
C12: Saldo al 31/12/2020 | D12: Saldo al 31/03/2021 | E12: Saldo al 30/06/2021 | F12: Saldo al 30/09/2021 | G12: Saldo al 31/12/2021
B14: I- DEUDA BRUTA + VALORES NEGOCIABLES VINCULADOS AL PBI ( II+VII ) | C14: =+C17+C76 -> 3.490966e+08 | D14: =+D17+D76 -> 3.4876584e+08 | E14: =+E17+E76 -> 3.5680432e+08 | F14: =+F17+F76 -> 3.5573596e+08 | G14: =+G17+G76 -> 3.7621495e+08
B17: II- DEUDA BRUTA ( III+IV+V+VI ) | C17: =+C20+C53+C63+C68 -> 3.3558222e+08 | D17: =+D20+D53+D63+D68 -> 3.3555613e+08 | E17: =+E20+E53+E63+E68 -> 3.4352394e+08 | F17: =+F20+F53+F63+F68 -> 3.4262009e+08 | G17: =+G20+G53+G63+G68 -> 3.6323261e+08
B20: III- MEDIANO Y LARGO PLAZO | C20: =+C22+C26+C28+C51 -> 3.1036076e+08 | D20: =+D22+D26+D28+D51 -> 3.1027652e+08 | E20: =+E22+E26+E28+E51 -> 3.1794643e+08 | F20: =+F22+F26+F28+F51 -> 3.1617308e+08 | G20: =+G22+G26+G28+G51 -> 3.2576771e+08
B22: TÍTULOS PÚBLICOS | C22: =+C23+C24 -> 2.1392576e+08 | D22: =+D23+D24 -> 2.1590099e+08 | E22: =+E23+E24 -> 2.2221473e+08 | F22: =+F23+F24 -> 2.2353849e+08 | G22: =+G23+G24 -> 2.3036901e+08
B23: - Moneda nacional | C23: 47590244 | D23: 49808170 | E23: 56062277 | F23: 55630559 | G23: 60334299
B24: - Moneda extranjera | C24: 1.6633551e+08 | D24: 1.6609282e+08 | E24: 1.6615245e+08 | F24: 1.6790793e+08 | G24: 1.7003471e+08
B26: LETRAS DEL TESORO (1) | C26: 8208699.9 | D26: 8139931.6 | E26: 9653177.7 | F26: 10061943 | G26: 9432983.6
B28: PRÉSTAMOS | C28: =+C30+C32+C43+C45+C47+C49 -> 81615693 | D28: =+D30+D32+D43+D45+D47+D49 -> 80188416 | E28: =+E30+E32+E43+E45+E47+E49 -> 80267709 | F28: =+F30+F32+F43+F45+F47+F49 -> 77326285 | G28: =+G30+G32+G43+G45+G47+G49 -> 78101973
B30: PRÉSTAMOS GARANTIZADOS | C30: 605045.6 | D30: 619031.92 | E30: 670951.94 | F30: 711511.65 | G30: 751015.37
B32: ORGANISMOS INTERNACIONALES | C32: =SUM(C33:C41) -> 71268154 | D32: =SUM(D33:D41) -> 70261710 | E32: =SUM(E33:E41) -> 70563443 | F32: =SUM(F33:F41) -> 68063590 | G32: =SUM(G33:G41) -> 68065416
B33: - BCIE | C33: 2625 | D33: 2625 | E33: 6822.1454 | F33: 6822.1454 | G33: 79285.845
B34: - BIRF | C34: 7721122.2 | D34: 7738428.4 | E34: 7852691 | F34: 7805008.6 | G34: 8517393
B35: - BID | C35: 13368114 | D35: 13197692 | E35: 13144787 | F35: 13246591 | G35: 14051577
B36: - FONPLATA | C36: 323383.07 | D36: 348643.67 | E36: 352687.52 | F36: 367188.01 | G36: 404331.3
B37: - FIDA | C37: 38557.759 | D37: 38109.226 | E37: 37364.73 | F37: 36666.192 | G37: 33561.959
B38: - CAF | C38: 3649093.5 | D38: 3511722.9 | E38: 3450619.7 | F38: 3315558.1 | G38: 3781438.9
B39: - OFID | C39: 94012.406 | D39: 94406.019 | E39: 98084.263 | F39: 97479.444 | G39: 123824.5
B40: - FMI | C40: 45965303 | D40: 45229181 | E40: 45519484 | F40: 43092415 | G40: 40952110
B41: - BEI | C41: 105942.52 | D41: 100902.09 | E41: 100902.09 | F41: 95861.662 | G41: 121894.5
B43: ORGANISMOS OFICIALES | C43: 5487770.2 | D43: 5238720.6 | E43: 5053276.5 | F43: 4647416.4 | G43: 4709868.6
B45: BANCA COMERCIAL | C45: 2028569.5 | D45: 1895794 | E45: 1835199 | F45: 1818368.8 | G45: 2530002
B47: AVALES | C47: 1919958.9 | D47: 1859913.6 | E47: 1806600.4 | F47: 1726713.1 | G47: 1667070.6
... B51: ADELANTOS TRANSITORIOS BCRA | C51: 6610612.6 | D51: 6047181.6 | E51: 5810813.5 | F51: 5246366.5 | G51: 7863747
B53: IV- CORTO PLAZO | C53: =SUM(C55:C61) -> 22614317 | D53: =SUM(D55:D61) -> 22713045 | E53: =SUM(E55:E61) -> 22997850 | F53: =SUM(F55:F61) -> 23888216 | G53: =SUM(G55:G61) -> 34921032
B55: ADELANTOS TRANSITORIOS BCRA | C55: 8368887 | D55: 9123226.6 | E55: 9341176.5 | F55: 5115200.7 | G55: 13285152
B56: LETRAS DEL TESORO | C56: 10559320 | D56: 10681786 | E56: 13656673 | F56: 18773016 | G56: 20687534
B57: BILATERALES | C57: 0 | D57: 0 | E57: 0 | F57: 0 | G57: 0
B58: BANCA COMERCIAL | C58: 0 | D58: 0 | E58: 0 | F58: 0 | G58: 0
B59: PAGARÉS DEL TESORO | C59: 843781.57 | D59: 0 | E59: 0 | F59: 0 | G59: 827250.61
B60: TÍTULOS PÚBLICOS | C60: 2842328 | D60: 2908031.7 | E60: 0 | F60: 0
B61: AVALES | C61: 0 | D61: 0 | E61: 0 | F61: 0 | G61: 121095.08
B63: V- DEUDA EN SITUACIÓN DE PAGO DIFERIDO (2) | C63: =+C65+C66 -> 106676.97 | D63: =+D65+D66 -> 105311.79 | E63: =+E65+E66 -> 105782.12 | F63: =+F65+F66 -> 105086.82 | G63: =+G65+G66 -> 104561.86
B65: CAPITAL | C65: 97761.849 | D65: 96714.591 | E65: 97102.771 | F65: 96586.672 | G65: 96201.236
B66: INTERÉS (3) | C66: 8915.1209 | D66: 8597.2025 | E66: 8679.353 | F66: 8500.1494 | G66: 8360.6238
B68: VI- DEUDA ELEGIBLE PENDIENTE DE REESTRUCTURACIÓN (4) | C68: =+C70+C71+C72 -> 2500462.6 | D68: =+D70+D71+D72 -> 2461252.8 | E68: =+E70+E71+E72 -> 2473882.4 | F68: =+F70+F71+F72 -> 2453700.4 | G68: =+G70+G71+G72 -> 2439303.2
B70: - Capital | C70: 1081386 | D70: 1065022.5 | E70: 1071627.2 | F70: 1064015.5 | G70: 1059021
B71: - Atrasos de Interés | C71: 878941.2 | D71: 871283.45 | E71: 873294.97 | F71: 868960.07 | G71: 865683.32
B72: - Intereses Compensatorios (5) | C72: 540135.42 | D72: 524946.89 | E72: 528960.28 | F72: 520724.86 | G72: 514598.8
B76: VII- VALORES NEGOCIABLES VINCULADOS AL PBI (6) | C76: =SUM(C78:C82) -> 13514386 | D76: =SUM(D78:D82) -> 13209714 | E76: =SUM(E78:E82) -> 13280376 | F76: =SUM(F78:F82) -> 13115868 | G76: =SUM(G78:G82) -> 12982343
B78: U$S- LEY NY (TVPY-TVYO) | C78: 5151027.2 | D78: 5151027.2 | E78: 5151027.2 | F78: 5151027.2 | G78: 5151027.2
B79: U$S- LEY ARG (TVPA) | C79: 929780.55 | D79: 929780.55 | E79: 929780.55 | F79: 929780.55 | G79: 929780.55
B80: EUR-LEY INGLESA (TVPE) | C80: 7174735.4 | D80: 6889496.1 | E80: 6964639.4 | F80: 6803327.5 | G80: 6678041.8
B81: ARP-LEY ARG (TVPP) | C81: 111509.05 | D81: 102004.99 | E81: 98017.885 | F81: 95031.434 | G81: 91318.041
B82: YEN- LEY JAPONESA | C82: 147333.96 | D82: 137405.22 | E82: 136910.52 | F82: 136701.34 | G82: 132175.51
B85: (1) Incluye las Letras en Garantía.
B86: (2) Deuda en situacion de pago diferido, no elegible para canjes de Dtos. 1735/04 y 563/10.
B87: (3) No incluye intereses moratorios ni punitorios.
B88: (4) Se trata de la deuda elegible y no presentada al canje (Dtos. 1735/04 y 563/10) y no cancelada a la fecha en el marco de los acuerdos contemplados en la Ley n° 27.249.
B89: (5) Intereses compensatorios estimados, devengados e impagos con posterioridad a la fecha de vencimiento de cada título.
B90: (6) Valor remanente total. Es la diferencia entre el máximo a pagar de 48 unidades por cada 100 de valor nocional y la suma de los montos pagados hasta la actualidad, de acuerdo con las condiciones establecidas en las respectivas normas de emisión.

Sheet A.2.2
A1: Indice
B2: MINISTERIO DE ECONOMÍA
B3: SECRETARÍA DE FINANZAS
B5: DEUDA BRUTA DE LA ADMINISTRACIÓN CENTRAL
B6: FLUJOS Y VARIACIONES
B7: 4to. TRIMESTRE DE 2021
C10: Miles de u$s | D10: Miles de $
B12: I - DEUDA BRUTA (EXCLUIDA LA ELEGIBLE PENDIENTE DE REESTRUCTURACIÓN), AL 30/09/2021 | C12: 3.4016639e+08 | D12: 3.3586328e+10
B14: II - DEUDA ELEGIBLE PENDIENTE DE REESTRUCTURACIÓN, AL 30/09/2021 (*) | C14: 2453700.4 | D14: 2.4226611e+08
B16: III - DEUDA BRUTA, AL 30/09/2021 (I + II) | C16: =+C12+C14 -> 3.4262009e+08 | D16: =+D12+D14 -> 3.3828594e+10
B18: VARIACIONES
B20: 1 - Financiamiento, canjes y emisiones | C20: =SUM(C22:C29) -> 31128619 | D20: =SUM(D22:D29) -> 3.0734842e+09
B22: Adelantos Transitorios del BCRA | C22: 12406948 | D22: 1225000000
B23: Letras del Tesoro - Organismos Públicos | C23: 7573997.9 | D23: 7.4781868e+08
B24: Letras Intransferibles | C24: 2242967 | D24: 2.2145934e+08
B25: Otros | C25: 526456.1 | D25: 51979643
B26: Pagarés del Tesoro | C26: 860890.26 | D26: 85000000
B27: Préstamos Organismos Multilaterales | C27: 2470105.9 | D27: 2.4388591e+08
B28: Préstamos Organismos Oficiales | C28: 102543.14 | D28: 10124597
B29: TItulos del Tesoro | C29: 4944710.4 | D29: 4.8821598e+08
B31: 2 - Amortizaciones, canjes y cancelaciones | C31: =SUM(C33:C39) -> 11540911 | D31: =SUM(D33:D39) -> 1.1394918e+09
B33: Adelantos Transitorios del BCRA | C33: 759609.05 | D33: 75000000
B34: Bonos de Consolidación | C34: 37455.821 | D34: 3698200.5
B35: Letras del Tesoro - Organismos Públicos | C35: 6004516 | D35: 5.9285588e+08
B36: Otros | C36: 26951.437 | D36: 2661050.1
B37: Préstamos Organismos Multilaterales | C37: 2271345.3 | D37: 2.2426128e+08
B38: Préstamos Organismos Oficiales | C38: 10577.341 | D38: 1044353.8
B39: TItulos del Tesoro | C39: 2430455.7 | D39: 2.3997104e+08
B41: a) Operaciones netas del período ( 1 - 2 ) | C41: =+C20-C31 -> 19587708 | D41: =+D20-D31 -> 1.9339923e+09
B43: b) Emisión Bonos de Consolidación | C43: 14164.28 | D43: 1398510.2
B45: c) Avales netos de cancelaciones | C45: 97744.213 | D45: 9650774.9
B47: d) Letras en garantía | C47: -670075.77 | D47: -66159932
B49: e) Ajustes de valuación - Excluyendo la deuda elegible pendiente de reestructuración | C49: =SUM(C51:C54) -> 1597377.7 | D49: =SUM(D51:D54) -> 1.6063022e+09
B51: Tipo de Cambio (excluye deudas ajustables por CER) | C51: -2031935.6 | D51: 9.9820972e+08
B52: Variación de la deuda ajustable por CER (efectos tipo de cambio y CER) | C52: 3271997.8 | D52: 5.7281295e+08
B53: Capitalización de Bonos del Canje, Préstamos Garantizados, Pagaré Banco Nación, Bonos de consolidación y Otros | C53: 0 | D53: 0
B54: Otras Operaciones (Registro CCF, amparos y excepciones y otros ajustes) | C54: 357315.46 | D54: 35279543
B56: f) Ajustes de valuación sobre deuda elegible pendiente de reestructuración | C56: =SUM(C58:C60) -> -14397.227 | D56: =SUM(D58:D60) -> 8372292
B58: Tipo de Cambio (excluye deudas ajustables por CER) | C58: -16896.08 | D58: 7900486.2
B59: Variación de la deuda ajustable por CER (efectos tipo de cambio y CER) | C59: 2948.788 | D59: 516230.16
B60: Otras Operaciones (Bajas Ley n° 27.249, amparos y excepciones y otros ajustes) | C60: -449.93546 | D60: -44424.378
B62: IV - TOTAL VARIACIONES (a+b+c+d+e+f) | C62: =+C41+C43+C45+C49+C47+C56 -> 20612521 | D62: =+D41+D43+D45+D49+D47+D56 -> 3.4935562e+09
B64: V - DEUDA BRUTA, AL 31/12/2021 (III + IV) | C64: =+C16+C62 -> 3.6323261e+08 | D64: =+D16+D62 -> 3.7322151e+10
B66: VI - DEUDA ELEGIBLE PENDIENTE DE REESTRUCTURACIÓN, AL 31/12/2021 (*) | C66: =+C14+C56 -> 2439303.2 | D66: =+D14+D56 -> 2.506384e+08
B68: VII - DEUDA BRUTA (EXCLUIDA LA ELEGIBLE PENDIENTE DE REESTRUCTURACIÓN), AL 31/12/2021 (V - VI) | C68: =+C64-C66 -> 3.6079331e+08 | D68: =+D64-D66 -> 3.7071512e+10
B71: (*) Se trata de la deuda elegible y no presentada al canje (Dtos. 1735/04 y 563/10) y no cancelada a la fecha en el marco de los acuerdos contemplados en la Ley n° 27.249.
B75: Efecto de las diferencias de cambio del período sobre el stock de Deuda de la Administración Central
B78: (En millones de u$s)
B79: Moneda | C79: Variación
C80: S/Saldos | D80: S/Atrasos | E80: Total
B82: Efecto de la variación de la relación Peso/dólar en deudas en pesos no ajustadas por CER | C82: -1614.0254 | D82: -0.019549265 | E82: =+C82+D82 -> -1614.0449
B83: Efecto de la variación de la relación Euro/dólar | C83: -125.86492 | D83: -16.891373 | E83: =+C83+D83 -> -142.7563
B84: Efecto de la variación de la relación DEG/dólar (1) | C84: -271.21696 | D84: 0 | E84: =+C84+D84 -> -271.21696
B85: Efecto de la variación de la relación Yen/dólar | C85: -22.148841 | D85: -0.95355509 | E85: =+C85+D85 -> -23.102396
B86: Efecto de la variación de la relación Franco Suizo/dólar | C86: 2.0663715 | D86: 0.34173821 | E86: =+C86+D86 -> 2.4081097
B87: Efecto de la variación de la relación Libra Esterlina/dólar | C87: 0.020286551 | D87: 0.014318435 | E87: =+C87+D87 -> 0.034604985
B88: Efecto de la variación de la relación del dólar con otras monedas (2) | C88: -0.15818091 | D88: 0 | E88: =+C88+D88 -> -0.15818091
B90: Total | C90: =SUM(C82:C89) -> -2031.3276 | D90: =SUM(D82:D89) -> -17.508421 | E90: =SUM(E82:E89) -> -2048.836
B92: (1) El DEG es una canasta de monedas.
B93: (2) Incluye: Corona Danesa, Corona Sueca, Dólar Canadiense, Dólar Australiano, Dinar Kuwaití y Dirham de los Emiratos Árabes Unidos.

Sheet A.2.3
A1: Indice
B2: MINISTERIO DE ECONOMÍA
B3: SECRETARÍA DE FINANZAS
B5: DEUDA BRUTA DE LA ADMINISTRACIÓN CENTRAL
B6: FLUJOS Y VARIACIONES
B7: ACUMULADO ENERO 2021 - DICIEMBRE 2021
C10: Miles de u$s | D10: Miles de $
B12: I - DEUDA BRUTA (EXCLUIDA LA ELEGIBLE PENDIENTE DE REESTRUCTURACIÓN), AL 31/12/2020 | C12: 3.3308176e+08 | D12: 2.8027164e+10
B14: II - DEUDA ELEGIBLE PENDIENTE DE REESTRUCTURACIÓN, AL 31/12/2020 (*) | C14: 2500462.6 | D14: 2.1040143e+08
B16: III - DEUDA BRUTA, AL 31/12/2020 (I + II) | C16: 3.3558222e+08 | D16: 2.8237566e+10
B18: VARIACIONES
B20: 1 - Financiamiento, canjes y emisiones | C20: =SUM(C22:C29) -> 97789473 | D20: =SUM(D22:D29) -> 9.0991923e+09
B22: Adelantos Transitorios del BCRA | C22: 24225131 | D22: 2297130000
B23: Letras del Tesoro - Organismos Públicos | C23: 37185533 | D23: 3.4542835e+09
B24: Letras Intransferibles | C24: 13763584 | D24: 1.212728e+09
B25: Otros | C25: 583603.18 | D25: 57218543
B26: Pagarés del Tesoro | C26: 860890.26 | D26: 85000000
B27: Préstamos Organismos Multilaterales | C27: 3600465.9 | D27: 3.4754346e+08
B28: Préstamos Organismos Oficiales | C28: 136979.45 | D28: 13266454
B29: TÍtulos del Tesoro | C29: 17433286 | D29: 1.6320223e+09
B31: 2 - Amortizaciones, canjes y cancelaciones | C31: =SUM(C33:C41) -> 72678259 | D31: =SUM(D33:D41) -> 6.6897569e+09
B33: Adelantos Transitorios del BCRA | C33: 14840296 | D33: 1.3845307e+09
B34: Bonos de Consolidación | C34: 141646.59 | D34: 13140812
B35: Letras del Tesoro - Organismos Públicos | C35: 25713881 | D35: 2.3734329e+09
B36: Letras Intransferibles | C36: 9625386.5 | D36: 8.0992815e+08
B37: Otros | C37: 59121.297 | D37: 5611898.1
B38: Pagarés del Tesoro | C38: 844962.76 | D38: 71108652
B39: Préstamos Organismos Multilaterales | C39: 5633512.8 | D39: 5.3846672e+08
B40: Préstamos Organismos Oficiales | C40: 612626.63 | D40: 56562824
B41: Títulos del Tesoro | C41: 15206825 | D41: 1.4369743e+09
B43: a) Operaciones netas del período ( 1 - 2 ) | C43: =+C20-C31 -> 25111214 | D43: =+D20-D31 -> 2.4094354e+09
B45: b) Emisión Bonos de Consolidación | C45: 41540.687 | D45: 3906642.8
B47: c) Avales netos de cancelaciones | C47: -2734.5085 | D47: 258197.08
B49: d) Letras en garantía | C49: -670075.77 | D49: -66159932
B51: e) Ajustes de valuación - Excluyendo la deuda elegible pendiente de reestructuración | C51: =SUM(C53:C56) -> 3231605.9 | D51: =SUM(D53:D56) -> 6.6969075e+09
B53: Tipo de Cambio (excluye deudas ajustables por CER) | C53: -8677715.8 | D53: 4.613254e+09
B54: Variación de la deuda ajustable por CER (efectos tipo de cambio y CER) | C54: 11441056 | D54: 2.0388003e+09
B55: Capitalización de Bonos del Canje, Préstamos Garantizados, Pagaré Banco Nación, Bonos de consolidación y Otros | C55: 260544.76 | D55: 23355727
B56: Otras Operaciones (Registro CCF, amparos y excepciones y otros ajustes) | C56: 207721.28 | D56: 21497481
B58: f) Ajustes de valuación sobre deuda elegible pendiente de reestructuración | C58: =SUM(C60:C62) -> -61159.459 | D58: =SUM(D60:D62) -> 40236973
B60: Tipo de Cambio (excluye deudas ajustables por CER) | C60: -68368.881 | D60: 38588020
B61: Variación de la deuda ajustable por CER (efectos tipo de cambio y CER) | C61: 11185.194 | D61: 2024348.1
B62: Otras Operaciones (Bajas Ley n° 27.249, amparos y excepciones y otros ajustes) | C62: -3975.7726 | D62: -375395.16
B64: IV - TOTAL VARIACIONES (a+b+c+d+e+f) | C64: =+C43+C45+C47++C51+C49+C58 -> 27650391 | D64: =+D43+D45+D47++D51+D49+D58 -> 9.0845849e+09
B66: V - DEUDA BRUTA, AL 31/12/2021 (III + IV) | C66: =+C16+C64 -> 3.6323261e+08 | D66: =+D16+D64 -> 3.7322151e+10
B68: VI - DEUDA ELEGIBLE PENDIENTE DE REESTRUCTURACIÓN, AL 31/12/2021 (*) | C68: =+C14+C58 -> 2439303.2 | D68: =+D14+D58 -> 2.506384e+08
B70: VII - DEUDA BRUTA (EXCLUIDA LA ELEGIBLE PENDIENTE DE REESTRUCTURACIÓN), AL 31/12/2021 (V - VI) | C70: =+C66-C68 -> 3.6079331e+08 | D70: =+D66-D68 -> 3.7071512e+10
B73: (*) Se trata de la deuda elegible y no presentada al canje (Dtos. 1735/04 y 563/10) y no cancelada a la fecha en el marco de los acuerdos contemplados en la Ley n° 27.249.

Sheet A.2.4
A1: Indice
B2: MINISTERIO DE ECONOMÍA
B3: SECRETARÍA DE FINANZAS
B6: Serie de Tipos de Cambio y Coeficiente de Estabilización de Referencia (CER)
B9: Fecha | C9: CER | D9: Coeficiente de pesificación (1) | E9: U$S / Peso | F9: Euro (Ref) / Peso
B10: 37290 | C10: 1 | D10: 1.399959 | E10: 1.4 | F10: 1.2064
B11: 37346 | C11: 1.0481 | D11: 1.4673678 | E11: 2.9 | F11: 2.5363
B12: 37437 | C12: 1.2495 | D12: 1.7492374 | E12: 3.8 | F12: 3.7549
B13: 37529 | C13: 1.3716 | D13: 1.9202837 | E13: 3.75 | F13: 3.6942
B14: 37621 | C14: 1.4053 | D14: 1.967407 | E14: 3.4 | F14: 3.5409
B15: 37711 | C15: 1.4341 | D15: 2.00774 | E15: 2.88 | F15: 3.1359
B16: 37802 | C16: 1.4404 | D16: 2.01656 | E16: 2.8 | F16: 3.2225
B17: 37894 | C17: 1.4448 | D17: 2.02272 | E17: 2.915 | F17: 3.397
B18: 37986 | C18: 1.4568 | D18: 2.03952 | E18: 2.9175 | F18: 3.6721
B19: 38077 | C19: 1.4678 | D19: 2.05492 | E19: 2.86 | F19: 3.5174
B20: 38168 | C20: 1.4983 | D20: 2.09762 | E20: 2.958 | F20: 3.6029
B21: 38260 | C21: 1.52 | D21: 2.128 | E21: 2.981 | F21: 3.7073
... B90: 44561 | C90: 38.6418 | D90: 54.09852 | E90: 102.75 | F90: 116.80118
B92: (1) Factor de conversión de dólares a pesos aplicable cuando a las obligaciones corresponde pesificarlas a un valor de 1,40 más CER (por ejemplo, depósitos bancarios y deudas del sector público, en dólares, con legislación nacional).

Sheet A.2.5
A1: Indice
B2: MINISTERIO DE ECONOMÍA
B3: SECRETARÍA DE FINANZAS
B6: SERIE DE DEUDA DEL SECTOR PÚBLICO NACIONAL
B7: POR AÑO Y POR INSTRUMENTO
B8: AJUSTADO POR OPERACIONES CON FECHA VALOR
B10: En millones de u$s - TC de fin de cada año
B11: INSTRUMENTO | C11: Saldo
C12: 31/12/92 (*) | D12: 34334 | E12: 34699 | F12: 35064 | G12: 35430 | H12: 35795 | I12: 36160 | J12: 36525 | K12: 36891 | L12: 37256 | M12: 37621 | N12: 37986 | O12: 38352 | P12: 38717 | Q12: 39082 | R12: 39447 | S12: 39813 | T12: 40178 | U12: 40543 | V12: 40908 | W12: 41274 | X12: 41639 | Y12: 42004 | Z12: 42369 | AA12: 42735 | AB12: 43100 | AC12: 43465 | AD12: 43830 | AE12: 44196 | AF12: 44561
B14: DEUDA PÚBLICA BRUTA + VALORES NEGOCIABLES VINCULADOS AL PBI (I + V) | C14: =+C17+C50 -> 63250 | D14: =+D17+D50 -> 71112 | E14: =+E17+E50 -> 81820 | F14: =+F17+F50 -> 88711 | G14: =+G17+G50 -> 99046 | H14: =+H17+H50 -> 103718 | I14: =+I17+I50 -> 114134 | J14: =+J17+J50 -> 123366 | ... AF14: =+AF17+AF50 -> 376214.95
B17: I- TOTAL DEUDA PÚBLICA BRUTA ( II+III +IV) | C17: =+C20+C38+C40 -> 63250 | D17: =+D20+D38+D40 -> 71112 | E17: =+E20+E38+E40 -> 81820 | F17: =+F20+F38+F40 -> 88711 | G17: =+G20+G38+G40 -> 99046 | H17: =+H20+H38+H40 -> 103718 | I17: =+I20+I38+I40 -> 114134 | J17: =+J20+J38+J40 -> 123366 | ... AF17: =+AF20+AF38+AF40 -> 363232.61
B20: II- DEUDA A VENCER | C20: =+C22+C24+C36 -> 54018 | D20: =+D22+D24+D36 -> 71112 | E20: =+E22+E24+E36 -> 81820 | F20: =+F22+F24+F36 -> 88711 | G20: =+G22+G24+G36 -> 99046 | H20: =+H22+H24+H36 -> 103718 | I20: =+I22+I24+I36 -> 114134 | J20: =+J22+J24+J36 -> 123366 | ... AF20: =+AF22+AF24+AF36 -> 360688.74
B22: TÍTULOS PUBLICOS Y LETRAS DEL TESORO | C22: 17184 | D22: 48401 | E22: 57109 | F22: 59048 | G22: 69393 | H22: 74801 | I22: 82363 | J22: 91555 | K22: 98895 | L22: 83051 | M22: 91656 | N22: 96885 | O22: 92224 | P22: 75628 | Q22: 92222 | R22: 99208 | S22: 99994 | T22: 100719 | U22: 115672 | V22: 125391 | W22: 133214 | X22: 137809 | Y22: 154775 | Z22: 160150 | AA22: 208400.33 | AB22: 256515.52 | AC22: 253709.2 | AD22: 225444.52 | AE22: 235536.1 | AF22: 260489.53
B24: PRÉSTAMOS | C24: =SUM(C26:C34) -> 36834 | D24: =SUM(D26:D34) -> 22711 | E24: =SUM(E26:E34) -> 24711 | F24: =SUM(F26:F34) -> 29663 | G24: =SUM(G26:G34) -> 29653 | H24: =SUM(H26:H34) -> 28917 | I24: =SUM(I26:I34) -> 31771 | J24: =SUM(J26:J34) -> 31811 | ... AF24: =SUM(AF26:AF34) -> 79050.318
B26: PRÉSTAMOS GARANTIZADOS | C26: 0 | D26: 0 | E26: 0 | F26: 0 | G26: 0 | H26: 0 | I26: 0 | J26: 0 | K26: 0 | L26: 21284 | M26: 11636 | N26: 14124 | O26: 14646 | P26: 14269 | Q26: 13981 | R26: 13037 | S26: 11995 | T26: 4541 | U26: 4425 | V26: 4121 | W26: 3753 | X26: 3035 | Y26: 2877 | Z26: 2076 | AA26: 1844.6747 | AB26: 1139.31 | AC26: 683.54 | AD26: 640.32505 | AE26: 605.0456 | AF26: 751.01537
B28: ORGANISMOS INTERNACIONALES | C28: 7279 | D28: 10944 | E28: 11627 | F28: 14862 | G28: 16257 | H28: 16795 | I28: 19167 | J28: 20311 | K28: 21757 | L28: 32357 | M28: 31376 | N28: 32115 | O28: 30601 | P28: 25260 | Q28: 15155 | R28: 15050 | S28: 14769 | T28: 16209 | U28: 16958 | V28: 17935 | W28: 18335 | X28: 19394 | Y28: 19857 | Z28: 19768 | AA28: 20230.498 | AB28: 21326.95 | AC28: 51037.44 | AD28: 68000.788 | AE28: 71268.154 | AF28: 68065.416
B30: ORGANISMOS OFICIALES | C30: 7380 | D30: 9698 | E30: 10870 | F30: 11904 | G30: 10063 | H30: 8311 | I30: 7634 | J30: 6258 | K30: 5017 | L30: 5876 | M30: 4935 | N30: 4428 | O30: 3389 | P30: 2952 | Q30: 1606 | R30: 1907 | S30: 1275 | T30: 1749 | U30: 1479 | V30: 1410 | W30: 849 | X30: 767 | Y30: 9026 | Z30: 9183 | AA30: 7844.7182 | AB30: 8280.38 | AC30: 6912.17 | AD30: 5398.0723 | AE30: 5487.7702 | AF30: 4709.8686
B32: BANCA COMERCIAL | C32: 21736 | D32: 1564 | E32: 1702 | F32: 1908 | G32: 2280 | H32: 2366 | I32: 3585 | J32: 3655 | K32: 2168 | L32: 715 | M32: 563 | N32: 527 | O32: 396 | P32: 294 | Q32: 859 | R32: 1165 | S32: 1453 | T32: 5102 | U32: 6055 | V32: 6586 | W32: 7273 | X32: 4702 | Y32: 4221 | Z32: 3126 | AA32: 1068.5919 | AB32: 2434.14 | AC32: 1194.16 | AD32: 2784.8972 | AE32: 2028.5695 | AF32: 2530.002
B34: OTROS ACREEDORES | C34: 439 | D34: 505 | E34: 512 | F34: 989 | G34: 1053 | H34: 1445 | I34: 1385 | J34: 1587 | K34: 1913 | L34: 911 | M34: 264 | N34: 273 | O34: 242 | P34: 1436 | Q34: 1539 | R34: 2098 | S34: 2449 | T34: 2928 | U34: 1797 | V34: 1682 | W34: 1960 | X34: 2986 | Y34: 1541 | Z34: 2839 | AA34: 3431.1811 | AB34: 3101.41 | AC34: 2448.23 | AD34: 4019.7644 | AE34: 3069.9354 | AF34: 2994.0159
B36: ADELANTOS TRANSITORIOS BCRA | C36: 0 | D36: 0 | E36: 0 | F36: 0 | G36: 0 | H36: 0 | I36: 0 | J36: 0 | K36: 0 | L36: 0 | M36: 1079 | N36: 2526 | O36: 4468 | P36: 5263 | Q36: 5986 | R36: 6774 | S36: 7700 | T36: 9626 | U36: 11615 | V36: 15597 | W36: 25972 | X36: 28002 | Y36: 29402 | Z36: 25517 | AA36: 24115.153 | AB36: 25153.14 | AC36: 13296.82 | AD36: 14237.082 | AE36: 14979.5 | AF36: 21148.899
B38: III- DEUDA EN SITUACIÓN DE PAGO DIFERIDO | C38: 9232 | D38: 0 | E38: 0 | F38: 0 | G38: 0 | H38: 0 | I38: 0 | J38: 0 | K38: 0 | L38: 28 | M38: 11704.252 | N38: 28434.741 | O38: 46195.829 | P38: 5157.8648 | Q38: 6750.8946 | R38: 7271.2359 | S38: 8461.1905 | T38: 8678.4855 | U38: 9062.1741 | V38: 9265.5751 | W38: 9376.5018 | X38: 9440.1029 | Y38: 49 | Z38: 44 | AA38: 42.906828 | AB38: 107.43 | AC38: 104.84 | AD38: 103.95523 | AE38: 106.67697 | AF38: 104.56186
B40: IV- DEUDA ELEGIBLE PENDIENTE DE REESTRUCTURACIÓN | C40: 0 | D40: 0 | E40: 0 | F40: 0 | G40: 0 | H40: 0 | I40: 0 | J40: 0 | K40: 0 | L40: 0 | M40: =+M42+M44+M46 -> 5 | N40: =+N42+N44+N46 -> 41 | O40: =+O42+O44+O46 -> 132 | P40: =+P42+P44+P46 -> 24011 | Q40: =+Q42+Q44+Q46 -> 27012 | R40: =+R42+R44+R46 -> 30360 | S40: =+S42+S44+S46 -> 31036 | T40: =+T42+T44+T46 -> 32531 | ... AF40: =+AF42+AF44+AF46 -> 2439.3032
B42: CAPITAL | M42: 0 | N42: 0 | O42: 0 | P42: 17966 | Q42: 19119 | R42: 20459 | S42: 19956 | T42: 20108 | U42: 6809 | V42: 6579 | W42: 6608 | X42: 6670 | Y42: 6352 | Z42: 6101 | AA42: 3613.9822 | AB42: 1258.4 | AC42: 1218.78 | AD42: 1058.0797 | AE42: 1081.386 | AF42: 1059.021
B44: MORA DE INTERÉS | M44: 0 | N44: 0 | O44: 0 | P44: 5591 | Q44: 6958 | R44: 8398 | S44: 9028 | T44: 9700 | U44: 4409 | V44: 4599 | W44: 4874 | X44: 5168 | Y44: 5280 | Z44: 5420 | AA44: 2510.2886 | AB44: 1022.69 | AC44: 1012.57 | AD44: 863.85757 | AE44: 878.9412 | AF44: 865.68332
B46: INTERESES COMPENSATORIOS (**) | M46: 5 | N46: 41 | O46: 132 | P46: 454 | Q46: 935 | R46: 1503 | S46: 2052 | T46: 2723 | U46: 3340 | V46: 3990 | W46: 4707 | X46: 5467 | Y46: 5945 | Z46: 6441 | AA46: 2343.8065 | AB46: 595.42 | AC46: 574.07 | AD46: 513.27222 | AE46: 540.13542 | AF46: 514.5988
B50: V- VALORES NEGOCIABLES VINCULADOS AL PBI (***) | C50: 0 | D50: 0 | E50: 0 | F50: 0 | G50: 0 | H50: 0 | I50: 0 | J50: 0 | K50: 0 | L50: 0 | M50: 0 | N50: 0 | O50: 0 | P50: 28784.426 | Q50: 29052.852 | R50: 28175.633 | S50: 19871.956 | T50: 18112.885 | U50: 22730.046 | V50: 19725.328 | W50: 15942.385 | X50: 15761.738 | Y50: 14430.352 | Z50: 13324.151 | AA50: 13001.694 | AB50: 13772.18 | AC50: 13192.94 | AD50: 12962.732 | AE50: 13514.386 | AF50: 12982.343
B53: (*) Los saldos de deuda al 31/12/92 se estimaron sobre la base de ajustar los registros obrante, retrotrayendo el efecto que sobre los saldos y la composición, produjera el Plan Brady.
B54: (**) Intereses compensatorios estimados, devengados e impagos con posterioridad a la fecha de vencimiento de cada título.
B55: (***) Valor remanente total. Es la diferencia entre el máximo a pagar de 48 unidades por cada 100 de valor nocional y la suma de los montos pagados hasta la actualidad, de acuerdo con las condiciones establecidas en las respectivas normas de emisión.

Sheet A.3.1
A1: Indice
B2: MINISTERIO DE ECONOMÍA
B3: SECRETARÍA DE FINANZAS
B6: PERFIL DE VENCIMIENTOS DE CAPITAL E INTERÉS DE LA DEUDA BRUTA DE LA ADMINISTRACIÓN CENTRAL
B7: PERIODO PROYECTADO ENERO 2022 A DICIEMBRE 2022
B8: DEUDA EN SITUACIÓN DE PAGO NORMAL (1)
B10: (En miles de U$S - Tipo de cambio 31/12/2021)
C11: 2022 | O11: Total
C12: Enero | D12: Febrero | E12: Marzo | F12: Abril | G12: Mayo | H12: Junio | I12: Julio | J12: Agosto | K12: Septiembre | L12: Octubre | M12: Noviembre | N12: Diciembre
B14: TÍTULOS PÚBLICOS | C14: =+C15+C16 -> 833577.29 | D14: =+D15+D16 -> 116944.44 | E14: =+E15+E16 -> 5090056.1 | F14: =+F15+F16 -> 8595798.4 | G14: =+G15+G16 -> 4134470.4 | H14: =+H15+H16 -> 2340439.9 | I14: =+I15+I16 -> 754141.37 | J14: =+J15+J16 -> 116340.78 | ... O14: =+O15+O16 -> 31925377
B15: CAPITAL | C15: 47679.392 | D15: 11216.185 | E15: 4882425.7 | F15: 8354309.3 | G15: 3611398.8 | H15: 2091938.2 | I15: 33386.581 | J15: 11199.659 | K15: 6452338.1 | L15: 54937.645 | M15: 2706994 | N15: 8401.6925 | O15: =+SUM(C15:N15) -> 28266225
B16: INTERÉS | C16: 785897.9 | D16: 105728.25 | E16: 207630.39 | F16: 241489.12 | G16: 523071.61 | H16: 248501.66 | I16: 720754.79 | J16: 105141.12 | K16: 178961.65 | L16: 164830.26 | M16: 128849.51 | N16: 248295.7 | O16: =+SUM(C16:N16) -> 3659152
B19: LETRAS DEL TESORO | C19: =+C20+C21 -> 5145329 | D19: =+D20+D21 -> 3956744.6 | E19: =+E20+E21 -> 3907782.7 | F19: =+F20+F21 -> 2658875.1 | G19: =+G20+G21 -> 2290399 | H19: =+H20+H21 -> 2578693.8 | I19: =+I20+I21 -> 1761872.9 | J19: =+J20+J21 -> 804173.27 | ... O19: =+O20+O21 -> 23632024
B20: CAPITAL | C20: 5100709.6 | D20: 3956744.6 | E20: 3907782.7 | F20: 2634172.1 | G20: 2290399 | H20: 2578693.8 | I20: 1761872.9 | J20: 804173.27 | K20: 124646.08 | L20: 57594.19 | M20: 0 | N20: 345913.78 | O20: =+SUM(C20:N20) -> 23562702
B21: INTERÉS | C21: 44619.392 | D21: 0 | E21: 0 | F21: 24702.997 | G21: 0 | H21: 0 | I21: 0 | J21: 0 | K21: 0 | L21: 0 | M21: 0 | N21: 0 | O21: =+SUM(C21:N21) -> 69322.389
B24: ORGANISMOS INTERNACIONALES | C24: =+C25+C26 -> 855069.86 | D24: =+D25+D26 -> 530620.07 | E24: =+E25+E26 -> 3146811 | F24: =+F25+F26 -> 859876.55 | G24: =+G25+G26 -> 524691.66 | H24: =+H25+H26 -> 3008574.9 | I24: =+I25+I26 -> 2206737.7 | J24: =+J25+J26 -> 459733.71 | ... O24: =+O25+O26 -> 21087950
B25: CAPITAL | C25: 826586.15 | D25: 142398.57 | E25: 3063219.5 | F25: 821068.3 | G25: 142806.39 | H25: 2977492.4 | I25: 2178282.3 | J25: 141091.95 | K25: 3062392.9 | L25: 2875799.5 | M25: 145612.54 | N25: 2956838.5 | O25: =+SUM(C25:N25) -> 19333589
B26: INTERÉS | C26: 28483.707 | D26: 388221.5 | E26: 83591.479 | F26: 38808.254 | G26: 381885.27 | H26: 31082.42 | I26: 28455.348 | J26: 318641.76 | K26: 84886.885 | L26: 40278.921 | M26: 300270.03 | N26: 29754.94 | O26: =+SUM(C26:N26) -> 1754360.5
B29: ORGANISMOS OFICIALES | C29: =+C30+C31 -> 198054.71 | D29: =+D30+D31 -> 189968.73 | E29: =+E30+E31 -> 207.7242 | F29: =+F30+F31 -> 6106.2279 | G29: =+G30+G31 -> 1858715.9 | H29: =+H30+H31 -> 22965.071 | I29: =+I30+I31 -> 196633.43 | J29: =+J30+J31 -> 294.65829 | ... O29: =+O30+O31 -> 2509328
B30: CAPITAL | C30: 170027.45 | D30: 189871.85 | E30: 121.29997 | F30: 4510.1276 | G30: 1531678.3 | H30: 420.75657 | I30: 170027.45 | J30: 185.79546 | K30: 121.29997 | L30: 4510.1276 | M30: 7300.4244 | N30: 1109.598 | O30: =+SUM(C30:N30) -> 2079884.4
B31: INTERÉS | C31: 28027.254 | D31: 96.887531 | E31: 86.424226 | F31: 1596.1003 | G31: 327037.61 | H31: 22544.315 | I31: 26605.978 | J31: 108.86282 | K31: 132.69062 | L31: 1731.4232 | M31: 424.03504 | N31: 21051.933 | O31: =+SUM(C31:N31) -> 429443.52
B34: PRESTAMOS GARANTIZADOS | C34: =+C35+C36 -> 3206.5201 | D34: =+D35+D36 -> 3206.5201 | E34: =+E35+E36 -> 2974.6257 | F34: =+F35+F36 -> 3206.5201 | G34: =+G35+G36 -> 3129.222 | H34: =+H35+H36 -> 3206.5201 | I34: =+I35+I36 -> 3129.222 | J34: =+J35+J36 -> 3206.5201 | ... O34: =+O35+O36 -> 37937.154
B35: CAPITAL | C35: 0 | D35: 0 | E35: 0 | F35: 0 | G35: 0 | H35: 0 | I35: 0 | J35: 0 | K35: 0 | L35: 0 | M35: 0 | N35: 0 | O35: =+SUM(C35:N35) -> 0
B36: INTERÉS | C36: 3206.5201 | D36: 3206.5201 | E36: 2974.6257 | F36: 3206.5201 | G36: 3129.222 | H36: 3206.5201 | I36: 3129.222 | J36: 3206.5201 | K36: 3206.5201 | L36: 3129.222 | M36: 3206.5201 | N36: 3129.222 | O36: =+SUM(C36:N36) -> 37937.154
B39: BANCA COMERCIAL | C39: =+C40+C41 -> 1010.7206 | D39: =+D40+D41 -> 2742.4245 | E39: =+E40+E41 -> 15.251372 | F39: =+F40+F41 -> 6061.9596 | G39: =+G40+G41 -> 26466.642 | H39: =+H40+H41 -> 767.87226 | I39: =+I40+I41 -> 997.61618 | J39: =+J40+J41 -> 2734.4124 | ... O39: =+O40+O41 -> 2166394.5
B40: CAPITAL | C40: 925.86266 | D40: 2572.7904 | E40: 13.621402 | F40: 5178.7598 | G40: 24682.978 | H40: 662.46742 | I40: 926.36181 | J40: 2573.2691 | K40: 14.007451 | L40: 5179.2605 | M40: 24683.437 | N40: 2093120.4 | O40: =+SUM(C40:N40) -> 2160533.2
B41: INTERÉS | C41: 84.85794 | D41: 169.6341 | E41: 1.6299703 | F41: 883.19977 | G41: 1783.6646 | H41: 105.40484 | I41: 71.254371 | J41: 161.14336 | K41: 1.2439211 | L41: 853.12798 | M41: 1651.6172 | N41: 94.511084 | O41: =+SUM(C41:N41) -> 5861.2891
B44: AVALES | C44: =+C45+C46 -> 36254.777 | D44: =+D45+D46 -> 11708.057 | E44: =+E45+E46 -> 16824.013 | F44: =+F45+F46 -> 11618.361 | G44: =+G45+G46 -> 9329.2731 | H44: =+H45+H46 -> 20588.246 | I44: =+I45+I46 -> 13834.926 | J44: =+J45+J46 -> 14798.989 | ... O44: =+O45+O46 -> 341795.31
B45: CAPITAL | C45: 33231.05 | D45: 8266.8029 | E45: 12447.513 | F45: 8709.7925 | G45: 6691.3432 | H45: 17254.671 | I45: 11094.814 | J45: 11664.555 | K45: 146762.9 | L45: 11301.291 | M45: 12033.153 | N45: 24677.862 | O45: =+SUM(C45:N45) -> 304135.75
B46: INTERÉS | C46: 3023.728 | D46: 3441.2543 | E46: 4376.4993 | F46: 2908.5686 | G46: 2637.9299 | H46: 3333.575 | I46: 2740.1114 | J46: 3134.434 | K46: 3970.6791 | L46: 2644.4555 | M46: 2423.8072 | N46: 3024.5197 | O46: =+SUM(C46:N46) -> 37659.562
B49: PAGARÉS DEL TESORO | C49: =+C50+C51 -> 0 | D49: =+D50+D51 -> 0 | E49: =+E50+E51 -> 830601.21 | F49: =+F50+F51 -> 0 | G49: =+G50+G51 -> 0 | H49: =+H50+H51 -> 0 | I49: =+I50+I51 -> 0 | J49: =+J50+J51 -> 0 | ... O49: =+O50+O51 -> 833951.82
B50: CAPITAL | C50: 0 | D50: 0 | E50: 827250.61 | F50: 0 | G50: 0 | H50: 0 | I50: 0 | J50: 0 | K50: 0 | L50: 0 | M50: 0 | N50: 0 | O50: =+SUM(C50:N50) -> 827250.61
B51: INTERÉS | C51: 0 | D51: 0 | E51: 3350.6061 | F51: 0 | G51: 0 | H51: 0 | I51: 0 | J51: 0 | K51: 3350.6061 | L51: 0 | M51: 0 | N51: 0 | O51: =+SUM(C51:N51) -> 6701.2121
B54: ADELANTOS TRANSITORIOS BCRA | C54: =+C55+C56 -> 0 | D54: =+D55+D56 -> 389294.4 | E54: =+E55+E56 -> 1415273.4 | F54: =+F55+F56 -> 1016058.4 | G54: =+G55+G56 -> 220437.96 | H54: =+H55+H56 -> 396107.06 | I54: =+I55+I56 -> 1304136.3 | J54: =+J55+J56 -> 0 | ... O54: =+O55+O56 -> 16448169
B55: CAPITAL | C55: 0 | D55: 389294.4 | E55: 1415273.4 | F55: 1016058.4 | G55: 220437.96 | H55: 396107.06 | I55: 1304136.3 | J55: 0 | K55: 271338.2 | L55: 3990267.6 | M55: 1265206.8 | N55: 6180048.7 | O55: =+SUM(C55:N55) -> 16448169
B56: INTERÉS | C56: 0 | D56: 0 | E56: 0 | F56: 0 | G56: 0 | H56: 0 | I56: 0 | J56: 0 | K56: 0 | L56: 0 | M56: 0 | N56: 0 | O56: =+SUM(C56:N56) -> 0
B59: TOTAL | C59: =+C60+C61 -> 7072502.9 | D59: =+D60+D61 -> 5201229.3 | E59: =+E60+E61 -> 14410546 | F59: =+F60+F61 -> 13157602 | G59: =+G60+G61 -> 9067640 | H59: =+H60+H61 -> 8371343.3 | I59: =+I60+I61 -> 6241483.4 | J59: =+J60+J61 -> 1401282.3 | ... O59: =+O60+O61 -> 98982927
B60: CAPITAL | C60: =+C15+C20+C25+C30+C35+C40+C45+C50+C55 -> 6179159.5 | D60: =+D15+D20+D25+D30+D35+D40+D45+D50+D55 -> 4700365.2 | E60: =+E15+E20+E25+E30+E35+E40+E45+E50+E55 -> 14108534 | F60: =+F15+F20+F25+F30+F35+F40+F45+F50+F55 -> 12844007 | G60: =+G15+G20+G25+G30+G35+G40+G45+G50+G55 -> 7828094.7 | H60: =+H15+H20+H25+H30+H35+H40+H45+H50+H55 -> 8062569.4 | I60: =+I15+I20+I25+I30+I35+I40+I45+I50+I55 -> 5459726.7 | J60: =+J15+J20+J25+J30+J35+J40+J45+J50+J55 -> 970888.5 | ... O60: =+O15+O20+O25+O30+O35+O40+O45+O50+O55 -> 92982489
B61: INTERÉS | C61: =+C16+C21+C26+C31+C36+C41+C46+C51+C56 -> 893343.35 | D61: =+D16+D21+D26+D31+D36+D41+D46+D51+D56 -> 500864.05 | E61: =+E16+E21+E26+E31+E36+E41+E46+E51+E56 -> 302011.66 | F61: =+F16+F21+F26+F31+F36+F41+F46+F51+F56 -> 313594.76 | G61: =+G16+G21+G26+G31+G36+G41+G46+G51+G56 -> 1239545.3 | H61: =+H16+H21+H26+H31+H36+H41+H46+H51+H56 -> 308773.89 | I61: =+I16+I21+I26+I31+I36+I41+I46+I51+I56 -> 781756.7 | J61: =+J16+J21+J26+J31+J36+J41+J46+J51+J56 -> 430393.84 | ... O61: =+O16+O21+O26+O31+O36+O41+O46+O51+O56 -> 6000437.6
B64: (1) No incluye estimación del pago eventual por los Valores Negociables Vinculadas al PBI.

Sheet A.3.2
A1: Indice
B2: MINISTERIO DE ECONOMÍA
B3: SECRETARÍA DE FINANZAS
B6: PERFIL MENSUAL DE VENCIMIENTOS DE CAPITAL DE LA DEUDA BRUTA DE LA ADMINISTRACIÓN CENTRAL
B8: (En millones de U$S - Stock de deuda y tipo de cambio 31/12/2021)
C9: 44562 | D9: 44593 | E9: 44621 | F9: 44652 | G9: 44682 | H9: 44713 | I9: 44743 | J9: 44774 | K9: 44805 | L9: 44835 | M9: 44866 | N9: 44896 | O9: 2022
B11: PERFIL DE VENCIMIENTOS DE LA DEUDA EN SITUACIÓN DE PAGO NORMAL
B13: TOTAL | C13: =+C14+C15 -> 6179.1595 | D13: =+D14+D15 -> 4700.3652 | E13: =+E14+E15 -> 14108.534 | F13: =+F14+F15 -> 12844.007 | G13: =+G14+G15 -> 7828.0947 | H13: =+H14+H15 -> 8062.5694 | I13: =+I14+I15 -> 5459.7267 | J13: =+J14+J15 -> 970.8885 | ... O13: =+O14+O15 -> 92982.489
B14: CORTO PLAZO | C14: 5047.9506 | D14: 3956.7446 | E14: 5712.3505 | F14: 3592.5987 | G14: 324.2966 | H14: 2979.8127 | I14: 3015.9267 | J14: 804.17327 | K14: 387.42145 | L14: 3990.2676 | M14: 1265.2068 | N14: 3844.2822 | O14: =+SUM(C14:N14) -> 34921.032
B15: MEDIANO Y LARGO PLAZO | C15: 1131.209 | D15: 743.6206 | E15: 8396.1839 | F15: 9251.4081 | G15: 7503.7981 | H15: 5082.7567 | I15: 2443.8 | J15: 166.71523 | K15: 9670.1921 | L15: 3009.322 | M15: 2896.6236 | N15: 7765.8282 | O15: =+SUM(C15:N15) -> 58061.457
B17: PRÉSTAMOS | C17: =+C18+C23+C31+C32+C28 -> 1030.7705 | D17: =+D18+D23+D31+D32+D28 -> 343.11001 | E17: =+E18+E23+E31+E32+E28 -> 3903.0525 | F17: =+F18+F23+F31+F32+F28 -> 839.46698 | G17: =+G18+G23+G31+G32+G28 -> 1705.859 | H17: =+H18+H23+H31+H32+H28 -> 2995.8303 | I17: =+I18+I23+I31+I32+I28 -> 2360.331 | J17: =+J18+J23+J31+J32+J28 -> 155.51557 | ... N17: =+N18+N23+N31+N32+N28 -> 5075.7463 | O17: =+SUM(C17:N17) -> 24705.393
B18: Organismos Internacionales | C18: =SUM(C19:C22) -> 826.58615 | D18: =SUM(D19:D22) -> 142.39857 | E18: =SUM(E19:E22) -> 3063.2195 | F18: =SUM(F19:F22) -> 821.0683 | G18: =SUM(G19:G22) -> 142.80639 | H18: =SUM(H19:H22) -> 2977.4924 | I18: =SUM(I19:I22) -> 2178.2823 | J18: =SUM(J19:J22) -> 141.09195 | ... N18: =SUM(N19:N22) -> 2956.8385 | O18: =+SUM(C18:N18) -> 19333.589
B19: . BIRF | C19: 15.201049 | D19: 2.8298787 | E19: 61.943313 | F19: 27.209996 | G19: 13.493342 | H19: 48.395584 | I19: 2.2383819 | J19: 3.2351618 | K19: 57.255741 | L19: 33.031532 | M19: 13.510603 | N19: 27.958372 | O19: =+SUM(C19:N19) -> 306.30295
B20: . BID | C20: 48.714193 | D20: 39.92362 | E20: 136.9617 | F20: 57.459383 | G20: 108.68356 | H20: 26.737115 | I20: 48.714193 | J20: 38.164354 | K20: 137.8897 | L20: 59.416431 | M20: 110.46887 | N20: 26.737115 | O20: =+SUM(C20:N20) -> 839.87023
B21: . FMI | C21: 717.28481 | D21: 0 | E21: 2819.0535 | F21: 717.28481 | G21: 0 | H21: 2819.0535 | I21: 2081.8754 | J21: 0 | K21: 2819.0535 | L21: 2764.1707 | M21: 0 | N21: 2819.0535 | O21: =+SUM(C21:N21) -> 17556.83
B22: . Otros | C22: 45.386093 | D22: 99.64507 | E22: 45.260953 | F22: 19.114103 | G22: 20.629486 | H22: 83.306204 | I22: 45.454311 | J22: 99.692434 | K22: 48.193935 | L22: 19.180771 | M22: 21.633068 | N22: 83.089455 | O22: =+SUM(C22:N22) -> 630.58588
B23: Banca Comercial | C23: =+C24+C26 -> 0.92586266 | D23: =+D24+D26 -> 2.5727904 | E23: =+E24+E26 -> 0.013621402 | F23: =+F24+F26 -> 5.1787598 | G23: =+G24+G26 -> 24.682978 | H23: =+H24+H26 -> 0.66246742 | I23: =+I24+I26 -> 0.92636181 | J23: =+J24+J26 -> 2.5732691 | ... N23: =+N24+N26 -> 2093.1204 | O23: =+SUM(C23:N23) -> 2160.5332
B24: . En moneda nacional | C24: =+C25 -> 0 | D24: =+D25 -> 0 | E24: =+E25 -> 0 | F24: =+F25 -> 0 | G24: =+G25 -> 0 | H24: =+H25 -> 0 | I24: =+I25 -> 0 | J24: =+J25 -> 0 | ... N24: =+N25 -> 2092.4574 | O24: =+SUM(C24:N24) -> 2092.4574
B25: FUCO | C25: 0 | D25: 0 | E25: 0 | F25: 0 | G25: 0 | H25: 0 | I25: 0 | J25: 0 | K25: 0 | L25: 0 | M25: 0 | N25: 2092.4574 | O25: =+SUM(C25:N25) -> 2092.4574
B26: . En moneda extranjera | C26: =+C27 -> 0.92586266 | D26: =+D27 -> 2.5727904 | E26: =+E27 -> 0.013621402 | F26: =+F27 -> 5.1787598 | G26: =+G27 -> 24.682978 | H26: =+H27 -> 0.66246742 | I26: =+I27 -> 0.92636181 | J26: =+J27 -> 2.5732691 | ... N26: =+N27 -> 0.66296935 | O26: =+SUM(C26:N26) -> 68.075784
B27: Otros | C27: 0.92586266 | D27: 2.5727904 | E27: 0.013621402 | F27: 5.1787598 | G27: 24.682978 | H27: 0.66246742 | I27: 0.92636181 | J27: 2.5732691 | K27: 0.014007451 | L27: 5.1792605 | M27: 24.683437 | N27: 0.66296935 | O27: =+SUM(C27:N27) -> 68.075784
B28: Pagarés | C28: =+C29 -> 0 | D28: =+D29 -> 0 | E28: =+E29 -> 827.25061 | F28: =+F29 -> 0 | G28: =+G29 -> 0 | H28: =+H29 -> 0 | I28: =+I29 -> 0 | J28: =+J29 -> 0 | ... N28: =+N29 -> 0 | O28: =+SUM(C28:N28) -> 827.25061
B29: . En moneda nacional no ajustable por CER | C29: =+C30 -> 0 | D29: =+D30 -> 0 | E29: =+E30 -> 827.25061 | F29: =+F30 -> 0 | G29: =+G30 -> 0 | H29: =+H30 -> 0 | I29: =+I30 -> 0 | J29: =+J30 -> 0 | ... N29: =+N30 -> 0 | O29: =+SUM(C29:N29) -> 827.25061
B30: Pagaré CUT | C30: 0 | D30: 0 | E30: 827.25061 | F30: 0 | G30: 0 | H30: 0 | I30: 0 | J30: 0 | K30: 0 | L30: 0 | M30: 0 | N30: 0 | O30: =+SUM(C30:N30) -> 827.25061
B31: Organismos Oficiales | C31: 170.02745 | D31: 189.87185 | E31: 0.12129997 | F31: 4.5101276 | G31: 1531.6783 | H31: 0.42075657 | I31: 170.02745 | J31: 0.18579546 | K31: 0.12129997 | L31: 4.5101276 | M31: 7.3004244 | N31: 1.109598 | O31: =+SUM(C31:N31) -> 2079.8844
B32: Avales | C32: =+C33+C34 -> 33.23105 | D32: =+D33+D34 -> 8.2668029 | E32: =+E33+E34 -> 12.447513 | F32: =+F33+F34 -> 8.7097925 | G32: =+G33+G34 -> 6.6913432 | H32: =+H33+H34 -> 17.254671 | I32: =+I33+I34 -> 11.094814 | J32: =+J33+J34 -> 11.664555 | ... N32: =+N33+N34 -> 24.677862 | O32: =+SUM(C32:N32) -> 304.13575
B33: . En moneda nacional | C33: 0.82147182 | D33: 0.82969079 | E33: 0.83735374 | F33: 0.8470599 | G33: 0.85694681 | H33: 0.86920258 | I33: 0.88148562 | J33: 0.89431767 | K33: 0.90154462 | L33: 0.86368366 | M33: 0.81482585 | N33: 0.80346654 | O33: =+SUM(C33:N33) -> 10.22105
B34: . En moneda extranjera | C34: 32.409578 | D34: 7.4371121 | E34: 11.61016 | F34: 7.8627326 | G34: 5.8343964 | H34: 16.385469 | I34: 10.213328 | J34: 10.770238 | K34: 145.86136 | L34: 10.437607 | M34: 11.218327 | N34: 23.874395 | O34: =+SUM(C34:N34) -> 293.9147
B36: ADELANTOS TRANSITORIOS BCRA | C36: 0 | D36: 389.2944 | E36: 1415.2734 | F36: 1016.0584 | G36: 220.43796 | H36: 396.10706 | I36: 1304.1363 | J36: 0 | K36: 271.3382 | L36: 3990.2676 | M36: 1265.2068 | N36: 6180.0487 | O36: =+SUM(C36:N36) -> 16448.169
B38: TÍTULOS PÚBLICOS Y LETRAS DEL TESORO | C38: =SUM(C39:C62)+C65 -> 5148.389 | D38: =SUM(D39:D62)+D65 -> 3967.9608 | E38: =SUM(E39:E62)+E65 -> 8790.2084 | F38: =SUM(F39:F62)+F65 -> 10988.481 | G38: =SUM(G39:G62)+G65 -> 5901.7978 | H38: =SUM(H39:H62)+H65 -> 4670.632 | I38: =SUM(I39:I62)+I65 -> 1795.2595 | J38: =SUM(J39:J62)+J65 -> 815.37293 | ... N38: =SUM(N39:N62)+N65 -> 354.31547 | O38: =+SUM(C38:N38) -> 51828.927 | P38: =+O38-A.3.7!C42 -> 0
B39: BONAR/$/6,72763943919512%/31-12-2028 | C39: 3.1778018 | D39: 3.3215243 | E39: 3.1519069 | F39: 3.2319102 | G39: 3.2500294 | H39: 3.2682503 | I39: 3.2865733 | J39: 3.304999 | K39: 3.3235281 | L39: 3.342161 | M39: 3.3608984 | N39: 3.3797408 | O39: =+SUM(C39:N39) -> 39.399323
B40: BONAR/$/BADLAR+200PB/03-04-2022 | C40: 0 | D40: 0 | E40: 0 | F40: 675.5248 | G40: 0 | H40: 0 | I40: 0 | J40: 0 | K40: 0 | L40: 0 | M40: 0 | N40: 0 | O40: =+SUM(C40:N40) -> 675.5248
B41: BONAR/DLK/4,50%U$S-2,35%$/13-02-2020 | C41: 0 | D41: 0 | E41: 0 | F41: 0.739069 | G41: 0 | H41: 0 | I41: 0 | J41: 0 | K41: 0 | L41: 0 | M41: 0 | N41: 0 | O41: =+SUM(C41:N41) -> 0.739069
B42: BONAR/U$S/1,00%/05-08-2023 | C42: 0 | D42: 0 | E42: 0 | F42: 0 | G42: 0 | H42: 0 | I42: 0 | J42: 0 | K42: 0 | L42: 0 | M42: 0 | N42: 0 | O42: =+SUM(C42:N42) -> 0
B43: BONAR/U$S/5,75%/18-04-2025 | C43: 0 | D43: 0 | E43: 0 | F43: 0 | G43: 0 | H43: 0 | I43: 0 | J43: 0 | K43: 0 | L43: 0 | M43: 0 | N43: 0 | O43: =+SUM(C43:N43) -> 0
B44: BONAR/U$S/8,00%/08-10-2020 | C44: 0 | D44: 0 | E44: 0 | F44: 7.92443 | G44: 0 | H44: 0 | I44: 0 | J44: 0 | K44: 0 | L44: 0 | M44: 0 | N44: 0 | O44: =+SUM(C44:N44) -> 7.92443
B45: BONAR/U$S/8,75%/07-05-2024 | C45: 0 | D45: 0 | E45: 0 | F45: 10.409319 | G45: 5.2046593 | H45: 0 | I45: 0 | J45: 0 | K45: 0 | L45: 0 | M45: 0 | N45: 0 | O45: =+SUM(C45:N45) -> 15.613978
B46: BONCER/$/1,20%+CER/18-03-2022 | C46: 0 | D46: 0 | E46: 4874.2519 | F46: 0 | G46: 0 | H46: 0 | I46: 0 | J46: 0 | K46: 0 | L46: 0 | M46: 0 | N46: 0 | O46: =+SUM(C46:N46) -> 4874.2519
B47: BONCER/$+CER//1,45%/13-08-2023 | C47: 0 | D47: 0 | E47: 0 | F47: 0 | G47: 0 | H47: 0 | I47: 0 | J47: 0 | K47: 0 | L47: 0 | M47: 0 | N47: 0 | O47: =+SUM(C47:N47) -> 0
B48: BONCER/$+CER/1,30%/20-09-2022 | C48: 0 | D48: 0 | E48: 0 | F48: 0 | G48: 0 | H48: 0 | I48: 0 | J48: 0 | K48: 6443.9926 | L48: 0 | M48: 0 | N48: 0 | O48: =+SUM(C48:N48) -> 6443.9926
B49: BONCER/$+CER/1,40%/25-03-2023 | C49: 0 | D49: 0 | E49: 0 | F49: 0 | G49: 0 | H49: 0 | I49: 0 | J49: 0 | K49: 0 | L49: 0 | M49: 0 | N49: 0 | O49: =+SUM(C49:N49) -> 0
B50: BONCER/$+CER/4,00%/06-03-2023 | C50: 0 | D50: 0 | E50: 0 | F50: 0 | G50: 0 | H50: 0 | I50: 0 | J50: 0 | K50: 0 | L50: 0 | M50: 0 | N50: 0 | O50: =+SUM(C50:N50) -> 0
... B61: Letras en Garantía | C61: 0 | D61: 0 | E61: 0 | F61: 0 | G61: 0 | H61: 0 | I61: 0 | J61: 0 | K61: 0 | L61: 0 | M61: 0 | N61: 345.91377 | O61: =+SUM(C61:N61) -> 345.91377
B62: LETRAS DEL TESORO | C62: =+C63+C64 -> 5100.7096 | D62: =+D63+D64 -> 3956.7446 | E62: =+E63+E64 -> 3907.7827 | F62: =+F63+F64 -> 2634.1769 | G62: =+G63+G64 -> 2290.399 | H62: =+H63+H64 -> 2578.6938 | I62: =+I63+I64 -> 1761.8729 | J62: =+J63+J64 -> 804.17327 | ... N62: =+N63+N64 -> 0 | O62: =+SUM(C62:N62) -> 23216.793
B63: . En moneda nacional | C63: 5047.9506 | D63: 3956.7446 | E63: 2811.568 | F63: 2576.5481 | G63: 2290.399 | H63: 2578.6938 | I63: 1711.7905 | J63: 804.17327 | K63: 124.64608 | L63: 0 | M63: 0 | N63: 0 | O63: =+SUM(C63:N63) -> 21902.514
B64: . En moneda extranjera | C64: 52.759046 | D64: 0 | E64: 1096.2147 | F64: 57.628842 | G64: 0 | H64: 0 | I64: 50.082463 | J64: 0 | K64: 0 | L64: 57.59419 | M64: 0 | N64: 0 | O64: =+SUM(C64:N64) -> 1314.2792
B65: OTROS (1) | C65: =+C66+C73 -> 44.50159 | D65: =+D66+D73 -> 5.0219517 | E65: =+E66+E73 -> 5.0219517 | F65: =+F66+F73 -> 30.100007 | G65: =+G66+G73 -> 5.0219517 | H65: =+H66+H73 -> 5.0219517 | I65: =+I66+I73 -> 30.100007 | J65: =+J66+J73 -> 5.0219517 | ... N65: =+N66+N73 -> 5.0219517 | O65: =+SUM(C65:N65) -> 196.4727
B66: En moneda nacional | C66: =+C67+C70 -> 31.373202 | D66: =+D67+D70 -> 5.0219517 | E66: =+E67+E70 -> 5.0219517 | F66: =+F67+F70 -> 30.100007 | G66: =+G67+G70 -> 5.0219517 | H66: =+H67+H70 -> 5.0219517 | I66: =+I67+I70 -> 30.100007 | J66: =+J67+J70 -> 5.0219517 | ... N66: =+N67+N70 -> 5.0219517 | O66: =+SUM(C66:N66) -> 183.34431
B67: · Ajustable por CER | C67: =+C68+C69 -> 6.2078925 | D67: =+D68+D69 -> 5.0219517 | E67: =+E68+E69 -> 5.0219517 | F67: =+F68+F69 -> 5.0219517 | G67: =+G68+G69 -> 5.0219517 | H67: =+H68+H69 -> 5.0219517 | I67: =+I68+I69 -> 5.0219517 | J67: =+J68+J69 -> 5.0219517 | ... N67: =+N68+N69 -> 5.0219517 | O67: =+SUM(C67:N67) -> 61.449361
B68: · Bonos de consolidación | C68: 6.051914 | D68: 5.0219517 | E68: 5.0219517 | F68: 5.0219517 | G68: 5.0219517 | H68: 5.0219517 | I68: 5.0219517 | J68: 5.0219517 | K68: 5.0219517 | L68: 5.0219517 | M68: 5.0219517 | N68: 5.0219517 | O68: =+SUM(C68:N68) -> 61.293383
B69: · Otros | C69: 0.15597849 | D69: 0 | E69: 0 | F69: 0 | G69: 0 | H69: 0 | I69: 0 | J69: 0 | K69: 0 | L69: 0 | M69: 0 | N69: 0 | O69: =+SUM(C69:N69) -> 0.15597849
B70: · No ajustable por CER | C70: =+C71+C72 -> 25.165309 | D70: =+D71+D72 -> 0 | E70: =+E71+E72 -> 0 | F70: =+F71+F72 -> 25.078056 | G70: =+G71+G72 -> 0 | H70: =+H71+H72 -> 0 | I70: =+I71+I72 -> 25.078056 | J70: =+J71+J72 -> 0 | ... N70: =+N71+N72 -> 0 | O70: =+SUM(C70:N70) -> 121.89495
B71: · Bonos de consolidación | C71: 25.079522 | D71: 0 | E71: 0 | F71: 25.078056 | G71: 0 | H71: 0 | I71: 25.078056 | J71: 0 | K71: 0 | L71: 46.573532 | M71: 0 | N71: 0 | O71: =+SUM(C71:N71) -> 121.80917
B72: · Otros | C72: 0.08578722 | D72: 0 | E72: 0 | F72: 0 | G72: 0 | H72: 0 | I72: 0 | J72: 0 | K72: 0 | L72: 0 | M72: 0 | N72: 0 | O72: =+SUM(C72:N72) -> 0.08578722
B73: En moneda extranjera | C73: =+C74+C75 -> 13.128388 | D73: =+D74+D75 -> 0 | E73: =+E74+E75 -> 0 | F73: =+F74+F75 -> 0 | G73: =+G74+G75 -> 0 | H73: =+H74+H75 -> 0 | I73: =+I74+I75 -> 0 | J73: =+J74+J75 -> 0 | ... N73: =+N74+N75 -> 0 | O73: =+SUM(C73:N73) -> 13.128388
B74: · Bonos de consolidación | C74: 2.9442002 | D74: 0 | E74: 0 | F74: 0 | G74: 0 | H74: 0 | I74: 0 | J74: 0 | K74: 0 | L74: 0 | M74: 0 | N74: 0 | O74: =+SUM(C74:N74) -> 2.9442002
B75: · Otros | C75: 10.184188 | D75: 0 | E75: 0 | F75: 0 | G75: 0 | H75: 0 | I75: 0 | J75: 0 | K75: 0 | L75: 0 | M75: 0 | N75: 0 | O75: =+SUM(C75:N75) -> 10.184188
B77: TOTAL DEUDA DENOMINADA EN PESOS | C77: =+C78+C79 -> 5083.323 | D77: =+D78+D79 -> 4358.0849 | E77: =+E78+E79 -> 9937.3551 | F77: =+F78+F79 -> 6255.4243 | G77: =+G78+G79 -> 6117.888 | H77: =+H78+H79 -> 2983.9603 | I77: =+I78+I79 -> 3050.1948 | J77: =+J78+J79 -> 816.26725 | ... N77: =+N78+N79 -> 8281.7112 | O77: =+SUM(C77:N77) -> 61752.517
B78: · Deuda ajustable por CER | C78: 446.34403 | D78: 2654.5214 | E78: 6371.3116 | F78: 1777.9115 | G78: 2191.5623 | H78: 2583.7157 | I78: 1716.8124 | J78: 809.19522 | K78: 6449.0146 | L78: 5.0219517 | M78: 1087.1248 | N78: 5.0219517 | O78: =+SUM(C78:N78) -> 26097.558
B79: · Deuda no ajustable por CER | C79: 4636.979 | D79: 1703.5635 | E79: 3566.0435 | F79: 4477.5127 | G79: 3926.3257 | H79: 400.24451 | I79: 1333.3824 | J79: 7.0720254 | K79: 400.20935 | L79: 4041.047 | M79: 2885.8909 | N79: 8276.6893 | O79: =+SUM(C79:N79) -> 35654.96
B80: TOTAL DEUDA EN MONEDA EXTRANJERA | C80: 1095.8365 | D80: 342.28032 | E80: 4171.1792 | F80: 6588.5825 | G80: 1710.2067 | H80: 5078.6092 | I80: 2409.5319 | J80: 154.62125 | K80: 3208.3896 | L80: 2953.5207 | M80: 188.81472 | N80: 3328.3992 | O80: =+SUM(C80:N80) -> 31229.972
B82: (1) Incluye bonos de consolidación, amparos y excepciones.

Sheet A.3.3
A1: Indice
B2: MINISTERIO DE ECONOMÍA
B3: SECRETARÍA DE FINANZAS
B6: PERFIL MENSUAL DE VENCIMIENTOS DE INTERÉS DE LA DEUDA BRUTA DE LA ADMINISTRACIÓN CENTRAL
B8: (En millones de U$S - Stock de deuda y tipo de cambio 31/12/2021)
C9: 44562 | D9: 44593 | E9: 44621 | F9: 44652 | G9: 44682 | H9: 44713 | I9: 44743 | J9: 44774 | K9: 44805 | L9: 44835 | M9: 44866 | N9: 44896 | O9: 2022
B11: PERFIL DE VENCIMIENTOS DE LA DEUDA EN SITUACIÓN DE PAGO NORMAL
B13: TOTAL | C13: =+C14+C15 -> 893.34335 | D13: =+D14+D15 -> 500.86405 | E13: =+E14+E15 -> 302.01166 | F13: =+F14+F15 -> 313.59476 | G13: =+G14+G15 -> 1239.5453 | H13: =+H14+H15 -> 308.77389 | I13: =+I14+I15 -> 781.7567 | J13: =+J14+J15 -> 430.39384 | ... O13: =+O14+O15 -> 6000.4376
B14: CORTO PLAZO | C14: 44.619392 | D14: 0 | E14: 0 | F14: 24.702967 | G14: 0 | H14: 0 | I14: 0 | J14: 0 | K14: 0 | L14: 0 | M14: 0 | N14: 0 | O14: =+SUM(C14:N14) -> 69.322359
B15: MEDIANO Y LARGO PLAZO | C15: 848.72396 | D15: 500.86405 | E15: 302.01166 | F15: 288.89179 | G15: 1239.5453 | H15: 308.77389 | I15: 781.7567 | J15: 430.39384 | K15: 274.51028 | L15: 213.46741 | M15: 436.82552 | N15: 305.35083 | O15: =+SUM(C15:N15) -> 5931.1152
B17: PRÉSTAMOS | C17: =+C18++C25+C28+C32+C23+C29 -> 62.825458 | D17: =+D18++D25+D28+D32+D23+D29 -> 395.13579 | E17: =+E18++E25+E28+E32+E23+E29 -> 94.381264 | F17: =+F18++F25+F28+F32+F23+F29 -> 47.402643 | G17: =+G18++G25+G28+G32+G23+G29 -> 716.4737 | H17: =+H18++H25+H28+H32+H23+H29 -> 60.272235 | I17: =+I18++I25+I28+I32+I23+I29 -> 61.001913 | J17: =+J18++J25+J28+J32+J23+J29 -> 325.25272 | ... N17: =+N18++N25+N28+N32+N23+N29 -> 57.055126 | O17: =+SUM(C17:N17) -> 2271.9626
B18: Organismos Internacionales | C18: =SUM(C19:C22) -> 28.483098 | D18: =SUM(D19:D22) -> 388.2215 | E18: =SUM(E19:E22) -> 83.591479 | F18: =SUM(F19:F22) -> 38.808254 | G18: =SUM(G19:G22) -> 381.88527 | H18: =SUM(H19:H22) -> 31.08242 | I18: =SUM(I19:I22) -> 28.455348 | J18: =SUM(J19:J22) -> 318.64176 | ... N18: =SUM(N19:N22) -> 29.75494 | O18: =+SUM(C18:N18) -> 1754.3599
B19: . BIRF | C19: 2.3189516 | D19: 1.6088375 | E19: 17.463908 | F19: 14.337592 | G19: 6.5607867 | H19: 16.578936 | I19: 2.8968042 | J19: 1.8257007 | K19: 17.441041 | L19: 15.252502 | M19: 6.845817 | N19: 16.2572 | O19: =+SUM(C19:N19) -> 119.38808
B20: . BID | C20: 19.219581 | D20: 10.998404 | E20: 56.652932 | F20: 18.755887 | G20: 41.995146 | H20: 4.6652142 | I20: 18.477404 | J20: 10.290885 | K20: 57.216083 | L20: 18.002867 | M20: 40.935581 | N20: 4.3856455 | O20: =+SUM(C20:N20) -> 301.59563
B21: . FMI | C21: 0 | D21: 366.25974 | E21: 0 | F21: 0 | G21: 325.93412 | H21: 0 | I21: 0 | J21: 297.27559 | K21: 0 | L21: 0 | M21: 245.15553 | N21: 0 | O21: =+SUM(C21:N21) -> 1234.625
B22: . Otros | C22: 6.9445655 | D22: 9.3545124 | E22: 9.4746392 | F22: 5.7147749 | G22: 7.3952242 | H22: 9.8382696 | I22: 7.0811393 | J22: 9.2495818 | K22: 10.229762 | L22: 7.0235519 | M22: 7.3330987 | N22: 9.1120951 | O22: =+SUM(C22:N22) -> 98.751214
B23: Préstamos Garantizados | C23: =+C24 -> 3.2065201 | D23: =+D24 -> 3.2065201 | E23: =+E24 -> 2.9746257 | F23: =+F24 -> 3.2065201 | G23: =+G24 -> 3.129222 | H23: =+H24 -> 3.2065201 | I23: =+I24 -> 3.129222 | J23: =+J24 -> 3.2065201 | ... N23: =+N24 -> 3.129222 | O23: =+SUM(C23:N23) -> 37.937154
B24: . En moneda nacional ajustable por CER | C24: 3.2065201 | D24: 3.2065201 | E24: 2.9746257 | F24: 3.2065201 | G24: 3.129222 | H24: 3.2065201 | I24: 3.129222 | J24: 3.2065201 | K24: 3.2065201 | L24: 3.129222 | M24: 3.2065201 | N24: 3.129222 | O24: =+SUM(C24:N24) -> 37.937154
B25: Banca Comercial | C25: =+C26 -> 0.08485794 | D25: =+D26 -> 0.1696341 | E25: =+E26 -> 0.0016299703 | F25: =+F26 -> 0.88319977 | G25: =+G26 -> 1.7836646 | H25: =+H26 -> 0.10540484 | I25: =+I26 -> 0.071254371 | J25: =+J26 -> 0.16114336 | ... N25: =+N26 -> 0.094511084 | O25: =+SUM(C25:N25) -> 5.8612891
B26: . En moneda extranjera | C26: =+C27 -> 0.08485794 | D26: =+D27 -> 0.1696341 | E26: =+E27 -> 0.0016299703 | F26: =+F27 -> 0.88319977 | G26: =+G27 -> 1.7836646 | H26: =+H27 -> 0.10540484 | I26: =+I27 -> 0.071254371 | J26: =+J27 -> 0.16114336 | ... N26: =+N27 -> 0.094511084 | O26: =+SUM(C26:N26) -> 5.8612891
B27: Otros | C27: 0.08485794 | D27: 0.1696341 | E27: 0.0016299703 | F27: 0.88319977 | G27: 1.7836646 | H27: 0.10540484 | I27: 0.071254371 | J27: 0.16114336 | K27: 0.0012439211 | L27: 0.85312798 | M27: 1.6516172 | N27: 0.094511084 | O27: =+SUM(C27:N27) -> 5.8612891
B28: Organismos Oficiales | C28: 28.027254 | D28: 0.096887531 | E28: 0.086424226 | F28: 1.5961003 | G28: 327.03761 | H28: 22.544315 | I28: 26.605978 | J28: 0.10886282 | K28: 0.13269062 | L28: 1.7314232 | M28: 0.42403504 | N28: 21.051933 | O28: =+SUM(C28:N28) -> 429.44352
B29: Pagarés | C29: =+C30 -> 0 | D29: =+D30 -> 0 | E29: =+E30 -> 3.3506061 | F29: =+F30 -> 0 | G29: =+G30 -> 0 | H29: =+H30 -> 0 | I29: =+I30 -> 0 | J29: =+J30 -> 0 | ... N29: =+N30 -> 0 | O29: =+SUM(C29:N29) -> 6.7012121
B30: . En moneda nacional ajustable por CER | C30: =+C31 -> 0 | D30: =+D31 -> 0 | E30: =+E31 -> 3.3506061 | F30: =+F31 -> 0 | G30: =+G31 -> 0 | H30: =+H31 -> 0 | I30: =+I31 -> 0 | J30: =+J31 -> 0 | ... N30: =+N31 -> 0 | O30: =+SUM(C30:N30) -> 6.7012121
B31: Pagaré 2038 - B.N.A. | C31: 0 | D31: 0 | E31: 3.3506061 | F31: 0 | G31: 0 | H31: 0 | I31: 0 | J31: 0 | K31: 3.3506061 | L31: 0 | M31: 0 | N31: 0 | O31: =+SUM(C31:N31) -> 6.7012121
B32: Avales | C32: =+C33+C34 -> 3.023728 | D32: =+D33+D34 -> 3.4412543 | E32: =+E33+E34 -> 4.3764993 | F32: =+F33+F34 -> 2.9085686 | G32: =+G33+G34 -> 2.6379299 | H32: =+H33+H34 -> 3.333575 | I32: =+I33+I34 -> 2.7401114 | J32: =+J33+J34 -> 3.134434 | ... N32: =+N33+N34 -> 3.0245197 | O32: =+SUM(C32:N32) -> 37.659562
B33: . En moneda nacional | C33: 2.1233504 | D33: 2.1141171 | E33: 2.1047913 | F33: 2.0953794 | G33: 2.0858585 | H33: 2.0762264 | I33: 2.0664565 | J33: 2.0565486 | K33: 2.0464964 | L33: 2.036363 | M33: 2.0266552 | N33: 2.0174966 | O33: =+SUM(C33:N33) -> 24.849739
B34: . En moneda extranjera | C34: 0.90037754 | D34: 1.3271372 | E34: 2.271708 | F34: 0.81318917 | G34: 0.55207143 | H34: 1.2573486 | I34: 0.67365493 | J34: 1.0778854 | K34: 1.9241826 | L34: 0.60809249 | M34: 0.39715193 | N34: 1.0070231 | O34: =+SUM(C34:N34) -> 12.809822
B36: TÍTULOS PÚBLICOS Y LETRAS DEL TESORO | C36: =+C37+C53+SUM(C67:C113)+C116 -> 830.5179 | D36: =+D37+D53+SUM(D67:D113)+D116 -> 105.72825 | E36: =+E37+E53+SUM(E67:E113)+E116 -> 207.63039 | F36: =+F37+F53+SUM(F67:F113)+F116 -> 266.19212 | G36: =+G37+G53+SUM(G67:G113)+G116 -> 523.07161 | H36: =+H37+H53+SUM(H67:H113)+H116 -> 248.50166 | I36: =+I37+I53+SUM(I67:I113)+I116 -> 720.75479 | J36: =+J37+J53+SUM(J67:J113)+J116 -> 105.14112 | ... N36: =+N37+N53+SUM(N67:N113)+N116 -> 248.2957 | O36: =+SUM(C36:N36) -> 3728.475
B37: PAR | C37: =+C38+C41+C48+C50 -> 0 | D37: =+D38+D41+D48+D50 -> 0 | E37: =+E38+E41+E48+E50 -> 18.60033 | F37: =+F38+F41+F48+F50 -> 2.5911594 | G37: =+G38+G41+G48+G50 -> 0 | H37: =+H38+H41+H48+H50 -> 0 | I37: =+I38+I41+I48+I50 -> 0 | J37: =+J38+J41+J48+J50 -> 0 | ... N37: =+N38+N41+N48+N50 -> 0 | O37: =+SUM(C37:N37) -> 40.43961
B38: Par/$+CER/T.Fija/2038 | C38: =+C39+C40 -> 0 | D38: =+D39+D40 -> 0 | E38: =+E39+E40 -> 6.4858394 | F38: =+F39+F40 -> 0 | G38: =+G39+G40 -> 0 | H38: =+H39+H40 -> 0 | I38: =+I39+I40 -> 0 | J38: =+J39+J40 -> 0 | ... N38: =+N39+N40 -> 0 | O38: =+SUM(C38:N38) -> 12.971679
B39: Emisión Canje 2005 | C39: 0 | D39: 0 | E39: 6.4601474 | F39: 0 | G39: 0 | H39: 0 | I39: 0 | J39: 0 | K39: 6.4601474 | L39: 0 | M39: 0 | N39: 0 | O39: =+SUM(C39:N39) -> 12.920295
B40: Emisión Canje 2010 | C40: 0 | D40: 0 | E40: 0.025692021 | F40: 0 | G40: 0 | H40: 0 | I40: 0 | J40: 0 | K40: 0.025692021 | L40: 0 | M40: 0 | N40: 0 | O40: =+SUM(C40:N40) -> 0.051384042
B41: Par/U$S/T.Fija/2038 | C41: =+C42+C45 -> 0 | D41: =+D42+D45 -> 0 | E41: =+E42+E45 -> 0.67161675 | F41: =+F42+F45 -> 2.5911594 | G41: =+G42+G45 -> 0 | H41: =+H42+H45 -> 0 | I41: =+I42+I45 -> 0 | J41: =+J42+J45 -> 0 | ... N41: =+N42+N45 -> 0 | O41: =+SUM(C41:N41) -> 4.5821827
B42: Emisión Canje 2005 | C42: =+C43+C44 -> 0 | D42: =+D43+D44 -> 0 | E42: =+E43+E44 -> 0 | F42: =+F43+F44 -> 2.1739209 | G42: =+G43+G44 -> 0 | H42: =+H43+H44 -> 0 | I42: =+I43+I44 -> 0 | J42: =+J43+J44 -> 0 | ... N42: =+N43+N44 -> 0 | O42: =+SUM(C42:N42) -> 2.7174012
B43: Leg. Nueva York | C43: 0 | D43: 0 | E43: 0 | F43: 0 | G43: 0 | H43: 0 | I43: 0 | J43: 0 | K43: 0 | L43: 0 | M43: 0 | N43: 0 | O43: =+SUM(C43:N43) -> 0
B44: Leg. Argentina | C44: 0 | D44: 0 | E44: 0 | F44: 2.1739209 | G44: 0 | H44: 0 | I44: 0 | J44: 0 | K44: 0.54348023 | L44: 0 | M44: 0 | N44: 0 | O44: =+SUM(C44:N44) -> 2.7174012
B45: Emisión Canje 2010 | C45: =+C46+C47 -> 0 | D45: =+D46+D47 -> 0 | E45: =+E46+E47 -> 0.67161675 | F45: =+F46+F47 -> 0.41723844 | G45: =+G46+G47 -> 0 | H45: =+H46+H47 -> 0 | I45: =+I46+I47 -> 0 | J45: =+J46+J47 -> 0 | ... N45: =+N46+N47 -> 0 | O45: =+SUM(C45:N45) -> 1.8647815
B46: Leg. Nueva York | C46: 0 | D46: 0 | E46: 0.67161675 | F46: 0 | G46: 0 | H46: 0 | I46: 0 | J46: 0 | K46: 0.67161675 | L46: 0 | M46: 0 | N46: 0 | O46: =+SUM(C46:N46) -> 1.3432335
B47: Leg. Argentina | C47: 0 | D47: 0 | E47: 0 | F47: 0.41723844 | G47: 0 | H47: 0 | I47: 0 | J47: 0 | K47: 0.10430961 | L47: 0 | M47: 0 | N47: 0 | O47: =+SUM(C47:N47) -> 0.52154805
B48: Par/EUR/T.Fija/2038 | C48: =+C49 -> 0 | D48: =+D49 -> 0 | E48: =+E49 -> 10.915441 | F48: =+F49 -> 0 | G48: =+G49 -> 0 | H48: =+H49 -> 0 | I48: =+I49 -> 0 | J48: =+J49 -> 0 | ... N48: =+N49 -> 0 | O48: =+SUM(C48:N48) -> 21.830881
B49: Emisión Canje 2010 | C49: 0 | D49: 0 | E49: 10.915441 | F49: 0 | G49: 0 | H49: 0 | I49: 0 | J49: 0 | K49: 10.915441 | L49: 0 | M49: 0 | N49: 0 | O49: =+SUM(C49:N49) -> 21.830881
B50: Par/JPY/T.Fija/2038 | C50: =+C51+C52 -> 0 | D50: =+D51+D52 -> 0 | E50: =+E51+E52 -> 0.52743363 | F50: =+F51+F52 -> 0 | G50: =+G51+G52 -> 0 | H50: =+H51+H52 -> 0 | I50: =+I51+I52 -> 0 | J50: =+J51+J52 -> 0 | ... N50: =+N51+N52 -> 0 | O50: =+SUM(C50:N50) -> 1.0548673
B51: Emisión Canje 2005 | C51: 0 | D51: 0 | E51: 0.50257694 | F51: 0 | G51: 0 | H51: 0 | I51: 0 | J51: 0 | K51: 0.50257694 | L51: 0 | M51: 0 | N51: 0 | O51: =+SUM(C51:N51) -> 1.0051539
B52: Emisión Canje 2010 | C52: 0 | D52: 0 | E52: 0.024856691 | F52: 0 | G52: 0 | H52: 0 | I52: 0 | J52: 0 | K52: 0.024856691 | L52: 0 | M52: 0 | N52: 0 | O52: =+SUM(C52:N52) -> 0.049713383
B53: DESCUENTO | C53: =+C54+C57+C64 -> 0 | D53: =+D54+D57+D64 -> 0 | E53: =+E54+E57+E64 -> 0 | F53: =+F54+F57+F64 -> 2.2922856 | G53: =+G54+G57+G64 -> 0 | H53: =+H54+H57+H64 -> 103.40109 | I53: =+I54+I57+I64 -> 0 | J53: =+J54+J57+J64 -> 0 | ... N53: =+N54+N57+N64 -> 103.40109 | O53: =+SUM(C53:N53) -> 209.09446
B54: Discount/$+CER/5,83%/2033 | C54: =+C55+C56 -> 0 | D54: =+D55+D56 -> 0 | E54: =+E55+E56 -> 0 | F54: =+F55+F56 -> 0 | G54: =+G55+G56 -> 0 | H54: =+H55+H56 -> 100.97971 | I54: =+I55+I56 -> 0 | J54: =+J55+J56 -> 0 | ... N54: =+N55+N56 -> 100.97971 | O54: =+SUM(C54:N54) -> 201.95941
B55: Emisión Canje 2005 | C55: 0 | D55: 0 | E55: 0 | F55: 0 | G55: 0 | H55: 99.780273 | I55: 0 | J55: 0 | K55: 0 | L55: 0 | M55: 0 | N55: 99.780273 | O55: =+SUM(C55:N55) -> 199.56055
B56: Emisión Canje 2010 | C56: 0 | D56: 0 | E56: 0 | F56: 0 | G56: 0 | H56: 1.1994328 | I56: 0 | J56: 0 | K56: 0 | L56: 0 | M56: 0 | N56: 1.1994328 | O56: =+SUM(C56:N56) -> 2.3988656
B57: Discount/U$S/8,28%/2033 | C57: =+C58+C61 -> 0 | D57: =+D58+D61 -> 0 | E57: =+E58+E61 -> 0 | F57: =+F58+F61 -> 2.2922856 | G57: =+G58+G61 -> 0 | H57: =+H58+H61 -> 0.57307141 | I57: =+I58+I61 -> 0 | J57: =+J58+J61 -> 0 | ... N57: =+N58+N61 -> 0.57307193 | O57: =+SUM(C57:N57) -> 3.438429
B58: Emisión Canje 2005 | C58: =+C59+C60 -> 0 | D58: =+D59+D60 -> 0 | E58: =+E59+E60 -> 0 | F58: =+F59+F60 -> 1.629362 | G58: =+G59+G60 -> 0 | H58: =+H59+H60 -> 0.4073405 | I58: =+I59+I60 -> 0 | J58: =+J59+J60 -> 0 | ... N58: =+N59+N60 -> 0.40734102 | O58: =+SUM(C58:N58) -> 2.4440435
B59: Leg. Nueva York | C59: 0 | D59: 0 | E59: 0 | F59: 0 | G59: 0 | H59: 0 | I59: 0 | J59: 0 | K59: 0 | L59: 0 | M59: 0 | N59: 0 | O59: =+SUM(C59:N59) -> 0
B60: Leg. Argentina | C60: 0 | D60: 0 | E60: 0 | F60: 1.629362 | G60: 0 | H60: 0.4073405 | I60: 0 | J60: 0 | K60: 0 | L60: 0 | M60: 0 | N60: 0.40734102 | O60: =+SUM(C60:N60) -> 2.4440435
B61: Emisión Canje 2010 | C61: =+C62+C63 -> 0 | D61: =+D62+D63 -> 0 | E61: =+E62+E63 -> 0 | F61: =+F62+F63 -> 0.66292363 | G61: =+G62+G63 -> 0 | H61: =+H62+H63 -> 0.16573091 | I61: =+I62+I63 -> 0 | J61: =+J62+J63 -> 0 | ... N61: =+N62+N63 -> 0.16573091 | O61: =+SUM(C61:N61) -> 0.99438544
B62: Leg. Nueva York | C62: 0 | D62: 0 | E62: 0 | F62: 0 | G62: 0 | H62: 0 | I62: 0 | J62: 0 | K62: 0 | L62: 0 | M62: 0 | N62: 0 | O62: =+SUM(C62:N62) -> 0
B63: Leg. Argentina | C63: 0 | D63: 0 | E63: 0 | F63: 0.66292363 | G63: 0 | H63: 0.16573091 | I63: 0 | J63: 0 | K63: 0 | L63: 0 | M63: 0 | N63: 0.16573091 | O63: =+SUM(C63:N63) -> 0.99438544
B64: Discount/JPY/4,33%/2033 | C64: =+C65+C66 -> 0 | D64: =+D65+D66 -> 0 | E64: =+E65+E66 -> 0 | F64: =+F65+F66 -> 0 | G64: =+G65+G66 -> 0 | H64: =+H65+H66 -> 1.848308 | I64: =+I65+I66 -> 0 | J64: =+J65+J66 -> 0 | ... N64: =+N65+N66 -> 1.848308 | O64: =+SUM(C64:N64) -> 3.6966159
B65: Emisión Canje 2005 | C65: 0 | D65: 0 | E65: 0 | F65: 0 | G65: 0 | H65: 1.2752696 | I65: 0 | J65: 0 | K65: 0 | L65: 0 | M65: 0 | N65: 1.2752696 | O65: =+SUM(C65:N65) -> 2.5505392
B66: Emisión Canje 2010 | C66: 0 | D66: 0 | E66: 0 | F66: 0 | G66: 0 | H66: 0.57303837 | I66: 0 | J66: 0 | K66: 0 | L66: 0 | M66: 0 | N66: 0.57303837 | O66: =+SUM(C66:N66) -> 1.1460767
B67: CUASIPAR/$+CER/3,31%/2045 | C67: 0 | D67: 0 | E67: 0 | F67: 0 | G67: 0 | H67: 139.02581 | I67: 0 | J67: 0 | K67: 0 | L67: 0 | M67: 0 | N67: 139.02581 | O67: =+SUM(C67:N67) -> 278.05161
B68: BONAR/$/6,72763943919512%/31-12-2028 | C68: 1.9064146 | D68: 1.8885988 | E68: 1.8699771 | F68: 1.8523064 | G68: 1.8341871 | H68: 1.8159662 | I68: 1.7976432 | J68: 1.7792175 | K68: 1.7606884 | L68: 1.7420555 | M68: 1.7233182 | N68: 1.7044757 | O68: =+SUM(C68:N68) -> 21.674849
B69: BONAR/$/BADLAR+200PB/03-04-2022 | C69: 60.907883 | D69: 0 | E69: 0 | F69: 60.23853 | G69: 0 | H69: 0 | I69: 0 | J69: 0 | K69: 0 | L69: 0 | M69: 0 | N69: 0 | O69: =+SUM(C69:N69) -> 121.14641
B70: BONAR/U$S/1,00%/05-08-2023 | C70: 0 | D70: 0 | E70: 0 | F70: 0.49997792 | G70: 0 | H70: 0 | I70: 0 | J70: 0.12499448 | K70: 0 | L70: 0 | M70: 0 | N70: 0 | O70: =+SUM(C70:N70) -> 0.6249724
B71: BONAR/U$S/5,75%/18-04-2025 | C71: 0 | D71: 0 | E71: 0 | F71: 0.28186615 | G71: 0 | H71: 0 | I71: 0 | J71: 0 | K71: 0 | L71: 0.05637323 | M71: 0 | N71: 0 | O71: =+SUM(C71:N71) -> 0.33823938
B72: BONAR/U$S/7,625%/18-04-2037 | C72: 0 | D72: 0 | E72: 0 | F72: 0.7665563 | G72: 0 | H72: 0 | I72: 0 | J72: 0 | K72: 0 | L72: 0.15331126 | M72: 0 | N72: 0 | O72: =+SUM(C72:N72) -> 0.91986756
B73: BONAR/U$S/8,00%/08-10-2020 | C73: 0 | D73: 0 | E73: 0 | F73: 0.6339544 | G73: 0 | H73: 0 | I73: 0 | J73: 0 | K73: 0 | L73: 0 | M73: 0 | N73: 0 | O73: =+SUM(C73:N73) -> 0.6339544
B74: BONAR/U$S/8,75%/07-05-2024 | C74: 0 | D74: 0 | E74: 0 | F74: 3.6454484 | G74: 0.68365824 | H74: 0 | I74: 0 | J74: 0 | K74: 0 | L74: 0 | M74: 0.4559544 | N74: 0 | O74: =+SUM(C74:N74) -> 4.785061
B75: BONCER/$/1,20%+CER/18-03-2022 | C75: 0 | D75: 0 | E75: 29.245511 | F75: 0 | G75: 0 | H75: 0 | I75: 0 | J75: 0 | K75: 0 | L75: 0 | M75: 0 | N75: 0 | O75: =+SUM(C75:N75) -> 29.245511
B76: BONCER/$/1,55%+CER/26-07-2024 | C76: 13.266785 | D76: 0 | E76: 0 | F76: 0 | G76: 0 | H76: 0 | I76: 11.756518 | J76: 0 | K76: 0 | L76: 0 | M76: 0 | N76: 0 | O76: =+SUM(C76:N76) -> 25.023303
... B112: BONO R.A./U$S/STEP UP/09-07-2041 | C112: 18.787842 | D112: 0 | E112: 0 | F112: 0 | G112: 0 | H112: 0 | I112: 18.787842 | J112: 0 | K112: 0 | L112: 0 | M112: 0 | N112: 0 | O112: =+SUM(C112:N112) -> 37.575684
B113: LETRAS DEL TESORO | C113: =+C114+C115 -> 44.620001 | D113: =+D114+D115 -> 0 | E113: =+E114+E115 -> 0 | F113: =+F114+F115 -> 24.703288 | G113: =+G114+G115 -> 0 | H113: =+H114+H115 -> 0 | I113: =+I114+I115 -> 0 | J113: =+J114+J115 -> 0 | ... N113: =+N114+N115 -> 0 | O113: =+SUM(C113:N113) -> 69.323289
B114: . En moneda nacional | C114: =44.6202917166027-0.000290430000063679 -> 44.620001 | D114: 0 | E114: 0 | F114: =24.7029971212652+0.000290430000063679 -> 24.703288 | G114: 0 | H114: 0 | I114: 0 | J114: 0 | K114: 0 | L114: 0 | M114: 0 | N114: 0 | O114: =+SUM(C114:N114) -> 69.323289
B115: . En moneda extranjera | C115: 0 | D115: 0 | E115: 0 | F115: 0 | G115: 0 | H115: 0 | I115: 0 | J115: 0 | K115: 0 | L115: 0 | M115: 0 | N115: 0 | O115: =+SUM(C115:N115) -> 0
B116: OTROS (1) | C116: =+C117+C122 -> 10.718687 | D116: =+D117+D122 -> 0.22165025 | E116: =+E117+E122 -> 0.23941033 | F116: =+F117+F122 -> 10.225975 | G116: =+G117+G122 -> 0.19654049 | H116: =+H117+H122 -> 0.18817057 | I116: =+I117+I122 -> 8.1762561 | J116: =+J117+J122 -> 0.17143073 | ... N116: =+N117+N122 -> 0.13795105 | O116: =+SUM(C116:N116) -> 36.691177
B117: . En moneda nacional | C117: =+C118+C120 -> 10.718687 | D117: =+D118+D120 -> 0.22165025 | E117: =+E118+E120 -> 0.21328033 | F117: =+F118+F120 -> 10.225975 | G117: =+G118+G120 -> 0.19654049 | H117: =+H118+H120 -> 0.18817057 | I117: =+I118+I120 -> 8.1762561 | J117: =+J118+J120 -> 0.17143073 | ... N117: =+N118+N120 -> 0.13795105 | O117: =+SUM(C117:N117) -> 36.638917
B118: · Ajustable por CER | C118: =+C119 -> 0.23003442 | D118: =+D119 -> 0.22165025 | E118: =+E119 -> 0.21328033 | F118: =+F119 -> 0.20491041 | G118: =+G119 -> 0.19654049 | H118: =+H119 -> 0.18817057 | I118: =+I119 -> 0.17980065 | J118: =+J119 -> 0.17143073 | ... N118: =+N119 -> 0.13795105 | O118: =+SUM(C118:N118) -> 2.2078416
B119: · Bonos de consolidación | C119: 0.23003442 | D119: 0.22165025 | E119: 0.21328033 | F119: 0.20491041 | G119: 0.19654049 | H119: 0.18817057 | I119: 0.17980065 | J119: 0.17143073 | K119: 0.16306081 | L119: 0.15469089 | M119: 0.14632097 | N119: 0.13795105 | O119: =+SUM(C119:N119) -> 2.2078416
B120: · No ajustable por CER | C120: =+C121 -> 10.488653 | D120: =+D121 -> 0 | E120: =+E121 -> 0 | F120: =+F121 -> 10.021065 | G120: =+G121 -> 0 | H120: =+H121 -> 0 | I120: =+I121 -> 7.9964554 | J120: =+J121 -> 0 | ... N120: =+N121 -> 0 | O120: =+SUM(C120:N120) -> 34.431075
B121: · Bonos de consolidación | C121: 10.488653 | D121: 0 | E121: 0 | F121: 10.021065 | G121: 0 | H121: 0 | I121: 7.9964554 | J121: 0 | K121: 0 | L121: 5.9249018 | M121: 0 | N121: 0 | O121: =+SUM(C121:N121) -> 34.431075
B122: . En moneda extranjera | C122: =+C123+C124 -> 0 | D122: =+D123+D124 -> 0 | E122: =+E123+E124 -> 0.02613 | F122: =+F123+F124 -> 0 | G122: =+G123+G124 -> 0 | H122: =+H123+H124 -> 0 | I122: =+I123+I124 -> 0 | J122: =+J123+J124 -> 0 | ... N122: =+N123+N124 -> 0 | O122: =+SUM(C122:N122) -> 0.05226
B123: · Bonos de Consolidación | C123: 0 | D123: 0 | E123: 0 | F123: 0 | G123: 0 | H123: 0 | I123: 0 | J123: 0 | K123: 0 | L123: 0 | M123: 0 | N123: 0 | O123: =+SUM(C123:N123) -> 0
B124: · Otros | C124: 0 | D124: 0 | E124: 0.02613 | F124: 0 | G124: 0 | H124: 0 | I124: 0 | J124: 0 | K124: 0.02613 | L124: 0 | M124: 0 | N124: 0 | O124: =+SUM(C124:N124) -> 0.05226
B126: TOTAL DEUDA DENOMINADA EN PESOS | C126: =+C127+C128 -> 143.53428 | D126: =+D127+D128 -> 111.04889 | E126: =+E127+E128 -> 203.91979 | F126: =+F127+F128 -> 260.78277 | G126: =+G127+G128 -> 527.60303 | H126: =+H127+H128 -> 251.36302 | I126: =+I127+I128 -> 33.63759 | J126: =+J127+J128 -> 110.27919 | ... N126: =+N127+N128 -> 251.02104 | O126: =+SUM(C126:N126) -> 2371.3794
B127: · Deuda ajustable por CER | C127: 16.70334 | D127: 40.081305 | E127: 195.96289 | F127: 27.307268 | G127: 62.099933 | H127: 243.4002 | I127: 15.06554 | J127: 40.031085 | K127: 166.89905 | L127: 27.17975 | M127: 62.127047 | N127: 243.27268 | O127: =+SUM(C127:N127) -> 1140.1301
B128: · Deuda no ajustable por CER | C128: 126.83094 | D128: 70.967585 | E128: 7.9569061 | F128: 233.4755 | G128: 465.50309 | H128: 7.9628222 | I128: 18.57205 | J128: 70.248106 | K128: 7.8778145 | L128: 142.60641 | M128: 71.499685 | N128: 7.7483559 | O128: =+SUM(C128:N128) -> 1231.2493
B129: TOTAL DEUDA EN MONEDA EXTRANJERA | C129: 749.80907 | D129: 389.81516 | E129: 98.091862 | F129: 52.811992 | G129: 711.94228 | H129: 57.410868 | I129: 748.11911 | J129: 320.11465 | K129: 99.733413 | L129: 43.681249 | M129: 303.19879 | N129: 54.329787 | O129: =+SUM(C129:N129) -> 3629.0582
B131: (1) Incluye bonos de consolidación, amparos y excepciones.

Sheet A.3.4
A1: Indice
B2: MINISTERIO DE ECONOMÍA
B3: SECRETARÍA DE FINANZAS
B6: PERFIL MENSUAL DE VENCIMIENTOS DE CAPITAL DE LA DEUDA BRUTA DE LA ADMINISTRACIÓN CENTRAL
B8: (En millones de U$S - Stock de deuda y tipo de cambio 31/12/2021)
C9: 44927 | D9: 44958 | E9: 44986 | F9: 45017 | G9: 45047 | H9: 45078 | I9: 45108 | J9: 45139 | K9: 45170 | L9: 45200 | M9: 45231 | N9: 45261 | O9: 2023
B11: PERFIL DE VENCIMIENTOS DE LA DEUDA EN SITUACIÓN DE PAGO NORMAL
B13: TOTAL | C13: =+C14+C15 -> 10294.139 | D13: =+D14+D15 -> 1574.1173 | E13: =+E14+E15 -> 10994.467 | F13: =+F14+F15 -> 5237.6507 | G13: =+G14+G15 -> 194.06869 | H13: =+H14+H15 -> 5786.8638 | I13: =+I14+I15 -> 3158.2185 | J13: =+J14+J15 -> 7525.0598 | ... O13: =+O14+O15 -> 51289.155
B14: CORTO PLAZO | C14: 0 | D14: 0 | E14: 0 | F14: 0 | G14: 0 | H14: 0 | I14: 0 | J14: 0 | K14: 0 | L14: 0 | M14: 0 | N14: 0 | O14: =SUM(C14:N14) -> 0
B15: MEDIANO Y LARGO PLAZO | C15: 10294.139 | D15: 1574.1173 | E15: 10994.467 | F15: 5237.6507 | G15: 194.06869 | H15: 5786.8638 | I15: 3158.2185 | J15: 7525.0598 | K15: 1230.2039 | L15: 3631.0903 | M15: 205.23059 | N15: 1458.0459 | O15: =SUM(C15:N15) -> 51289.155
B17: PRÉSTAMOS | C17: =+C18+C23+C25+C26 -> 3039.261 | D17: =+D18+D23+D25+D26 -> 150.22824 | E17: =+E18+E23+E25+E26 -> 3079.8844 | F17: =+F18+F23+F25+F26 -> 2893.7674 | G17: =+G18+G23+G25+G26 -> 177.4935 | H17: =+H18+H23+H25+H26 -> 2954.3066 | I17: =+I18+I23+I25+I26 -> 3020.7568 | J17: =+J18+J23+J25+J26 -> 140.7301 | ... N17: =+N18+N23+N25+N26 -> 1096.2151 | O17: =+SUM(C17:N17) -> 20852.673
B18: Organismos Internacionales | C18: =SUM(C19:C22) -> 2849.5418 | D18: =SUM(D19:D22) -> 129.55349 | E18: =SUM(E19:E22) -> 3065.4533 | F18: =SUM(F19:F22) -> 2875.6114 | G18: =SUM(G19:G22) -> 144.56038 | H18: =SUM(H19:H22) -> 2948.2277 | I18: =SUM(I19:I22) -> 2850.4847 | J18: =SUM(J19:J22) -> 129.44773 | ... O18: =SUM(O19:O22) -> 20331.369
B19: . BIRF | C19: 0.15132 | D19: 3.2351618 | E19: 57.255741 | F19: 30.926526 | G19: 13.548826 | H19: 31.038926 | I19: 0.15132 | J19: 3.2351618 | K19: 57.255741 | L19: 30.912207 | M19: 24.77665 | N19: 31.038926 | O19: =SUM(C19:N19) -> 283.5265
B20: . BID | C20: 49.149379 | D20: 38.164354 | E20: 141.4822 | F20: 61.333314 | G20: 109.37849 | H20: 26.737115 | I20: 50.092351 | J20: 38.164354 | K20: 140.63119 | L20: 61.333314 | M20: 118.75349 | N20: 29.088142 | O20: =SUM(C20:N20) -> 864.30769
B21: . FMI | C21: 2764.1707 | D21: 0 | E21: 2819.0535 | F21: 2764.1707 | G21: 0 | H21: 2819.0535 | I21: 2764.1707 | J21: 0 | K21: 962.21134 | L21: 2764.1707 | M21: 0 | N21: 962.21134 | O21: =SUM(C21:N21) -> 18619.213
B22: . Otros | C22: 36.070308 | D22: 88.153972 | E22: 47.661834 | F22: 19.180771 | G22: 21.633068 | H22: 71.398131 | I22: 36.070308 | J22: 88.048211 | K22: 48.764073 | L22: 19.180771 | M22: 16.761995 | N22: 71.398131 | O22: =SUM(C22:N22) -> 564.32157
B23: Banca Comercial | C23: =+C24 -> 0.92683067 | D23: =+D24 -> 2.5737641 | E23: =+E24 -> 0.014523279 | F23: =+F24 -> 5.1678607 | G23: =+G24 -> 24.671987 | H23: =+H24 -> 0.65144009 | I23: =+I24 -> 0.91524649 | J23: =+J24 -> 2.562112 | ... N23: =+N24 -> 0.65153591 | O23: =SUM(C23:N23) -> 67.978123
B24: . En moneda extranjera | C24: 0.92683067 | D24: 2.5737641 | E24: 0.014523279 | F24: 5.1678607 | G24: 24.671987 | H24: 0.65144009 | I24: 0.91524649 | J24: 2.562112 | K24: 0.0027850661 | L24: 5.1679554 | M24: 24.672082 | N24: 0.65153591 | O24: =SUM(C24:N24) -> 67.978123
B25: Organismos Oficiales | C25: 181.33624 | D25: 0.18579546 | E25: 0.33258921 | F25: 4.5101276 | G25: 7.3004244 | H25: 0.82262133 | I25: 161.80755 | J25: 0.43579546 | K25: 0.33258921 | L25: 4.5101276 | M25: 7.4998867 | N25: 0.75563533 | O25: =SUM(C25:N25) -> 369.82938
B26: Avales | C26: =+C27+C28 -> 7.4561358 | D26: =+D27+D28 -> 17.915196 | E26: =+E27+E28 -> 14.083957 | F26: =+F27+F28 -> 8.4780071 | G26: =+G27+G28 -> 0.96070772 | H26: =+H27+H28 -> 4.6047995 | I26: =+I27+I28 -> 7.5492549 | J26: =+J27+J28 -> 8.2844684 | ... O26: =+O27+O28 -> 83.496924
B27: . En moneda nacional | C27: 0.80364064 | D27: 0.81904588 | E27: 0.83457032 | F27: 0.8495992 | G27: 0.86504559 | H27: 0.88078249 | I27: 0.89675979 | J27: 0.91291592 | K27: 0.92923953 | L27: 0.94567276 | M27: 1.1817247 | N27: 0.9757108 | O27: =SUM(C27:N27) -> 10.894708
B28: . En moneda extranjera | C28: 6.6524951 | D28: 17.09615 | E28: 13.249386 | F28: 7.6284079 | G28: 0.09566213 | H28: 3.7240171 | I28: 6.6524951 | J28: 7.3715525 | K28: 9.8450631 | L28: 0.09566213 | M28: 0.09566213 | N28: 0.09566213 | O28: =SUM(C28:N28) -> 72.602216
B30: ADELANTOS TRANSITORIOS BCRA | C30: 19.46472 | D30: 846.71533 | E30: 1012.1655 | F30: 0 | G30: 0 | H30: 2822.3844 | I30: 0 | J30: 0 | K30: 0 | L30: 0 | M30: 0 | N30: 0 | O30: =SUM(C30:N30) -> 4700.7299
B32: TÍTULOS PÚBLICOS Y LETRAS DEL TESORO | C32: =+SUM(C33:C56)+C59 -> 7235.4129 | D32: =+SUM(D33:D56)+D59 -> 577.17376 | E32: =+SUM(E33:E56)+E59 -> 6902.4171 | F32: =+SUM(F33:F56)+F59 -> 2343.8834 | G32: =+SUM(G33:G56)+G59 -> 16.575189 | H32: =+SUM(H33:H56)+H59 -> 10.172763 | I32: =+SUM(I33:I56)+I59 -> 137.46176 | J32: =+SUM(J33:J56)+J59 -> 7384.3297 | ... N32: =+SUM(N33:N56)+N59 -> 361.83078 | O32: =SUM(C32:N32) -> 25735.752
B33: BONAR/$/6,72763943919512%/31-12-2028 | C33: 3.3986889 | D33: 3.5288414 | E33: 3.3826375 | F33: 3.4564914 | G33: 3.4758698 | H33: 3.4953568 | I33: 3.514953 | J33: 3.5346591 | K33: 3.5544757 | L33: 3.5744034 | M33: 3.5944428 | N33: 3.6145946 | O33: =SUM(C33:N33) -> 42.125415
B34: BONAR/$/BADLAR+200PB/03-04-2022 | C34: 0 | D34: 0 | E34: 0 | F34: 0 | G34: 0 | H34: 0 | I34: 0 | J34: 0 | K34: 0 | L34: 0 | M34: 0 | N34: 0 | O34: =SUM(C34:N34) -> 0
B35: BONAR/DLK/4,50%U$S-2,35%$/13-02-2020 | C35: 0 | D35: 0 | E35: 0 | F35: 0 | G35: 0 | H35: 0 | I35: 0 | J35: 0 | K35: 0 | L35: 0 | M35: 0 | N35: 0 | O35: =SUM(C35:N35) -> 0
B36: BONAR/U$S/1,00%/05-08-2023 | C36: 0 | D36: 0 | E36: 0 | F36: 0 | G36: 0 | H36: 0 | I36: 0 | J36: 24.998895 | K36: 0 | L36: 0 | M36: 0 | N36: 0 | O36: =SUM(C36:N36) -> 24.998895
B37: BONAR/U$S/5,75%/18-04-2025 | C37: 0 | D37: 0 | E37: 0 | F37: 0.64706664 | G37: 0 | H37: 0 | I37: 0 | J37: 0 | K37: 0 | L37: 0 | M37: 0 | N37: 0 | O37: =SUM(C37:N37) -> 0.64706664
B38: BONAR/U$S/8,00%/08-10-2020 | C38: 0 | D38: 0 | E38: 0 | F38: 0 | G38: 0 | H38: 0 | I38: 0 | J38: 0 | K38: 0 | L38: 0 | M38: 0 | N38: 0 | O38: =SUM(C38:N38) -> 0
B39: BONAR/U$S/8,75%/07-05-2024 | C39: 0 | D39: 0 | E39: 0 | F39: 0 | G39: 5.2046593 | H39: 0 | I39: 0 | J39: 0 | K39: 0 | L39: 0 | M39: 0 | N39: 0 | O39: =SUM(C39:N39) -> 5.2046593
B40: BONCER/$/1,20%+CER/18-03-2022 | C40: 0 | D40: 0 | E40: 0 | F40: 0 | G40: 0 | H40: 0 | I40: 0 | J40: 0 | K40: 0 | L40: 0 | M40: 0 | N40: 0 | O40: =SUM(C40:N40) -> 0
B41: BONCER/$+CER//1,45%/13-08-2023 | C41: 0 | D41: 0 | E41: 0 | F41: 0 | G41: 0 | H41: 0 | I41: 0 | J41: 5055.6047 | K41: 0 | L41: 0 | M41: 0 | N41: 0 | O41: =SUM(C41:N41) -> 5055.6047
B42: BONCER/$+CER/1,30%/20-09-2022 | C42: 0 | D42: 0 | E42: 0 | F42: 0 | G42: 0 | H42: 0 | I42: 0 | J42: 0 | K42: 0 | L42: 0 | M42: 0 | N42: 0 | O42: =SUM(C42:N42) -> 0
B43: BONCER/$+CER/1,40%/25-03-2023 | C43: 0 | D43: 0 | E43: 5684.8714 | F43: 0 | G43: 0 | H43: 0 | I43: 0 | J43: 0 | K43: 0 | L43: 0 | M43: 0 | N43: 0 | O43: =SUM(C43:N43) -> 5684.8714
B44: BONCER/$+CER/4,00%/06-03-2023 | C44: 0 | D44: 0 | E44: 1207.4856 | F44: 0 | G44: 0 | H44: 0 | I44: 0 | J44: 0 | K44: 0 | L44: 0 | M44: 0 | N44: 0 | O44: =SUM(C44:N44) -> 1207.4856
... B55: Letras en Garantía | C55: 0 | D55: 0 | E55: 0 | F55: 0 | G55: 0 | H55: 0 | I55: 0 | J55: 0 | K55: 0 | L55: 0 | M55: 0 | N55: 351.53877 | O55: =SUM(C55:N55) -> 351.53877
B56: LETRAS DEL TESORO | C56: =+C57+C58 -> 94.251493 | D56: =+D57+D58 -> 0 | E56: =+E57+E58 -> 0 | F56: =+F57+F58 -> 113.00624 | G56: =+G57+G58 -> 0 | H56: =+H57+H58 -> 0 | I56: =+I57+I58 -> 128.92485 | J56: =+J57+J58 -> 0 | ... O56: =+O57+O58 -> 448.02578
B57: . En moneda nacional | C57: 0 | D57: 0 | E57: 0 | F57: 0 | G57: 0 | H57: 0 | I57: 0 | J57: 0 | K57: 0 | L57: 0 | M57: 0 | N57: 0 | O57: =SUM(C57:N57) -> 0
B58: . En moneda extranjera | C58: 94.251493 | D58: 0 | E58: 0 | F58: 113.00624 | G58: 0 | H58: 0 | I58: 128.92485 | J58: 0 | K58: 0 | L58: 111.8432 | M58: 0 | N58: 0 | O58: =SUM(C58:N58) -> 448.02578
B59: OTROS (1) | C59: =+C60 -> 5.1077389 | D59: =+D60 -> 5.0219517 | E59: =+E60 -> 5.0219517 | F59: =+F60 -> 5.0219517 | G59: =+G60 -> 5.0219517 | H59: =+H60 -> 5.0219517 | I59: =+I60 -> 5.0219517 | J59: =+J60 -> 5.0219517 | ... N59: =+N60 -> 5.0219517 | O59: =SUM(C59:N59) -> 60.349208
B60: En moneda nacional | C60: =+C61+C63 -> 5.1077389 | D60: =+D61+D63 -> 5.0219517 | E60: =+E61+E63 -> 5.0219517 | F60: =+F61+F63 -> 5.0219517 | G60: =+G61+G63 -> 5.0219517 | H60: =+H61+H63 -> 5.0219517 | I60: =+I61+I63 -> 5.0219517 | J60: =+J61+J63 -> 5.0219517 | ... N60: =+N61+N63 -> 5.0219517 | O60: =SUM(C60:N60) -> 60.349208
B61: · Ajustable por CER | C61: =+C62 -> 5.0219517 | D61: =+D62 -> 5.0219517 | E61: =+E62 -> 5.0219517 | F61: =+F62 -> 5.0219517 | G61: =+G62 -> 5.0219517 | H61: =+H62 -> 5.0219517 | I61: =+I62 -> 5.0219517 | J61: =+J62 -> 5.0219517 | ... N61: =+N62 -> 5.0219517 | O61: =SUM(C61:N61) -> 60.263421
B62: · Bonos de consolidación | C62: 5.0219517 | D62: 5.0219517 | E62: 5.0219517 | F62: 5.0219517 | G62: 5.0219517 | H62: 5.0219517 | I62: 5.0219517 | J62: 5.0219517 | K62: 5.0219517 | L62: 5.0219517 | M62: 5.0219517 | N62: 5.0219517 | O62: =SUM(C62:N62) -> 60.263421
B63: · No ajustable por CER | C63: =+C64+C65 -> 0.08578722 | D63: =+D64+D65 -> 0 | E63: =+E64+E65 -> 0 | F63: =+F64+F65 -> 0 | G63: =+G64+G65 -> 0 | H63: =+H64+H65 -> 0 | I63: =+I64+I65 -> 0 | J63: =+J64+J65 -> 0 | ... N63: =+N64+N65 -> 0 | O63: =SUM(C63:N63) -> 0.08578722
B64: · Bonos de consolidación | C64: 0 | D64: 0 | E64: 0 | F64: 0 | G64: 0 | H64: 0 | I64: 0 | J64: 0 | K64: 0 | L64: 0 | M64: 0 | N64: 0 | O64: =SUM(C64:N64) -> 0
B65: · Otros | C65: 0.08578722 | D65: 0 | E65: 0 | F65: 0 | G65: 0 | H65: 0 | I65: 0 | J65: 0 | K65: 0 | L65: 0 | M65: 0 | N65: 0 | O65: =SUM(C65:N65) -> 0.08578722
B67: TOTAL DEUDA DENOMINADA EN PESOS | C67: =+C68+C69 -> 28.774789 | D67: =+D68+D69 -> 1424.7081 | E67: =+E68+E69 -> 7915.4171 | F67: =+F68+F69 -> 2231.0797 | G67: =+G68+G69 -> 12.235576 | H67: =+H68+H69 -> 2833.438 | I67: =+I68+I69 -> 9.4336645 | J67: =+J68+J69 -> 5067.947 | ... N67: =+N68+N69 -> 11.267712 | O67: =SUM(C67:N67) -> 20192.01
B68: · Deuda ajustable por CER | C68: 5.0219517 | D68: 5.0219517 | E68: 6897.379 | F68: 5.0219517 | G68: 5.0219517 | H68: 5.0219517 | I68: 5.0219517 | J68: 5060.6267 | K68: 5.0219517 | L68: 5.0219517 | M68: 5.0219517 | N68: 5.0219517 | O68: =SUM(C68:N68) -> 12008.225
B69: · Deuda no ajustable por CER | C69: 23.752837 | D69: 1419.6862 | E69: 1018.0381 | F69: 2226.0577 | G69: 7.2136241 | H69: 2828.416 | I69: 4.4117128 | J69: 7.3202838 | K69: 6.1391702 | L69: 628.85441 | M69: 7.6488762 | N69: 6.2457603 | O69: =SUM(C69:N69) -> 8183.7847
B70: TOTAL DEUDA EN MONEDA EXTRANJERA | C70: 10265.364 | D70: 149.4092 | E70: 3079.0498 | F70: 3006.5711 | G70: 181.83311 | H70: 2953.4258 | I70: 3148.7849 | J70: 2457.1128 | K70: 1219.0428 | L70: 2997.214 | M70: 192.55976 | N70: 1446.7781 | O70: =SUM(C70:N70) -> 31097.145
B72: (1) Incluye bonos de consolidación, amparos y excepciones.

Sheet A.3.5
A1: Indice
B2: MINISTERIO DE ECONOMÍA
B3: SECRETARÍA DE FINANZAS
B6: PERFIL MENSUAL DE VENCIMIENTOS DE INTERÉS DE LA DEUDA BRUTA DE LA ADMINISTRACIÓN CENTRAL
B8: (En millones de U$S - Stock de deuda y tipo de cambio 31/12/2021)
C9: 44927 | D9: 44958 | E9: 44986 | F9: 45017 | G9: 45047 | H9: 45078 | I9: 45108 | J9: 45139 | K9: 45170 | L9: 45200 | M9: 45231 | N9: 45261 | O9: 2023
B11: PERFIL DE VENCIMIENTOS DE LA DEUDA EN SITUACIÓN DE PAGO NORMAL
B13: TOTAL | C13: =SUM(C14:C15) -> 1102.8275 | D13: =SUM(D14:D15) -> 319.09867 | E13: =SUM(E14:E15) -> 226.72516 | F13: =SUM(F14:F15) -> 205.66141 | G13: =SUM(G14:G15) -> 209.09995 | H13: =SUM(H14:H15) -> 300.56128 | I13: =SUM(I14:I15) -> 1098.8062 | J13: =SUM(J14:J15) -> 144.59705 | ... N13: =SUM(N14:N15) -> 297.00415 | O13: =SUM(C13:N13) -> 4374.6318
B14: CORTO PLAZO | C14: 0 | D14: 0 | E14: 0 | F14: 0 | G14: 0 | H14: 0 | I14: 0 | J14: 0 | K14: 0 | L14: 0 | M14: 0 | N14: 0 | O14: =SUM(C14:N14) -> 0
B15: MEDIANO Y LARGO PLAZO | C15: 1102.8275 | D15: 319.09867 | E15: 226.72516 | F15: 205.66141 | G15: 209.09995 | H15: 300.56128 | I15: 1098.8062 | J15: 144.59705 | K15: 160.32552 | L15: 200.77269 | M15: 109.15219 | N15: 297.00415 | O15: =SUM(C15:N15) -> 4374.6318
B17: PRÉSTAMOS | C17: =+C18+C23+C25+C27+C28+C31 -> 59.061219 | D17: =+D18+D23+D25+D27+D28+D31 -> 214.67304 | E17: =+E18+E23+E25+E27+E28+E31 -> 89.902173 | F17: =+F18+F23+F25+F27+F28+F31 -> 47.068105 | G17: =+G18+G23+G25+G27+G28+G31 -> 185.06802 | H17: =+H18+H23+H25+H27+H28+H31 -> 52.529642 | I17: =+I18+I23+I25+I27+I28+I31 -> 55.280217 | J17: =+J18+J23+J25+J27+J28+J31 -> 97.08165 | ... N17: =+N18+N23+N25+N27+N28+N31 -> 49.466508 | O17: =SUM(C17:N17) -> 1069.2548
B18: Organismos Internacionales | C18: =+SUM(C19:C22) -> 27.681496 | D18: =+SUM(D19:D22) -> 208.308 | E18: =+SUM(E19:E22) -> 80.60308 | F18: =+SUM(F19:F22) -> 39.139812 | G18: =+SUM(G19:G22) -> 178.13148 | H18: =+SUM(H19:H22) -> 28.022133 | I18: =+SUM(I19:I22) -> 26.190863 | J18: =+SUM(J19:J22) -> 91.433951 | ... N18: =+SUM(N19:N22) -> 26.655325 | O18: =SUM(C18:N18) -> 902.1777
B19: . BIRF | C19: 2.9108293 | D19: 1.8333742 | E19: 16.839084 | F19: 14.99913 | G19: 6.6652128 | H19: 15.918444 | I19: 2.9032423 | J19: 1.7845148 | K19: 16.679554 | L19: 14.909473 | M19: 6.7053068 | N19: 15.6701 | O19: =SUM(C19:N19) -> 117.81826
B20: . BID | C20: 18.124019 | D20: 9.9315435 | E20: 54.283512 | F20: 17.156176 | G20: 38.484091 | H20: 4.0581463 | I20: 17.177008 | J20: 9.2483471 | K20: 53.118286 | L20: 16.486578 | M20: 37.434908 | N20: 3.7752421 | O20: =SUM(C20:N20) -> 279.27786
B21: . FMI | C21: 0 | D21: 188.23584 | E21: 0 | F21: 0 | G21: 126.01622 | H21: 0 | I21: 0 | J21: 73.183726 | K21: 0 | L21: 0 | M21: 28.056139 | N21: 0 | O21: =SUM(C21:N21) -> 415.49192
B22: . Otros | C22: 6.6466471 | D22: 8.3072459 | E22: 9.480484 | F22: 6.9845065 | G22: 6.965959 | H22: 8.0455426 | I22: 6.1106121 | J22: 7.217363 | K22: 9.032132 | L22: 6.7594546 | M22: 6.8297351 | N22: 7.2099825 | O22: =SUM(C22:N22) -> 89.589664
B23: Préstamos Garantizados | C23: =SUM(C24:C24) -> 3.2065201 | D23: =SUM(D24:D24) -> 3.2065201 | E23: =SUM(E24:E24) -> 2.9746257 | F23: =SUM(F24:F24) -> 3.2065201 | G23: =SUM(G24:G24) -> 3.129222 | H23: =SUM(H24:H24) -> 3.2065201 | I23: =SUM(I24:I24) -> 3.129222 | J23: =SUM(J24:J24) -> 3.2065201 | ... N23: =SUM(N24:N24) -> 3.129222 | O23: =SUM(C23:N23) -> 37.937154
B24: . En moneda nacional ajustable por CER | C24: 3.2065201 | D24: 3.2065201 | E24: 2.9746257 | F24: 3.2065201 | G24: 3.129222 | H24: 3.2065201 | I24: 3.129222 | J24: 3.2065201 | K24: 3.2065201 | L24: 3.129222 | M24: 3.2065201 | N24: 3.129222 | O24: =SUM(C24:N24) -> 37.937154
B25: Banca Comercial | C25: =+C26 -> 0.062811338 | D25: =+D26 -> 0.14681512 | E25: =+E26 -> 0.00072809352 | F25: =+F26 -> 0.79898529 | G25: =+G26 -> 1.4919644 | H25: =+H26 -> 0.083194211 | I25: =+I26 -> 0.051242815 | J25: =+J26 -> 0.12341173 | ... N25: =+N26 -> 0.073160843 | O25: =SUM(C25:N25) -> 4.9361828
B26: . En moneda extranjera | C26: 0.062811338 | D26: 0.14681512 | E26: 0.00072809352 | F26: 0.79898529 | G26: 1.4919644 | H26: 0.083194211 | I26: 0.051242815 | J26: 0.12341173 | K26: 0.00046630608 | L26: 0.75412216 | M26: 1.3492805 | N26: 0.073160843 | O26: =SUM(C26:N26) -> 4.9361828
B27: Organismos Oficiales | C27: 25.599149 | D27: 0.10797777 | E27: 0.12976483 | F27: 1.6613469 | G27: 0.34405524 | H27: 19.121066 | I27: 23.580133 | J27: 0.10514691 | K27: 0.12790093 | L27: 1.5915024 | M27: 0.27083937 | N27: 17.709347 | O27: =SUM(C27:N27) -> 90.348229
B28: Pagarés del Tesoro | C28: =+C29 -> 0 | D28: =+D29 -> 0 | E28: =+E29 -> 3.3506061 | F28: =+F29 -> 0 | G28: =+G29 -> 0 | H28: =+H29 -> 0 | I28: =+I29 -> 0 | J28: =+J29 -> 0 | ... N28: =+N29 -> 0 | O28: =SUM(C28:N28) -> 6.7012121
B29: . En moneda nacional ajustable por CER | C29: =+C30 -> 0 | D29: =+D30 -> 0 | E29: =+E30 -> 3.3506061 | F29: =+F30 -> 0 | G29: =+G30 -> 0 | H29: =+H30 -> 0 | I29: =+I30 -> 0 | J29: =+J30 -> 0 | ... N29: =+N30 -> 0 | O29: =SUM(C29:N29) -> 6.7012121
B30: Pagaré 2038 - B.N.A. | C30: 0 | D30: 0 | E30: 3.3506061 | F30: 0 | G30: 0 | H30: 0 | I30: 0 | J30: 0 | K30: 3.3506061 | L30: 0 | M30: 0 | N30: 0 | O30: =SUM(C30:N30) -> 6.7012121
B31: Avales | C31: =C32+C33 -> 2.5112435 | D31: =D32+D33 -> 2.9037277 | E31: =E32+E33 -> 2.843368 | F31: =F32+F33 -> 2.2614407 | G31: =G32+G33 -> 1.9712964 | H31: =H32+H33 -> 2.0967295 | I31: =I32+I33 -> 2.3287568 | J31: =J32+J33 -> 2.2126206 | ... N31: =N32+N33 -> 1.899453 | O31: =SUM(C31:N31) -> 27.15428
B32: . En moneda nacional | C32: 2.0084656 | D32: 1.9994326 | E32: 1.9902265 | F32: 1.9808459 | G32: 1.9712964 | H32: 1.9615733 | I32: 1.9516733 | J32: 1.9415937 | K32: 1.9313325 | L32: 1.9208878 | M32: 1.9102584 | N32: 1.899453 | O32: =SUM(C32:N32) -> 23.467039
B33: . En moneda extranjera | C33: 0.50277795 | D33: 0.9042951 | E33: 0.85314142 | F33: 0.28059478 | G33: 0 | H33: 0.13515622 | I33: 0.37708347 | J33: 0.27102692 | K33: 0.36316519 | L33: 0 | M33: 0 | N33: 0 | O33: =SUM(C33:N33) -> 3.6872411
B35: TÍTULOS PÚBLICOS Y LETRAS DEL TESORO | C35: =+C36+C51+SUM(C64:C111)+C114 -> 1043.7663 | D35: =+D36+D51+SUM(D64:D111)+D114 -> 104.42562 | E35: =+E36+E51+SUM(E64:E111)+E114 -> 136.82299 | F35: =+F36+F51+SUM(F64:F111)+F114 -> 158.5933 | G35: =+G36+G51+SUM(G64:G111)+G114 -> 24.031933 | H35: =+H36+H51+SUM(H64:H111)+H114 -> 248.03164 | I35: =+I36+I51+SUM(I64:I111)+I114 -> 1043.526 | J35: =+J36+J51+SUM(J64:J111)+J114 -> 47.515403 | ... O35: =+O36+O51+SUM(O64:O111)+O114 -> 3305.377
B36: PAR | C36: =+C37+C40+C46+C48 -> 0 | D36: =+D37+D40+D46+D48 -> 0 | E36: =+E37+E40+E46+E48 -> 19.24812 | F36: =+F37+F40+F46+F48 -> 0 | G36: =+G37+G40+G46+G48 -> 0 | H36: =+H37+H40+H46+H48 -> 0 | I36: =+I37+I40+I46+I48 -> 0 | J36: =+J37+J40+J46+J48 -> 0 | ... N36: =+N37+N40+N46+N48 -> 0 | O36: =SUM(C36:N36) -> 38.49624
B37: Par/$+CER/T.Fija/2038 | C37: =+C38+C39 -> 0 | D37: =+D38+D39 -> 0 | E37: =+E38+E39 -> 6.4858394 | F37: =+F38+F39 -> 0 | G37: =+G38+G39 -> 0 | H37: =+H38+H39 -> 0 | I37: =+I38+I39 -> 0 | J37: =+J38+J39 -> 0 | ... N37: =+N38+N39 -> 0 | O37: =SUM(C37:N37) -> 12.971679
B38: Emisión Canje 2005 | C38: 0 | D38: 0 | E38: 6.4601474 | F38: 0 | G38: 0 | H38: 0 | I38: 0 | J38: 0 | K38: 6.4601474 | L38: 0 | M38: 0 | N38: 0 | O38: =SUM(C38:N38) -> 12.920295
B39: Emisión Canje 2010 | C39: 0 | D39: 0 | E39: 0.025692021 | F39: 0 | G39: 0 | H39: 0 | I39: 0 | J39: 0 | K39: 0.025692021 | L39: 0 | M39: 0 | N39: 0 | O39: =SUM(C39:N39) -> 0.051384042
B40: Par/U$S/T.Fija/2038 | C40: =+C41+C43 -> 0 | D40: =+D41+D43 -> 0 | E40: =+E41+E43 -> 1.3194066 | F40: =+F41+F43 -> 0 | G40: =+G41+G43 -> 0 | H40: =+H41+H43 -> 0 | I40: =+I41+I43 -> 0 | J40: =+J41+J43 -> 0 | ... N40: =+N41+N43 -> 0 | O40: =SUM(C40:N40) -> 2.6388132
B41: Emisión Canje 2005 | C41: =+C42 -> 0 | D41: =+D42 -> 0 | E41: =+E42 -> 0.54348023 | F41: =+F42 -> 0 | G41: =+G42 -> 0 | H41: =+H42 -> 0 | I41: =+I42 -> 0 | J41: =+J42 -> 0 | ... O41: =+O42 -> 1.0869605
B42: Leg. Argentina | C42: 0 | D42: 0 | E42: 0.54348023 | F42: 0 | G42: 0 | H42: 0 | I42: 0 | J42: 0 | K42: 0.54348023 | L42: 0 | M42: 0 | N42: 0 | O42: =SUM(C42:N42) -> 1.0869605
B43: Emisión Canje 2010 | C43: =+C44+C45 -> 0 | D43: =+D44+D45 -> 0 | E43: =+E44+E45 -> 0.77592636 | F43: =+F44+F45 -> 0 | G43: =+G44+G45 -> 0 | H43: =+H44+H45 -> 0 | I43: =+I44+I45 -> 0 | J43: =+J44+J45 -> 0 | ... N43: =+N44+N45 -> 0 | O43: =SUM(C43:N43) -> 1.5518527
B44: Leg. Nueva York | C44: 0 | D44: 0 | E44: 0.67161675 | F44: 0 | G44: 0 | H44: 0 | I44: 0 | J44: 0 | K44: 0.67161675 | L44: 0 | M44: 0 | N44: 0 | O44: =SUM(C44:N44) -> 1.3432335
B45: Leg. Argentina | C45: 0 | D45: 0 | E45: 0.10430961 | F45: 0 | G45: 0 | H45: 0 | I45: 0 | J45: 0 | K45: 0.10430961 | L45: 0 | M45: 0 | N45: 0 | O45: =SUM(C45:N45) -> 0.20861922
B46: Par/EUR/T.Fija/2038 | C46: =+C47 -> 0 | D46: =+D47 -> 0 | E46: =+E47 -> 10.915441 | F46: =+F47 -> 0 | G46: =+G47 -> 0 | H46: =+H47 -> 0 | I46: =+I47 -> 0 | J46: =+J47 -> 0 | ... O46: =+O47 -> 21.830881
B47: Emisión Canje 2010 | C47: 0 | D47: 0 | E47: 10.915441 | F47: 0 | G47: 0 | H47: 0 | I47: 0 | J47: 0 | K47: 10.915441 | L47: 0 | M47: 0 | N47: 0 | O47: =SUM(C47:N47) -> 21.830881
B48: Par/JPY/T.Fija/2038 | C48: =+C49+C50 -> 0 | D48: =+D49+D50 -> 0 | E48: =+E49+E50 -> 0.52743363 | F48: =+F49+F50 -> 0 | G48: =+G49+G50 -> 0 | H48: =+H49+H50 -> 0 | I48: =+I49+I50 -> 0 | J48: =+J49+J50 -> 0 | ... N48: =+N49+N50 -> 0 | O48: =SUM(C48:N48) -> 1.0548673
B49: Emisión Canje 2005 | C49: 0 | D49: 0 | E49: 0.50257694 | F49: 0 | G49: 0 | H49: 0 | I49: 0 | J49: 0 | K49: 0.50257694 | L49: 0 | M49: 0 | N49: 0 | O49: =SUM(C49:N49) -> 1.0051539
B50: Emisión Canje 2010 | C50: 0 | D50: 0 | E50: 0.024856691 | F50: 0 | G50: 0 | H50: 0 | I50: 0 | J50: 0 | K50: 0.024856691 | L50: 0 | M50: 0 | N50: 0 | O50: =SUM(C50:N50) -> 0.049713383
B51: DESCUENTO | C51: =+C52+C55+C61 -> 0 | D51: =+D52+D55+D61 -> 0 | E51: =+E52+E55+E61 -> 0 | F51: =+F52+F55+F61 -> 0 | G51: =+G52+G55+G61 -> 0 | H51: =+H52+H55+H61 -> 103.40109 | I51: =+I52+I55+I61 -> 0 | J51: =+J52+J55+J61 -> 0 | ... O51: =+O52+O55+O61 -> 206.80217
B52: Discount/$+CER/5,83%/2033 | C52: =+C53+C54 -> 0 | D52: =+D53+D54 -> 0 | E52: =+E53+E54 -> 0 | F52: =+F53+F54 -> 0 | G52: =+G53+G54 -> 0 | H52: =+H53+H54 -> 100.97971 | I52: =+I53+I54 -> 0 | J52: =+J53+J54 -> 0 | ... N52: =+N53+N54 -> 100.97971 | O52: =SUM(C52:N52) -> 201.95941
B53: Emisión Canje 2005 | C53: 0 | D53: 0 | E53: 0 | F53: 0 | G53: 0 | H53: 99.780273 | I53: 0 | J53: 0 | K53: 0 | L53: 0 | M53: 0 | N53: 99.780273 | O53: =SUM(C53:N53) -> 199.56055
B54: Emisión Canje 2010 | C54: 0 | D54: 0 | E54: 0 | F54: 0 | G54: 0 | H54: 1.1994328 | I54: 0 | J54: 0 | K54: 0 | L54: 0 | M54: 0 | N54: 1.1994328 | O54: =SUM(C54:N54) -> 2.3988656
B55: Discount/U$S/8,28%/2033 | C55: =+C56+C59 -> 0 | D55: =+D56+D59 -> 0 | E55: =+E56+E59 -> 0 | F55: =+F56+F59 -> 0 | G55: =+G56+G59 -> 0 | H55: =+H56+H59 -> 0.57307193 | I55: =+I56+I59 -> 0 | J55: =+J56+J59 -> 0 | ... N55: =+N56+N59 -> 0.57307193 | O55: =SUM(C55:N55) -> 1.1461439
B56: Emisión Canje 2005 | C56: =+C57+C58 -> 0 | D56: =+D57+D58 -> 0 | E56: =+E57+E58 -> 0 | F56: =+F57+F58 -> 0 | G56: =+G57+G58 -> 0 | H56: =+H57+H58 -> 0.40734102 | I56: =+I57+I58 -> 0 | J56: =+J57+J58 -> 0 | ... N56: =+N57+N58 -> 0.40734102 | O56: =SUM(C56:N56) -> 0.81468204
B57: Leg. Nueva York | C57: 0 | D57: 0 | E57: 0 | F57: 0 | G57: 0 | H57: 0 | I57: 0 | J57: 0 | K57: 0 | L57: 0 | M57: 0 | N57: 0 | O57: =SUM(C57:N57) -> 0
B58: Leg. Argentina | C58: 0 | D58: 0 | E58: 0 | F58: 0 | G58: 0 | H58: 0.40734102 | I58: 0 | J58: 0 | K58: 0 | L58: 0 | M58: 0 | N58: 0.40734102 | O58: =SUM(C58:N58) -> 0.81468204
B59: Emisión Canje 2010 | C59: =+C60 -> 0 | D59: =+D60 -> 0 | E59: =+E60 -> 0 | F59: =+F60 -> 0 | G59: =+G60 -> 0 | H59: =+H60 -> 0.16573091 | I59: =+I60 -> 0 | J59: =+J60 -> 0 | ... O59: =+O60 -> 0.33146181
B60: Leg. Argentina | C60: 0 | D60: 0 | E60: 0 | F60: 0 | G60: 0 | H60: 0.16573091 | I60: 0 | J60: 0 | K60: 0 | L60: 0 | M60: 0 | N60: 0.16573091 | O60: =SUM(C60:N60) -> 0.33146181
B61: Discount/JPY/4,33%/2033 | C61: =+C62+C63 -> 0 | D61: =+D62+D63 -> 0 | E61: =+E62+E63 -> 0 | F61: =+F62+F63 -> 0 | G61: =+G62+G63 -> 0 | H61: =+H62+H63 -> 1.848308 | I61: =+I62+I63 -> 0 | J61: =+J62+J63 -> 0 | ... N61: =+N62+N63 -> 1.848308 | O61: =SUM(C61:N61) -> 3.6966159
B62: Emisión Canje 2005 | C62: 0 | D62: 0 | E62: 0 | F62: 0 | G62: 0 | H62: 1.2752696 | I62: 0 | J62: 0 | K62: 0 | L62: 0 | M62: 0 | N62: 1.2752696 | O62: =SUM(C62:N62) -> 2.5505392
B63: Emisión Canje 2010 | C63: 0 | D63: 0 | E63: 0 | F63: 0 | G63: 0 | H63: 0.57303837 | I63: 0 | J63: 0 | K63: 0 | L63: 0 | M63: 0 | N63: 0.57303837 | O63: =SUM(C63:N63) -> 1.1460767
B64: CUASIPAR/$+CER/3,31%/2045 | C64: 0 | D64: 0 | E64: 0 | F64: 0 | G64: 0 | H64: 139.02581 | I64: 0 | J64: 0 | K64: 0 | L64: 0 | M64: 0 | N64: 139.02581 | O64: =SUM(C64:N64) -> 278.05161
B65: BONAR/$/6,72763943919512%/31-12-2028 | C65: 1.6855277 | D65: 1.6664734 | E65: 1.6466894 | F65: 1.6277251 | G65: 1.6083467 | H65: 1.5888597 | I65: 1.5692635 | J65: 1.5495573 | K65: 1.5297408 | L65: 1.5098131 | M65: 1.4897736 | N65: 1.4696219 | O65: =SUM(C65:N65) -> 18.941392
B66: BONAR/$/BADLAR+200PB/03-04-2022 | C66: 0 | D66: 0 | E66: 0 | F66: 0 | G66: 0 | H66: 0 | I66: 0 | J66: 0 | K66: 0 | L66: 0 | M66: 0 | N66: 0 | O66: =SUM(C66:N66) -> 0
B67: BONAR/U$S/1,00%/05-08-2023 | C67: 0 | D67: 0.12499448 | E67: 0 | F67: 0 | G67: 0 | H67: 0 | I67: 0 | J67: 0.12499448 | K67: 0 | L67: 0 | M67: 0 | N67: 0 | O67: =SUM(C67:N67) -> 0.24998896
B68: BONAR/U$S/5,75%/18-04-2025 | C68: 0 | D68: 0 | E68: 0 | F68: 0.05637323 | G68: 0 | H68: 0 | I68: 0 | J68: 0 | K68: 0 | L68: 0.03777006 | M68: 0 | N68: 0 | O68: =SUM(C68:N68) -> 0.09414329
B69: BONAR/U$S/7,625%/18-04-2037 | C69: 0 | D69: 0 | E69: 0 | F69: 0.15331126 | G69: 0 | H69: 0 | I69: 0 | J69: 0 | K69: 0 | L69: 0.15331126 | M69: 0 | N69: 0 | O69: =SUM(C69:N69) -> 0.30662252
B70: BONAR/U$S/8,00%/08-10-2020 | C70: 0 | D70: 0 | E70: 0 | F70: 0 | G70: 0 | H70: 0 | I70: 0 | J70: 0 | K70: 0 | L70: 0 | M70: 0 | N70: 0 | O70: =SUM(C70:N70) -> 0
B71: BONAR/U$S/8,75%/07-05-2024 | C71: 0 | D71: 0 | E71: 0 | F71: 0 | G71: 0.4559544 | H71: 0 | I71: 0 | J71: 0 | K71: 0 | L71: 0 | M71: 0.22825055 | N71: 0 | O71: =SUM(C71:N71) -> 0.68420495
B72: BONCER/$/1,20%+CER/18-03-2022 | C72: 0 | D72: 0 | E72: 0 | F72: 0 | G72: 0 | H72: 0 | I72: 0 | J72: 0 | K72: 0 | L72: 0 | M72: 0 | N72: 0 | O72: =SUM(C72:N72) -> 0
B73: BONCER/$/1,55%+CER/26-07-2024 | C73: 11.756518 | D73: 0 | E73: 0 | F73: 0 | G73: 0 | H73: 0 | I73: 11.756518 | J73: 0 | K73: 0 | L73: 0 | M73: 0 | N73: 0 | O73: =SUM(C73:N73) -> 23.513035
... B110: BONO R.A./U$S/STEP UP/09-07-2041 | C110: 26.302979 | D110: 0 | E110: 0 | F110: 0 | G110: 0 | H110: 0 | I110: 26.302979 | J110: 0 | K110: 0 | L110: 0 | M110: 0 | N110: 0 | O110: =SUM(C110:N110) -> 52.605958
B111: LETRAS DEL TESORO | C111: =+C112+C113 -> 0 | D111: =+D112+D113 -> 0 | E111: =+E112+E113 -> 0 | F111: =+F112+F113 -> 0 | G111: =+G112+G113 -> 0 | H111: =+H112+H113 -> 0 | I111: =+I112+I113 -> 0 | J111: =+J112+J113 -> 0 | ... N111: =+N112+N113 -> 0 | O111: =SUM(C111:N111) -> 0
B112: . En moneda nacional | C112: 0 | D112: 0 | E112: 0 | F112: 0 | G112: 0 | H112: 0 | I112: 0 | J112: 0 | K112: 0 | L112: 0 | M112: 0 | N112: 0 | O112: =SUM(C112:N112) -> 0
B113: . En moneda extranjera | C113: 0 | D113: 0 | E113: 0 | F113: 0 | G113: 0 | H113: 0 | I113: 0 | J113: 0 | K113: 0 | L113: 0 | M113: 0 | N113: 0 | O113: =SUM(C113:N113) -> 0
B114: OTROS (1) | C114: =+C115+C120 -> 0.12958113 | D114: =+D115+D120 -> 0.12121121 | E114: =+E115+E120 -> 0.13897129 | F114: =+F115+F120 -> 0.10447137 | G114: =+G115+G120 -> 0.096101455 | H114: =+H115+H120 -> 0.087731533 | I114: =+I115+I120 -> 0.079361615 | J114: =+J115+J120 -> 0.070991693 | ... N114: =+N115+N120 -> 0.037512018 | O114: =SUM(C114:N114) -> 1.0548189
B115: . En moneda nacional | C115: =+C116+C118 -> 0.12958113 | D115: =+D116+D118 -> 0.12121121 | E115: =+E116+E118 -> 0.11284129 | F115: =+F116+F118 -> 0.10447137 | G115: =+G116+G118 -> 0.096101455 | H115: =+H116+H118 -> 0.087731533 | I115: =+I116+I118 -> 0.079361615 | J115: =+J116+J118 -> 0.070991693 | ... O115: =+O116+O118 -> 1.0025589
B116: · Ajustable por CER | C116: =+C117 -> 0.12958113 | D116: =+D117 -> 0.12121121 | E116: =+E117 -> 0.11284129 | F116: =+F117 -> 0.10447137 | G116: =+G117 -> 0.096101455 | H116: =+H117 -> 0.087731533 | I116: =+I117 -> 0.079361615 | J116: =+J117 -> 0.070991693 | ... N116: =+N117 -> 0.037512018 | O116: =SUM(C116:N116) -> 1.0025589
B117: · Bonos de consolidación | C117: 0.12958113 | D117: 0.12121121 | E117: 0.11284129 | F117: 0.10447137 | G117: 0.096101455 | H117: 0.087731533 | I117: 0.079361615 | J117: 0.070991693 | K117: 0.062621775 | L117: 0.054251853 | M117: 0.045881935 | N117: 0.037512018 | O117: =SUM(C117:N117) -> 1.0025589
B118: · No ajustable por CER | C118: =+C119 -> 0 | D118: =+D119 -> 0 | E118: =+E119 -> 0 | F118: =+F119 -> 0 | G118: =+G119 -> 0 | H118: =+H119 -> 0 | I118: =+I119 -> 0 | J118: =+J119 -> 0 | ... N118: =+N119 -> 0 | O118: =SUM(C118:N118) -> 0
B119: · Bonos de consolidación | C119: 0 | D119: 0 | E119: 0 | F119: 0 | G119: 0 | H119: 0 | I119: 0 | J119: 0 | K119: 0 | L119: 0 | M119: 0 | N119: 0 | O119: =SUM(C119:N119) -> 0
B120: . En moneda extranjera | C120: =+C121 -> 0 | D120: =+D121 -> 0 | E120: =+E121 -> 0.02613 | F120: =+F121 -> 0 | G120: =+G121 -> 0 | H120: =+H121 -> 0 | I120: =+I121 -> 0 | J120: =+J121 -> 0 | ... N120: =+N121 -> 0 | O120: =SUM(C120:N120) -> 0.05226
B121: · Otros | C121: 0 | D121: 0 | E121: 0.02613 | F121: 0 | G121: 0 | H121: 0 | I121: 0 | J121: 0 | K121: 0.02613 | L121: 0 | M121: 0 | N121: 0 | O121: =SUM(C121:N121) -> 0.05226
B123: TOTAL DEUDA DENOMINADA EN PESOS | C123: =+C124+C125 -> 25.571859 | D123: =+D124+D125 -> 109.50658 | E123: =+E124+E125 -> 132.35004 | F123: =+F124+F125 -> 163.57099 | G123: =+G124+G125 -> 28.676497 | H123: =+H124+H125 -> 250.77835 | I123: =+I124+I125 -> 25.197533 | J123: =+J124+J125 -> 52.538522 | ... N123: =+N124+N125 -> 250.14493 | O123: =SUM(C123:N123) -> 1294.9091
B124: · Deuda ajustable por CER | C124: 15.092619 | D124: 39.980866 | E124: 124.73099 | F124: 27.206829 | G124: 16.010158 | H124: 243.29976 | I124: 14.965101 | J124: 39.930646 | K124: 60.968849 | L124: 27.079311 | M124: 16.037237 | N124: 243.17225 | O124: =SUM(C124:N124) -> 868.47461
B125: · Deuda no ajustable por CER | C125: 10.479241 | D125: 69.525717 | E125: 7.6190536 | F125: 136.36416 | G125: 12.666339 | H125: 7.4785906 | I125: 10.232431 | J125: 12.607876 | K125: 7.2467588 | L125: 133.00117 | M125: 12.240493 | N125: 6.9726883 | O125: =SUM(C125:N125) -> 426.43451
B126: TOTAL DEUDA EN MONEDA EXTRANJERA | C126: 1077.2556 | D126: 209.59209 | E126: 94.375125 | F126: 42.090424 | G126: 180.42345 | H126: 49.782929 | I126: 1073.6087 | J126: 92.058531 | K126: 92.109915 | L126: 40.692211 | M126: 80.874459 | N126: 46.859213 | O126: =SUM(C126:N126) -> 3079.7227
B128: (1) Incluye bonos de consolidación, amparos y excepciones.

Sheet A.3.6
A1: Indice
B2: MINISTERIO DE ECONOMÍA
B3: SECRETARÍA DE FINANZAS
B6: PERFIL ANUAL DE VENCIMIENTOS DE CAPITAL E INTERÉS DE LA DEUDA BRUTA DE LA ADMINISTRACIÓN CENTRAL
B7: DEUDA EN SITUACIÓN DE PAGO NORMAL (1)
B9: (En miles de U$S - Tipo de cambio 31/12/2021)
B10: TIPO DE ACREEDOR | C10: 2022 | D10: 2023 | E10: 2024 | F10: 2025 | G10: 2026 | H10: 2027 | I10: 2028 | J10: 2029 | K10: 2030 | L10: 2031 | M10: 2032/2089 (3) | N10: TOTAL
B13: TÍTULOS PÚBLICOS | C13: =+C15+C16 -> 31925377 | D13: =+D15+D16 -> 28241565 | E13: =+E15+E16 -> 24766012 | F13: =+F15+F16 -> 22910379 | G13: =+G15+G16 -> 12372093 | H13: =+H15+H16 -> 11236299 | I13: =+I15+I16 -> 13335137 | J13: =+J15+J16 -> 17762343 | ... N13: =+N15+N16 -> 2.8026583e+08
B14: Como % del total de servicios (2) | C14: =+C13/$N$70 -> 0.076344494 | D14: =+D13/$N$70 -> 0.067535238 | E14: =+E13/$N$70 -> 0.059224003 | F14: =+F13/$N$70 -> 0.054786549 | G14: =+G13/$N$70 -> 0.029585904 | H14: =+H13/$N$70 -> 0.026869833 | I14: =+I13/$N$70 -> 0.031888872 | J14: =+J13/$N$70 -> 0.042475837 | ... N14: =+N13/$N$70 -> 0.67021144
B15: CAPITAL | C15: 28266225 | D15: 24936188 | E15: 20770837 | F15: 18711679 | G15: 8293975.2 | H15: 7399836.1 | I15: 9274782.8 | J15: 13836676 | K15: 8478240.1 | L15: 25134218 | M15: 65266351 | N15: =SUM(C15:M15) -> 2.3036901e+08
B16: INTERÉS | C16: 3659152 | D16: 3305377 | E16: 3995174.5 | F16: 4198699.5 | G16: 4078117.6 | H16: 3836463.1 | I16: 4060353.9 | J16: 3925667.6 | K16: 3842870.7 | L16: 3507238.7 | M16: 11487709 | N16: =SUM(C16:M16) -> 49896823
B18: LETRAS DEL TESORO | C18: =+C20+C21 -> 23286111 | D18: =+D20+D21 -> 448025.78 | E18: =+E20+E21 -> 45310.327 | F18: =+F20+F21 -> 0 | G18: =+G20+G21 -> 0 | H18: =+H20+H21 -> 0 | I18: =+I20+I21 -> 0 | J18: =+J20+J21 -> 0 | ... N18: =+N20+N21 -> 23779447
B19: Como % del total de servicios (2) | C19: =+C18/$N$70 -> 0.055685053 | D19: =+D18/$N$70 -> 0.0010713828 | E19: =+E18/$N$70 -> 0.00010835249 | F19: =+F18/$N$70 -> 0 | G19: =+G18/$N$70 -> 0 | H19: =+H18/$N$70 -> 0 | I19: =+I18/$N$70 -> 0 | J19: =+J18/$N$70 -> 0 | ... N19: =+N18/$N$70 -> 0.056864788
B20: CAPITAL | C20: 23216788 | D20: 448025.78 | E20: 45310.327 | F20: 0 | G20: 0 | H20: 0 | I20: 0 | J20: 0 | K20: 0 | L20: 0 | M20: 0 | N20: =SUM(C20:M20) -> 23710124
B21: INTERÉS | C21: 69322.389 | D21: 0 | E21: 0 | F21: 0 | G21: 0 | H21: 0 | I21: 0 | J21: 0 | K21: 0 | L21: 0 | M21: 0 | N21: =SUM(C21:M21) -> 69322.389
B23: LETRAS EN GARANTÍA | C23: =+C25+C26 -> 345913.78 | D23: =+D25+D26 -> 351538.78 | E23: =+E25+E26 -> 351538.78 | F23: =+F25+F26 -> 351538.78 | G23: =+G25+G26 -> 351538.78 | H23: =+H25+H26 -> 351538.78 | I23: =+I25+I26 -> 351538.78 | J23: =+J25+J26 -> 351538.78 | ... N23: =+N25+N26 -> 6410393.6
B24: Como % del total de servicios (2) | C24: =+C23/$N$70 -> 0.00082719812 | D24: =+D23/$N$70 -> 0.00084064942 | E24: =+E23/$N$70 -> 0.00084064942 | F24: =+F23/$N$70 -> 0.00084064942 | G24: =+G23/$N$70 -> 0.00084064942 | H24: =+H23/$N$70 -> 0.00084064942 | I24: =+I23/$N$70 -> 0.00084064942 | J24: =+J23/$N$70 -> 0.00084064942 | ... N24: =+N23/$N$70 -> 0.015329443
B25: CAPITAL | C25: 345913.78 | D25: 351538.78 | E25: 351538.78 | F25: 351538.78 | G25: 351538.78 | H25: 351538.78 | I25: 351538.78 | J25: 351538.78 | K25: 351538.78 | L25: 351538.78 | M25: 2900630.8 | N25: =SUM(C25:M25) -> 6410393.6
B26: INTERÉS | C26: 0 | D26: 0 | E26: 0 | F26: 0 | G26: 0 | H26: 0 | I26: 0 | J26: 0 | K26: 0 | L26: 0 | M26: 0 | N26: =SUM(C26:M26) -> 0
B28: PRÉSTAMOS | C28: =+C30+C31 -> 26977356 | D28: =+D30+D31 -> 21921928 | E28: =+E30+E31 -> 7681481.7 | F28: =+F30+F31 -> 2771191.3 | G28: =+G30+G31 -> 2579195.2 | H28: =+H30+H31 -> 3456451.9 | I28: =+I30+I31 -> 2397683.4 | J28: =+J30+J31 -> 2266207.5 | ... N28: =+N30+N31 -> 86570672
B29: Como % del total de servicios (2) | C29: =+C28/$N$70 -> 0.064512084 | D29: =+D28/$N$70 -> 0.052422825 | E29: =+E28/$N$70 -> 0.018369049 | F29: =+F28/$N$70 -> 0.0066268659 | G29: =+G28/$N$70 -> 0.0061677376 | H29: =+H28/$N$70 -> 0.0082655585 | I29: =+I28/$N$70 -> 0.0057336808 | J29: =+J28/$N$70 -> 0.0054192772 | ... N29: =+N28/$N$70 -> 0.20702008
B30: CAPITAL | C30: =+C35+C40+C45+C50+C55+C60 -> 24705393 | D30: =+D35+D40+D45+D50+D55+D60 -> 20852673 | E30: =+E35+E40+E45+E50+E55+E60 -> 7065502.1 | F30: =+F35+F40+F45+F50+F55+F60 -> 2235554.6 | G30: =+G35+G40+G45+G50+G55+G60 -> 2099317.5 | H30: =+H35+H40+H45+H50+H55+H60 -> 3031551.2 | I30: =+I35+I40+I45+I50+I55+I60 -> 2030031.7 | J30: =+J35+J40+J45+J50+J55+J60 -> 1949382.6 | ... M30: =+M35+M40+M45+M50+M55+M60 -> 10868547 | N30: =SUM(C30:M30) -> 79050318
B31: INTERÉS | C31: =+C36+C41+C46+C51+C56+C61 -> 2271963.2 | D31: =+D36+D41+D46+D51+D56+D61 -> 1069254.8 | E31: =+E36+E41+E46+E51+E56+E61 -> 615979.59 | F31: =+F36+F41+F46+F51+F56+F61 -> 535636.66 | G31: =+G36+G41+G46+G51+G56+G61 -> 479877.7 | H31: =+H36+H41+H46+H51+H56+H61 -> 424900.78 | I31: =+I36+I41+I46+I51+I56+I61 -> 367651.65 | J31: =+J36+J41+J46+J51+J56+J61 -> 316824.96 | ... M31: =+M36+M41+M46+M51+M56+M61 -> 950317.5 | N31: =SUM(C31:M31) -> 7520354.1
B34: ORGANISMOS INTERNACIONALES | C34: =+C35+C36 -> 21087950 | D34: =+D35+D36 -> 21233546 | E34: =+E35+E36 -> 7097202.3 | F34: =+F35+F36 -> 2219277 | G34: =+G35+G36 -> 2054027.1 | H34: =+H35+H36 -> 2003432.1 | I34: =+I35+I36 -> 1916234.7 | J34: =+J35+J36 -> 1818038.9 | ... N34: =+N35+N36 -> 74153216
B35: CAPITAL | C35: 19333589 | D35: 20331369 | E35: 6629860.2 | F35: 1816192 | G35: 1691160.8 | H35: 1677917.4 | I35: 1626430.8 | J35: 1564041.9 | K35: 1522017.3 | L35: 1471302.9 | M35: 10401536 | N35: =SUM(C35:M35) -> 68065416
B36: INTERÉS | C36: 1754360.5 | D36: 902177.7 | E36: 467342.1 | F36: 403084.99 | G36: 362866.3 | H36: 325514.74 | I36: 289803.94 | J36: 253997.03 | K36: 221777.22 | L36: 189842.05 | M36: 917033.4 | N36: =SUM(C36:M36) -> 6087800
B39: ORGANISMOS OFICIALES | C39: =+C40+C41 -> 2509328 | D39: =+D40+D41 -> 460177.61 | E39: =+E40+E41 -> 418354.63 | F39: =+F40+F41 -> 404466.28 | G39: =+G40+G41 -> 383269.5 | H39: =+H40+H41 -> 370618.62 | I39: =+I40+I41 -> 358128.2 | J39: =+J40+J41 -> 345504.21 | ... N39: =+N40+N41 -> 5520020.5
B40: CAPITAL | C40: 2079884.4 | D40: 369829.38 | E40: 340696.34 | F40: 339665.36 | G40: 331090.29 | H40: 330997.07 | I40: 330997.07 | J40: 330997.07 | K40: 111648.47 | L40: 44148.465 | M40: 99914.667 | N40: =SUM(C40:M40) -> 4709868.6
B41: INTERÉS | C41: 429443.52 | D41: 90348.229 | E41: 77658.286 | F41: 64800.923 | G41: 52179.214 | H41: 39621.557 | I41: 27131.13 | J41: 14507.14 | K41: 5959.3426 | L41: 3268.8693 | M41: 5233.656 | N41: =SUM(C41:M41) -> 810151.86
B44: PRÉSTAMOS GARANTIZADOS | C44: =+C45+C46 -> 37937.154 | D44: =+D45+D46 -> 37937.154 | E44: =+E45+E46 -> 38014.452 | F44: =+F45+F46 -> 37937.154 | G44: =+G45+G46 -> 37937.154 | H44: =+H45+H46 -> 188136.55 | I44: =+I45+I46 -> 30409.42 | J44: =+J45+J46 -> 30332.121 | ... N44: =+N45+N46 -> 1081101.5
B45: CAPITAL | C45: 0 | D45: 0 | E45: 0 | F45: 0 | G45: 0 | H45: 152100.65 | I45: 0 | J45: 0 | K45: 41252.208 | L45: 557662.51 | M45: 0 | N45: =SUM(C45:M45) -> 751015.37
B46: INTERÉS | C46: 37937.154 | D46: 37937.154 | E46: 38014.452 | F46: 37937.154 | G46: 37937.154 | H46: 36035.896 | I46: 30409.42 | J46: 30332.121 | K46: 29472.7 | L46: 14072.898 | M46: 0 | N46: =SUM(C46:M46) -> 330086.1
B49: BANCA COMERCIAL | C49: =+C50+C51 -> 2166394.5 | D49: =+D50+D51 -> 72914.306 | E49: =+E50+E51 -> 71937.024 | F49: =+F50+F51 -> 67089.093 | G49: =+G50+G51 -> 64373.559 | H49: =+H50+H51 -> 57160.126 | I49: =+I50+I51 -> 25846.217 | J49: =+J50+J51 -> 15130.907 | ... N49: =+N50+N51 -> 2552871
B50: CAPITAL | C50: 2160533.2 | D50: 67978.123 | E50: 67945.215 | F50: 64041.931 | G50: 62182.383 | H50: 55766.292 | I50: 25074.767 | J50: 14703.807 | K50: 7606.5874 | L50: 4169.7067 | M50: 0 | N50: =SUM(C50:M50) -> 2530002
B51: INTERÉS | C51: 5861.2891 | D51: 4936.1828 | E51: 3991.8097 | F51: 3047.1622 | G51: 2191.1761 | H51: 1393.8339 | I51: 771.45077 | J51: 427.10056 | K51: 183.73335 | L51: 65.257065 | M51: 0 | N51: =SUM(C51:M51) -> 22868.996
B54: AVALES | C54: =+C55+C56 -> 341795.31 | D54: =+D55+D56 -> 110651.2 | E54: =+E55+E56 -> 49272.124 | F54: =+F55+F56 -> 35720.507 | G54: =+G55+G56 -> 32886.643 | H54: =+H55+H56 -> 830403.28 | I54: =+I55+I56 -> 60363.566 | J54: =+J55+J56 -> 30226.174 | ... N54: =+N55+N56 -> 1958177.5
B55: CAPITAL | C55: 304135.75 | D55: 83496.924 | E55: 27000.39 | F55: 15655.288 | G55: 14884.007 | H55: 814769.75 | I55: 47529.073 | J55: 20709.843 | K55: 144239.43 | L55: 232598.32 | M55: 83146.95 | N55: =SUM(C55:M55) -> 1788165.7
B56: INTERÉS | C56: 37659.562 | D56: 27154.28 | E56: 22271.734 | F56: 20065.219 | G56: 18002.636 | H56: 15633.534 | I56: 12834.493 | J56: 9516.3308 | K56: 5615.9895 | L56: 1257.9998 | M56: 0 | N56: =SUM(C56:M56) -> 170011.78
B59: PAGARÉS DEL TESORO | C59: =+C60+C61 -> 833951.82 | D59: =+D60+D61 -> 6701.2121 | E59: =+E60+E61 -> 6701.2121 | F59: =+F60+F61 -> 6701.2121 | G59: =+G60+G61 -> 6701.2121 | H59: =+H60+H61 -> 6701.2121 | I59: =+I60+I61 -> 6701.2121 | J59: =+J60+J61 -> 26975.218 | ... N59: =+N60+N61 -> 1305285.6
B60: CAPITAL | C60: 827250.61 | D60: 0 | E60: 0 | F60: 0 | G60: 0 | H60: 0 | I60: 0 | J60: 18929.978 | K60: 37859.956 | L60: 37859.956 | M60: 283949.67 | N60: =SUM(C60:M60) -> 1205850.2
B61: INTERÉS | C61: 6701.2121 | D61: 6701.2121 | E61: 6701.2121 | F61: 6701.2121 | G61: 6701.2121 | H61: 6701.2121 | I61: 6701.2121 | J61: 8045.2406 | K61: 8685.0738 | L61: 7746.1469 | M61: 28050.441 | N61: =SUM(C61:M61) -> 99435.387
B64: ADELANTOS TRANSITORIOS BCRA | C64: =+C66+C67 -> 16448169 | D64: =+D66+D67 -> 4700729.9 | E64: =+E66+E67 -> 0 | F64: =+F66+F67 -> 0 | G64: =+G66+G67 -> 0 | H64: =+H66+H67 -> 0 | I64: =+I66+I67 -> 0 | J64: =+J66+J67 -> 0 | ... N64: =+N66+N67 -> 21148899
B65: Como % del total de servicios (2) | C65: =+C64/$N$70 -> 0.039333196 | D65: =+D64/$N$70 -> 0.011241053 | E65: =+E64/$N$70 -> 0 | F65: =+F64/$N$70 -> 0 | G65: =+G64/$N$70 -> 0 | H65: =+H64/$N$70 -> 0 | I65: =+I64/$N$70 -> 0 | J65: =+J64/$N$70 -> 0 | ... N65: =+N64/$N$70 -> 0.050574249
B66: CAPITAL | C66: 16448169 | D66: 4700729.9 | E66: 0 | F66: 0 | G66: 0 | H66: 0 | I66: 0 | J66: 0 | K66: 0 | L66: 0 | M66: 0 | N66: =SUM(C66:M66) -> 21148899
B67: INTERÉS | C67: 0 | D67: 0 | E67: 0 | F67: 0 | G67: 0 | H67: 0 | I67: 0 | J67: 0 | K67: 0 | L67: 0 | M67: 0 | N67: =SUM(C67:M67) -> 0
B70: TOTAL | C70: =+C72+C73 -> 98982927 | D70: =+D72+D73 -> 55663787 | E70: =+E72+E73 -> 32844343 | F70: =+F72+F73 -> 26033109 | G70: =+G72+G73 -> 15302827 | H70: =+H72+H73 -> 15044290 | I70: =+I72+I73 -> 16084359 | J70: =+J72+J73 -> 20380090 | ... N70: =+N72+N73 -> 4.1817524e+08
B71: Como % del total de servicios (2) | C71: =+C70/$N$70 -> 0.23670202 | D71: =+D70/$N$70 -> 0.13311115 | E71: =+E70/$N$70 -> 0.078542054 | F71: =+F70/$N$70 -> 0.062254065 | G71: =+G70/$N$70 -> 0.036594291 | H71: =+H70/$N$70 -> 0.035976041 | I71: =+I70/$N$70 -> 0.038463202 | J71: =+J70/$N$70 -> 0.048735763 | ... N71: =+N70/$N$70 -> 1
B72: CAPITAL | C72: =+C15+C20+C25+C30+C66 -> 92982489 | D72: =+D15+D20+D25+D30+D66 -> 51289155 | E72: =+E15+E20+E25+E30+E66 -> 28233189 | F72: =+F15+F20+F25+F30+F66 -> 21298772 | G72: =+G15+G20+G25+G30+G66 -> 10744831 | H72: =+H15+H20+H25+H30+H66 -> 10782926 | I72: =+I15+I20+I25+I30+I66 -> 11656353 | J72: =+J15+J20+J25+J30+J66 -> 16137597 | ... M72: =+M15+M20+M25+M30+M66 -> 79035529 | N72: =SUM(C72:M72) -> 3.6068874e+08
B73: INTERÉS | C73: =+C67+C31+C26+C21+C16 -> 6000437.6 | D73: =+D67+D31+D26+D21+D16 -> 4374631.8 | E73: =+E67+E31+E26+E21+E16 -> 4611154.1 | F73: =+F67+F31+F26+F21+F16 -> 4734336.1 | G73: =+G67+G31+G26+G21+G16 -> 4557995.3 | H73: =+H67+H31+H26+H21+H16 -> 4261363.9 | I73: =+I67+I31+I26+I21+I16 -> 4428005.6 | J73: =+J67+J31+J26+J21+J16 -> 4242492.5 | ... M73: =+M67+M31+M26+M21+M16 -> 12438026 | N73: =SUM(C73:M73) -> 57486500
B76: (1) No incluye estimación del pago eventual por los Valores Negociables Vinculadas al PBI.
B77: (2) Como porcentaje del total de los servicios proyectados (capital mas interés) para el período 01/01/2022 - 31/12/2089.
B78: (3) A partir del año 2053 el total de servicios corresponde al Bono del Tesoro Consolidado 2089.

Sheet A.3.7
A1: Indice
B2: MINISTERIO DE ECONOMÍA
B3: SECRETARÍA DE FINANZAS
B6: PERFIL ANUAL DE VENCIMIENTOS DE CAPITAL DE LA DEUDA BRUTA DE LA ADMINISTRACIÓN CENTRAL
B8: (En millones de U$S - Stock de deuda y tipo de cambio 31/12/2021)
C9: 2022 | D9: 2023 | E9: 2024 | F9: 2025 | G9: 2026 | H9: 2027 | I9: 2028 | J9: 2029 | K9: 2030 | L9: 2031 | M9: 2032 | N9: 2033 | O9: 2034 | P9: 2035 | Q9: 2036 | R9: 2037 | S9: 2038 | T9: 2039 | U9: 2040 | V9: 2041 | W9: 2042 | X9: 2043 | Y9: 2044 | Z9: 2045 | AA9: 2046 | AB9: 2047 | AC9: 2048 | AD9: 2049 | AE9: 2050 | AF9: 2051 | AG9: 2052-2089 (2) | AH9: Total
B11: PERFIL DE VENCIMIENTOS DE LA DEUDA EN SITUACIÓN DE PAGO NORMAL
B13: TOTAL | C13: =+C14+C15 -> 92982.489 | D13: =+D14+D15 -> 51289.155 | E13: =+E14+E15 -> 28233.189 | F13: =+F14+F15 -> 21298.772 | G13: =+G14+G15 -> 10744.831 | H13: =+H14+H15 -> 10782.926 | I13: =+I14+I15 -> 11656.353 | J13: =+J14+J15 -> 16137.597 | ... AG13: =+AG14+AG15 -> 9.9518129 | AH13: =SUM(C13:AG13) -> 360688.74
B14: CORTO PLAZO | C14: 34921.032 | D14: 0 | E14: 0 | F14: 0 | G14: 0 | H14: 0 | I14: 0 | J14: 0 | K14: 0 | L14: 0 | M14: 0 | N14: 0 | O14: 0 | P14: 0 | Q14: 0 | R14: 0 | S14: 0 | T14: 0 | U14: 0 | V14: 0 | W14: 0 | X14: 0 | Y14: 0 | Z14: 0 | AA14: 0 | AB14: 0 | AC14: 0 | AD14: 0 | AE14: 0 | AF14: 0 | AG14: 0 | AH14: =SUM(C14:AG14) -> 34921.032
B15: MEDIANO Y LARGO PLAZO | C15: 58061.457 | D15: 51289.155 | E15: 28233.189 | F15: 21298.772 | G15: 10744.831 | H15: 10782.926 | I15: 11656.353 | J15: 16137.597 | K15: 10694.403 | L15: 27833.499 | M15: 13099.877 | N15: 12947.488 | O15: 12540.432 | P15: 12556.529 | Q15: 5278.4945 | R15: 5161.6749 | S15: 4196.4688 | T15: 2781.507 | U15: 2484.8999 | V15: 2328.184 | W15: 1311.0237 | X15: 1269.2972 | Y15: 1177.0282 | Z15: 1155.058 | AA15: 285.88903 | AB15: 145.77514 | AC15: 119.74473 | AD15: 89.81841 | AE15: 70.709186 | AF15: 25.678708 | AG15: 9.9518129 | AH15: =SUM(C15:AG15) -> 325767.71
B17: PRÉSTAMOS | C17: =+C18+C23+C25+C30+C31+C36 -> 24705.393 | D17: =+D18+D23+D25+D30+D31+D36 -> 20852.673 | E17: =+E18+E23+E25+E30+E31+E36 -> 7065.5021 | F17: =+F18+F23+F25+F30+F31+F36 -> 2235.5546 | G17: =+G18+G23+G25+G30+G31+G36 -> 2099.3175 | H17: =+H18+H23+H25+H30+H31+H36 -> 3031.5512 | I17: =+I18+I23+I25+I30+I31+I36 -> 2030.0317 | J17: =+J18+J23+J25+J30+J31+J36 -> 1949.3826 | ... AG17: =+AG18+AG23+AG25+AG30+AG31+AG36 -> 4.9761541 | AH17: =SUM(C17:AG17) -> 79050.318
B18: Organismos Internacionales | C18: =SUM(C19:C22) -> 19333.589 | D18: =SUM(D19:D22) -> 20331.369 | E18: =SUM(E19:E22) -> 6629.8602 | F18: =SUM(F19:F22) -> 1816.192 | G18: =SUM(G19:G22) -> 1691.1608 | H18: =SUM(H19:H22) -> 1677.9174 | I18: =SUM(I19:I22) -> 1626.4308 | J18: =SUM(J19:J22) -> 1564.0419 | ... AG18: =SUM(AG19:AG22) -> 4.9761541 | AH18: =SUM(C18:AG18) -> 68065.416
B19: . BIRF | C19: 306.30295 | D19: 283.5265 | E19: 308.43829 | F19: 320.7048 | G19: 387.06985 | H19: 425.97113 | I19: 427.45926 | J19: 428.22743 | K19: 428.22743 | L19: 428.22743 | M19: 428.22743 | N19: 428.22743 | O19: 428.22743 | P19: 428.22743 | Q19: 428.40693 | R19: 393.82176 | S19: 309.88976 | T19: 245.51282 | U19: 178.48312 | V19: 176.14377 | W19: 176.14377 | X19: 176.14377 | Y19: 176.14377 | Z19: 176.3993 | AA19: 166.96602 | AB19: 145.68935 | AC19: 119.65894 | AD19: 89.732622 | AE19: 70.623399 | AF19: 25.592921 | AG19: 4.9761541 | AH19: =SUM(C19:AG19) -> 8517.393
B20: . BID | C20: 839.87023 | D20: 864.30769 | E20: 963.46888 | F20: 951.92379 | G20: 946.10736 | H20: 916.62922 | I20: 916.62922 | J20: 885.47976 | K20: 885.47976 | L20: 869.56802 | M20: 738.15898 | N20: 651.53778 | O20: 609.32351 | P20: 554.3091 | Q20: 520.46982 | R20: 468.12801 | S20: 368.28223 | T20: 264.5901 | U20: 223.01984 | V20: 196.83318 | W20: 179.0231 | X20: 144.03308 | Y20: 52.851998 | Z20: 30.626293 | AA20: 10.925638 | AB20: 0 | AC20: 0 | AD20: 0 | AE20: 0 | AF20: 0 | AG20: 0 | AH20: =SUM(C20:AG20) -> 14051.577
B21: . FMI | C21: 17556.83 | D21: 18619.213 | E21: 4776.0672 | F21: 0 | G21: 0 | H21: 0 | I21: 0 | J21: 0 | K21: 0 | L21: 0 | M21: 0 | N21: 0 | O21: 0 | P21: 0 | Q21: 0 | R21: 0 | S21: 0 | T21: 0 | U21: 0 | V21: 0 | W21: 0 | X21: 0 | Y21: 0 | Z21: 0 | AA21: 0 | AB21: 0 | AC21: 0 | AD21: 0 | AE21: 0 | AF21: 0 | AG21: 0 | AH21: =SUM(C21:AG21) -> 40952.11
B22: . Otros | C22: 630.58588 | D22: 564.32157 | E22: 581.88582 | F22: 543.56343 | G22: 357.98357 | H22: 335.31706 | I22: 282.34232 | J22: 250.3347 | K22: 208.3101 | L22: 173.50743 | M22: 132.91244 | N22: 100.5444 | O22: 96.517721 | P22: 83.325242 | Q22: 64.878084 | R22: 34.945182 | S22: 34.878515 | T22: 31.615702 | U22: 28.352888 | V22: 8.2149573 | W22: 0 | X22: 0 | Y22: 0 | Z22: 0 | AA22: 0 | AB22: 0 | AC22: 0 | AD22: 0 | AE22: 0 | AF22: 0 | AG22: 0 | AH22: =SUM(C22:AG22) -> 4544.337
B23: Préstamos Garantizados | C23: =SUM(C24:C24) -> 0 | D23: =SUM(D24:D24) -> 0 | E23: =SUM(E24:E24) -> 0 | F23: =SUM(F24:F24) -> 0 | G23: =SUM(G24:G24) -> 0 | H23: =SUM(H24:H24) -> 152.10065 | I23: =SUM(I24:I24) -> 0 | J23: =SUM(J24:J24) -> 0 | ... AG23: =SUM(AG24:AG24) -> 0 | AH23: =SUM(C23:AG23) -> 751.01537
B24: . En moneda nacional ajustable por CER | C24: 0 | D24: 0 | E24: 0 | F24: 0 | G24: 0 | H24: 152.10065 | I24: 0 | J24: 0 | K24: 41.252208 | L24: 557.66251 | M24: 0 | N24: 0 | O24: 0 | P24: 0 | Q24: 0 | R24: 0 | S24: 0 | T24: 0 | U24: 0 | V24: 0 | W24: 0 | X24: 0 | Y24: 0 | Z24: 0 | AA24: 0 | AB24: 0 | AC24: 0 | AD24: 0 | AE24: 0 | AF24: 0 | AG24: 0 | AH24: =SUM(C24:AG24) -> 751.01537
B25: Banca Comercial | C25: =+C26+C28 -> 2160.5332 | D25: =+D26+D28 -> 67.978123 | E25: =+E26+E28 -> 67.945215 | F25: =+F26+F28 -> 64.041931 | G25: =+G26+G28 -> 62.182383 | H25: =+H26+H28 -> 55.766292 | I25: =+I26+I28 -> 25.074767 | J25: =+J26+J28 -> 14.703807 | ... AG25: =+AG26+AG28 -> 0 | AH25: =SUM(C25:AG25) -> 2530.002
B26: . En moneda nacional | C26: =+C27 -> 2092.4574 | D26: =+D27 -> 0 | E26: =+E27 -> 0 | F26: =+F27 -> 0 | G26: =+G27 -> 0 | H26: =+H27 -> 0 | I26: =+I27 -> 0 | J26: =+J27 -> 0 | ... AG26: =+AG27 -> 0 | AH26: =SUM(C26:AG26) -> 2092.4574
B27: FUCO | C27: 2092.4574 | D27: 0 | E27: 0 | F27: 0 | G27: 0 | H27: 0 | I27: 0 | J27: 0 | K27: 0 | L27: 0 | M27: 0 | N27: 0 | O27: 0 | P27: 0 | Q27: 0 | R27: 0 | S27: 0 | T27: 0 | U27: 0 | V27: 0 | W27: 0 | X27: 0 | Y27: 0 | Z27: 0 | AA27: 0 | AB27: 0 | AC27: 0 | AD27: 0 | AE27: 0 | AF27: 0 | AG27: 0 | AH27: =SUM(C27:AG27) -> 2092.4574
B28: . En moneda extranjera | C28: =+C29 -> 68.075784 | D28: =+D29 -> 67.978123 | E28: =+E29 -> 67.945215 | F28: =+F29 -> 64.041931 | G28: =+G29 -> 62.182383 | H28: =+H29 -> 55.766292 | I28: =+I29 -> 25.074767 | J28: =+J29 -> 14.703807 | ... AG28: =+AG29 -> 0 | AH28: =SUM(C28:AG28) -> 437.5446
B29: Otros | C29: 68.075784 | D29: 67.978123 | E29: 67.945215 | F29: 64.041931 | G29: 62.182383 | H29: 55.766292 | I29: 25.074767 | J29: 14.703807 | K29: 7.6065874 | L29: 4.1697067 | M29: 0 | N29: 0 | O29: 0 | P29: 0 | Q29: 0 | R29: 0 | S29: 0 | T29: 0 | U29: 0 | V29: 0 | W29: 0 | X29: 0 | Y29: 0 | Z29: 0 | AA29: 0 | AB29: 0 | AC29: 0 | AD29: 0 | AE29: 0 | AF29: 0 | AG29: 0 | AH29: =SUM(C29:AG29) -> 437.5446
B30: Organismos Oficiales | C30: 2079.8844 | D30: 369.82938 | E30: 340.69634 | F30: 339.66536 | G30: 331.09029 | H30: 330.99707 | I30: 330.99707 | J30: 330.99707 | K30: 111.64847 | L30: 44.148465 | M30: 44.148465 | N30: 10.748465 | O30: 6.2695746 | P30: 6.0990619 | Q30: 5.727471 | R30: 5.727471 | S30: 5.727471 | T30: 4.7271339 | U30: 3.7267969 | V30: 3.7254937 | W30: 2.1993363 | X30: 1.0879262 | Y30: 0 | Z30: 0 | AA30: 0 | AB30: 0 | AC30: 0 | AD30: 0 | AE30: 0 | AF30: 0 | AG30: 0 | AH30: =SUM(C30:AG30) -> 4709.8686
B31: Pagarés del Tesoro | C31: =+C32+C34 -> 827.25061 | D31: =+D32+D34 -> 0 | E31: =+E32+E34 -> 0 | F31: =+F32+F34 -> 0 | G31: =+G32+G34 -> 0 | H31: =+H32+H34 -> 0 | I31: =+I32+I34 -> 0 | J31: =+J32+J34 -> 18.929978 | ... AG31: =+AG32+AG34 -> 0 | AH31: =SUM(C31:AG31) -> 1205.8502
B32: . En moneda nacional ajustable por CER | C32: =+C33 -> 0 | D32: =+D33 -> 0 | E32: =+E33 -> 0 | F32: =+F33 -> 0 | G32: =+G33 -> 0 | H32: =+H33 -> 0 | I32: =+I33 -> 0 | J32: =+J33 -> 18.929978 | ... AG32: =+AG33 -> 0 | AH32: =SUM(C32:AG32) -> 378.59956
B33: Pagaré 2038 - B.N.A. | C33: 0 | D33: 0 | E33: 0 | F33: 0 | G33: 0 | H33: 0 | I33: 0 | J33: 18.929978 | K33: 37.859956 | L33: 37.859956 | M33: 37.859956 | N33: 37.859956 | O33: 37.859956 | P33: 37.859956 | Q33: 37.859956 | R33: 37.859956 | S33: 56.789933 | T33: 0 | U33: 0 | V33: 0 | W33: 0 | X33: 0 | Y33: 0 | Z33: 0 | AA33: 0 | AB33: 0 | AC33: 0 | AD33: 0 | AE33: 0 | AF33: 0 | AG33: 0 | AH33: =SUM(C33:AG33) -> 378.59956
B34: . En moneda nacional no ajustable por CER | C34: =+C35 -> 827.25061 | D34: =+D35 -> 0 | E34: =+E35 -> 0 | F34: =+F35 -> 0 | G34: =+G35 -> 0 | H34: =+H35 -> 0 | I34: =+I35 -> 0 | J34: =+J35 -> 0 | ... AG34: =+AG35 -> 0 | AH34: =SUM(C34:AG34) -> 827.25061
B35: Pagaré CUT | C35: 827.25061 | D35: 0 | E35: 0 | F35: 0 | G35: 0 | H35: 0 | I35: 0 | J35: 0 | K35: 0 | L35: 0 | M35: 0 | N35: 0 | O35: 0 | P35: 0 | Q35: 0 | R35: 0 | S35: 0 | T35: 0 | U35: 0 | V35: 0 | W35: 0 | X35: 0 | Y35: 0 | Z35: 0 | AA35: 0 | AB35: 0 | AC35: 0 | AD35: 0 | AE35: 0 | AF35: 0 | AG35: 0 | AH35: =SUM(C35:AG35) -> 827.25061
B36: Avales | C36: =+C37+C38 -> 304.13575 | D36: =+D37+D38 -> 83.496924 | E36: =+E37+E38 -> 27.00039 | F36: =+F37+F38 -> 15.655288 | G36: =+G37+G38 -> 14.884007 | H36: =+H37+H38 -> 814.76975 | I36: =+I37+I38 -> 47.529073 | J36: =+J37+J38 -> 20.709843 | ... AG36: =+AG37+AG38 -> 0 | AH36: =SUM(C36:AG36) -> 1788.1657
B37: . En moneda nacional | C37: 10.22105 | D37: 10.894708 | E37: 12.738778 | F37: 14.507342 | G37: 14.405696 | H37: 14.769745 | I37: 17.529073 | J37: 20.709843 | K37: 24.239427 | L37: 232.59832 | M37: 0 | N37: 0 | O37: 0 | P37: 0 | Q37: 0 | R37: 0 | S37: 0 | T37: 0 | U37: 0 | V37: 0 | W37: 0 | X37: 0 | Y37: 0 | Z37: 0 | AA37: 0 | AB37: 0 | AC37: 0 | AD37: 0 | AE37: 0 | AF37: 0 | AG37: 0 | AH37: =SUM(C37:AG37) -> 372.61398
B38: . En moneda extranjera | C38: 293.9147 | D38: 72.602216 | E38: 14.261611 | F38: 1.1479456 | G38: 0.47831081 | H38: 800 | I38: 30 | J38: 0 | K38: 120 | L38: 0 | M38: 0 | N38: 0 | O38: 0 | P38: 83.14695 | Q38: 0 | R38: 0 | S38: 0 | T38: 0 | U38: 0 | V38: 0 | W38: 0 | X38: 0 | Y38: 0 | Z38: 0 | AA38: 0 | AB38: 0 | AC38: 0 | AD38: 0 | AE38: 0 | AF38: 0 | AG38: 0 | AH38: =SUM(C38:AG38) -> 1415.5517
B40: ADELANTOS TRANSITORIOS BCRA | C40: 16448.169 | D40: 4700.7299 | E40: 0 | F40: 0 | G40: 0 | H40: 0 | I40: 0 | J40: 0 | K40: 0 | L40: 0 | M40: 0 | N40: 0 | O40: 0 | P40: 0 | Q40: 0 | R40: 0 | S40: 0 | T40: 0 | U40: 0 | V40: 0 | W40: 0 | X40: 0 | Y40: 0 | Z40: 0 | AA40: 0 | AB40: 0 | AC40: 0 | AD40: 0 | AE40: 0 | AF40: 0 | AG40: 0 | AH40: =SUM(C40:AG40) -> 21148.899
B42: TÍTULOS PÚBLICOS Y LETRAS DEL TESORO | C42: =+C43+C58+SUM(C70:C119)+C122 -> 51828.927 | D42: =+D43+D58+SUM(D70:D119)+D122 -> 25735.752 | E42: =+E43+E58+SUM(E70:E119)+E122 -> 21167.687 | F42: =+F43+F58+SUM(F70:F119)+F122 -> 19063.218 | G42: =+G43+G58+SUM(G70:G119)+G122 -> 8645.514 | H42: =+H43+H58+SUM(H70:H119)+H122 -> 7751.3749 | I42: =+I43+I58+SUM(I70:I119)+I122 -> 9626.3216 | J42: =+J43+J58+SUM(J70:J119)+J122 -> 14188.215 | ... AG42: =+AG43+AG58+SUM(AG70:AG119)+AG122 -> 4.9756588 | AH42: =SUM(C42:AG42) -> 260489.53
B43: PAR | C43: =+C44+C47+C53+C55 -> 0 | D43: =+D44+D47+D53+D55 -> 0 | E43: =+E44+E47+E53+E55 -> 0 | F43: =+F44+F47+F53+F55 -> 0 | G43: =+G44+G47+G53+G55 -> 0 | H43: =+H44+H47+H53+H55 -> 0 | I43: =+I44+I47+I53+I55 -> 0 | J43: =+J44+J47+J53+J55 -> 80.327925 | ... AG43: =+AG44+AG47+AG53+AG55 -> 0 | AH43: =SUM(C43:AG43) -> 1606.5585
B44: Par/$+CER/T.Fija/2038 | C44: =+C45+C46 -> 0 | D44: =+D45+D46 -> 0 | E44: =+E45+E46 -> 0 | F44: =+F45+F46 -> 0 | G44: =+G45+G46 -> 0 | H44: =+H45+H46 -> 0 | I44: =+I45+I46 -> 0 | J44: =+J45+J46 -> 36.643161 | ... AG44: =+AG45+AG46 -> 0 | AH44: =SUM(C44:AG44) -> 732.86321
B45: Emisión Canje 2005 | C45: 0 | D45: 0 | E45: 0 | F45: 0 | G45: 0 | H45: 0 | I45: 0 | J45: 36.498008 | K45: 72.996016 | L45: 72.996016 | M45: 72.996016 | N45: 72.996016 | O45: 72.996016 | P45: 72.996016 | Q45: 72.996016 | R45: 72.996016 | S45: 109.49402 | T45: 0 | U45: 0 | V45: 0 | W45: 0 | X45: 0 | Y45: 0 | Z45: 0 | AA45: 0 | AB45: 0 | AC45: 0 | AD45: 0 | AE45: 0 | AF45: 0 | AG45: 0 | AH45: =SUM(C45:AG45) -> 729.96016
B46: Emisión Canje 2010 | C46: 0 | D46: 0 | E46: 0 | F46: 0 | G46: 0 | H46: 0 | I46: 0 | J46: 0.14515266 | K46: 0.29030532 | L46: 0.29030532 | M46: 0.29030532 | N46: 0.29030532 | O46: 0.29030532 | P46: 0.29030532 | Q46: 0.29030532 | R46: 0.29030532 | S46: 0.43545797 | T46: 0 | U46: 0 | V46: 0 | W46: 0 | X46: 0 | Y46: 0 | Z46: 0 | AA46: 0 | AB46: 0 | AC46: 0 | AD46: 0 | AE46: 0 | AF46: 0 | AG46: 0 | AH46: =SUM(C46:AG46) -> 2.9030532
B47: Par/U$S/T.Fija/2038 | C47: =+C48+C50 -> 0 | D47: =+D48+D50 -> 0 | E47: =+E48+E50 -> 0 | F47: =+F48+F50 -> 0 | G47: =+G48+G50 -> 0 | H47: =+H48+H50 -> 0 | I47: =+I48+I50 -> 0 | J47: =+J48+J50 -> 3.5184176 | ... AG47: =+AG48+AG50 -> 0 | AH47: =SUM(C47:AG47) -> 70.368352
B48: Emisión Canje 2005 | C48: =+C49 -> 0 | D48: =+D49 -> 0 | E48: =+E49 -> 0 | F48: =+F49 -> 0 | G48: =+G49 -> 0 | H48: =+H49 -> 0 | I48: =+I49 -> 0 | J48: =+J49 -> 1.4492806 | ... AG48: =+AG49 -> 0 | AH48: =SUM(C48:AG48) -> 28.985612
B49: Leg. Argentina | C49: 0 | D49: 0 | E49: 0 | F49: 0 | G49: 0 | H49: 0 | I49: 0 | J49: 1.4492806 | K49: 2.8985612 | L49: 2.8985612 | M49: 2.8985612 | N49: 2.8985612 | O49: 2.8985612 | P49: 2.8985612 | Q49: 2.8985612 | R49: 2.8985612 | S49: 4.3478418 | T49: 0 | U49: 0 | V49: 0 | W49: 0 | X49: 0 | Y49: 0 | Z49: 0 | AA49: 0 | AB49: 0 | AC49: 0 | AD49: 0 | AE49: 0 | AF49: 0 | AG49: 0 | AH49: =SUM(C49:AG49) -> 28.985612
B50: Emisión Canje 2010 | C50: =+C51+C52 -> 0 | D50: =+D51+D52 -> 0 | E50: =+E51+E52 -> 0 | F50: =+F51+F52 -> 0 | G50: =+G51+G52 -> 0 | H50: =+H51+H52 -> 0 | I50: =+I51+I52 -> 0 | J50: =+J51+J52 -> 2.069137 | ... AG50: =+AG51+AG52 -> 0 | AH50: =SUM(C50:AG50) -> 41.38274
B51: Leg. Nueva York | C51: 0 | D51: 0 | E51: 0 | F51: 0 | G51: 0 | H51: 0 | I51: 0 | J51: 1.790978 | K51: 3.581956 | L51: 3.581956 | M51: 3.581956 | N51: 3.581956 | O51: 3.581956 | P51: 3.581956 | Q51: 3.581956 | R51: 3.581956 | S51: 5.372934 | T51: 0 | U51: 0 | V51: 0 | W51: 0 | X51: 0 | Y51: 0 | Z51: 0 | AA51: 0 | AB51: 0 | AC51: 0 | AD51: 0 | AE51: 0 | AF51: 0 | AG51: 0 | AH51: =SUM(C51:AG51) -> 35.81956
B52: Leg. Argentina | C52: 0 | D52: 0 | E52: 0 | F52: 0 | G52: 0 | H52: 0 | I52: 0 | J52: 0.278159 | K52: 0.556318 | L52: 0.556318 | M52: 0.556318 | N52: 0.556318 | O52: 0.556318 | P52: 0.556318 | Q52: 0.556318 | R52: 0.556318 | S52: 0.834477 | T52: 0 | U52: 0 | V52: 0 | W52: 0 | X52: 0 | Y52: 0 | Z52: 0 | AA52: 0 | AB52: 0 | AC52: 0 | AD52: 0 | AE52: 0 | AF52: 0 | AG52: 0 | AH52: =SUM(C52:AG52) -> 5.56318
B53: Par/EUR/T.Fija/2038 | C53: =+C54 -> 0 | D53: =+D54 -> 0 | E53: =+E54 -> 0 | F53: =+F54 -> 0 | G53: =+G54 -> 0 | H53: =+H54 -> 0 | I53: =+I54 -> 0 | J53: =+J54 -> 32.294203 | ... AG53: =+AG54 -> 0 | AH53: =SUM(C53:AG53) -> 645.88406
B54: Emisión Canje 2010 | C54: 0 | D54: 0 | E54: 0 | F54: 0 | G54: 0 | H54: 0 | I54: 0 | J54: 32.294203 | K54: 64.588406 | L54: 64.588406 | M54: 64.588406 | N54: 64.588406 | O54: 64.588406 | P54: 64.588406 | Q54: 64.588406 | R54: 64.588406 | S54: 96.882608 | T54: 0 | U54: 0 | V54: 0 | W54: 0 | X54: 0 | Y54: 0 | Z54: 0 | AA54: 0 | AB54: 0 | AC54: 0 | AD54: 0 | AE54: 0 | AF54: 0 | AG54: 0 | AH54: =SUM(C54:AG54) -> 645.88406
B55: Par/JPY/T.Fija/2038 | C55: =+C56+C57 -> 0 | D55: =+D56+D57 -> 0 | E55: =+E56+E57 -> 0 | F55: =+F56+F57 -> 0 | G55: =+G56+G57 -> 0 | H55: =+H56+H57 -> 0 | I55: =+I56+I57 -> 0 | J55: =+J56+J57 -> 7.8721437 | ... AG55: =+AG56+AG57 -> 0 | AH55: =SUM(C55:AG55) -> 157.44287
B56: Emisión Canje 2005 | C56: 0 | D56: 0 | E56: 0 | F56: 0 | G56: 0 | H56: 0 | I56: 0 | J56: 7.5011483 | K56: 15.002297 | L56: 15.002297 | M56: 15.002297 | N56: 15.002297 | O56: 15.002297 | P56: 15.002297 | Q56: 15.002297 | R56: 15.002297 | S56: 22.503445 | T56: 0 | U56: 0 | V56: 0 | W56: 0 | X56: 0 | Y56: 0 | Z56: 0 | AA56: 0 | AB56: 0 | AC56: 0 | AD56: 0 | AE56: 0 | AF56: 0 | AG56: 0 | AH56: =SUM(C56:AG56) -> 150.02297
B57: Emisión Canje 2010 | C57: 0 | D57: 0 | E57: 0 | F57: 0 | G57: 0 | H57: 0 | I57: 0 | J57: 0.37099539 | K57: 0.74199079 | L57: 0.74199079 | M57: 0.74199079 | N57: 0.74199079 | O57: 0.74199079 | P57: 0.74199079 | Q57: 0.74199079 | R57: 0.74199079 | S57: 1.1129862 | T57: 0 | U57: 0 | V57: 0 | W57: 0 | X57: 0 | Y57: 0 | Z57: 0 | AA57: 0 | AB57: 0 | AC57: 0 | AD57: 0 | AE57: 0 | AF57: 0 | AG57: 0 | AH57: =SUM(C57:AG57) -> 7.4199079
B58: DESCUENTO | C58: =+C59+C62+C67 -> 0 | D58: =+D59+D62+D67 -> 0 | E58: =+E59+E62+E67 -> 356.33554 | F58: =+F59+F62+F67 -> 356.33554 | G58: =+G59+G62+G67 -> 356.33554 | H58: =+H59+H62+H67 -> 356.33554 | I58: =+I59+I62+I67 -> 356.33554 | J58: =+J59+J62+J67 -> 356.33554 | ... AG58: =+AG59+AG62+AG67 -> 0 | AH58: =SUM(C58:AG58) -> 3563.3554
B59: Discount/$+CER/5,83%/2033 | C59: =+C60+C61 -> 0 | D59: =+D60+D61 -> 0 | E59: =+E60+E61 -> 346.41408 | F59: =+F60+F61 -> 346.41408 | G59: =+G60+G61 -> 346.41408 | H59: =+H60+H61 -> 346.41408 | I59: =+I60+I61 -> 346.41408 | J59: =+J60+J61 -> 346.41408 | ... AG59: =+AG60+AG61 -> 0 | AH59: =SUM(C59:AG59) -> 3464.1408
B60: Emisión Canje 2005 | C60: 0 | D60: 0 | E60: 342.29939 | F60: 342.29939 | G60: 342.29939 | H60: 342.29939 | I60: 342.29939 | J60: 342.29939 | K60: 342.29939 | L60: 342.29939 | M60: 342.29939 | N60: 342.29939 | O60: 0 | P60: 0 | Q60: 0 | R60: 0 | S60: 0 | T60: 0 | U60: 0 | V60: 0 | W60: 0 | X60: 0 | Y60: 0 | Z60: 0 | AA60: 0 | AB60: 0 | AC60: 0 | AD60: 0 | AE60: 0 | AF60: 0 | AG60: 0 | AH60: =SUM(C60:AG60) -> 3422.9939
B61: Emisión Canje 2010 | C61: 0 | D61: 0 | E61: 4.1146923 | F61: 4.1146923 | G61: 4.1146923 | H61: 4.1146923 | I61: 4.1146923 | J61: 4.1146923 | K61: 4.1146923 | L61: 4.1146923 | M61: 4.1146923 | N61: 4.1146923 | O61: 0 | P61: 0 | Q61: 0 | R61: 0 | S61: 0 | T61: 0 | U61: 0 | V61: 0 | W61: 0 | X61: 0 | Y61: 0 | Z61: 0 | AA61: 0 | AB61: 0 | AC61: 0 | AD61: 0 | AE61: 0 | AF61: 0 | AG61: 0 | AH61: =SUM(C61:AG61) -> 41.146923
B62: Discount/U$S/8,28%/2033 | C62: =+C63+C65 -> 0 | D62: =+D63+D65 -> 0 | E62: =+E63+E65 -> 1.3842317 | F62: =+F63+F65 -> 1.3842317 | G62: =+G63+G65 -> 1.3842317 | H62: =+H63+H65 -> 1.3842317 | I62: =+I63+I65 -> 1.3842317 | J62: =+J63+J65 -> 1.3842317 | ... AG62: =+AG63+AG65 -> 0 | AH62: =SUM(C62:AG62) -> 13.842317
B63: Emisión Canje 2005 | C63: =+C64 -> 0 | D63: =+D64 -> 0 | E63: =+E64 -> 0.9839155 | F63: =+F64 -> 0.9839155 | G63: =+G64 -> 0.9839155 | H63: =+H64 -> 0.9839155 | I63: =+I64 -> 0.9839155 | J63: =+J64 -> 0.9839155 | ... AG63: =+AG64 -> 0 | AH63: =SUM(C63:AG63) -> 9.839155
B64: Leg. Argentina | C64: 0 | D64: 0 | E64: 0.9839155 | F64: 0.9839155 | G64: 0.9839155 | H64: 0.9839155 | I64: 0.9839155 | J64: 0.9839155 | K64: 0.9839155 | L64: 0.9839155 | M64: 0.9839155 | N64: 0.9839155 | O64: 0 | P64: 0 | Q64: 0 | R64: 0 | S64: 0 | T64: 0 | U64: 0 | V64: 0 | W64: 0 | X64: 0 | Y64: 0 | Z64: 0 | AA64: 0 | AB64: 0 | AC64: 0 | AD64: 0 | AE64: 0 | AF64: 0 | AG64: 0 | AH64: =SUM(C64:AG64) -> 9.839155
B65: Emisión Canje 2010 | C65: =+C66 -> 0 | D65: =+D66 -> 0 | E65: =+E66 -> 0.4003162 | F65: =+F66 -> 0.4003162 | G65: =+G66 -> 0.4003162 | H65: =+H66 -> 0.4003162 | I65: =+I66 -> 0.4003162 | J65: =+J66 -> 0.4003162 | ... AG65: =+AG66 -> 0 | AH65: =SUM(C65:AG65) -> 4.003162
B66: Leg. Argentina | C66: 0 | D66: 0 | E66: 0.4003162 | F66: 0.4003162 | G66: 0.4003162 | H66: 0.4003162 | I66: 0.4003162 | J66: 0.4003162 | K66: 0.4003162 | L66: 0.4003162 | M66: 0.4003162 | N66: 0.4003162 | O66: 0 | P66: 0 | Q66: 0 | R66: 0 | S66: 0 | T66: 0 | U66: 0 | V66: 0 | W66: 0 | X66: 0 | Y66: 0 | Z66: 0 | AA66: 0 | AB66: 0 | AC66: 0 | AD66: 0 | AE66: 0 | AF66: 0 | AG66: 0 | AH66: =SUM(C66:AG66) -> 4.003162
B67: Discount/JPY/4,33%/2033 | C67: =+C68+C69 -> 0 | D67: =+D68+D69 -> 0 | E67: =+E68+E69 -> 8.5372192 | F67: =+F68+F69 -> 8.5372192 | G67: =+G68+G69 -> 8.5372192 | H67: =+H68+H69 -> 8.5372192 | I67: =+I68+I69 -> 8.5372192 | J67: =+J68+J69 -> 8.5372192 | ... AG67: =+AG68+AG69 -> 0 | AH67: =SUM(C67:AG67) -> 85.372192
B68: Emisión Canje 2005 | C68: 0 | D68: 0 | E68: 5.8903907 | F68: 5.8903907 | G68: 5.8903907 | H68: 5.8903907 | I68: 5.8903907 | J68: 5.8903907 | K68: 5.8903907 | L68: 5.8903907 | M68: 5.8903907 | N68: 5.8903907 | O68: 0 | P68: 0 | Q68: 0 | R68: 0 | S68: 0 | T68: 0 | U68: 0 | V68: 0 | W68: 0 | X68: 0 | Y68: 0 | Z68: 0 | AA68: 0 | AB68: 0 | AC68: 0 | AD68: 0 | AE68: 0 | AF68: 0 | AG68: 0 | AH68: =SUM(C68:AG68) -> 58.903907
B69: Emisión Canje 2010 | C69: 0 | D69: 0 | E69: 2.6468285 | F69: 2.6468285 | G69: 2.6468285 | H69: 2.6468285 | I69: 2.6468285 | J69: 2.6468285 | K69: 2.6468285 | L69: 2.6468285 | M69: 2.6468285 | N69: 2.6468285 | O69: 0 | P69: 0 | Q69: 0 | R69: 0 | S69: 0 | T69: 0 | U69: 0 | V69: 0 | W69: 0 | X69: 0 | Y69: 0 | Z69: 0 | AA69: 0 | AB69: 0 | AC69: 0 | AD69: 0 | AE69: 0 | AF69: 0 | AG69: 0 | AH69: =SUM(C69:AG69) -> 26.468285
B70: CUASIPAR/$+CER/3,31%/2045 | C70: 0 | D70: 0 | E70: 0 | F70: 0 | G70: 0 | H70: 0 | I70: 0 | J70: 0 | K70: 0 | L70: 0 | M70: 0 | N70: 0 | O70: 0 | P70: 0 | Q70: 840.03508 | R70: 840.03508 | S70: 840.03508 | T70: 840.03508 | U70: 840.03508 | V70: 840.03508 | W70: 840.03508 | X70: 840.03508 | Y70: 840.03508 | Z70: 840.03508 | AA70: 0 | AB70: 0 | AC70: 0 | AD70: 0 | AE70: 0 | AF70: 0 | AG70: 0 | AH70: =SUM(C70:AG70) -> 8400.3508
B71: BONO GLOBAL/EUR/0,125%/09-07-2030 | C71: 0 | D71: 0 | E71: 52.99947 | F71: 211.99788 | G71: 211.99788 | H71: 211.99788 | I71: 211.99788 | J71: 211.99788 | K71: 211.99788 | L71: 0 | M71: 0 | N71: 0 | O71: 0 | P71: 0 | Q71: 0 | R71: 0 | S71: 0 | T71: 0 | U71: 0 | V71: 0 | W71: 0 | X71: 0 | Y71: 0 | Z71: 0 | AA71: 0 | AB71: 0 | AC71: 0 | AD71: 0 | AE71: 0 | AF71: 0 | AG71: 0 | AH71: =SUM(C71:AG71) -> 1324.9867
B72: BONO GLOBAL/EUR/0,50%/09-07-2029 | C72: 0 | D72: 0 | E72: 0 | F72: 20.550128 | G72: 20.550128 | H72: 20.550128 | I72: 20.550128 | J72: 20.550128 | K72: 0 | L72: 0 | M72: 0 | N72: 0 | O72: 0 | P72: 0 | Q72: 0 | R72: 0 | S72: 0 | T72: 0 | U72: 0 | V72: 0 | W72: 0 | X72: 0 | Y72: 0 | Z72: 0 | AA72: 0 | AB72: 0 | AC72: 0 | AD72: 0 | AE72: 0 | AF72: 0 | AG72: 0 | AH72: =SUM(C72:AG72) -> 102.75064
B73: BONO GLOBAL/EUR/STEP UP/09-01-2038 | C73: 0 | D73: 0 | E73: 0 | F73: 0 | G73: 0 | H73: 41.818843 | I73: 83.637687 | J73: 83.637687 | K73: 83.637687 | L73: 83.637687 | M73: 83.637687 | N73: 83.637687 | O73: 83.637687 | P73: 83.637687 | Q73: 83.637687 | R73: 83.637687 | S73: 41.818843 | T73: 0 | U73: 0 | V73: 0 | W73: 0 | X73: 0 | Y73: 0 | Z73: 0 | AA73: 0 | AB73: 0 | AC73: 0 | AD73: 0 | AE73: 0 | AF73: 0 | AG73: 0 | AH73: =SUM(C73:AG73) -> 920.01456
B74: BONO GLOBAL/EUR/STEP UP/09-07-2035 | C74: 0 | D74: 0 | E74: 0 | F74: 0 | G74: 0 | H74: 0 | I74: 0 | J74: 0 | K74: 0 | L74: 67.931172 | M74: 67.931172 | N74: 67.931172 | O74: 67.931172 | P74: 67.931172 | Q74: 0 | R74: 0 | S74: 0 | T74: 0 | U74: 0 | V74: 0 | W74: 0 | X74: 0 | Y74: 0 | Z74: 0 | AA74: 0 | AB74: 0 | AC74: 0 | AD74: 0 | AE74: 0 | AF74: 0 | AG74: 0 | AH74: =SUM(C74:AG74) -> 339.65586
B75: BONO GLOBAL/EUR/STEP UP/09-07-2041 | C75: 0 | D75: 0 | E75: 0 | F75: 0 | G75: 0 | H75: 0 | I75: 127.68979 | J75: 127.68979 | K75: 127.68979 | L75: 127.68979 | M75: 127.68979 | N75: 127.68979 | O75: 127.68979 | P75: 127.68979 | Q75: 127.68979 | R75: 127.68979 | S75: 127.68979 | T75: 127.68979 | U75: 127.68979 | V75: 127.68979 | W75: 0 | X75: 0 | Y75: 0 | Z75: 0 | AA75: 0 | AB75: 0 | AC75: 0 | AD75: 0 | AE75: 0 | AF75: 0 | AG75: 0 | AH75: =SUM(C75:AG75) -> 1787.6571
B76: BONO GLOBAL/EUR/STEP UP/09-07-2046 | C76: 0 | D76: 0 | E76: 0 | F76: 12.820801 | G76: 12.820801 | H76: 12.820801 | I76: 12.820801 | J76: 12.820801 | K76: 12.820801 | L76: 12.820801 | M76: 12.820801 | N76: 12.820801 | O76: 12.820801 | P76: 12.820801 | Q76: 12.820801 | R76: 12.820801 | S76: 12.820801 | T76: 12.820801 | U76: 12.820801 | V76: 12.820801 | W76: 12.820801 | X76: 12.820801 | Y76: 12.820801 | Z76: 12.820801 | AA76: 12.820801 | AB76: 0 | AC76: 0 | AD76: 0 | AE76: 0 | AF76: 0 | AG76: 0 | AH76: =SUM(C76:AG76) -> 282.05762
B77: BONO GLOBAL/U$S/1,00%/09-07-2029 | C77: 0 | D77: 0 | E77: 0 | F77: 527.00574 | G77: 527.00574 | H77: 527.00574 | I77: 527.00574 | J77: 527.00574 | K77: 0 | L77: 0 | M77: 0 | N77: 0 | O77: 0 | P77: 0 | Q77: 0 | R77: 0 | S77: 0 | T77: 0 | U77: 0 | V77: 0 | W77: 0 | X77: 0 | Y77: 0 | Z77: 0 | AA77: 0 | AB77: 0 | AC77: 0 | AD77: 0 | AE77: 0 | AF77: 0 | AG77: 0 | AH77: =SUM(C77:AG77) -> 2635.0287
B78: BONO GLOBAL/U$S/STEP UP/09-01-2038 | C78: 0 | D78: 0 | E78: 0 | F78: 0 | G78: 0 | H78: 518.41206 | I78: 1036.8241 | J78: 1036.8241 | K78: 1036.8241 | L78: 1036.8241 | M78: 1036.8241 | N78: 1036.8241 | O78: 1036.8241 | P78: 1036.8241 | Q78: 1036.8241 | R78: 1036.8241 | S78: 518.41206 | T78: 0 | U78: 0 | V78: 0 | W78: 0 | X78: 0 | Y78: 0 | Z78: 0 | AA78: 0 | AB78: 0 | AC78: 0 | AD78: 0 | AE78: 0 | AF78: 0 | AG78: 0 | AH78: =SUM(C78:AG78) -> 11405.065
B79: BONO GLOBAL/U$S/STEP UP/09-07-2030 | C79: 0 | D79: 0 | E79: 643.62448 | F79: 2574.4979 | G79: 2574.4979 | H79: 2574.4979 | I79: 2574.4979 | J79: 2574.4979 | K79: 2574.4979 | L79: 0 | M79: 0 | N79: 0 | O79: 0 | P79: 0 | Q79: 0 | R79: 0 | S79: 0 | T79: 0 | U79: 0 | V79: 0 | W79: 0 | X79: 0 | Y79: 0 | Z79: 0 | AA79: 0 | AB79: 0 | AC79: 0 | AD79: 0 | AE79: 0 | AF79: 0 | AG79: 0 | AH79: =SUM(C79:AG79) -> 16090.612
... B118: Letras en Garantía | C118: 345.91377 | D118: 351.53877 | E118: 351.53877 | F118: 351.53877 | G118: 351.53877 | H118: 351.53877 | I118: 351.53877 | J118: 351.53877 | K118: 351.53877 | L118: 351.53877 | M118: 351.53877 | N118: 351.53877 | O118: 351.53877 | P118: 351.53877 | Q118: 351.53877 | R118: 351.53877 | S118: 351.53877 | T118: 303.25772 | U118: 119.51365 | V118: 11.463 | W118: 5.625 | X118: 0 | Y118: 0 | Z118: 0 | AA118: 0 | AB118: 0 | AC118: 0 | AD118: 0 | AE118: 0 | AF118: 0 | AG118: 0 | AH118: =SUM(C118:AG118) -> 6410.3935
B119: LETRAS DEL TESORO | C119: =+C120+C121 -> 23216.793 | D119: =+D120+D121 -> 448.02578 | E119: =+E120+E121 -> 45.310327 | F119: =+F120+F121 -> 0 | G119: =+G120+G121 -> 0 | H119: =+H120+H121 -> 0 | I119: =+I120+I121 -> 0 | J119: =+J120+J121 -> 0 | ... AG119: =+AG120+AG121 -> 0 | AH119: =SUM(C119:AG119) -> 23710.129
B120: . En moneda nacional | C120: 21902.514 | D120: 0 | E120: 0 | F120: 0 | G120: 0 | H120: 0 | I120: 0 | J120: 0 | K120: 0 | L120: 0 | M120: 0 | N120: 0 | O120: 0 | P120: 0 | Q120: 0 | R120: 0 | S120: 0 | T120: 0 | U120: 0 | V120: 0 | W120: 0 | X120: 0 | Y120: 0 | Z120: 0 | AA120: 0 | AB120: 0 | AC120: 0 | AD120: 0 | AE120: 0 | AF120: 0 | AG120: 0 | AH120: =SUM(C120:AG120) -> 21902.514
B121: . En moneda extranjera | C121: 1314.2792 | D121: 448.02578 | E121: 45.310327 | F121: 0 | G121: 0 | H121: 0 | I121: 0 | J121: 0 | K121: 0 | L121: 0 | M121: 0 | N121: 0 | O121: 0 | P121: 0 | Q121: 0 | R121: 0 | S121: 0 | T121: 0 | U121: 0 | V121: 0 | W121: 0 | X121: 0 | Y121: 0 | Z121: 0 | AA121: 0 | AB121: 0 | AC121: 0 | AD121: 0 | AE121: 0 | AF121: 0 | AG121: 0 | AH121: =SUM(C121:AG121) -> 1807.6153
B122: OTROS (1) | C122: =+C123+C130 -> 196.4727 | D122: =+D123+D130 -> 60.349208 | E122: =+E123+E130 -> 17.571045 | F122: =+F123+F130 -> 0.08578722 | G122: =+G123+G130 -> 0.08578722 | H122: =+H123+H130 -> 0.62178723 | I122: =+I123+I130 -> 0.08578722 | J122: =+J123+J130 -> 0.08578722 | ... AG122: =+AG123+AG130 -> 4.9756588 | AH122: =SUM(C122:AG122) -> 282.22087
B123: . En moneda nacional | C123: =+C124+C127 -> 183.34431 | D123: =+D124+D127 -> 60.349208 | E123: =+E124+E127 -> 17.571045 | F123: =+F124+F127 -> 0.08578722 | G123: =+G124+G127 -> 0.08578722 | H123: =+H124+H127 -> 0.08578722 | I123: =+I124+I127 -> 0.08578722 | J123: =+J124+J127 -> 0.08578722 | ... AG123: =+AG124+AG127 -> 4.9756588 | AH123: =SUM(C123:AG123) -> 268.55648
B124: · Ajustable por CER | C124: =+C125+C126 -> 61.449361 | D124: =+D125+D126 -> 60.263421 | E124: =+E125+E126 -> 17.485258 | F124: =+F125+F126 -> 0 | G124: =+G125+G126 -> 0 | H124: =+H125+H126 -> 0 | I124: =+I125+I126 -> 0 | J124: =+J125+J126 -> 0 | ... AG124: =+AG125+AG126 -> 0 | AH124: =SUM(C124:AG124) -> 139.19804
B125: · Bonos de consolidación | C125: 61.293383 | D125: 60.263421 | E125: 17.485258 | F125: 0 | G125: 0 | H125: 0 | I125: 0 | J125: 0 | K125: 0 | L125: 0 | M125: 0 | N125: 0 | O125: 0 | P125: 0 | Q125: 0 | R125: 0 | S125: 0 | T125: 0 | U125: 0 | V125: 0 | W125: 0 | X125: 0 | Y125: 0 | Z125: 0 | AA125: 0 | AB125: 0 | AC125: 0 | AD125: 0 | AE125: 0 | AF125: 0 | AG125: 0 | AH125: =SUM(C125:AG125) -> 139.04206
B126: · Otros | C126: 0.15597849 | D126: 0 | E126: 0 | F126: 0 | G126: 0 | H126: 0 | I126: 0 | J126: 0 | K126: 0 | L126: 0 | M126: 0 | N126: 0 | O126: 0 | P126: 0 | Q126: 0 | R126: 0 | S126: 0 | T126: 0 | U126: 0 | V126: 0 | W126: 0 | X126: 0 | Y126: 0 | Z126: 0 | AA126: 0 | AB126: 0 | AC126: 0 | AD126: 0 | AE126: 0 | AF126: 0 | AG126: 0 | AH126: =SUM(C126:AG126) -> 0.15597849
B127: · No ajustable por CER | C127: =+C128+C129 -> 121.89495 | D127: =+D128+D129 -> 0.08578722 | E127: =+E128+E129 -> 0.08578722 | F127: =+F128+F129 -> 0.08578722 | G127: =+G128+G129 -> 0.08578722 | H127: =+H128+H129 -> 0.08578722 | I127: =+I128+I129 -> 0.08578722 | J127: =+J128+J129 -> 0.08578722 | ... AG127: =+AG128+AG129 -> 4.9756588 | AH127: =SUM(C127:AG127) -> 129.35844
B128: · Bonos de consolidación | C128: 121.80917 | D128: 0 | E128: 0 | F128: 0 | G128: 0 | H128: 0 | I128: 0 | J128: 0 | K128: 0 | L128: 0 | M128: 0 | N128: 0 | O128: 0 | P128: 0 | Q128: 0 | R128: 0 | S128: 0 | T128: 0 | U128: 0 | V128: 0 | W128: 0 | X128: 0 | Y128: 0 | Z128: 0 | AA128: 0 | AB128: 0 | AC128: 0 | AD128: 0 | AE128: 0 | AF128: 0 | AG128: 0 | AH128: =SUM(C128:AG128) -> 121.80917
B129: · Otros | C129: 0.08578722 | D129: 0.08578722 | E129: 0.08578722 | F129: 0.08578722 | G129: 0.08578722 | H129: 0.08578722 | I129: 0.08578722 | J129: 0.08578722 | K129: 0.08578722 | L129: 0.08578722 | M129: 0.08578722 | N129: 0.08578722 | O129: 0.08578722 | P129: 0.08578722 | Q129: 0.08578722 | R129: 0.08578722 | S129: 0.08578722 | T129: 0.08578722 | U129: 0.08578722 | V129: 0.08578722 | W129: 0.08578722 | X129: 0.08578722 | Y129: 0.08578722 | Z129: 0.08578722 | AA129: 0.08578722 | AB129: 0.08578722 | AC129: 0.08578722 | AD129: 0.08578722 | AE129: 0.08578722 | AF129: 0.08578722 | AG129: 4.9756588 | AH129: =SUM(C129:AG129) -> 7.5492754
B130: . En moneda extranjera | C130: =+C131+C132 -> 13.128388 | D130: =+D131+D132 -> 0 | E130: =+E131+E132 -> 0 | F130: =+F131+F132 -> 0 | G130: =+G131+G132 -> 0 | H130: =+H131+H132 -> 0.53600001 | I130: =+I131+I132 -> 0 | J130: =+J131+J132 -> 0 | ... AG130: =+AG131+AG132 -> 0 | AH130: =SUM(C130:AG130) -> 13.664388
B131: · Bonos de consolidación | C131: 2.9442002 | D131: 0 | E131: 0 | F131: 0 | G131: 0 | H131: 0 | I131: 0 | J131: 0 | K131: 0 | L131: 0 | M131: 0 | N131: 0 | O131: 0 | P131: 0 | Q131: 0 | R131: 0 | S131: 0 | T131: 0 | U131: 0 | V131: 0 | W131: 0 | X131: 0 | Y131: 0 | Z131: 0 | AA131: 0 | AB131: 0 | AC131: 0 | AD131: 0 | AE131: 0 | AF131: 0 | AG131: 0 | AH131: =SUM(C131:AG131) -> 2.9442002
B132: · Otros | C132: 10.184188 | D132: 0 | E132: 0 | F132: 0 | G132: 0 | H132: 0.53600001 | I132: 0 | J132: 0 | K132: 0 | L132: 0 | M132: 0 | N132: 0 | O132: 0 | P132: 0 | Q132: 0 | R132: 0 | S132: 0 | T132: 0 | U132: 0 | V132: 0 | W132: 0 | X132: 0 | Y132: 0 | Z132: 0 | AA132: 0 | AB132: 0 | AC132: 0 | AD132: 0 | AE132: 0 | AF132: 0 | AG132: 0 | AH132: =SUM(C132:AG132) -> 10.720188
B134: TOTAL DEUDA DENOMINADA EN PESOS | C134: =+C135+C136 -> 61752.517 | D134: =+D135+D136 -> 20192.01 | E134: =+E135+E136 -> 8590.4375 | F134: =+F135+F136 -> 2108.3525 | G134: =+G135+G136 -> 1877.4534 | H134: =+H135+H136 -> 623.62936 | I134: =+I135+I136 -> 478.08612 | J134: =+J135+J136 -> 447.40513 | ... AG134: =+AG135+AG136 -> 4.9756588 | AH134: =SUM(C134:AG134) -> 107807.64
B135: · Deuda ajustable por CER | C135: 26097.558 | D135: 12008.225 | E135: 8514.5106 | F135: 2014.3622 | G135: 819.57033 | H135: 529.10445 | I135: 377.00379 | J135: 401.98722 | K135: 498.81257 | L135: 1015.2229 | M135: 457.56036 | N135: 457.56036 | O135: 111.14628 | P135: 111.14628 | Q135: 951.18136 | R135: 951.18136 | S135: 1006.7545 | T135: 840.03508 | U135: 840.03508 | V135: 840.03508 | W135: 840.03508 | X135: 840.03508 | Y135: 840.03508 | Z135: 840.03508 | AA135: 0 | AB135: 0 | AC135: 0 | AD135: 0 | AE135: 0 | AF135: 0 | AG135: 0 | AH135: =SUM(C135:AG135) -> 62203.133
B136: · Deuda no ajustable por CER | C136: 35654.96 | D136: 8183.7847 | E136: 75.926966 | F136: 93.990255 | G136: 1057.883 | H136: 94.524911 | I136: 101.08233 | J136: 45.417909 | K136: 48.947493 | L136: 241.30224 | M136: 0.08578722 | N136: 0.08578722 | O136: 0.08578722 | P136: 0.08578722 | Q136: 0.08578722 | R136: 0.08578722 | S136: 0.08578722 | T136: 0.08578722 | U136: 0.08578722 | V136: 0.08578722 | W136: 0.08578722 | X136: 0.08578722 | Y136: 0.08578722 | Z136: 0.08578722 | AA136: 0.08578722 | AB136: 0.08578722 | AC136: 0.08578722 | AD136: 0.08578722 | AE136: 0.08578722 | AF136: 0.08578722 | AG136: 4.9756588 | AH136: =SUM(C136:AG136) -> 45604.511
B137: TOTAL DEUDA EN MONEDA EXTRANJERA | C137: 31229.972 | D137: 31097.145 | E137: 19642.751 | F137: 19190.42 | G137: 8867.3781 | H137: 10159.297 | I137: 11178.267 | J137: 15690.192 | K137: 10146.643 | L137: 26576.974 | M137: 12642.231 | N137: 12489.842 | O137: 12429.2 | P137: 12445.297 | Q137: 4327.2274 | R137: 4210.4077 | S137: 3189.6285 | T137: 1941.3862 | U137: 1644.779 | V137: 1488.0631 | W137: 470.90279 | X137: 429.17636 | Y137: 336.90735 | Z137: 314.93717 | AA137: 285.80324 | AB137: 145.68935 | AC137: 119.65894 | AD137: 89.732622 | AE137: 70.623399 | AF137: 25.592921 | AG137: 4.9761541 | AH137: =SUM(C137:AG137) -> 252881.1
B139: (1) Incluye bonos de consolidación, amparos y excepciones.
B140: (2) A partir del año 2052 el total de servicios corresponde a los vencimientos del Bono del Tesoro Consolidado $ 2089.

Sheet A.3.8
A1: Indice
B2: MINISTERIO DE ECONOMÍA
B3: SECRETARÍA DE FINANZAS
B6: PERFIL ANUAL DE VENCIMIENTOS DE INTERÉS DE LA DEUDA BRUTA DE LA ADMINISTRACIÓN CENTRAL
B8: (En millones de U$S - Stock de deuda y tipo de cambio 31/12/2021)
C9: 2022 | D9: =+C9+1 -> 2023 | E9: =+D9+1 -> 2024 | F9: =+E9+1 -> 2025 | G9: =+F9+1 -> 2026 | H9: =+G9+1 -> 2027 | I9: =+H9+1 -> 2028 | J9: =+I9+1 -> 2029 | K9: =+J9+1 -> 2030 | ... AF9: =+AE9+1 -> 2051 | AG9: 2052-2089 | AH9: Total
B11: PERFIL DE VENCIMIENTOS DE LA DEUDA EN SITUACIÓN DE PAGO NORMAL
B13: TOTAL | C13: =+C14+C15 -> 6000.4376 | D13: =+D14+D15 -> 4374.6318 | E13: =+E14+E15 -> 4611.1541 | F13: =+F14+F15 -> 4734.3361 | G13: =+G14+G15 -> 4557.9953 | H13: =+H14+H15 -> 4261.3639 | I13: =+I14+I15 -> 4428.0056 | J13: =+J14+J15 -> 4242.4925 | ... AG13: =+AG14+AG15 -> 0.0758486 | AH13: =SUM(C13:AG13) -> 57486.5
B14: CORTO PLAZO | C14: 69.322359 | D14: 0 | E14: 0 | F14: 0 | G14: 0 | H14: 0 | I14: 0 | J14: 0 | K14: 0 | L14: 0 | M14: 0 | N14: 0 | O14: 0 | P14: 0 | Q14: 0 | R14: 0 | S14: 0 | T14: 0 | U14: 0 | V14: 0 | W14: 0 | X14: 0 | Y14: 0 | Z14: 0 | AA14: 0 | AB14: 0 | AC14: 0 | AD14: 0 | AE14: 0 | AF14: 0 | AG14: 0 | AH14: =+SUM(C14:AG14) -> 69.322359
B15: MEDIANO Y LARGO PLAZO | C15: 5931.1152 | D15: 4374.6318 | E15: 4611.1541 | F15: 4734.3361 | G15: 4557.9953 | H15: 4261.3639 | I15: 4428.0056 | J15: 4242.4925 | K15: 4114.5648 | L15: 3723.4919 | M15: 3109.6418 | N15: 2518.5412 | O15: 1936.8551 | P15: 1372.0328 | Q15: 901.81601 | R15: 711.08448 | S15: 523.57402 | T15: 402.03439 | U15: 314.48836 | V15: 227.91561 | W15: 153.96654 | X15: 116.08073 | Y15: 78.815661 | Z15: 42.292462 | AA15: 13.156094 | AB15: 6.5679134 | AC15: 4.5303724 | AD15: 2.7611981 | AE15: 1.4118396 | AF15: 0.38388737 | AG15: 0.0758486 | AH15: =+SUM(C15:AG15) -> 57417.177
B17: PRÉSTAMOS | C17: =+C18+C23+C25+C27+C28+C33 -> 2271.9626 | D17: =+D18+D23+D25+D27+D28+D33 -> 1069.2548 | E17: =+E18+E23+E25+E27+E28+E33 -> 615.97959 | F17: =+F18+F23+F25+F27+F28+F33 -> 535.63666 | G17: =+G18+G23+G25+G27+G28+G33 -> 479.8777 | H17: =+H18+H23+H25+H27+H28+H33 -> 424.90078 | I17: =+I18+I23+I25+I27+I28+I33 -> 367.65165 | J17: =+J18+J23+J25+J27+J28+J33 -> 316.82496 | ... AG17: =+AG18+AG23+AG25+AG27+AG28+AG33 -> 0.0758486 | AH17: =+SUM(C17:AG17) -> 7520.3535
B18: Organismos Internacionales | C18: =SUM(C19:C22) -> 1754.3599 | D18: =SUM(D19:D22) -> 902.1777 | E18: =SUM(E19:E22) -> 467.3421 | F18: =SUM(F19:F22) -> 403.08499 | G18: =SUM(G19:G22) -> 362.8663 | H18: =SUM(H19:H22) -> 325.51474 | I18: =SUM(I19:I22) -> 289.80394 | J18: =SUM(J19:J22) -> 253.99703 | ... AG18: =SUM(AG19:AG22) -> 0.0758486 | AH18: =+SUM(C18:AG18) -> 6087.7994
B19: . BIRF | C19: 119.38808 | D19: 117.81826 | E19: 113.90908 | F19: 109.23624 | G19: 104.478 | H19: 98.756352 | I19: 92.903524 | J19: 86.579469 | K19: 80.471011 | L19: 74.362553 | M19: 68.422173 | N19: 62.145637 | O19: 56.037179 | P19: 49.928721 | Q19: 43.934029 | R19: 37.7281 | S19: 32.182122 | T19: 27.632033 | U19: 24.456134 | V19: 21.794254 | W19: 19.220606 | X19: 16.646957 | Y19: 14.113186 | Z19: 11.49966 | AA19: 8.9481159 | AB19: 6.5679134 | AC19: 4.5303724 | AD19: 2.7611981 | AE19: 1.4118396 | AF19: 0.38388737 | AG19: 0.0758486 | AH19: =+SUM(C19:AG19) -> 1508.3225
B20: . BID | C20: 301.59563 | D20: 279.27786 | E20: 255.91789 | F20: 231.16923 | G20: 207.6433 | H20: 184.75873 | I20: 162.75407 | J20: 140.25973 | K20: 119.43073 | L20: 98.600764 | M20: 79.358227 | N20: 64.914829 | O20: 53.098721 | P20: 42.386208 | Q20: 33.143195 | R20: 25.098279 | S20: 18.475 | T20: 13.821474 | U20: 10.684448 | V20: 7.8624775 | W20: 5.3464369 | X20: 3.147174 | Y20: 1.5141018 | Z20: 0.69298645 | AA20: 0.24543088 | AB20: 0 | AC20: 0 | AD20: 0 | AE20: 0 | AF20: 0 | AG20: 0 | AH20: =+SUM(C20:AG20) -> 2341.1969
B21: . FMI | C21: 1234.625 | D21: 415.49192 | E21: 20.697285 | F21: 0 | G21: 0 | H21: 0 | I21: 0 | J21: 0 | K21: 0 | L21: 0 | M21: 0 | N21: 0 | O21: 0 | P21: 0 | Q21: 0 | R21: 0 | S21: 0 | T21: 0 | U21: 0 | V21: 0 | W21: 0 | X21: 0 | Y21: 0 | Z21: 0 | AA21: 0 | AB21: 0 | AC21: 0 | AD21: 0 | AE21: 0 | AF21: 0 | AG21: 0 | AH21: =+SUM(C21:AG21) -> 1670.8142
B22: . Otros | C22: 98.751214 | D22: 89.589664 | E22: 76.81785 | F22: 62.679527 | G22: 50.745012 | H22: 41.999665 | I22: 34.146344 | J22: 27.157824 | K22: 21.875479 | L22: 16.878736 | M22: 12.957683 | N22: 10.041059 | O22: 7.7539199 | P22: 5.6082187 | Q22: 3.8725952 | R22: 2.6535172 | S22: 1.9464316 | T22: 1.2395467 | U22: 0.62053722 | V22: 0.1309442 | W22: 0 | X22: 0 | Y22: 0 | Z22: 0 | AA22: 0 | AB22: 0 | AC22: 0 | AD22: 0 | AE22: 0 | AF22: 0 | AG22: 0 | AH22: =+SUM(C22:AG22) -> 567.46577
B23: Préstamos Garantizados | C23: =+C24 -> 37.937154 | D23: =+D24 -> 37.937154 | E23: =+E24 -> 38.014452 | F23: =+F24 -> 37.937154 | G23: =+G24 -> 37.937154 | H23: =+H24 -> 36.035896 | I23: =+I24 -> 30.40942 | J23: =+J24 -> 30.332121 | ... AG23: =+AG24 -> 0 | AH23: =+SUM(C23:AG23) -> 330.0861
