Workbook
Name _._IMPUESTOS_SOBRE_COMBUSTIBLES_Y_GAS_NATURAL: [1]C!$B$27:$N$27
Name _._IMPUESTOS_SOBRE_ENERGIA_ELECTRICA: [1]C!$B$28:$N$28
Name __r: #REF!
Name __r: #REF!
Name __r: #REF!
Name __r: #REF!
Name __r: #REF!
Name __r: #REF!
Name __r: #REF!
Name __r: #REF!
Name __r: #REF!
Name __r: #REF!
Name __r: #REF!
Name __r: #REF!
Name __r: #REF!
Name __r: #REF!
Name __r: #REF!
Name __r: #REF!
Name __r: #REF!
Name _r: #REF!
Name _r: #REF!
Name _r: #REF!
Name _r: #REF!
Name _r: #REF!
Name _r: #REF!
Name _r: #REF!
Name _r: #REF!
Name _r: #REF!
Name _r: #REF!
Name _r: #REF!
Name _r: #REF!
Name _r: #REF!
Name _r: #REF!
Name _r: #REF!
Name _r: #REF!
Name _r: #REF!
Name A_impresión_IM: '[2]03-08'!#REF!
Name ACC: '[3]CARTERA FONDO'!#REF!
Name ACP: '[3]CARTERA FONDO'!#REF!
Name AMPO5: "Gráfico 8"
Name AÑO: #REF!
Name AÑO: #REF!
Name año2003: #REF!
Name año2003: #REF!
Name cacho: [4]GRAFPROM!#REF!
Name cacho: [4]GRAFPROM!#REF!
Name cacho: [4]GRAFPROM!#REF!
Name carajo: #REF!
Name carajo: #REF!
Name CDF: '[3]CARTERA FONDO'!#REF!
Name CDF: '[3]CARTERA FONDO'!#REF!
Name CFA: '[3]CARTERA FONDO'!#REF!
Name CFD: '[3]CARTERA FONDO'!#REF!
Name CLH: '[3]CARTERA FONDO'!#REF!
Name Coef: [5]CoefStocks!$A$4:$AT$260
Name Coef: [5]CoefStocks!$A$4:$AT$260
Name Coef: [5]CoefStocks!$A$4:$AT$260
Name COPA: #N/A
Name COPARTICIPACION_FEDERAL__LEY_N__23548: [1]C!$B$13:$N$13
Name CUADRO_10.3.1: '[6]fondo promedio'!$A$36:$L$74

Sheet INDICE
B2: MINISTERIO DE ECONOMÍA
B3: SECRETARÍA DE FINANZAS
B5: DEUDA DE LA ADMINISTRACIÓN CENTRAL
B8: ÍNDICE
B10: HOJA | C10: CONTENIDO
B11: Deuda al 31/12/2019: nivel y composición
B12: A.1.1 | C12: Deuda de la Administración Central - Por instrumento y tipo de plazo
B13: A.1.2 | C13: Deuda Bruta de la Administración Central - Por Deuda Directa o Indirecta
B14: A.1.3 | C14: Deuda Bruta de la Administración Central - Por legislación, situación e instrumento
B15: A.1.4 | C15: Deuda Bruta de la Administración Central - Por tipo de moneda y tasa
B16: A.1.5 | C16: Tasa promedio ponderada por moneda e instrumento
B17: A.1.6 | C17: Vida promedio por instrumento
B18: A.1.7 | C18: Títulos públicos y letras del tesoro emitidos en moneda nacional
B19: A.1.8 | C19: Títulos públicos, letras del tesoro, pagarés y préstamos garantizados emitidos en moneda nacional y ajustables por CER
B20: A.1.9 | C20: Títulos públicos, letras del tesoro y pagarés emitidos en moneda extranjera
B21: A.1.10 | C21: Deuda elegible pendiente de reestructuración, desagregada por instrumento
B23: Evolución reciente de la deuda
B24: A.2.1 | C24: Deuda Bruta de la Administración Central - Serie de saldos trimestrales - 4to. Trimestre 2018/4to. Trimestre 2019
B25: A.2.2 | C25: Deuda Bruta de la Administración Central - Flujos y variaciones 4to. Trimestre 2019
B26: A.2.3 | C26: Deuda Bruta de la Administración Central - Flujos y variaciones acumulados 2019
B27: A.2.4 | C27: Serie de Tipos de Cambio y Coeficiente de Estabilización de Referencia (CER)
B28: A.2.5 | C28: Serie de la Deuda del Sector Público Nacional por año - 1992/2019
B30: Vencimientos de capital e interés de la deuda al 31-12-2019 proyectados
B31: A.3.1 | C31: Perfil mensual de vencimientos de capital e interés de la Deuda Bruta de la Administración Central - 01/2020 a 12/2020
B32: A.3.2 | C32: Perfil mensual de vencimientos de capital de la Deuda Bruta de la Administración Central, desagregado por instrumento - 2020
B33: A.3.3 | C33: Perfil mensual de vencimientos de interés de la Deuda Bruta de la Administración Central, desagregado por instrumento - 2020
B34: A.3.4 | C34: Perfil mensual de vencimientos de capital de la Deuda Bruta de la Administración Central, desagregado por instrumento - 2021
B35: A.3.5 | C35: Perfil mensual de vencimientos de interés de la Deuda Bruta de la Administración Central, desagregado por instrumento - 2021
B36: A.3.6 | C36: Perfil anual de vencimientos de capital e interés de la Deuda Bruta de la Administración Central
B37: A.3.7 | C37: Perfil anual de vencimientos de capital de la Deuda Bruta de la Administración Central, desagregado por instrumento
B38: A.3.8 | C38: Perfil anual de vencimientos de interés de la Deuda Bruta de la Administración Central, desagregado por instrumento
B40: Otros Cuadros
B41: A.4.1 | C41: Valores Negociables Vinculados al PBI
B42: A.4.2 | C42: Activos financieros de la Administración Central
B43: A.4.3 | C43: Activos financieros con cargo a provincias
B44: A.4.4 | C44: Flujos netos anuales con Organismos Internacionales
B45: A.4.5 | C45: Deuda Bruta de la Administración Central - Por residencia del tenedor
B46: A.4.6 | C46: Deuda Bruta Externa de la Administración Central - Perfil de vencimientos de capital
B47: A.4.7 | C47: Indicadores de sostenibilidad de la Deuda Bruta de la Administración Central

Sheet A.1.1
A1: Indice
B2: =+INDICE!B2 -> MINISTERIO DE ECONOMÍA
B3: SECRETARÍA DE FINANZAS
B6: DEUDA DE LA ADMINISTRACIÓN CENTRAL
B7: POR INSTRUMENTO Y POR TIPO DE PLAZO
B10: Datos al 31/12/2019
C11: Miles de u$s | D11: Miles de $
B13: I- DEUDA BRUTA + VALORES NEGOCIABLES VINCULADOS AL PBI (II + VI) | C13: =+C16+C84 -> 3.3602735e+08 | D13: =+D16+D84 -> 2.0126358e+10
B16: II- DEUDA BRUTA (III + IV + V) | C16: =+C19+C61+C66 -> 3.2306462e+08 | D16: =+D19+D61+D66 -> 1.9349955e+10
B19: III- DEUDA EN SITUACIÓN DE PAGO NORMAL | C19: =+C21+C54 -> 3.2052545e+08 | D19: =+D21+D54 -> 1.9197872e+10
B21: MEDIANO Y LARGO PLAZO | C21: =+C23+C27+C29+C52 -> 3.0116072e+08 | D21: =+D23+D27+D29+D52 -> 1.8038022e+10
B23: TÍTULOS PÚBLICOS | C23: =+C24+C25 -> 1.9415281e+08 | D23: =+D24+D25 -> 1.1628783e+10
B24: - Moneda nacional | C24: 38723467 | D24: 2.3193421e+09
B25: - Moneda extranjera | C25: 1.5542934e+08 | D25: 9.3094405e+09
B27: LETRAS DEL TESORO (1) | C27: 23113729 | D27: 1.3843968e+09
B29: PRÉSTAMOS | C29: =+C31+C33+C44+C46+C48+C50 -> 79052379 | D29: =+D31+D33+D44+D46+D48+D50 -> 4.7348422e+09
B31: PRÉSTAMOS GARANTIZADOS | C31: 640325.05 | D31: 38352269
B33: ORGANISMOS INTERNACIONALES | C33: =SUM(C34:C42) -> 68000788 | D33: =SUM(D34:D42) -> 4.0729072e+09
B34: - BCIE | C34: 2625 | D34: 157224.38
B35: - BIRF | C35: 7127849.6 | D35: 4.2692255e+08
B36: - BID | C36: 12646999 | D36: 7.5749198e+08
B37: - FONPLATA | C37: 237350.83 | D37: 14216128
B38: - FIDA | C38: 41144.733 | D38: 2464363.8
B39: - CAF | C39: 3655847.8 | D39: 2.1896701e+08
B40: - OFID | C40: 74644.737 | D40: 4470846.5
B41: - FMI | C41: 44128471 | D41: 2.6430748e+09
B42: - BEI | C42: 85856.372 | D42: 5142367.4
B44: ORGANISMOS OFICIALES | C44: 5398072.3 | D44: 3.2331754e+08
B46: BANCA COMERCIAL | C46: =2784897.19483012-C59 -> 2284020.7 | D46: =166801417.48435-D59 -> 1.3680142e+08
B48: AVALES | C48: 2396978.6 | D48: 1.4356703e+08
B50: PAGARÉS DEL TESORO | C50: 332193.96 | D50: 19896757
B52: ADELANTOS TRANSITORIOS BCRA | C52: 4841806.5 | D52: 290000000
B54: CORTO PLAZO (2) | C54: =SUM(C55:C60) -> 19364729 | D54: =SUM(D55:D60) -> 1.1598504e+09
B56: ADELANTOS TRANSITORIOS BCRA | C56: 9395275.1 | D56: 562730000
B57: LETRAS DEL TESORO | C57: 8177985.1 | D57: 4.8982042e+08
B58: PAGARÉS DEL TESORO | C58: 1290591.9 | D58: 77300000
B59: BANCA COMERCIAL | C59: 500876.53 | D59: 30000000
B61: IV- DEUDA EN SITUACIÓN DE PAGO DIFERIDO | C61: =+C63+C64 -> 103955.23 | D61: =+D63+D64 -> 6226398.8
B63: CAPITAL | C63: 95681.181 | D63: 5730824.4
B64: INTERÉS | C64: 8274.0532 | D64: 495574.42
B66: V- DEUDA ELEGIBLE PENDIENTE DE REESTRUCTURACIÓN (3) | C66: =+C68+C73+C78 -> 2435209.5 | D66: =+D68+D73+D78 -> 1.4585687e+08
B68: CAPITAL | C68: =+C70+C71 -> 1058079.7 | D68: =+D70+D71 -> 63373685
B70: - Moneda nacional | C70: 51462.773 | D70: 3082362.8
B71: - Moneda extranjera | C71: 1006617 | D71: 60291323
B73: ATRASOS DE INTERÉS | C73: =+C75+C76 -> 863857.57 | D73: =+D75+D76 -> 51740749
B75: - Moneda nacional | C75: 1910.8236 | D75: 114448.78
B76: - Moneda extranjera | C76: 861946.75 | D76: 51626301
B78: INTERESES COMPENSATORIOS (4) | C78: =+C80+C81 -> 513272.22 | D78: =+D80+D81 -> 30742439
B80: - Moneda nacional | C80: 9810.2731 | D80: 587586.3
B81: - Moneda extranjera | C81: 503461.94 | D81: 30154853
B84: VI- VALORES NEGOCIABLES VINCULADOS AL PBI (5) | C84: 12962732 | D84: 7.7640282e+08
B87: VII- ACTIVOS FINANCIEROS (6) | C87: =+A.4.2!C37+A.4.2!C52 -> 1753531.4 | D87: 1.0502776e+08
B89: VIII- DEUDA NETA (II - VII) | C89: =+C16-C87 -> 3.2131109e+08 | D89: =+D16-D87 -> 1.9244928e+10
B92: (1) Incluye las Letras en Garantía.
B93: (2) Incluye operaciones de hasta un año de plazo.
B94: (3) Se trata de la deuda elegible y no presentada al canje (Dtos. 1735/04 y 563/10) y no cancelada a la fecha en el marco de los acuerdos contemplados en la Ley n° 27.249.
B95: (4) Intereses compensatorios estimados, devengados e impagos con posterioridad a la fecha de vencimiento de cada bono.
B96: (5) Valor remanente total. Es la diferencia entre el máximo a pagar de 48 unidades por cada 100 de valor nocional y la suma de los montos pagados hasta la actualidad, de acuerdo con las condiciones establecidas en las respectivas normas de emisión.
B97: (6) Activos Financieros son créditos a favor del Estado Nacional que se originan en operaciones de Crédito Público. Dato provisorio.

Sheet A.1.2
A1: Indice
B2: =+INDICE!B2 -> MINISTERIO DE ECONOMÍA
B3: SECRETARÍA DE FINANZAS
B6: DEUDA BRUTA DE LA ADMINISTRACIÓN CENTRAL
B7: POR DEUDA DIRECTA E INDIRECTA
B10: Datos al 31/12/2019
C11: Miles de u$s
B13: I- DEUDA BRUTA (II + III) | C13: =+C16+C47 -> 3.2306462e+08
B16: II- DEUDA DIRECTA | C16: =+C18+C29+C36+C41 -> 3.1176384e+08
B18: LARGO PLAZO | C18: =SUM(C20:C27) -> 2.8985995e+08
B20: Títulos Públicos | C20: 1.9415281e+08
B21: Préstamos Garantizados | C21: 640325.05
B22: Organismos Intenacionales | C22: 66549766
B23: Organismos Oficiales | C23: 5350516.8
B24: Banca Comercial | C24: 2247237.7
B25: Adelantos Transitorios | C25: 4841806.5
B26: Letras del Tesoro | C26: 15745290
B27: Pagarés del Tesoro | C27: 332193.96
B29: CORTO PLAZO (1) | C29: =SUM(C31:C35) -> 19364729
B31: Adelantos Transitorios | C31: 9395275.1
B32: Letras del Tesoro | C32: 8177985.1
B33: Pagarés del Tesoro | C33: 1290591.9
B34: Banca Comercial | C34: 500876.53
B36: DEUDA EN SITUACIÓN DE PAGO DIFERIDO | C36: =+C38+C39 -> 103955.23
B38: Capital | C38: 95681.181
B39: Interés (2) | C39: 8274.0532
B41: DEUDA ELEGIBLE PENDIENTE DE REESTRUCTURACIÓN (3) | C41: =+C43+C44+C45 -> 2435209.5
B43: Capital | C43: 1058079.7
B44: Atrasos de Interés | C44: 863857.57
B45: Intereses compensatorios (4) | C45: 513272.22
B47: III- DEUDA INDIRECTA | C47: =+C49 -> 11300779
B49: DEUDA A VENCER | C49: =SUM(C51:C53) -> 11300779
B51: Avales | C51: 2396978.6
B52: Garantías a las provincias | C52: 1535361.3
B53: Letras en garantía | C53: 7368439.5
B56: (1) Incluye operaciones de hasta un año de plazo.
B57: (2) No incluye intereses moratorios ni punitorios.
B58: (3) Se trata de la deuda elegible y no presentada al canje (Dtos. 1735/04 y 563/10) y no cancelada a la fecha en el marco de los acuerdos contemplados en la Ley n° 27.249.
B59: (4) Intereses compensatorios estimados, devengados e impagos con posterioridad a la fecha de vencimiento de cada título.

Sheet A.1.3
A1: Indice
B2: =+INDICE!B2 -> MINISTERIO DE ECONOMÍA
B3: SECRETARÍA DE FINANZAS
B6: DEUDA BRUTA DE LA ADMINISTRACIÓN CENTRAL
B7: POR LEGISLACIÓN, INSTRUMENTO Y SITUACIÓN
B10: Datos al 31/12/2019
C11: Saldo Bruto | D11: %
C12: Miles de u$s
B14: DEUDA BRUTA + VALORES NEGOCIABLES VINCULADOS AL PBI | C14: =+C17+C64 -> 3.3602735e+08
B17: - DEUDA BRUTA | C17: =+C19+C21+C23 -> 3.2306462e+08 | D17: =+D19+D21+D23 -> 1
B19: - EN SITUACIÓN DE PAGO NORMAL | C19: =+C28+C47 -> 3.2052545e+08 | D19: =+C19/$C$17 -> 0.99214038
B21: - EN SITUACIÓN DE PAGO DIFERIDO | C21: =+C36+C54 -> 103955.23 | D21: =+C21/$C$17 -> 0.00032177846
B23: - ELEGIBLE PENDIENTE DE REESTRUCTURACIÓN (1) | C23: =+C40+C58 -> 2435209.5 | D23: =+C23/$C$17 -> 0.0075378404
B26: I- LEGISLACIÓN ARGENTINA | C26: =+C28+C36+C40 -> 1.8047064e+08 | D26: =+D28+D36+D40 -> 0.55862088
B28: - EN SITUACIÓN DE PAGO NORMAL | C28: =SUM(C29:C34) -> 1.8034445e+08 | D28: =+C28/$C$17 -> 0.55823026
B29: TÍTULOS PÚBLICOS Y LETRAS DEL TESORO | C29: 1.5894188e+08 | D29: =+C29/$C$17 -> 0.4919817
B30: PRÉSTAMOS GARANTIZADOS | C30: 640325.05 | D30: =+C30/$C$17 -> 0.001982034
B31: ANTICIPO - BCRA | C31: 14237082 | D31: =+C31/$C$17 -> 0.044068836
B32: AVALES | C32: 2396978.6 | D32: =+C32/$C$17 -> 0.007419502
B33: BANCA | C33: 2505397.8 | D33: =+C33/$C$17 -> 0.007755098
B34: PAGÁRES | C34: 1622785.8 | D34: =+C34/$C$17 -> 0.0050230998
B36: - EN SITUACIÓN DE PAGO DIFERIDO | C36: =+C37+C38 -> 62140.321 | D36: =+C36/$C$17 -> 0.00019234642
B37: BANCA | C37: 60760.484 | D37: =+C37/$C$17 -> 0.00018807533
B38: OTROS | C38: 1379.8369 | D38: =+C38/$C$17 -> 4.2710863e-06
B40: - ELEGIBLE PENDIENTE DE REESTRUCTURACIÓN (1) | C40: =SUM(C41:C43) -> 64053.987 | D40: =+C40/$C$17 -> 0.00019826989
B41: CAPITAL | C41: 51462.785 | D41: =+C41/$C$17 -> 0.00015929564
B42: ATRASOS DE INTERÉS | C42: 2780.9178 | D42: =+C42/$C$17 -> 8.6079306e-06
B43: INTERESES COMPENSATORIOS (2) | C43: 9810.2835 | D43: =+C43/$C$17 -> 3.036632e-05
B45: II- LEGISLACIÓN EXTRANJERA | C45: =+C47+C54+C58 -> 1.4259398e+08 | D45: =+D47+D54+D58 -> 0.44137912
B47: - EN SITUACIÓN DE PAGO NORMAL | C47: =SUM(C48:C52) -> 1.4018101e+08 | D47: =+C47/$C$17 -> 0.43391012
B48: TÍTULOS PÚBLICOS Y LETRAS DEL TESORO | C48: 66502646 | D48: =+C48/$C$17 -> 0.20584936
B49: ORGANISMOS INTERNACIONALES | C49: 68000788 | D49: =+C49/$C$17 -> 0.21048665
B50: AVALES | C50: 0 | D50: =+C50/$C$17 -> 0
B51: BILATERALES | C51: 5398072.3 | D51: =+C51/$C$17 -> 0.016708955
B52: BANCA | C52: 279499.42 | D52: =+C52/$C$17 -> 0.0008651502
B54: - EN SITUACIÓN DE PAGO DIFERIDO | C54: =SUM(C55:C56) -> 41814.913 | D54: =+C54/$C$17 -> 0.00012943204
B55: BANCA | C55: 33130.081 | D55: =+C55/$C$17 -> 0.00010254939
B56: OTROS | C56: 8684.8323 | D56: =+C56/$C$17 -> 2.6882647e-05
B58: - ELEGIBLE PENDIENTE DE REESTRUCTURACIÓN (1) | C58: =SUM(C59:C61) -> 2371155.5 | D58: =+C58/$C$17 -> 0.0073395705
B59: CAPITAL | C59: 1006617 | D59: =+C59/$C$17 -> 0.0031158378
B60: ATRASOS DE INTERÉS | C60: 861076.66 | D60: =+C60/$C$17 -> 0.0026653388
B61: INTERESES COMPENSATORIOS (2) | C61: 503461.93 | D61: =+C61/$C$17 -> 0.0015583939
B64: - VALORES NEGOCIABLES VINCULADOS AL PBI (3) | C64: =+C66+C71 -> 12962732 | D64: =+D66+D71 -> 1
B66: I- LEGISLACIÓN ARGENTINA | C66: =+C68+C69 -> 1086436.8 | D66: =SUM(D68:D69) -> 0.083812337
B68: U$S-LEY ARG (TVPA) | C68: 929780.55 | D68: =+C68/$C$64 -> 0.071727208
B69: ARG-LEY ARG (TVPP) | C69: 156656.29 | D69: =+C69/$C$64 -> 0.01208513
B71: II- LEGISLACIÓN EXTRANJERA | C71: =+C73+C74+C75 -> 11876295 | D71: =SUM(D73:D75) -> 0.91618766
B73: U$S-LEY NY (TVPY-TVYO) | C73: 5151027.2 | D73: =+C73/$C$64 -> 0.39737204
B74: EUR- LEY INGLRESA (TVPE) | C74: 6585218.4 | D74: =+C74/$C$64 -> 0.50801162
B75: YEN- LEY JAPONESA | C75: 140049.33 | D75: =+C75/$C$64 -> 0.010803998
B78: (1) Se trata de la deuda elegible y no presentada al canje (Dtos. 1735/04 y 563/10) y no cancelada a la fecha en el marco de los acuerdos contemplados en la Ley n° 27.249.
B79: (2) Intereses compensatorios estimados, devengados e impagos con posterioridad a la fecha de vencimiento de cada título.
B80: (3) Valor remanente total. Es la diferencia entre el máximo a pagar de 48 unidades por cada 100 de valor nocional y la suma de los montos pagados hasta la actualidad, de acuerdo con las condiciones establecidas en las respectivas normas de emisión.

Sheet A.1.4
A1: Indice
B2: =+INDICE!B2 -> MINISTERIO DE ECONOMÍA
B3: SECRETARÍA DE FINANZAS
B6: DEUDA BRUTA DE LA ADMINISTRACIÓN CENTRAL
B7: POR MONEDA Y TASA
C10: AL 31/12/2019
C11: Deuda Bruta de la Administración Central (Excluida la elegible pendiente de reestructuración) | E11: Deuda elegible pendiente de reestructuración | G11: Total Deuda Bruta
C13: Miles de u$s | D13: % | E13: Miles de u$s | F13: % | G13: Miles de u$s | H13: %
B15: TOTAL | C15: =+C17+C28 -> 3.2062941e+08 | D15: =+D17+D28 -> 0.99246216 | E15: =+E17+E28 -> 2435209.5 | F15: =+F17+F28 -> 0.0075378404 | G15: =+G17+G28 -> 3.2306462e+08 | H15: =+H17+H28 -> 1
B17: Moneda local (1) | C17: =+C19+C24 -> 71582514 | D17: =+D19+D24 -> 0.22157336 | E17: =+E19+E24 -> 63183.869 | F17: =+F19+F24 -> 0.00019557657 | G17: =+G19+G24 -> 71645698 | H17: =+H19+H24 -> 0.22176894
B19: Deuda no ajustable por CER | C19: =SUM(C20:C22) -> 47129925 | D19: =SUM(D20:D22) -> 0.1458839 | E19: =SUM(E20:E22) -> 528.18495 | F19: =SUM(F20:F22) -> 1.6349204e-06 | G19: =SUM(G20:G22) -> 47130454 | H19: =SUM(H20:H22) -> 0.14588553
B20: Tasa fija | C20: 18925634 | D20: =+C20/$G$15 -> 0.058581575 | E20: 15.065927 | F20: =+E20/$G$15 -> 4.6634406e-08 | G20: =+C20+E20 -> 18925649 | H20: =+F20+D20 -> 0.058581622
B21: Tasa Cero | C21: 19378713 | D21: =+C21/$G$15 -> 0.059984016 | E21: 0 | F21: =+E21/$G$15 -> 0 | G21: =+C21+E21 -> 19378713 | H21: =+F21+D21 -> 0.059984016
B22: Tasas Variables | C22: 8825578.1 | D22: =+C22/$G$15 -> 0.027318306 | E22: 513.11902 | F22: =+E22/$G$15 -> 1.588286e-06 | G22: =+C22+E22 -> 8826091.2 | H22: =+F22+D22 -> 0.027319894
B24: Deuda ajustable por CER | C24: =SUM(C25:C26) -> 24452589 | D24: =SUM(D25:D26) -> 0.075689467 | E24: =SUM(E25:E26) -> 62655.684 | F24: =SUM(F25:F26) -> 0.00019394165 | G24: =SUM(G25:G26) -> 24515244 | H24: =SUM(H25:H26) -> 0.075883408
B25: Tasa fija | C25: 23719447 | D25: =+C25/$G$15 -> 0.073420131 | E25: 54181.903 | F25: =+E25/$G$15 -> 0.00016771228 | G25: =+C25+E25 -> 23773629 | H25: =+F25+D25 -> 0.073587844
B26: Tasa cero | C26: 733141.89 | D26: =+C26/$G$15 -> 0.0022693351 | E26: 8473.7817 | F26: =+E26/$G$15 -> 2.6229371e-05 | G26: =+C26+E26 -> 741615.67 | H26: =+F26+D26 -> 0.0022955645
B28: Moneda extranjera | C28: =+C30+C37+C47+C50+C44 -> 2.4904689e+08 | D28: =+D30+D37+D47+D50+D44 -> 0.7708888 | E28: =+E30+E37+E47+E50+E44 -> 2372025.7 | F28: =+F30+F37+F47+F50+F44 -> 0.0073422638 | G28: =+G30+G37+G47+G50+G44 -> 2.5141892e+08 | H28: =+H30+H37+H47+H50+H44 -> 0.77823106
B30: Deuda en dólares estadounidenses | C30: =SUM(C31:C33) -> 1.8263308e+08 | D30: =SUM(D31:D33) -> 0.5653144 | E30: =SUM(E31:E33) -> 1467619.6 | F30: =SUM(F31:F33) -> 0.004542805 | G30: =SUM(G31:G33) -> 1.841007e+08 | H30: =SUM(H31:H33) -> 0.56985721
B31: Tasa fija | C31: 94167632 | D31: =+C31/$G$15 -> 0.29148234 | E31: 1379688.2 | F31: =+E31/$G$15 -> 0.004270626 | G31: =+C31+E31 -> 95547320 | H31: =+F31+D31 -> 0.29575297
B32: Tasa Cero | C32: 19561887 | D32: =+C32/$G$15 -> 0.060551004 | E32: 63 | F32: =+E32/$G$15 -> 1.9500743e-07 | G32: =+C32+E32 -> 19561950 | H32: =+F32+D32 -> 0.060551199
B33: Tasas Variables | C33: =+C34+C35 -> 68903563 | D33: =+D34+D35 -> 0.21328106 | E33: =+E34+E35 -> 87868.416 | F33: =+F34+F35 -> 0.00027198403 | G33: =+C33+E33 -> 68991432 | H33: =+H34+H35 -> 0.21355304
B34: Tasa Libo | C34: 18185903 | D34: =+C34/$G$15 -> 0.056291844 | E34: 80677.426 | F34: =+E34/$G$15 -> 0.00024972535 | G34: =+C34+E34 -> 18266581 | H34: =+F34+D34 -> 0.05654157
B35: Otras tasas variables | C35: 50717660 | D35: =+C35/$G$15 -> 0.15698921 | E35: 7190.9894 | F35: =+E35/$G$15 -> 2.2258672e-05 | G35: =+C35+E35 -> 50724851 | H35: =+F35+D35 -> 0.15701147
B37: Deuda en Euros | C37: =SUM(C38:C40) -> 20923263 | D37: =SUM(D38:D40) -> 0.064764946 | E37: =SUM(E38:E40) -> 856021.6 | F37: =SUM(F38:F40) -> 0.0026496916 | G37: =SUM(G38:G40) -> 21779284 | H37: =SUM(H38:H40) -> 0.067414638
B38: Tasa fija | C38: 20613223 | D38: =+C38/$G$15 -> 0.063805265 | E38: 840951.34 | F38: =+E38/$G$15 -> 0.0026030438 | G38: =+C38+E38 -> 21454175 | H38: =+F38+D38 -> 0.066408308
B39: Tasa Cero | C39: 16814.258 | D39: =+C39/$G$15 -> 5.2046116e-05 | E39: 0 | F39: =+E39/$G$15 -> 0 | G39: =+C39+E39 -> 16814.258 | H39: =+F39+D39 -> 5.2046116e-05
B40: Tasas Variables | C40: =SUM(C41:C42) -> 293224.94 | D40: =+D41+D42 -> 0.00090763558 | E40: =+E41+E42 -> 15070.258 | F40: =+F41+F42 -> 4.6647813e-05 | G40: =+C40+E40 -> 308295.2 | H40: =+H41+H42 -> 0.00095428339
B41: Tasa Libo | C41: 283373.18 | D41: =+C41/$G$15 -> 0.00087714086 | E41: 7516.1818 | F41: =+E41/$G$15 -> 2.3265258e-05 | G41: =+C41+E41 -> 290889.36 | H41: =+F41+D41 -> 0.00090040612
B42: Otras tasas variables | C42: 9851.7637 | D42: =+C42/$G$15 -> 3.0494716e-05 | E42: 7554.076 | F42: =+E42/$G$15 -> 2.3382554e-05 | G42: =+C42+E42 -> 17405.84 | H42: =+F42+D42 -> 5.387727e-05
B44: Deuda en Derechos especiales de giro | C44: =+C45 -> 44141598 | D44: =+SUM(D45:D46) -> 0.13663396 | E44: =+SUM(E45:E46) -> 0 | F44: =+SUM(F45:F46) -> 0 | G44: =+SUM(G45:G46) -> 44141598 | H44: =+SUM(H45:H46) -> 0.13663396
B45: Tasa Variable | C45: 44141598 | D45: =+C45/$G$15 -> 0.13663396 | E45: 0 | F45: =+E45/$G$15 -> 0 | G45: =+C45+E45 -> 44141598 | H45: =+F45+D45 -> 0.13663396
B47: Deuda en Yenes | C47: =+SUM(C48:C48) -> 760001.93 | D47: =+SUM(D48:D48) -> 0.0023524765 | E47: =+SUM(E48:E48) -> 29507.264 | F47: =+SUM(F48:F48) -> 9.1335486e-05 | G47: =+SUM(G48:G48) -> 789509.19 | H47: =+SUM(H48:H48) -> 0.002443812
B48: Tasa fija | C48: 760001.93 | D48: =+C48/$G$15 -> 0.0023524765 | E48: 29507.264 | F48: =+E48/$G$15 -> 9.1335486e-05 | G48: =+C48+E48 -> 789509.19 | H48: =+F48+D48 -> 0.002443812
B50: Deuda en otras monedas extranjeras (2) | C50: =SUM(C51:C51) -> 588950.07 | D50: =SUM(D51:D51) -> 0.0018230101 | E50: =SUM(E51:E51) -> 18877.219 | F50: =SUM(F51:F51) -> 5.8431712e-05 | G50: =SUM(G51:G51) -> 607827.28 | H50: =SUM(H51:H51) -> 0.0018814418
B51: Tasa fija | C51: 588950.07 | D51: =+C51/$G$15 -> 0.0018230101 | E51: 18877.219 | F51: =+E51/$G$15 -> 5.8431712e-05 | G51: =+C51+E51 -> 607827.28 | H51: =+F51+D51 -> 0.0018814418
B54: (1) La deuda emitida en dólares, pero cuyo pago de capital e interés es en pesos, se clasifica como deuda en Moneda Local.
B55: (2) Incluye: Libras esterlinas, Franco Suizo, Corona Danesa, Corona Sueca, Dólar Canadiense, Dinar Kuwaiti, Dólar Australiano y Dirham de Emiratos Árabes Unidos.

Sheet A.1.5
A1: Indice
B2: =+INDICE!B2 -> MINISTERIO DE ECONOMÍA
B3: SECRETARÍA DE FINANZAS
B6: TASA PROMEDIO PONDERADA (1)
B7: POR MONEDA E INSTRUMENTO
B10: Datos al 31/12/2019
B11: TASA PROMEDIO PONDERADA TOTAL | C11: 0.0683702
B13: Deuda en pesos no ajustables por CER | C13: 0.22375586
B15: Títulos Públicos | C15: 0.31316824
B16: Letras del Tesoro | C16: 0.46124717
B17: Otros préstamos | C17: 0.088454462
B18: Adelantos Transitorios BCRA | C18: 0
B20: Deuda en pesos ajustables por CER | C20: 0.037025269
B22: Títulos Públicos | C22: 0.035037518
B23: Letras del Tesoro | C23: 0.092720316
B24: Préstamos garantizados | C24: 0.05
B25: Otros préstamos | C25: 0.0177
B27: Deuda en dólares estadounidenses | C27: 0.04449113
... B56: Otros préstamos | C56: 0.069
B59: (1) Nota Metodológica: Cálculo realizado sobre la deuda en situación de pago normal. Se aplican las tasas de referencia vigentes al 31/12/2019, incluyendo la tasa "plena" en aquellos instrumentos que capitalizan parte de los intereses que devengan.

Sheet A.1.6
A1: Indice
B2: =+INDICE!B2 -> MINISTERIO DE ECONOMÍA
B3: =+A.1.5!B3 -> SECRETARÍA DE FINANZAS
B6: VIDA PROMEDIO (1)
B7: POR INSTRUMENTO
B10: Datos al 31/12/2019 | C10: - En años -
B12: VIDA PROMEDIO TOTAL | C12: 6.9359943
B14: Títulos Públicos | C14: 8.6644495
B16: Letras en Garantía | C16: 10.828226
B18: Letras del Tesoro | C18: 1.0911559
B20: Total Préstamos | C20: 5.1452953
B22: - Organismos Internacionales | C22: 5.4973516
B24: - Organismos Oficiales | C24: 4.1665155
B26: - Préstamos Garantizados (Canje Noviembre 2001) | C26: 10.868862
B28: - Pagarés del Tesoro | C28: 3.7027543
B30: - Banca Comercial | C30: 1.3549629
B32: - Avales | C32: 1.2133014
B34: Adelantos Transitorios | C34: 1.3400842
B37: (1) Nota Metodológica: Cálculo realizado sobre la deuda en situación de pago normal.

Sheet A.1.7
A1: Indice
B2: =+INDICE!B2 -> MINISTERIO DE ECONOMÍA
B3: SECRETARÍA DE FINANZAS
B6: TÍTULOS PÚBLICOS Y LETRAS DEL TESORO
B7: EMITIDOS EN MONEDA NACIONAL
B8: DATOS AL 31/12/2019
H11: En miles de u$s
B12: Fecha de emisión | C12: Denominación | D12: Tasa vigente | E12: Vencimiento | F12: Valor nominal original en circulación | G12: Valor nominal residual en circulación (1) | H12: Valor nominal actualizado en circulación (2)
L14: =+K14-J14 -> 0
C18: TÍTULOS PÚBLICOS | F18: =+F20+F23+F39 -> 16203519 | G18: =+G20+G23+G39 -> 15483558 | H18: =+H20+H23+H39 -> 15960048
C20: BONOS DE CONSOLIDACIÓN | F20: =+F21 -> 90051.553 | G20: =+G21 -> 81046.398 | H20: =+H21 -> 142211.47
B21: 40182 | C21: PR15/$/BADLAR/04-10-2022 | D21: Badlar Bancos Privados | E21: 2022 | F21: 90051.553 | G21: 81046.398 | H21: 142211.47
C23: BONOS | F23: =SUM(F24:F37) -> 16113468 | G23: =SUM(G24:G37) -> 15402511 | H23: =SUM(H24:H37) -> 15817834
B24: 43294 | C24: BONAR/DLK/4,50% U$S/13-02-2020 (3) | D24: 0.045 | E24: 2020 | F24: 1637771.5 | G24: 1637771.5 | H24: 1637771.5
B25: 43193 | C25: BONAR/$/6,72763943919512%/31-12-2028 | D25: 0.067276394 | E25: 2028 | F25: 782776.57 | G25: 705558.06 | H25: 705558.06
B26: 42828 | C26: BONAR/$/BADLAR+200PB/03-04-2022 | D26: Badlar Bancos Privados + 2,00% | E26: 2022 | F26: 895319.19 | G26: 895319.19 | H26: 895319.19
B27: 41631 | C27: BONAR/$/BADLAR+300PB/23-12-2020 | D27: Badlar Bancos Privados + 3,00% | E27: 2020 | F27: 591447.28 | G27: 591447.28 | H27: 591447.28
B28: 42430 | C28: BONAR/$/BADLAR+325PB/01-03-2020 | D28: Badlar Bancos Privados + 3,25% | E28: 2020 | F28: 279281.88 | G28: 279281.88 | H28: 279281.88
B29: 32875 | C29: BONO CONSOLIDADO/$/02-01-2089 | D29: Tasa Cero | E29: 2089 | F29: 14716.816 | G29: 13245.134 | H29: 13245.134
B30: 43272 | C30: BONTE/$/26,00%/21-11-2020 | D30: 0.26 | E30: 2020 | F30: 2083791 | G30: 2083791 | H30: 2083791
B31: 42660 | C31: BONTE/$/15,50%/17-10-2026 | D31: 0.155 | E31: 2026 | F31: 1612316.8 | G31: 1612316.8 | H31: 1612316.8
B32: 42660 | C32: BONTE/$/16,00%/17-10-2023 | D32: 0.16 | E32: 2023 | F32: 1071046.9 | G32: 1071046.9 | H32: 1071046.9
B33: 43172 | C33: BONTE/$/17,25%/13-09-2021 | D33: 0.1725 | E33: 2021 | F33: 1474292.1 | G33: 1474292.1 | H33: 1889614.9
B34: 42646 | C34: BONTE/$/18,20%/03-10-2021 | D34: 0.182 | E34: 2021 | F34: 1043492.8 | G34: 1043492.8 | H34: 1043492.8
B35: 42907 | C35: BOTAPO/$/TPE/21-06-2020 | D35: Tasa Política Económica | E35: 2020 | F35: 2377131.9 | G35: 2377131.9 | H35: 2377131.9
B36: 43504 | C36: BONAR/$/BADLAR+200/08-02-2021 | D36: Badlar Bancos Privados + 2,00% | E36: 2021 | F36: 667835.38 | G36: 667835.38 | H36: 667835.38
B37: 43523 | C37: BONOS PGN 2021/DLK/28-06-2021 | D37: Tasa Cero | E37: 2021 | F37: 1582247.6 | G37: 949981.47 | H37: 949981.47
C39: AMPAROS Y EXCEPCIONES | H39: 2.5156491
C41: LETRAS DEL TESORO | F41: =+SUM(F43:F71) -> 11988755 | G41: =+SUM(G43:G71) -> 10388789 | H41: =+SUM(H43:H71) -> 12363889
B43: 43362 | C43: LETRA/DLK/CMEA/21-09-2020 | D43: Tasa Cero | E43: 2020 | F43: 185335.3 | G43: 185335.3 | H43: 185335.3
B44: 43668 | C44: LETRA/$/FFSIT/20-01-2020 | D44: Tasa Badlar Pública | E44: 2020 | F44: 16695.884 | G44: 16695.884 | H44: 16695.884
B45: 43691 | C45: LETRA/$/FFSIT/12-02-2020 | D45: Tasa Badlar Pública | E45: 2020 | F45: 20869.856 | G45: 20869.856 | H45: 20869.856
B46: 43724 | C46: LETRA/$/FFSIT/16-03-2020 | D46: Tasa Badlar Pública | E46: 2020 | F46: 68620.085 | G46: 68620.085 | H46: 68620.085
B47: 43822 | C47: LETES/$/BADLAR+300PB/22-06-20 | D47: Badlar Bancos Privados + 3,00% | E47: 2020 | F47: 410862.96 | G47: 410862.96 | H47: 410862.96
B48: 43829 | C48: LETES/$/BADLAR+200PB/03-04-20 | D48: Badlar Bancos Privados + 2,00% | E48: 2020 | F48: 207145.79 | G48: 207145.79 | H48: 207145.79
B49: 43721 | C49: LETRA/$/FGS/13-03-2020 | D49: Tasa Badlar Pública + 5,00% | E49: 2020 | F49: 584355.96 | G49: 584355.96 | H49: 584355.96
B50: 43745 | C50: LETRA/$/FGS/01-04-2020 | D50: Tasa Badlar Pública + 5,00% | E50: 2020 | F50: 200350.61 | G50: 200350.61 | H50: 200350.61
B51: 43760 | C51: LETRA/$/FGS/17-04-2020 | D51: Tasa Badlar Pública + 5,00% | E51: 2020 | F51: 33391.769 | G51: 33391.769 | H51: 33391.769
B52: 43773 | C52: LETRA/$/FGS/30-04-2020 | D52: Tasa Badlar Pública + 5,00% | E52: 2020 | F52: 66783.538 | G52: 66783.538 | H52: 66783.538
B53: 43798 | C53: LETRA/$/FGS/27-05-2020 | D53: Tasa Badlar Pública + 5,00% | E53: 2020 | F53: 83479.422 | G53: 83479.422 | H53: 83479.422
B54: 43825 | C54: LETRA/$/FGS/23-06-2020 | D54: Badlar Bancos Privados + 3,00% | E54: 2020 | F54: 1274288.9 | G54: 1274288.9 | H54: 1274288.9
B55: 43703 | C55: LETRA/$/SRT/24-08-2020 | D55: Tasa Badlar Pública | E55: 2020 | F55: 1388.9645 | G55: 1388.9645 | H55: 1388.9645
B56: 43608 | C56: LETRA/DLK/4,25%/04-09-2019 | D56: 0.0425 | E56: 2020 | F56: 322337.62 | G56: 193402.57 | H56: 193402.57
B57: 43608 | C57: LETRA/DLK/4,25%/03-10-2019 | D57: 0.0425 | E57: 2020 | F57: 435680.25 | G57: 370328.21 | H57: 370328.21
B58: 43608 | C58: LETRA/DLK/4,25%/05-11-2019 | D58: 0.0425 | E58: 2020 | F58: 240776.1 | G58: 204659.68 | H58: 204659.68
B59: 43608 | C59: LETRA/DLK/4,25%/04-12-2019 | D59: 0.0425 | E59: 2020 | F59: 424015.26 | G59: 360412.97 | H59: 360412.97
B60: 43364 | C60: LECAP/$/30-09-2019 | D60: 0.414 | E60: 2020 | F60: 733228.33 | G60: 439937 | H60: 739208.54
B61: 43392 | C61: LECAP/$/31-10-2019 | D61: 0.402 | E61: 2020 | F61: 663880.82 | G61: 564298.69 | H61: 906940.86
B62: 43403 | C62: LECAP/$/30-04-2020 | D62: 0.36 | E62: 2020 | F62: 457971.68 | G62: 457971.68 | H62: 692723.39
B63: 43496 | C63: LECAP/$/31-07-2020 | D63: 0.318 | E63: 2020 | F63: 820068.3 | G63: 820068.3 | H63: 1093446.3
B64: 43518 | C64: LECAP/$/28-02-2020 | D64: 0.318 | E64: 2020 | F64: 396584.41 | G64: 396584.41 | H64: 515139.36
B65: 43665 | C65: LECAP/$/29-05-2020 | D65: 0.0375 | E65: 2020 | F65: 757727.34 | G65: 757727.34 | H65: 910864.04
B66: 43616 | C66: LECAP/$/30/08/2019 | D66: 0.51 | E66: 2020 | F66: 753900.62 | G66: 452340.37 | H66: 603661.8
B67: 43644 | C67: LECAP/$/13/09/2019 | D67: 0.51 | E67: 2020 | F67: 990027.65 | G67: 594016.59 | H67: 745787.83
... B69: 43677 | C69: LECAP/$/15-11-2019 | D69: 0.51 | E69: 2020 | F69: 676125.78 | G69: 574706.91 | H69: 693090.79
B70: 43756 | C70: LETRA/$/INTRASP/15-04-2020 | D70: Tasa Badlar Pública | E70: 2020 | F70: 165125.8 | G70: 165125.8 | H70: 165125.8
B71: 43776 | C71: LETRA/$/INTRA SP/05-05-2020 | D71: Tasa Badlar Pública | E71: 2020 | F71: 237097.3 | G71: 237097.3 | H71: 237097.3
C73: PAGARÉS DEL TESORO | F73: =+SUM(F75:F77) -> 1290591.9 | G73: =+SUM(G75:G77) -> 1290591.9 | H73: =+SUM(H75:H77) -> 1290591.9
B75: 43766 | C75: PAGARE CUT 2019-MIN.INTERIOR | E75: 2020 | F75: 1085232.5 | G75: 1085232.5 | H75: 1085232.5
B76: 43766 | C76: PAGARE CUT 2019-INTA | E76: 2020 | F76: 135236.66 | G76: 135236.66 | H76: 135236.66
B77: 43766 | C77: PAGARE CUT 2019-SUP.SEGUROS | E77: 2020 | F77: 70122.715 | G77: 70122.715 | H77: 70122.715
B80: TOTAL | F80: =+F41+F18+F73 -> 29482866 | G80: =+G41+G18+G73 -> 27162939 | H80: =+H41+H18+H73 -> 29614529
B82: (1) Valor nominal original (VNO) menos amortizaciones vencidas. Surge de multiplicar el VNO por el valor residual al 31-12-2019.
B83: (2) Surge de multiplicar el valor nominal residual por el coeficiente de capitalización al 31-12-2019.
B84: (3) DLK: Instrumentos emitidos en u$s que se pagan en Pesos de acuerdo a la normativa de emisión.

Sheet A.1.8
A1: Indice
B2: =+INDICE!B2 -> MINISTERIO DE ECONOMÍA
B3: SECRETARÍA DE FINANZAS
B6: TÍTULOS PÚBLICOS, LETRAS DEL TESORO, PRÉSTAMOS GARANTIZADOS Y PAGARÉS
B7: EMITIDOS EN MONEDA NACIONAL AJUSTABLES POR CER
B8: DATOS AL 31/12/2019
H11: En miles de u$s
B12: Fecha de emisión | C12: Denominación | D12: Tasa Vigente | E12: Vencimiento | F12: Valor nominal original en circulación (1) | G12: Valor nominal residual en circulación (2) | H12: Valor nominal actualizado en circulación (3)
C17: TÍTULOS PÚBLICOS | F17: =+F22+F19+F30+F37 -> 5474876.9 | G17: =+G22+G19+G30+G37 -> 5456394.8 | H17: =+H22+H19+H30+H37 -> 22763419
C19: BONOS DE CONSOLIDACIÓN | F19: =+F20 -> 32271.974 | G19: =+G20 -> 13789.815 | H19: =+H20 -> 214651.46
B20: 38061 | C20: PR13/$+CER/2,00%/15-03-2024 | D20: 0.02 | E20: 2024 | F20: 32271.974 | G20: 13789.815 | H20: 214651.46
C22: BONOS | F22: =SUM(F23:F28) -> 4827535.2 | G22: =SUM(G23:G28) -> 4827535.2 | H22: =SUM(H23:H28) -> 12089128
B23: 42573 | C23: BONCER/$+CER/2,50%/22-07-2021 | D23: 0.025 | E23: 2021 | F23: 958168.98 | G23: 958168.98 | H23: 2860617.6
B24: 42671 | C24: BONCER/$+CER/2,25%/28-04-2020 | D24: 0.0225 | E24: 2020 | F24: 1843244.6 | G24: 1843244.6 | H24: 5238971
B25: 43165 | C25: BONCER/$+CER/4,00%/06-03-2023 | D25: 0.04 | E25: 2023 | F25: 472368.1 | G25: 472368.1 | H25: 1002486.3
B26: 43217 | C26: BONCER/$+CER/4,00%/27-04-2025 | D26: 0.04 | E26: 2025 | F26: 485813.47 | G26: 485813.47 | H26: 991947.64
B27: 43433 | C27: BONCER/$+CER/8,50%/29-11-2022 | D27: 0.085 | E27: 2022 | F27: 567063.53 | G27: 567063.53 | H27: 898390.25
B28: 43165 | C28: BOGATO/$/CER+4%/06-03-2020 | D28: 0.04 | E28: 2020 | F28: 500876.53 | G28: 500876.53 | H28: 1096715.3
C30: BONOS DE LA REESTRUCTURACIÓN - DTO. 1735/04 y 563/10 | F30: =SUM(F31:F35) -> 615069.73 | G30: =SUM(G31:G35) -> 615069.73 | H30: =SUM(H31:H35) -> 10458655
B31: 37986 | C31: PAR/$+CER/TASA FIJA/31-12-2038/DTO. 1735-04 | D31: 0.0118 | E31: 2038 | F31: 47209.898 | G31: 47209.898 | H31: 606032.12
B32: 37986 | C32: PAR/$+CER/TASA FIJA/31-12-2038/DTO. 563-10 | D32: 0.0118 | E32: 2038 | F32: 187.75387 | G32: 187.75387 | H32: 2410.1911
B33: 37986 | C33: DISCOUNT/$+CER/5,83%/31-12-2033/DTO. 1735-04 | D33: 0.0583 | E33: 2033 | F33: 174324.37 | G33: 174324.37 | H33: 2841859.6
B34: 37986 | C34: DISCOUNT/$+CER/5,83%/31-12-2033/DTO. 563-10 | D34: 0.0583 | E34: 2033 | F34: 2095.509 | G34: 2095.509 | H34: 34161.257
B35: 37986 | C35: CUASIPAR/$+CER/3,31%/31-12-2045/DTO. 1735-04 | D35: 0.0331 | E35: 2045 | F35: 391252.2 | G35: 391252.2 | H35: 6974192.2
C37: AMPAROS Y EXCEPCIONES | H37: 984.37376
C39: LETRAS DEL TESORO | F39: =SUM(F41:F42) -> 874651.24 | G39: =SUM(G41:G42) -> 524790.74 | H39: =SUM(H41:H42) -> 733141.89
B41: 43524 | C41: LETES/$+CER/ 30-08-2019 | D41: Tasa Cero | E41: 2019 | F41: 130146.91 | G41: 78088.149 | H41: 112110.57
B42: 43553 | C42: LETES/$+CER/ 30-09-2019 | D42: Tasa Cero | E42: 2019 | F42: 744504.33 | G42: 446702.6 | H42: 621031.32
C44: PRÉSTAMOS GARANTIZADOS | F44: =+F46 -> 28907.881 | G44: =+G46 -> 28907.881 | H44: =+H46 -> 640325.05
C46: PRÉSTAMOS TASA FIJA 5,00% | F46: =SUM(F47:F56) -> 28907.881 | G46: =SUM(G47:G56) -> 28907.881 | H46: =SUM(H47:H56) -> 640325.05
B47: 37201 | C47: PTMO. GAR. TASA FIJA BONTE 27 | D47: 0.05 | E47: 2027 | F47: 977.74441 | G47: 977.74441 | H47: 18741.842
B48: 37201 | C48: PTMO. GAR. TASA FIJA GL 20 | D48: 0.05 | E48: 2020 | F48: 600.81081 | G48: 600.81081 | H48: 11517.814
B49: 37201 | C49: PTMO. GAR. TASA FIJA GL 27 | D49: 0.05 | E49: 2027 | F49: 2778.1902 | G49: 2778.1902 | H49: 53237.009
B50: 37201 | C50: PTMO. GAR. TASA FIJA GL 30 | D50: 0.05 | E50: 2030 | F50: 210.639 | G50: 210.639 | H50: 4038.0449
B51: 37201 | C51: PTMO. GAR. TASA FIJA GL 31 | D51: 0.05 | E51: 2031 | F51: 48.244428 | G51: 48.244428 | H51: 924.86747
B52: 37201 | C52: PTMO. GAR. TASA FIJA GL 31 MEGA | D52: 0.05 | E52: 2031 | F52: 15759.473 | G52: 15759.473 | H52: 372055.18
B53: 37201 | C53: PTMO. GAR. TASA VAR. GL 20 | D53: 0.05 | E53: 2020 | F53: 277.31584 | G53: 277.31584 | H53: 5294.5222
B54: 37201 | C54: PTMO. GAR. TASA VAR. GL 27 | D54: 0.05 | E54: 2027 | F54: 2844.9682 | G54: 2844.9682 | H54: 54299.111
B55: 37201 | C55: PTMO. GAR. TASA VAR. GL 30 | D55: 0.05 | E55: 2030 | F55: 1582.3684 | G55: 1582.3684 | H55: 30210.623
B56: 37201 | C56: PTMO. GAR. TASA VAR. GL 31 MEGA | D56: 0.05 | E56: 2031 | F56: 3828.1263 | G56: 3828.1263 | H56: 90006.028
C58: PAGARÉS DEL TESORO | F58: =+F60 -> 24485.784 | G58: =+G60 -> 24485.784 | H58: =+H60 -> 314323.31
B60: 38930 | C60: PAGARÉ 2038-BNA | D60: 0.0118 | E60: 2038 | F60: 24485.784 | G60: 24485.784 | H60: 314323.31
B62: TOTAL | F62: =+F58+F44+F39+F17 -> 6402921.9 | G62: =+G58+G44+G39+G17 -> 6034579.2 | H62: =+H58+H44+H39+H17 -> 24451209
B64: (1) En el caso de los préstamos garantizados, el monto surge de multiplicar por 1,40 el VNO en circulación.
B65: (2) Valor nominal original (VNO) menos amortizaciones vencidas. Surge de multiplicar el VNO por el valor residual al 31-12-2019.
B66: (3) Surge de multiplicar el valor nominal residual por el coeficiente de capitalización y el coeficiente de estabilización de referencia al 31-12-2019.

Sheet A.1.9
A1: Indice
B2: =+INDICE!B2 -> MINISTERIO DE ECONOMÍA
B3: SECRETARÍA DE FINANZAS
B6: TÍTULOS PÚBLICOS, LETRAS DEL TESORO Y PAGARÉS
B7: EMITIDOS EN MONEDA EXTRANJERA
B8: DATOS AL 31/12/2019
H11: En miles de u$s
B12: Fecha de emisión | C12: Denominación | D12: Tasa vigente | E12: Vencimiento | F12: Valor nominal original en circulación | G12: Valor nominal residual en circulación (1) | H12: Valor nominal actualizado en circulación (2)
C18: TÍTULOS PÚBLICOS | F18: =+F20+F48+F66 -> 1.0126828e+08 | G18: =+G20+G48+G66 -> 99942077 | H18: =+H20+H48+H66 -> 1.0541618e+08
C20: BONOS | F20: =SUM(F21:F46) -> 73226561 | G20: =SUM(G21:G46) -> 71900356 | H20: =SUM(H21:H46) -> 71900356
B21: 41766 | C21: BONAR/U$S/8,75%/07-05-2024 | D21: 0.0875 | E21: 2024 | F21: 7960418.5 | G21: 6634212.8 | H21: 6634212.8
B22: 42285 | C22: BONAR/U$S/8,00%/08-10-2020 | D22: 0.08 | E22: 2020 | F22: 2947560.7 | G22: 2947560.7 | H22: 2947560.7
B23: 42368 | C23: BONAR/U$S/7,75 %/30-12-2022 | D23: 0.0775 | E23: 2022 | F23: 4497753.4 | G23: 4497753.4 | H23: 4497753.4
B24: 42368 | C24: BONAR/U$S/7,875%/30-12-2025 | D24: 0.07875 | E24: 2025 | F24: 4510462.6 | G24: 4510462.6 | H24: 4510462.6
B25: 42368 | C25: BONAR/U$S/7,875%/30-12-2027 | D25: 0.07875 | E25: 2027 | F25: 4690499.6 | G25: 4690499.6 | H25: 4690499.6
B26: 42482 | C26: BIRAD/U$S/6,875%/22-04-2021 | D26: 0.06875 | E26: 2021 | F26: 4500000 | G26: 4500000 | H26: 4500000
B27: 42482 | C27: BIRAD/U$S/7,50%/22-04-2026 | D27: 0.075 | E27: 2026 | F27: 6500000 | G27: 6500000 | H27: 6500000
B28: 42482 | C28: BIRAD/U$S/7,625%/22-04-2046 | D28: 0.07625 | E28: 2046 | F28: 2750000 | G28: 2750000 | H28: 2750000
B29: 42557 | C29: BIRAD/U$S/6,625%/06-07-2028 | D29: 0.06625 | E29: 2028 | F29: 1000000 | G29: 1000000 | H29: 1000000
B30: 42557 | C30: BIRAD/U$S/7,125%/06-07-2036 | D30: 0.07125 | E30: 2036 | F30: 1750000 | G30: 1750000 | H30: 1750000
B31: 42587 | C31: BONAR/U$S/1,00%/05-08-2023 | D31: 0.01 | E31: 2023 | F31: 694687.19 | G31: 694687.19 | H31: 694687.19
B32: 42655 | C32: BIRAE/EUR/3,875%/15-01-2022 | D32: 0.03875 | E32: 2022 | F32: 1401188.2 | G32: 1401188.2 | H32: 1401188.2
... B46: 43433 | C46: BONAR/U$S/8,00%/29-05-2020 | D46: 0.08 | E46: 2020 | F46: 2120284.8 | G46: 2120284.8 | H46: 2120284.8
C48: BONOS DE LA REESTRUCTURACIÓN - DTO. 1735/04 y 563/10 | F48: =SUM(F49:F64) -> 28041721 | G48: =SUM(G49:G64) -> 28041721 | H48: =SUM(H49:H64) -> 33502040
B49: 37986 | C49: PAR/U$S/TASA FIJA/31-12-2038/DTO. 1735-04/LEY NY | D49: 0.025 | E49: 2038 | F49: 5296689.2 | G49: 5296689.2 | H49: 5296689.2
B50: 37986 | C50: PAR/U$S/TASA FIJA/31-12-2038/DTO. 1735-04/LEY ARG | D50: 0.025 | E50: 2038 | F50: 1229562.8 | G50: 1229562.8 | H50: 1229562.8
B51: 37986 | C51: PAR/U$S/TASA FIJA/31-12-2038/DTO. 563-10/LEY NY | D51: 0.025 | E51: 2038 | F51: 96939.179 | G51: 96939.179 | H51: 96939.179
B52: 37986 | C52: PAR/U$S/TASA FIJA/31-12-2038/DTO. 563-10/LEY ARG | D52: 0.025 | E52: 2038 | F52: 71439.702 | G52: 71439.702 | H52: 71439.702
B53: 37986 | C53: PAR/EUR/TASA FIJA/31-12-2038/DTO. 1735-04 | D53: 0.0226 | E53: 2038 | F53: 5643887.6 | G53: 5643887.6 | H53: 5643887.6
B54: 37986 | C54: PAR/EUR/TASA FIJA/31-12-2038/DTO. 563-10 | D54: 0.0226 | E54: 2038 | F54: 1612275.5 | G54: 1612275.5 | H54: 1612275.5
B55: 37986 | C55: PAR/JPY/TASA FIJA/31-12-2038/DTO. 1735-04 | D55: 0.0045 | E55: 2038 | F55: 158959.98 | G55: 158959.98 | H55: 158959.98
B56: 37986 | C56: PAR/JPY/TASA FIJA/31-12-2038/DTO. 563-10 | D56: 0.0045 | E56: 2038 | F56: 7861.9188 | G56: 7861.9188 | H56: 7861.9188
B57: 37986 | C57: DISCOUNT/USD/8,28%/31-12-2033/DTO. 1735-04/LEY NY | D57: 0.0828 | E57: 2033 | F57: 3039534.1 | G57: 3039534.1 | H57: 4261542.4
B58: 37986 | C58: DISCOUNT/USD/8,28%/31-12-2033/DTO. 1735-04/LEY ARG | D58: 0.0828 | E58: 2033 | F58: 5042239.3 | G58: 5042239.3 | H58: 7069411
B59: 37986 | C59: DISCOUNT/USD/8,28%/31-12-2033/DTO. 563-10/LEY NY | D59: 0.0828 | E59: 2033 | F59: 929895.89 | G59: 929895.89 | H59: 1303749.4
B60: 37986 | C60: DISCOUNT/USD/8,28%/31-12-2033/DTO. 563-10/LEY ARG | D60: 0.0828 | E60: 2033 | F60: 131475.87 | G60: 131475.87 | H60: 184334.17
... B64: 37986 | C64: DISCOUNT/JPY/4,33%/31-12-2033/DTO. 563-10 | D64: 0.0433 | E64: 2033 | F64: 23468.926 | G64: 23468.926 | H64: 28045.026
C66: AMPAROS | H66: 13780.741
C68: LETRAS DEL TESORO | F68: =SUM(F70:F90) -> 19871845 | G68: =SUM(G70:G90) -> 18194684 | H68: =SUM(H70:H90) -> 18194684
B70: 43693 | C70: LETRA/U$S/MENDOZA/28-10-2024 | D70: Tasa Cero | E70: 2024 | F70: 1023362.9 | G70: 1016367.1 | H70: 1016367.1
B71: 43721 | C71: LETRA/U$S/FGS/13-03-2020 | D71: Tasa Cero | E71: 2020 | F71: 275000 | G71: 275000 | H71: 275000
B72: 43745 | C72: LETRA/U$S/FGS/01-04-2020 | D72: Tasa Cero | E72: 2020 | F72: 57133.953 | G72: 57133.953 | H72: 57133.953
B73: 43760 | C73: LETRA/U$S/FGS/17-04-2020 | D73: Tasa Cero | E73: 2020 | F73: 175593.54 | G73: 175593.54 | H73: 175593.54
B74: 43773 | C74: LETRA/U$S/FGS/30-04-2020 | D74: Tasa Cero | E74: 2020 | F74: 120525.74 | G74: 120525.74 | H74: 120525.74
B75: 43798 | C75: LETRA/U$S/FGS/27-05-2020 | D75: Tasa Cero | E75: 2020 | F75: 384498.22 | G75: 384498.22 | H75: 384498.22
B76: 43490 | C76: LETES/U$S/30-08-2019 (R) | D76: Tasa Cero | E76: 2020 | F76: 1300446.7 | G76: 780268.03 | H76: 780268.03
B77: 43504 | C77: LETES/U$S/13-09-2019 (R) | D77: Tasa Cero | E77: 2020 | F77: 781104.97 | G77: 468662.98 | H77: 468662.98
B78: 43518 | C78: LETES/U$S/27-09-2019 (R) | D78: Tasa Cero | E78: 2020 | F78: 1200984.7 | G78: 1020837 | H78: 1020837
B79: 43539 | C79: LETES/U$S/11-10-2019 (R) | D79: Tasa Cero | E79: 2020 | F79: 1017673.9 | G79: 865022.78 | H79: 865022.78
B80: 43553 | C80: LETES/U$S/25-10-2019 (R) | D80: Tasa Cero | E80: 2020 | F80: 1135671.8 | G80: 965321.01 | H80: 965321.01
B81: 43567 | C81: LETES/U$S/15-11-2019 (R) | D81: Tasa Cero | E81: 2020 | F81: 933569.47 | G81: 793534.05 | H81: 793534.05
... B90: 43455 | C90: LETRAS EN GARANTIA | D90: Tasa Cero | E90: 2041 | F90: 2918576.5 | G90: 2916480.7 | H90: 2916480.7
C92: LETRAS ADQUIRIDAS POR EL BCRA | F92: =SUM(F94:F104) -> 50013167 | G92: =SUM(G94:G104) -> 50013167 | H92: =SUM(H94:H104) -> 50013167
B94: 40550 | C94: LETRA/U$S/FDA/TITULOS/07-01-2021 | D94: Libor-1,00% | E94: 2021 | F94: 7504000 | G94: 7504000 | H94: 7504000
B95: 41019 | C95: LETRA/U$S/FDA/TITULOS/20-04-2022 | D95: Libor-1,00% | E95: 2022 | F95: 5674000 | G95: 5674000 | H95: 5674000
B96: 41290 | C96: LETRA/U$S/FDA/TITULOS/16-01-2023 | D96: Libor-1,00% | E96: 2023 | F96: 7132655 | G96: 7132655 | H96: 7132655
B97: 41669 | C97: LETRA/U$S/FDA/TITULOS/30-01-2024 | D97: Libor-1,00% | E97: 2024 | F97: 7896764.9 | G97: 7896764.9 | H97: 7896764.9
B98: 42156 | C98: LETRA/U$S/FDA/TITULOS/01-06-2025 | D98: Libor-1,00% | E98: 2025 | F98: 10562540 | G98: 10562540 | H98: 10562540
B99: 40616 | C99: LETRA/U$S/FOI/14-03-2021 | D99: Libor-1,00% | E99: 2021 | F99: 2121386.5 | G99: 2121386.5 | H99: 2121386.5
B100: 41088 | C100: LETRA/U$S/FOI/28-06-2022 | D100: Libor-1,00% | E100: 2022 | F100: 2083648 | G100: 2083648 | H100: 2083648
B101: 41502 | C101: LETRA/U$S/FOI/18-08-2023 | D101: Libor-1,00% | E101: 2023 | F101: 2292296.8 | G101: 2292296.8 | H101: 2292296.8
B102: 41876 | C102: LETRA/U$S/FOI/25-08-2024 | D102: Libor-1,00% | E102: 2024 | F102: 3043000 | G102: 3043000 | H102: 3043000
B103: 42489 | C103: LETRA/U$S/BCRA/29-04-2026 | D103: Libor-1,00% | E103: 2026 | F103: 376299.93 | G103: 376299.93 | H103: 376299.93
B104: 43829 | C104: LETRA/U$S/BCRA/2029 | D104: Libor-1,00% | E104: 2026 | F104: 1326575.8 | G104: 1326575.8 | H104: 1326575.8
C106: PAGARÉS DEL TESORO | F106: =+F108 -> 17870.65 | G106: =+G108 -> 17870.65 | H106: =+H108 -> 17870.65
B108: 40947 | C108: PAGARE -CAMMESA 2021 | D108: Tasa Cero | E108: 2021 | F108: 17870.65 | G108: 17870.65 | H108: 17870.65
B110: TOTAL | F110: =+F106+F92+F68+F18 -> 1.7117116e+08 | G110: =+G106+G92+G68+G18 -> 1.681678e+08 | H110: =+H106+H92+H68+H18 -> 1.736419e+08
B112: (1) Valor nominal original (VNO) menos amortizaciones vencidas. Surge de multiplicar el VNO por el valor residual al 31-12-2019.
B113: (2) Surge de multiplicar el valor nominal residual por el coeficiente de capitalización al 31-12-2019.

Sheet A.1.10
A1: Indice
B2: =+INDICE!B2 -> MINISTERIO DE ECONOMÍA
B3: SECRETARÍA DE FINANZAS
B6: DEUDA ELEGIBLE PENDIENTE DE REESTRUCTURACIÓN
B7: DATOS AL 31/12/2019
G10: En miles de u$s
B11: Denominación | C11: Moneda de origen | D11: Capital | E11: Atrasos de Interés (1) | F11: Intereses Compensatorios (2) | G11: Total
B17: EN MONEDA NACIONAL | D17: =SUM(D19:D32) -> 465.31161 | E17: =SUM(E19:E32) -> 44.363588 | F17: =SUM(F19:F32) -> 18.509755 | G17: =SUM(G19:G32) -> 528.18495
B19: BOCON PRE.2ºS./$/C.A./02/PRE3 | C19: Pesos | D19: 8.3416876 | E19: 0.073085177 | F19: 0.83325726 | G19: 9.2480301
B20: BOCON PRO.1ºS./$/C.A./07/PRO1 | C20: Pesos | D20: 149.05736 | E20: 9.8806977 | F20: 4.8392153 | G20: 163.77727
B21: BOCON PRO.2ºS./$/C.A./10/PRO3 | C21: Pesos | D21: 2.3879482 | E21: 0.24163676 | F21: 0.033840825 | G21: 2.6634258
B22: BOCON PRO.3ºS./$/C.A./07/PRO5 | C22: Pesos | D22: 100.53328 | E22: 7.6518143 | F22: 3.3670275 | G22: 111.55212
B23: BOCON PRO.5°S./$/C.A./07/PRO9 | C23: Pesos | D23: 103.05192 | E23: 10.843749 | F23: 3.4011232 | G23: 117.29679
B24: EUROLETRA/$/11,75%/2007 | C24: Pesos | D24: 5.342683 | E24: 3.4527089 | F24: 5.7719528 | G24: 14.567345
B25: EUROLETRA/$/8,75%/2002 | C25: Pesos | D25: 0.21834878 | E25: 0.016895519 | F25: 0.26333772 | G25: 0.49858202
B26: Dto.1023/7-7-95/CHACO | C26: Pesos | D26: 0.041783621 | E26: 0.0076881209 | F26: 0 | G26: 0.049471742
B27: Dto.1023/7-7-95/CHUBUT | C27: Pesos | D27: 1.8151488 | E27: 0.14494165 | F27: 0 | G27: 1.9600905
B28: Dto.1023/7-7-95/CHUBUT | C28: Pesos | D28: 16.247123 | E28: 0.69301878 | F28: 0 | G28: 16.940142
B29: Dto.1023/7-7-95/RIO NEGRO | C29: Pesos | D29: 2.5751049 | E29: 0.20593722 | F29: 0 | G29: 2.7810422
B30: Dto.1023/7-7-95/SALTA | C30: Pesos | D30: 3.2668446 | E30: 0.26125687 | F30: 0 | G30: 3.5281015
... B32: Dto.1023/7-7-95/M.C.B.A. | C32: Pesos | D32: 72.12782 | E32: 10.865801 | F32: 0 | G32: 82.993621
B34: EN MONEDA NACIONAL AJUSTABLE POR CER | D34: =+SUM(D36:D59) -> 50997.461 | E34: =+SUM(E36:E59) -> 1866.46 | F34: =+SUM(F36:F59) -> 9791.7633 | G34: =+F34+E34+D34 -> 62655.684
B36: LETES/U$S/15-3-2002(P) | C36: Pesos Ajustados por CER | D36: 4548.8711 | E36: 0 | F36: 0 | G36: 4548.8711
B37: LETES/U$S/15-2-2002(P) | C37: Pesos Ajustados por CER | D37: 1580.8115 | E37: 0 | F37: 0 | G37: 1580.8115
B38: LETES/U$S/8-3-2002(P) | C38: Pesos Ajustados por CER | D38: 1601.9284 | E38: 0 | F38: 0 | G38: 1601.9284
B39: LETES/U$S/22-2-2002(P) | C39: Pesos Ajustados por CER | D39: 354.9246 | E39: 0 | F39: 0 | G39: 354.9246
B40: LETES/U$S/22-3-2002(P) | C40: Pesos Ajustados por CER | D40: 387.24615 | E40: 0 | F40: 0 | G40: 387.24615
B41: BONEX/1992(P) | C41: Pesos Ajustados por CER | D41: 3250.6306 | E41: 25.518818 | F41: 884.35211 | G41: 4160.5015
B42: FERROBONOS(P) | C42: Pesos Ajustados por CER | D42: 2.8093657 | E42: 0.81975167 | F42: 0 | G42: 3.6291174
B43: PRE4(P) | C43: Pesos Ajustados por CER | D43: 1220.3061 | E43: 25.189669 | F43: 333.07576 | G43: 1578.5715
B44: PRO2(P) | C44: Pesos Ajustados por CER | D44: 5664.526 | E44: 302.85787 | F44: 1026.8527 | G44: 6994.2366
B45: PRO4(P) | C45: Pesos Ajustados por CER | D45: 2075.7873 | E45: 210.26711 | F45: 220.72538 | G45: 2506.7797
B46: PRO6(P) | C46: Pesos Ajustados por CER | D46: 5301.9767 | E46: 325.07837 | F46: 929.90781 | G46: 6556.9629
B47: PRO8(P) | C47: Pesos Ajustados por CER | D47: 101.50555 | E47: 10.076234 | F47: 0.63159012 | G47: 112.21338
... B59: BONO/U$S/ENC.+4.35%/2004(P) | C59: Pesos Ajustados por CER | D59: 43.71193 | E59: 2.0157443 | F59: 10.661952 | G59: 56.389626
B61: EN MONEDA EXTRANJERA | D61: =+SUM(D63:D82)+SUM(D103:D177) -> 1006617 | E61: =+SUM(E63:E82)+SUM(E103:E177) -> 861946.75 | F61: =+SUM(F63:F82)+SUM(F103:F177) -> 503461.94 | G61: =+F61+E61+D61 -> 2372025.7
B63: EUROLETRA/CHF/7%/2003 | C63: CHF | D63: 7744.3687 | E63: 1084.2116 | F63: 6717.5945 | G63: 15546.175
B64: DISCOUNT/DEM/L.+0,8125%/2023 | C64: EUR | D64: 280.83513 | E64: 90.792044 | F64: 32.209917 | G64: 403.83709
B65: PAR BONDS/DEM/5,87%/2023 | C65: EUR | D65: 3765.4833 | E65: 2873.4403 | F65: 1071.7465 | G65: 7710.6702
B66: EUROLETRA/EUR/8,75%/2003 | C66: EUR | D66: 4202.8864 | E66: 735.50513 | F66: 4860.4631 | G66: 9798.8546
B67: EUROLETRA/DEM/7%/2004 | C67: EUR | D67: 26794.537 | E67: 5626.8528 | F67: 22684.553 | G67: 55105.943
B68: EUROLETRA/DEM/8%/2009 | C68: EUR | D68: 909.75282 | E68: 582.24181 | F68: 471.6563 | G68: 1963.6509
B69: EUROLETRA/EUR/11%-8%/2008 | C69: EUR | D69: 2595.536 | E69: 1453.5001 | F69: 1693.443 | G69: 5742.4791
B70: EUROLETRA/EUR/T.FIJA/2010 | C70: EUR | D70: 1325.8536 | E70: 1020.9073 | F70: 691.76411 | G70: 3038.5249
B71: EUROLETRA/DEM/7,875%/2005 | C71: EUR | D71: 299.74851 | E71: 94.420782 | F71: 253.29686 | G71: 647.46616
B72: EUROLETRA/DEM/14%-9%/2008 | C72: EUR | D72: 170.7936 | E72: 107.59996 | F72: 114.13282 | G72: 392.52639
B73: BONO R.A./EUR/9%/2003 | C73: EUR | D73: 1952.1354 | E73: 351.38437 | F73: 2257.1566 | G73: 4560.6763
B74: BONO R.A./EUR/10%/2007 | C74: EUR | D74: 916.93756 | E74: 550.16254 | F74: 790.85865 | G74: 2257.9587
... B82: EUROLETRA/EUR/8,125%/2004 | C82: EUR | D82: 6664.4255 | E82: 1624.4537 | F82: 6254.5177 | G82: 14543.397
B86: MINISTERIO DE FINANZAS
B87: SECRETARÍA DE FINANZAS
B90: =+B6 -> DEUDA ELEGIBLE PENDIENTE DE REESTRUCTURACIÓN
B91: =+B7 -> DATOS AL 31/12/2019
G94: En miles de u$s
B95: Denominación | C95: Moneda de origen | D95: Capital | E95: Atrasos de Interés (1) | F95: Intereses Compensatorios (2) | G95: Total
B101: (Continuación)
B103: BOCON PRO.1ºS./U$S/L./07/PRO2 | C103: U$S | D103: 0 | E103: 1.26446 | F103: 0 | G103: 1.26446
B104: BONO/U$S/ENCUESTA+4.35%/2004 | C104: U$S | D104: 0 | E104: 1.87 | F104: 0 | G104: 1.87
B105: BONO/U$S/ENCUESTA+4%/2002 | C105: U$S | D105: 0 | E105: 14.02309 | F105: 0 | G105: 14.02309
B106: BONTES/U$S/ENCUESTA+3,2%/2003 | C106: U$S | D106: 0 | E106: 15.68152 | F106: 0 | G106: 15.68152
B107: BOCON PRO.5ºS./U$S/L./07/PRO10 | C107: U$S | D107: 0 | E107: 25.04966 | F107: 0 | G107: 25.04966
B108: BOCON PRO.2ºS./U$S/L./10/PRO4 | C108: U$S | D108: 0 | E108: 27.7379 | F108: 0 | G108: 27.7379
B109: BONO/U$S/ENCUESTA+3,3%/2002 | C109: U$S | D109: 0 | E109: 41.03004 | F109: 0 | G109: 41.03004
B110: EUROLETRA/U$S/ENC.+4,95%/2004 | C110: U$S | D110: 0 | E110: 501.22017 | F110: 0 | G110: 501.22017
B111: EUROLETRA/U$S/BAD.+2,98%/2004 | C111: U$S | D111: 0.007 | E111: 242.21741 | F111: 0.010390558 | G111: 242.2348
B112: GLOBAL BOND/$/10%-12%/2008 | C112: U$S | D112: 0.356 | E112: 0.27767533 | F112: 0.32443467 | G112: 0.95811
B113: GLOBAL BOND/U$S/8,875%/2029 | C113: U$S | D113: 2 | E113: 2.14881 | F113: 0 | G113: 4.14881
B114: GLOBAL BOND/U$S/T.CERO/2004 | C114: U$S | D114: 63 | E114: 0 | F114: 0 | G114: 63
... B177: GLOBAL BOND/U$S/11,375%/2017 | C177: U$S | D177: 181636.8 | E177: 297405.42 | F177: 0 | G177: 479042.22
B179: TOTAL | D179: =+D61+D17+D34 -> 1058079.7 | E179: =+E61+E17+E34 -> 863857.57 | F179: =+F61+F17+F34 -> 513272.22 | G179: =+D179+E179+F179 -> 2435209.5
B181: (1) No incluye intereses moratorios ni punitorios.
B182: (2) Intereses compensatorios estimados, devengados e impagos con posterioridad a la fecha de vencimiento de cada título.

Sheet A.2.1
A1: Indice
B2: =+INDICE!B2 -> MINISTERIO DE ECONOMÍA
B3: =+A.1.10!B3 -> SECRETARÍA DE FINANZAS
B6: DEUDA BRUTA DE LA ADMINISTRACIÓN CENTRAL
B7: SERIE POR TRIMESTRE Y POR INSTRUMENTO
B10: En miles de u$s - TC del trimestre
B11: INSTRUMENTO | C11: 2018 | D11: 2019
C12: Saldo al 31/12/2018 | D12: Saldo al 31/03/2019 | E12: Saldo al 30/06/2019 | F12: Saldo al 30/09/2019 | G12: Saldo al 31/12/2019
B14: I- DEUDA BRUTA + VALORES NEGOCIABLES VINCULADOS AL PBI ( II+VII ) | C14: =+C17+C74 -> 3.4538474e+08 | D14: =+D17+D74 -> 3.3792935e+08 | E14: =+E17+E74 -> 3.5038828e+08 | F14: =+F17+F74 -> 3.2403783e+08 | G14: =+G17+G74 -> 3.3602735e+08
B17: II- DEUDA BRUTA ( III+IV+V+VI ) | C17: =+C20+C53+C61+C66 -> 3.321918e+08 | D17: =+D20+D53+D61+D66 -> 3.2489795e+08 | E17: =+E20+E53+E61+E66 -> 3.3726739e+08 | F17: =+F20+F53+F61+F66 -> 3.1125103e+08 | G17: =+G20+G53+G61+G66 -> 3.2306462e+08
B20: III- MEDIANO Y LARGO PLAZO | C20: =+C22+C26+C28+C51 -> 2.9054808e+08 | D20: =+D22+D26+D28+D51 -> 2.8821517e+08 | E20: =+E22+E26+E28+E51 -> 3.0086194e+08 | F20: =+F22+F26+F28+F51 -> 2.9350376e+08 | G20: =+G22+G26+G28+G51 -> 3.0116072e+08
B22: TÍTULOS PÚBLICOS | C22: =+C23+C24 -> 2.1525157e+08 | D22: =+D23+D24 -> 2.1332991e+08 | E22: =+E23+E24 -> 2.1482729e+08 | F22: =+F23+F24 -> 1.9100641e+08 | G22: =+G23+G24 -> 1.9415281e+08
B23: - Moneda nacional | C23: 43400131 | D23: 41502108 | E23: 47617911 | F23: 37459863 | G23: 38723467
B24: - Moneda extranjera | C24: 1.7185144e+08 | D24: 1.718278e+08 | E24: 1.6720938e+08 | F24: 1.5354655e+08 | G24: 1.5542934e+08
B26: LETRAS DEL TESORO (1) | C26: 11555685 | D26: 12306696 | E26: 13735015 | F26: 26559882 | G26: 23113729
B28: PRÉSTAMOS | C28: =+C30+C32+C43+C45+C47+C49 -> 61262527 | D28: =+D30+D32+D43+D45+D47+D49 -> 60737869 | E28: =+E30+E32+E43+E45+E47+E49 -> 71211255 | F28: =+F30+F32+F43+F45+F47+F49 -> 75351975 | G28: =+G30+G32+G43+G45+G47+G49 -> 79052379
B30: PRÉSTAMOS GARANTIZADOS | C30: 683538.52 | D30: 637850.15 | E30: 729146.87 | F30: 584431.07 | G30: 640325.05
B32: ORGANISMOS INTERNACIONALES | C32: =SUM(C33:C41) -> 51037436 | D32: =SUM(D33:D41) -> 50871977 | E32: =SUM(E33:E41) -> 62752778 | F32: =SUM(F33:F41) -> 67389879 | G32: =SUM(G33:G41) -> 68000788
B33: - BCIE | C33: 2625 | D33: 2625 | E33: 2625 | F33: 2625 | G33: 2625
B34: - BIRF | C34: 6879346 | D34: 6802881.8 | E34: 6960726.8 | F34: 7060899.9 | G34: 7127849.6
B35: - BID | C35: 12331943 | D35: 12176419 | E35: 12911927 | F35: 12756148 | G35: 12646999
B36: - FONPLATA | C36: 167338.58 | D36: 193602.05 | E36: 205327.1 | F36: 211076.42 | G36: 237350.83
B37: - FIDA | C37: 45161.6 | D37: 44668.879 | E37: 42243.593 | F37: 40925.303 | G37: 41144.733
B38: - CAF | C38: 3467422.1 | D38: 3475803 | E38: 3557602.7 | F38: 3662650.5 | G38: 3655847.8
B39: - OFID | C39: 41262.805 | D39: 42507.082 | E39: 55733.582 | F39: 60890.877 | G39: 74644.737
B40: - FMI | C40: 28031771 | D40: 28062904 | E40: 38940381 | F40: 43508807 | G40: 44128471
B41: - BEI | C41: 70566 | D41: 70566 | E41: 76211.278 | F41: 85856.372 | G41: 85856.372
B43: ORGANISMOS OFICIALES | C43: 6912168.6 | D43: 6869745 | E43: 5320477.2 | F43: 5289399.3 | G43: 5398072.3
B45: BANCA COMERCIAL | C45: 1194162.8 | D45: 1140918.9 | E45: 1187129 | F45: 972022.71 | G45: 2284020.7
B47: AVALES | C47: 931193.36 | D47: 871628.7 | E47: 831158.82 | F47: 811485.5 | G47: 2396978.6
... B51: ADELANTOS TRANSITORIOS BCRA | C51: 2478291.8 | D51: 1840690.3 | E51: 1088382.8 | F51: 585493.32 | G51: 4841806.5
B53: IV- CORTO PLAZO | C53: =SUM(C55:C59) -> 38733469 | D53: =SUM(D55:D59) -> 34101861 | E53: =SUM(E55:E59) -> 33844412 | F53: =SUM(F55:F59) -> 15238796 | G53: =SUM(G55:G59) -> 19364729
B55: ADELANTOS TRANSITORIOS BCRA | C55: 10818524 | D55: 9755428.1 | E55: 10754965 | F55: 8148781.3 | G55: 9395275.1
B56: LETRAS DEL TESORO | C56: 22694282 | D56: 22346432 | E56: 23089447 | F56: 7090014.6 | G56: 8177985.1
B57: PAGARÉS DEL TESORO | C57: 1013005.1 | D57: 0 | E57: 0 | F57: 0 | G57: 1290591.9
B58: BANCA COMERCIAL | C58: 0 | D58: 0 | E58: 0 | F58: 0 | G58: 500876.53
B59: TÍTULOS PÚBLICOS | C59: 4207658.3 | D59: 2000000 | E59: 0 | F59: 0 | G59: 0
B61: V- DEUDA EN SITUACIÓN DE PAGO DIFERIDO | C61: =+C63+C64 -> 104835.13 | D61: =+D63+D64 -> 104084.63 | E61: =+E63+E64 -> 104717.07 | F61: =+F63+F64 -> 102962.75 | G61: =+G63+G64 -> 103955.23
B63: CAPITAL | C63: 96391.014 | D63: 95790.927 | E63: 96324.436 | F63: 94889.592 | G63: 95681.181
B64: INTERÉS (2) | C64: 8444.1139 | D64: 8293.7073 | E64: 8392.6373 | F64: 8073.1588 | G64: 8274.0532
B66: VI- DEUDA ELEGIBLE PENDIENTE DE REESTRUCTURACIÓN (3) | C66: =+C68+C69+C70 -> 2805421.7 | D66: =+D68+D69+D70 -> 2476841.8 | E66: =+E68+E69+E70 -> 2456320.2 | F66: =+F68+F69+F70 -> 2405504.3 | G66: =+G68+G69+G70 -> 2435209.5
B68: - Capital | C68: 1218781.3 | D68: 1074824.3 | E68: 1070536.5 | F68: 1043557.9 | G68: 1058079.7
B69: - Atrasos de Interés | C69: 1012570 | D69: 880087.07 | E69: 866535.11 | F69: 858847.84 | G69: 863857.57
B70: - Intereses Compensatorios (4) | C70: 574070.48 | D70: 521930.42 | E70: 519248.63 | F70: 503098.61 | G70: 513272.22
B74: VII- VALORES NEGOCIABLES VINCULADOS AL PBI (5) | C74: =SUM(C76:C80) -> 13192940 | D74: =SUM(D76:D80) -> 13031401 | E74: =SUM(E76:E80) -> 13120890 | F74: =SUM(F76:F80) -> 12786802 | G74: =SUM(G76:G80) -> 12962732
B76: U$S- LEY NY (TVPY-TVYO) | C76: 5156899.1 | D76: 5156899.1 | E76: 5151027.2 | F76: 5151027.2 | G76: 5151027.2
B77: U$S- LEY ARG (TVPA) | C77: 929780.55 | D77: 929780.55 | E77: 929780.55 | F77: 929780.55 | G77: 929780.55
B78: ARP-LEY ARG (TVPP) | C78: 249787.58 | D78: 217839.1 | E78: 221043.69 | F78: 163016.08 | G78: 156656.29
B79: EUR-LEY INGLESA (TVPE) | C79: 6718519.4 | D79: 6589650.4 | E79: 6678041.8 | F79: 6402215.9 | G79: 6585218.4
B80: YEN- LEY JAPONESA | C80: 137953.55 | D80: 137231.67 | E80: 140997.02 | F80: 140762.15 | G80: 140049.33
B83: (1) Incluye las Letras en Garantía.
B84: (2) No incluye intereses moratorios ni punitorios.
B85: (3) Se trata de la deuda elegible y no presentada al canje (Dtos. 1735/04 y 563/10) y no cancelada a la fecha en el marco de los acuerdos contemplados en la Ley n° 27.249.
B86: (4) Intereses compensatorios estimados, devengados e impagos con posterioridad a la fecha de vencimiento de cada título.
B87: (5) Valor remanente total. Es la diferencia entre el máximo a pagar de 48 unidades por cada 100 de valor nocional y la suma de los montos pagados hasta la actualidad, de acuerdo con las condiciones establecidas en las respectivas normas de emisión.

Sheet A.2.2
A1: Indice
B2: =+INDICE!B2 -> MINISTERIO DE ECONOMÍA
B3: =+A.2.1!B3 -> SECRETARÍA DE FINANZAS
B5: DEUDA BRUTA DE LA ADMINISTRACIÓN CENTRAL
B6: FLUJOS Y VARIACIONES
B7: 4to. TRIMESTRE DE 2019
C10: Miles de u$s | D10: Miles de $
B12: I - DEUDA BRUTA (EXCLUIDA LA ELEGIBLE PENDIENTE DE REESTRUCTURACIÓN), AL 30/09/2019 | C12: 3.0884552e+08 | D12: 1.7776623e+10
B14: II - DEUDA ELEGIBLE PENDIENTE DE REESTRUCTURACIÓN, AL 30/09/2019 | C14: 2405504.3 | D14: 1.3845674e+08
B16: III - DEUDA BRUTA, AL 30/09/2019 (I + II) | C16: =+C12+C14 -> 3.1125103e+08 | D16: =+D12+D14 -> 1.791508e+10
B18: VARIACIONES
B20: 1 - Financiamiento | C20: =SUM(C22:C30) -> 21200127 | D20: =SUM(D22:D30) -> 1.2202433e+09
B22: Adelantos Transitorios del BCRA | C22: 10381648 | D22: 597550000
B23: Préstamos Organismos Multilaterales | C23: 435124.03 | D23: 25045000
B24: Financiamiento Banco Nación | C24: 521210.67 | D24: 30000000
B25: Letras del Tesoro - Organismos Públicos | C25: 5466299.1 | D25: 3.1463088e+08
B26: Letras Intransferibles | C26: 1326575.8 | D26: 76355450
B27: Titulos del Tesoro | C27: 144327.23 | D27: 8307229.8
B28: Pagarés del Tesoro | C28: 1342986.2 | D28: 77300000
B29: Préstamos Organismos Oficiales | C29: 109171.73 | D29: 6283739
B30: Otros | C30: 1472784.7 | D30: 84770981
B32: 2 - Amortizaciones y Cancelaciones | C32: =SUM(C34:C40) -> 13374942 | D32: =SUM(D34:D40) -> 7.6983891e+08
B34: Adelantos Transitorios del BCRA | C34: 4300856.7 | D34: 247550000
B35: Préstamos Organismos Multilaterales | C35: 443857.17 | D35: 25547664
B36: Letras del Tesoro - Organismos Públicos | C36: 8321430.6 | D36: 4.789674e+08
B37: Titulos del Tesoro | C37: 174333.73 | D37: 10034353
B38: Préstamos Organismos Oficiales | C38: 28151.374 | D38: 1620345.3
B39: Bonos de Consolidación | C39: 19145.469 | D39: 1101980.6
B40: Otros | C40: 87166.706 | D40: 5017167.4
B42: a) Financiamiento, neto de amortizaciones ( 1 - 2 ) | C42: =+C20-C32 -> 7825185.5 | D42: =+D20-D32 -> 4.5040437e+08
B44: b) Emisión Bonos de Consolidación | C44: 8873.7458 | D44: 510757.72
B46: c) Avales netos de cancelaciones | C46: -399408.81 | D46: -22989292
B48: d) Letras en garantía | C48: -48686.05 | D48: -2802286.3
B50: e) Ajustes de valuación - Excluyendo la deuda elegible pendiente de reestructuración | C50: =SUM(C52:C55) -> 4397922.7 | D50: =SUM(D52:D55) -> 1.0023517e+09
B52: Tipo de Cambio (excluye deudas ajustables por CER) | C52: -585454.26 | D52: 6.6094132e+08
B53: Variación de la deuda ajustable por CER (efectos tipo de cambio y CER) | C53: 2038734.3 | D53: 1.7192175e+08
B54: Capitalización de Bonos del Canje, Préstamos Garantizados, Pagaré Banco Nación, Bonos de consolidación y Otros | C54: 933485.55 | D54: 53729841
B55: Otras Operaciones (Registro CCF, amparos y excepciones y otros ajustes (1)) | C55: 2011157.1 | D55: 1.1575879e+08
B57: f) Ajustes de valuación sobre deuda elegible pendiente de reestructuración | C57: =SUM(C59:C61) -> 29705.226 | D57: =SUM(D59:D61) -> 7400136.4
B59: Tipo de Cambio (excluye deudas ajustables por CER) | C59: 24328.721 | D59: 6944266.4
B60: Variación de la deuda ajustable por CER (efectos tipo de cambio y CER) | C60: 5469.2154 | D60: 461206.29
B61: Otras Operaciones (Bajas Ley n° 27.249, amparos y excepciones y otros ajustes) | C61: -92.710657 | D61: -5336.2678
B63: IV - TOTAL VARIACIONES (a+b+c+d+e+f) | C63: =+C42+C44+C46+C48+C50+C57 -> 11813592 | D63: =+D42+D44+D46+D48+D50+D57 -> 1.4348754e+09
B65: V - DEUDA BRUTA, AL 31/12/2019 (III + IV) | C65: =+C16+C63 -> 3.2306462e+08 | D65: =+D16+D63 -> 1.9349955e+10
B67: VI - DEUDA ELEGIBLE PENDIENTE DE REESTRUCTURACIÓN, AL 31/12/2019 | C67: =+C14+C57 -> 2435209.5 | D67: =+D14+D57 -> 1.4585687e+08
B69: VII - DEUDA BRUTA (EXCLUIDA LA ELEGIBLE PENDIENTE DE REESTRUCTURACIÓN), AL 31/12/2019 (V - VI) | C69: =+C65-C67 -> 3.2062941e+08 | D69: =+D65-D67 -> 1.9204098e+10
B72: (1) EX-2019-102447651- -APN-DGD#MHA / u$s 2.016.035.590,86 corresponden a la actualización del registro de instrumentos de la deuda pública indirecta - Avales otorgados y/o endosados a favor de distintas entidades.
B76: Efecto de las diferencias de cambio del período sobre el stock de Deuda de la Administración Central
B79: (En millones de u$s)
B80: Moneda | C80: Variación
C81: S/Saldos | D81: S/Atrasos | E81: Total
B83: Efecto de la variación de la relación Peso/dólar en deudas en pesos no ajustadas por CER | C83: -1799.4442 | D83: -0.03 | E83: -1799.4742
B84: Efecto de la variación de la relación Euro/dólar | C84: 580.57094 | D84: 24.67 | E84: 605.24094
B85: Efecto de la variación de la relación DEG/dólar (1) | C85: 619.84794 | D85: 0 | E85: 619.84794
B86: Efecto de la variación de la relación Yen/dólar | C86: -3.8682312 | D86: -0.15 | E86: -4.0182312
B87: Efecto de la variación de la relación Franco Suizo/dólar | C87: 15.617058 | D87: 0.47 | E87: 16.087058
B88: Efecto de la variación de la relación Libra Esterlina/dólar | C88: 0.3905546 | D88: 0.24 | E88: 0.6305546
B89: Efecto de la variación de la relación del dólar con otras monedas (2) | C89: 0.55958556 | D89: 0 | E89: 0.55958556
B91: Total | C91: =SUM(C83:C90) -> -586.32631 | D91: =SUM(D83:D90) -> 25.2 | E91: =SUM(E83:E90) -> -561.12631
B93: (1) El DEG es una canasta de monedas.
B94: (2) Incluye: Corona Danesa, Corona Sueca, Dólar Canadiense, Dólar Australiano, Dinar Kuwaití y Dirham de los Emiratos Árabes Unidos.

Sheet A.2.3
A1: Indice
B2: =+INDICE!B2 -> MINISTERIO DE ECONOMÍA
B3: =+INDICE!B3 -> SECRETARÍA DE FINANZAS
B5: DEUDA BRUTA DE LA ADMINISTRACIÓN CENTRAL
B6: FLUJOS Y VARIACIONES
B7: ACUMULADO ENERO 2019 - DICIEMBRE 2019
C10: Miles de u$s | D10: Miles de $
B12: I - DEUDA BRUTA (EXCLUIDA LA ELEGIBLE PENDIENTE DE REESTRUCTURACIÓN), AL 31/12/2018 | C12: 3.2938638e+08 | D12: 1.2453539e+10
B14: II - DEUDA ELEGIBLE PENDIENTE DE REESTRUCTURACIÓN, AL 31/12/2018 | C14: 2805421.7 | D14: 1.0606823e+08
B16: III - DEUDA BRUTA, AL 31/12/2018 (I + II) | C16: =+C12+C14 -> 3.321918e+08 | D16: =+D12+D14 -> 1.2559607e+10
B18: VARIACIONES
B20: 1 - Financiamiento | C20: =SUM(C22:C30) -> 98622529 | D20: =SUM(D22:D30) -> 4.4245842e+09
B22: Adelantos Transitorios del BCRA | C22: 16636408 | D22: 852730000
B23: Préstamos Organismos Multilaterales | C23: 18918031 | D23: 8.1949079e+08
B24: Financiamiento Banco Nación | C24: 521210.67 | D24: 30000000
B25: Letras del Tesoro - Organismos Públicos | C25: 43732272 | D25: 1.8947768e+09
B26: Letras Intransferibles | C26: 1326575.8 | D26: 76355450
B27: Títulos del Tesoro | C27: 14081049 | D27: 5.6331524e+08
B28: Pagarés del Tesoro | C28: 1342986.2 | D28: 77300000
B29: Préstamos Organismos Oficiales | C29: 416295.65 | D29: 18890657
B30: Otros | C30: 1647700.4 | D30: 91725246
B32: 2 - Amortizaciones y Cancelaciones | C32: =SUM(C34:C43) -> 93179644 | D32: =SUM(D34:D43) -> 4.0643922e+09
B34: Adelantos Transitorios del BCRA | C34: 10555617 | D34: 502730000
B35: Préstamos Organismos Multilaterales | C35: 1799300.9 | D35: 81347538
B36: Letras del Tesoro - Organismos Públicos | C36: 45373246 | D36: 2.011786e+09
B37: Títulos del Tesoro | C37: 29450764 | D37: 1.2137924e+09
B38: Bonos Internacionales | C38: 2750000 | D38: 1.1922157e+08
B39: Pagarés del Tesoro | C39: 1170622.6 | D39: 44327786
B40: Préstamos Organismos Oficiales | C40: 1909006.6 | D40: 82436343
B41: Bonos de Consolidación | C41: 68455.385 | D41: 3144632.1
B42: Préstamos Garantizados | C42: 14253.971 | D42: 538918.42
B43: Otros | C43: 88377.19 | D43: 5066880.1
B45: a) Financiamiento, neto de amortizaciones ( 1 - 2 ) | C45: =+C20-C32 -> 5442885 | D45: =+D20-D32 -> 3.6019207e+08
B47: b) Emisión Bonos de Consolidación | C47: 44839.791 | D47: 2015756.2
B49: c) Avales netos de cancelaciones | C49: -479083.05 | D49: -26202778
B51: d) Letras en garantía | C51: -48686.05 | D51: -2802286.3
B53: e) Ajustes de valuación - Excluyendo la deuda elegible pendiente de reestructuración | C53: =SUM(C55:C58) -> -13716928 | D53: =SUM(D55:D58) -> 6.4173565e+09
B55: Tipo de Cambio (excluye deudas ajustables por CER) | C55: -20432016 | D55: 5.5711371e+09
B56: Variación de la deuda ajustable por CER (efectos tipo de cambio y CER) | C56: -1060268 | D56: 4.8063782e+08
B57: Capitalización de Bonos del Canje, Préstamos Garantizados, Pagaré Banco Nación, Bonos de consolidación y Otros | C57: 5738018.1 | D57: 2.4869593e+08
B58: Otras Operaciones (Registro CCF, amparos y excepciones y otros ajustes (1)) | C58: 2037337.9 | D58: 1.1688571e+08
B60: f) Ajustes de valuación sobre deuda elegible pendiente de reestructuración | C60: =SUM(C62:C64) -> -370212.2 | D60: =SUM(D62:D64) -> 39788648
B62: Tipo de Cambio (excluye deudas ajustables por CER) | C62: -17221.198 | D62: 51983408
B63: Variación de la deuda ajustable por CER (efectos tipo de cambio y CER) | C63: -2841.4253 | D63: 1278915.6
B64: Otras Operaciones (Bajas Ley n° 27.249, amparos y excepciones y otros ajustes) | C64: -350149.58 | D64: -13473675
B66: IV - TOTAL VARIACIONES (a+b+c+d+e+f) | C66: =+C45+C47+C49+C51+C53+C60 -> -9127184.9 | D66: =+D45+D47+D49+D51+D53+D60 -> 6.790348e+09
B68: V - DEUDA BRUTA, AL 31/12/2019 (III + IV) | C68: =+C16+C66 -> 3.2306462e+08 | D68: =+D16+D66 -> 1.9349955e+10
B70: VI - DEUDA ELEGIBLE PENDIENTE DE REESTRUCTURACIÓN, AL 31/12/2019 | C70: =+C14+C60 -> 2435209.5 | D70: =+D14+D60 -> 1.4585687e+08
B72: VII - DEUDA BRUTA (EXCLUIDA LA ELEGIBLE PENDIENTE DE REESTRUCTURACIÓN), AL 31/12/2019 (V - VI) | C72: =+C68-C70 -> 3.2062941e+08 | D72: =+D68-D70 -> 1.9204098e+10
B75: (1) EX-2019-102447651- -APN-DGD#MHA / u$s 2.016.035.590,86 corresponden a la actualización del registro de instrumentos de la deuda pública indirecta - Avales otorgados y/o endosados a favor de distintas entidades.

Sheet A.2.4
A1: Indice
B2: =+INDICE!B2 -> MINISTERIO DE ECONOMÍA
B3: SECRETARÍA DE FINANZAS
B6: Serie de Tipos de Cambio y Coeficiente de Estabilización de Referencia (CER)
B9: Fecha | C9: CER | D9: Coeficiente de pesificación (1) | E9: U$S / Peso | F9: Euro (Ref) / Peso
B10: 37290 | C10: 1 | D10: 1.399959 | E10: 1.4 | F10: 1.2064
B11: 37346 | C11: 1.0481 | D11: 1.4673678 | E11: 2.9 | F11: 2.5363
B12: 37437 | C12: 1.2495 | D12: 1.7492374 | E12: 3.8 | F12: 3.7549
B13: 37529 | C13: 1.3716 | D13: 1.9202837 | E13: 3.75 | F13: 3.6942
B14: 37621 | C14: 1.4053 | D14: 1.967407 | E14: 3.4 | F14: 3.5409
B15: 37711 | C15: 1.4341 | D15: 2.00774 | E15: 2.88 | F15: 3.1359
B16: 37802 | C16: 1.4404 | D16: 2.01656 | E16: 2.8 | F16: 3.2225
B17: 37894 | C17: 1.4448 | D17: 2.02272 | E17: 2.915 | F17: 3.397
B18: 37986 | C18: 1.4568 | D18: 2.03952 | E18: 2.9175 | F18: 3.6721
B19: 38077 | C19: 1.4678 | D19: 2.05492 | E19: 2.86 | F19: 3.5174
B20: 38168 | C20: 1.4983 | D20: 2.09762 | E20: 2.958 | F20: 3.6029
B21: 38260 | C21: 1.52 | D21: 2.128 | E21: 2.981 | F21: 3.7073
... B82: 43830 | C82: 18.7009 | D82: 26.18126 | E82: 59.895 | F82: 67.139334
B84: (1) Factor de conversión de dólares a pesos aplicable cuando a las obligaciones corresponde pesificarlas a un valor de 1,40 más CER (por ejemplo, depósitos bancarios y deudas del sector público, en dólares, con legislación nacional).

Sheet A.2.5
A1: Indice
B2: =+INDICE!B2 -> MINISTERIO DE ECONOMÍA
B3: =+INDICE!B3 -> SECRETARÍA DE FINANZAS
B6: SERIE DE DEUDA DEL SECTOR PÚBLICO NACIONAL
B7: POR AÑO Y POR INSTRUMENTO
B8: AJUSTADO POR OPERACIONES CON FECHA VALOR
B10: En millones de u$s - TC de fin de cada año
B11: INSTRUMENTO | C11: Saldo
C12: 31/12/92 (*) | D12: 34334 | E12: 34699 | F12: 35064 | G12: 35430 | H12: 35795 | I12: 36160 | J12: 36525 | K12: 36891 | L12: 37256 | M12: 37621 | N12: 37986 | O12: 38352 | P12: 38717 | Q12: 39082 | R12: 39447 | S12: 39813 | T12: 40178 | U12: 40543 | V12: 40908 | W12: 41274 | X12: 41639 | Y12: 42004 | Z12: 42369 | AA12: 42735 | AB12: 43100 | AC12: 43465 | AD12: 43830
B14: DEUDA PÚBLICA BRUTA + VALORES NEGOCIABLES VINCULADOS AL PBI (I + V) | C14: =+C17+C50 -> 63250 | D14: =+D17+D50 -> 71112 | E14: =+E17+E50 -> 81820 | F14: =+F17+F50 -> 88711 | G14: =+G17+G50 -> 99046 | H14: =+H17+H50 -> 103718 | I14: =+I17+I50 -> 114134 | J14: =+J17+J50 -> 123366 | ... AD14: =+AD17+AD50 -> 336027.35
B17: I- TOTAL DEUDA PÚBLICA BRUTA ( II+III +IV) | C17: =+C20+C38+C40 -> 63250 | D17: =+D20+D38+D40 -> 71112 | E17: =+E20+E38+E40 -> 81820 | F17: =+F20+F38+F40 -> 88711 | G17: =+G20+G38+G40 -> 99046 | H17: =+H20+H38+H40 -> 103718 | I17: =+I20+I38+I40 -> 114134 | J17: =+J20+J38+J40 -> 123366 | ... AD17: =+AD20+AD38+AD40 -> 323064.62
B20: II- DEUDA A VENCER | C20: =+C22+C24+C36 -> 54018 | D20: =+D22+D24+D36 -> 71112 | E20: =+E22+E24+E36 -> 81820 | F20: =+F22+F24+F36 -> 88711 | G20: =+G22+G24+G36 -> 99046 | H20: =+H22+H24+H36 -> 103718 | I20: =+I22+I24+I36 -> 114134 | J20: =+J22+J24+J36 -> 123366 | ... AD20: =+AD22+AD24+AD36 -> 320525.45
B22: TÍTULOS PUBLICOS Y LETRAS DEL TESORO | C22: 17184 | D22: 48401 | E22: 57109 | F22: 59048 | G22: 69393 | H22: 74801 | I22: 82363 | J22: 91555 | K22: 98895 | L22: 83051 | M22: 91656 | N22: 96885 | O22: 92224 | P22: 75628 | Q22: 92222 | R22: 99208 | S22: 99994 | T22: 100719 | U22: 115672 | V22: 125391 | W22: 133214 | X22: 137809 | Y22: 154775 | Z22: 160150 | AA22: 208400.33 | AB22: 256515.52 | AC22: 253709.2 | AD22: 225444.52
B24: PRÉSTAMOS | C24: =SUM(C26:C34) -> 36834 | D24: =SUM(D26:D34) -> 22711 | E24: =SUM(E26:E34) -> 24711 | F24: =SUM(F26:F34) -> 29663 | G24: =SUM(G26:G34) -> 29653 | H24: =SUM(H26:H34) -> 28917 | I24: =SUM(I26:I34) -> 31771 | J24: =SUM(J26:J34) -> 31811 | ... AD24: =SUM(AD26:AD34) -> 80843.847
B26: PRÉSTAMOS GARANTIZADOS | C26: 0 | D26: 0 | E26: 0 | F26: 0 | G26: 0 | H26: 0 | I26: 0 | J26: 0 | K26: 0 | L26: 21284 | M26: 11636 | N26: 14124 | O26: 14646 | P26: 14269 | Q26: 13981 | R26: 13037 | S26: 11995 | T26: 4541 | U26: 4425 | V26: 4121 | W26: 3753 | X26: 3035 | Y26: 2877 | Z26: 2076 | AA26: 1844.6747 | AB26: 1139.31 | AC26: 683.54 | AD26: 640.32505
B28: ORGANISMOS INTERNACIONALES | C28: 7279 | D28: 10944 | E28: 11627 | F28: 14862 | G28: 16257 | H28: 16795 | I28: 19167 | J28: 20311 | K28: 21757 | L28: 32357 | M28: 31376 | N28: 32115 | O28: 30601 | P28: 25260 | Q28: 15155 | R28: 15050 | S28: 14769 | T28: 16209 | U28: 16958 | V28: 17935 | W28: 18335 | X28: 19394 | Y28: 19857 | Z28: 19768 | AA28: 20230.498 | AB28: 21326.95 | AC28: 51037.44 | AD28: 68000.788
B30: ORGANISMOS OFICIALES | C30: 7380 | D30: 9698 | E30: 10870 | F30: 11904 | G30: 10063 | H30: 8311 | I30: 7634 | J30: 6258 | K30: 5017 | L30: 5876 | M30: 4935 | N30: 4428 | O30: 3389 | P30: 2952 | Q30: 1606 | R30: 1907 | S30: 1275 | T30: 1749 | U30: 1479 | V30: 1410 | W30: 849 | X30: 767 | Y30: 9026 | Z30: 9183 | AA30: 7844.7182 | AB30: 8280.38 | AC30: 6912.17 | AD30: 5398.0723
B32: BANCA COMERCIAL | C32: 21736 | D32: 1564 | E32: 1702 | F32: 1908 | G32: 2280 | H32: 2366 | I32: 3585 | J32: 3655 | K32: 2168 | L32: 715 | M32: 563 | N32: 527 | O32: 396 | P32: 294 | Q32: 859 | R32: 1165 | S32: 1453 | T32: 5102 | U32: 6055 | V32: 6586 | W32: 7273 | X32: 4702 | Y32: 4221 | Z32: 3126 | AA32: 1068.5919 | AB32: 2434.14 | AC32: 1194.16 | AD32: 2784.8972
B34: OTROS ACREEDORES | C34: 439 | D34: 505 | E34: 512 | F34: 989 | G34: 1053 | H34: 1445 | I34: 1385 | J34: 1587 | K34: 1913 | L34: 911 | M34: 264 | N34: 273 | O34: 242 | P34: 1436 | Q34: 1539 | R34: 2098 | S34: 2449 | T34: 2928 | U34: 1797 | V34: 1682 | W34: 1960 | X34: 2986 | Y34: 1541 | Z34: 2839 | AA34: 3431.1811 | AB34: 3101.41 | AC34: 2448.23 | AD34: 4019.7644
B36: ADELANTOS TRANSITORIOS BCRA | C36: 0 | D36: 0 | E36: 0 | F36: 0 | G36: 0 | H36: 0 | I36: 0 | J36: 0 | K36: 0 | L36: 0 | M36: 1079 | N36: 2526 | O36: 4468 | P36: 5263 | Q36: 5986 | R36: 6774 | S36: 7700 | T36: 9626 | U36: 11615 | V36: 15597 | W36: 25972 | X36: 28002 | Y36: 29402 | Z36: 25517 | AA36: 24115.153 | AB36: 25153.14 | AC36: 13296.82 | AD36: 14237.082
B38: III- ATRASOS PENDIENTE DE REESTRUCTURACIÓN | C38: 9232 | D38: 0 | E38: 0 | F38: 0 | G38: 0 | H38: 0 | I38: 0 | J38: 0 | K38: 0 | L38: 28 | M38: 11704.252 | N38: 28434.741 | O38: 46195.829 | P38: 5157.8648 | Q38: 6750.8946 | R38: 7271.2359 | S38: 8461.1905 | T38: 8678.4855 | U38: 9062.1741 | V38: 9265.5751 | W38: 9376.5018 | X38: 9440.1029 | Y38: 49 | Z38: 44 | AA38: 42.906828 | AB38: 107.43 | AC38: 104.84 | AD38: 103.95523
B40: IV- TOTAL DEUDA ELEGIBLE PENDIENTE DE REESTRUCTURACIÓN | C40: 0 | D40: 0 | E40: 0 | F40: 0 | G40: 0 | H40: 0 | I40: 0 | J40: 0 | K40: 0 | L40: 0 | M40: =+M42+M44+M46 -> 5 | N40: =+N42+N44+N46 -> 41 | O40: =+O42+O44+O46 -> 132 | P40: =+P42+P44+P46 -> 24011 | Q40: =+Q42+Q44+Q46 -> 27012 | R40: =+R42+R44+R46 -> 30360 | S40: =+S42+S44+S46 -> 31036 | T40: =+T42+T44+T46 -> 32531 | ... AD40: =+AD42+AD44+AD46 -> 2435.2095
B42: CAPITAL | M42: 0 | N42: 0 | O42: 0 | P42: 17966 | Q42: 19119 | R42: 20459 | S42: 19956 | T42: 20108 | U42: 6809 | V42: 6579 | W42: 6608 | X42: 6670 | Y42: 6352 | Z42: 6101 | AA42: 3613.9822 | AB42: 1258.4 | AC42: 1218.78 | AD42: 1058.0797
B44: MORA DE INTERÉS | M44: 0 | N44: 0 | O44: 0 | P44: 5591 | Q44: 6958 | R44: 8398 | S44: 9028 | T44: 9700 | U44: 4409 | V44: 4599 | W44: 4874 | X44: 5168 | Y44: 5280 | Z44: 5420 | AA44: 2510.2886 | AB44: 1022.69 | AC44: 1012.57 | AD44: 863.85757
B46: INTERESES COMPENSATORIOS (**) | M46: 5 | N46: 41 | O46: 132 | P46: 454 | Q46: 935 | R46: 1503 | S46: 2052 | T46: 2723 | U46: 3340 | V46: 3990 | W46: 4707 | X46: 5467 | Y46: 5945 | Z46: 6441 | AA46: 2343.8065 | AB46: 595.42 | AC46: 574.07 | AD46: 513.27222
B50: V- VALORES NEGOCIABLES VINCULADOS AL PBI (***) | C50: 0 | D50: 0 | E50: 0 | F50: 0 | G50: 0 | H50: 0 | I50: 0 | J50: 0 | K50: 0 | L50: 0 | M50: 0 | N50: 0 | O50: 0 | P50: 28784.426 | Q50: 29052.852 | R50: 28175.633 | S50: 19871.956 | T50: 18112.885 | U50: 22730.046 | V50: 19725.328 | W50: 15942.385 | X50: 15761.738 | Y50: 14430.352 | Z50: 13324.151 | AA50: 13001.694 | AB50: 13772.18 | AC50: 13192.94 | AD50: 12962.732
B52: (*) Los saldos de deuda al 31/12/92 se estimaron sobre la base de ajustar los registros obrante, retrotrayendo el efecto que sobre los saldos y la composición, produjera el Plan Brady.
B53: (**) Intereses compensatorios estimados, devengados e impagos con posterioridad a la fecha de vencimiento de cada título.
B54: (***) Valor remanente total. Es la diferencia entre el máximo a pagar de 48 unidades por cada 100 de valor nocional y la suma de los montos pagados hasta la actualidad, de acuerdo con las condiciones establecidas en las respectivas normas de emisión.

Sheet A.3.1
A1: Indice
B2: =+INDICE!B2 -> MINISTERIO DE ECONOMÍA
B3: =+A.2.4!B3 -> SECRETARÍA DE FINANZAS
B6: PERFIL DE VENCIMIENTOS DE CAPITAL E INTERÉS DE LA DEUDA BRUTA DE LA ADMINISTRACIÓN CENTRAL
B7: PERIODO PROYECTADO ENERO 2020 A DICIEMBRE 2020
B8: DEUDA EN SITUACIÓN DE PAGO NORMAL (1)
B10: (En miles de U$S - Tipo de cambio 31/12/2019)
C11: 2020 | O11: Total
C12: Enero | D12: Febrero | E12: Marzo | F12: Abril | G12: Mayo | H12: Junio | I12: Julio | J12: Agosto | K12: Septiembre | L12: Octubre | M12: Noviembre | N12: Diciembre | O12: 2020
B14: TÍTULOS PÚBLICOS | C14: =+SUM(C15:C16) -> 1167749.8 | D14: =+SUM(D15:D16) -> 1947290.6 | E14: =+SUM(E15:E16) -> 2258001.7 | F14: =+SUM(F15:F16) -> 6637122.6 | G14: =+SUM(G15:G16) -> 4278635.7 | H14: =+SUM(H15:H16) -> 4635967.9 | I14: =+SUM(I15:I16) -> 927689.7 | J14: =+SUM(J15:J16) -> 192356.84 | ... N14: =+SUM(N15:N16) -> 2428678.6 | O14: =+O15+O16 -> 32445397
B15: CAPITAL | C15: 87064.485 | D15: 1699554 | E15: 1437546.2 | F15: 5311737.3 | G15: 3508223.2 | H15: 2438891.9 | I15: 72848.292 | J15: 61815.034 | K15: 62001.047 | L15: 3433959.1 | M15: 2145848.1 | N15: 653532.63 | O15: =SUM(C15:N15) -> 20913021
B16: INTERÉS | C16: 1080685.3 | D16: 247736.58 | E16: 820455.48 | F16: 1325385.2 | G16: 770412.51 | H16: 2197076 | I16: 854841.41 | J16: 130541.8 | K16: 369295.62 | L16: 1278915.4 | M16: 681884.65 | N16: 1775146 | O16: =SUM(C16:N16) -> 11532376
B19: LETRAS DEL TESORO | C19: =+SUM(C20:C21) -> 749066.67 | D19: =+SUM(D20:D21) -> 1196033 | E19: =+SUM(E20:E21) -> 3686995.5 | F19: =+SUM(F20:F21) -> 2519760.6 | G19: =+SUM(G20:G21) -> 1984442.7 | H19: =+SUM(H20:H21) -> 2385898 | I19: =+SUM(I20:I21) -> 789910.07 | J19: =+SUM(J20:J21) -> 9350934.5 | ... N19: =+SUM(N20:N21) -> 243892.62 | O19: =+O20+O21 -> 24015479
B20: CAPITAL | C20: 692456.01 | D20: 1138990.2 | E20: 3594818.3 | F20: 2430121.1 | G20: 1940589.6 | H20: 1939561 | I20: 789910.07 | J20: 9350742.4 | K20: 185335.3 | L20: 923210.27 | M20: 0 | N20: 243892.62 | O20: =SUM(C20:N20) -> 23229627
B21: INTERÉS | C21: 56610.66 | D21: 57042.787 | E21: 92177.191 | F21: 89639.468 | G21: 43853.113 | H21: 446336.99 | I21: 0 | J21: 192.17708 | K21: 0 | L21: 0 | M21: 0 | N21: 0 | O21: =SUM(C21:N21) -> 785852.39
B24: ORGANISMOS INTERNACIONALES | C24: =+SUM(C25:C26) -> 150366.36 | D24: =+SUM(D25:D26) -> 559541.1 | E24: =+SUM(E25:E26) -> 382375.57 | F24: =+SUM(F25:F26) -> 164138.24 | G24: =+SUM(G25:G26) -> 627987.9 | H24: =+SUM(H25:H26) -> 222718.35 | I24: =+SUM(I25:I26) -> 146707.22 | J24: =+SUM(J25:J26) -> 575745.89 | ... N24: =+SUM(N25:N26) -> 216318.81 | O24: =+O25+O26 -> 4192467
B25: CAPITAL | C25: 106512.55 | D25: 139604.16 | E25: 266660.62 | F25: 114675.49 | G25: 146276 | H25: 169310.24 | I25: 106511.45 | J25: 140395.48 | K25: 239587.92 | L25: 111952.95 | M25: 146378.44 | N25: 165684.95 | O25: =SUM(C25:N25) -> 1853550.2
B26: INTERÉS | C26: 43853.816 | D26: 419936.95 | E26: 115714.96 | F26: 49462.749 | G26: 481711.9 | H26: 53408.108 | I26: 40195.775 | J26: 435350.41 | K26: 112378.74 | L26: 47607.117 | M26: 488662.35 | N26: 50633.859 | O26: =SUM(C26:N26) -> 2338916.7
B29: ORGANISMOS OFICIALES | C29: =+SUM(C30:C31) -> 158087.07 | D29: =+SUM(D30:D31) -> 112.29725 | E29: =+SUM(E30:E31) -> 2925.7068 | F29: =+SUM(F30:F31) -> 20533.422 | G29: =+SUM(G30:G31) -> 2125043 | H29: =+SUM(H30:H31) -> 38547.867 | I29: =+SUM(I30:I31) -> 196349.03 | J29: =+SUM(J30:J31) -> 111.11836 | ... N29: =+SUM(N30:N31) -> 36781.923 | O29: =+O30+O31 -> 2608600.9
B30: CAPITAL | C30: 111186.07 | D30: 0 | E30: 1274.6468 | F30: 19976.345 | G30: 1948875.9 | H30: 420.75657 | I30: 149979.9 | J30: 0 | K30: 121.29997 | L30: 19976.345 | M30: 7595.7079 | N30: 420.75657 | O30: =SUM(C30:N30) -> 2259827.7
B31: INTERÉS | C31: 46900.998 | D31: 112.29725 | E31: 1651.06 | F31: 557.07725 | G31: 176167.06 | H31: 38127.11 | I31: 46369.129 | J31: 111.11836 | K31: 1154.9305 | L31: 556.55566 | M31: 704.61712 | N31: 36361.166 | O31: =SUM(C31:N31) -> 348773.12
B34: PRESTAMOS GARANTIZADOS | C34: =+SUM(C35:C36) -> 2732.1887 | D34: =+SUM(D35:D36) -> 19544.525 | E34: =+SUM(E35:E36) -> 2533.7875 | F34: =+SUM(F35:F36) -> 2662.1373 | G34: =+SUM(G35:G36) -> 2597.9624 | H34: =+SUM(H35:H36) -> 2662.1373 | I34: =+SUM(I35:I36) -> 2597.9624 | J34: =+SUM(J35:J36) -> 2662.1373 | ... N34: =+SUM(N35:N36) -> 2597.9624 | O34: =+O35+O36 -> 48513.037
B35: CAPITAL | C35: 0 | D35: 16812.336 | E35: 0 | F35: 0 | G35: 0 | H35: 0 | I35: 0 | J35: 0 | K35: 0 | L35: 0 | M35: 0 | N35: 0 | O35: =SUM(C35:N35) -> 16812.336
B36: INTERÉS | C36: 2732.1887 | D36: 2732.1887 | E36: 2533.7875 | F36: 2662.1373 | G36: 2597.9624 | H36: 2662.1373 | I36: 2597.9624 | J36: 2662.1373 | K36: 2662.1373 | L36: 2597.9624 | M36: 2662.1373 | N36: 2597.9624 | O36: =SUM(C36:N36) -> 31700.701
B39: BANCA COMERCIAL | C39: =+SUM(C40:C41) -> 68658.928 | D39: =+SUM(D40:D41) -> 944.87011 | E39: =+SUM(E40:E41) -> 177.86755 | F39: =+SUM(F40:F41) -> 569535.46 | G39: =+SUM(G40:G41) -> 17964.083 | H39: =+SUM(H40:H41) -> 15.14431 | I39: =+SUM(I40:I41) -> 15.14431 | J39: =+SUM(J40:J41) -> 894.97829 | ... N39: =+SUM(N40:N41) -> 2003521.3 | O39: =+O40+O41 -> 2680721.3
B40: CAPITAL | C40: 11.55135 | D40: 763.63058 | E40: 11.84339 | F40: 500888.29 | G40: 16383.312 | H40: 11.89378 | I40: 12.03425 | J40: 781.03441 | K40: 12.10367 | L40: 12.23977 | M40: 17378.145 | N40: 2003518.5 | O40: =SUM(C40:N40) -> 2539784.6
B41: INTERÉS | C41: 68647.377 | D41: 181.23953 | E41: 166.02416 | F41: 68647.173 | G41: 1580.7713 | H41: 3.25053 | I41: 3.11006 | J41: 113.94388 | K41: 3.04065 | L41: 2.90454 | M41: 1585.0846 | N41: 2.76542 | O41: =SUM(C41:N41) -> 140936.68
B44: AVALES | C44: =+SUM(C45:C46) -> 60686.534 | D44: =+SUM(D45:D46) -> 9954.1335 | E44: =+SUM(E45:E46) -> 15945.38 | F44: =+SUM(F45:F46) -> 6025.7709 | G44: =+SUM(G45:G46) -> 5976.0385 | H44: =+SUM(H45:H46) -> 11912.093 | I44: =+SUM(I45:I46) -> 2061.3747 | J44: =+SUM(J45:J46) -> 11821.381 | ... N44: =+SUM(N45:N46) -> 2002929 | O44: =+O45+O46 -> 2163086.1
B45: CAPITAL | C45: 24551.77 | D45: 6994.4573 | E45: 11668.664 | F45: 4057.0071 | G45: 4122.2045 | H45: 8859.2128 | I45: 1021.2574 | J45: 9105.3435 | K45: 14306.446 | L45: 7044.8463 | M45: 7285.4778 | N45: 2000272.6 | O45: =SUM(C45:N45) -> 2099289.3
B46: INTERÉS | C46: 36134.765 | D46: 2959.6762 | E46: 4276.716 | F46: 1968.7637 | G46: 1853.8339 | H46: 3052.88 | I46: 1040.1173 | J46: 2716.0375 | K46: 3753.0661 | L46: 1775.3902 | M46: 1609.2205 | N46: 2656.4235 | O46: =SUM(C46:N46) -> 63796.889
B49: PAGARÈS | C49: =+SUM(C50:C51) -> 1311.4102 | D49: =+SUM(D50:D51) -> 12885.992 | E49: =+SUM(E50:E51) -> 1293373.6 | F49: =+SUM(F50:F51) -> 0 | G49: =+SUM(G50:G51) -> 0 | H49: =+SUM(H50:H51) -> 0 | I49: =+SUM(I50:I51) -> 1267.7281 | J49: =+SUM(J50:J51) -> 0 | ... N49: =+SUM(N50:N51) -> 1224.3235 | O49: =+O50+O51 -> 1312844.8
B50: CAPITAL | C50: 1311.4102 | D50: 12885.992 | E50: 1290591.9 | F50: 0 | G50: 0 | H50: 0 | I50: 1267.7281 | J50: 0 | K50: 0 | L50: 0 | M50: 0 | N50: 1224.3235 | O50: =SUM(C50:N50) -> 1307281.3
B51: INTERÉS | C51: 0 | D51: 0 | E51: 2781.7613 | F51: 0 | G51: 0 | H51: 0 | I51: 0 | J51: 0 | K51: 2781.7613 | L51: 0 | M51: 0 | N51: 0 | O51: =SUM(C51:N51) -> 5563.5226
B54: ADELANTOS TRANSITORIOS BCRA | C54: =+SUM(C55:C56) -> 422405.88 | D54: =+SUM(D55:D56) -> 325569.75 | E54: =+SUM(E55:E56) -> 1010101 | F54: =+SUM(F55:F56) -> 511728.86 | G54: =+SUM(G55:G56) -> 887386.26 | H54: =+SUM(H55:H56) -> 679522.5 | I54: =+SUM(I55:I56) -> 233742.38 | J54: =+SUM(J55:J56) -> 0 | ... N54: =+SUM(N55:N56) -> 867351.2 | O54: =+O55+O56 -> 9395275.1
B55: CAPITAL | C55: 422405.88 | D55: 325569.75 | E55: 1010101 | F55: 511728.86 | G55: 887386.26 | H55: 679522.5 | I55: 233742.38 | J55: 0 | K55: 189999.17 | L55: 413724.02 | M55: 3853744.1 | N55: 867351.2 | O55: =SUM(C55:N55) -> 9395275.1
B56: INTERÉS | C56: 0 | D56: 0 | E56: 0 | F56: 0 | G56: 0 | H56: 0 | I56: 0 | J56: 0 | K56: 0 | L56: 0 | M56: 0 | N56: 0 | O56: =SUM(C56:N56) -> 0
B59: TOTAL | C59: =+C60+C61 -> 2781064.9 | D59: =+D60+D61 -> 4071876.2 | E59: =+E60+E61 -> 8652430.1 | F59: =+F60+F61 -> 10431507 | G59: =+G60+G61 -> 9930033.6 | H59: =+H60+H61 -> 7977243.9 | I59: =+I60+I61 -> 2300340.6 | J59: =+J60+J61 -> 10134527 | ... O59: =+O60+O61 -> 78862385
B60: CAPITAL | C60: =+C15+C20+C25+C30+C35+C40+C45+C50+C55 -> 1445499.7 | D60: =+D15+D20+D25+D30+D35+D40+D45+D50+D55 -> 3341174.5 | E60: =+E15+E20+E25+E30+E35+E40+E45+E50+E55 -> 7612673.2 | F60: =+F15+F20+F25+F30+F35+F40+F45+F50+F55 -> 8893184.5 | G60: =+G15+G20+G25+G30+G35+G40+G45+G50+G55 -> 8451856.4 | H60: =+H15+H20+H25+H30+H35+H40+H45+H50+H55 -> 5236577.4 | I60: =+I15+I20+I25+I30+I35+I40+I45+I50+I55 -> 1355293.1 | J60: =+J15+J20+J25+J30+J35+J40+J45+J50+J55 -> 9562839.3 | ... N60: =+N15+N20+N25+N30+N35+N40+N45+N50+N55 -> 5935897.6 | O60: =SUM(C60:N60) -> 63614469
B61: INTERÉS | C61: =+C16+C21+C26+C31+C36+C41+C46+C51+C56 -> 1335565.1 | D61: =+D16+D21+D26+D31+D36+D41+D46+D51+D56 -> 730701.72 | E61: =+E16+E21+E26+E31+E36+E41+E46+E51+E56 -> 1039757 | F61: =+F16+F21+F26+F31+F36+F41+F46+F51+F56 -> 1538322.6 | G61: =+G16+G21+G26+G31+G36+G41+G46+G51+G56 -> 1478177.2 | H61: =+H16+H21+H26+H31+H36+H41+H46+H51+H56 -> 2740666.5 | I61: =+I16+I21+I26+I31+I36+I41+I46+I51+I56 -> 945047.5 | J61: =+J16+J21+J26+J31+J36+J41+J46+J51+J56 -> 571687.62 | ... N61: =+N16+N21+N26+N31+N36+N41+N46+N51+N56 -> 1867398.2 | O61: =SUM(C61:N61) -> 15247916
B64: (1) No incluye estimación del pago eventual por los Valores Negociables Vinculadas al PBI.

Sheet A.3.2
A1: Indice
B2: =+INDICE!B2 -> MINISTERIO DE ECONOMÍA
B3: SECRETARÍA DE FINANZAS
B6: PERFIL MENSUAL DE VENCIMIENTOS DE CAPITAL DE LA DEUDA BRUTA DE LA ADMINISTRACIÓN CENTRAL
B8: (En millones de U$S - Stock de deuda y tipo de cambio 31/12/19)
C9: 43831 | D9: 43862 | E9: 43891 | F9: 43922 | G9: 43952 | H9: 43983 | I9: 44013 | J9: 44044 | K9: 44075 | L9: 44105 | M9: 44136 | N9: 44166 | O9: 2020
B11: PERFIL DE VENCIMIENTOS DE LA DEUDA EN SITUACIÓN DE PAGO NORMAL
B13: TOTAL | C13: =+C14+C15 -> 1445.4997 | D13: =+D14+D15 -> 3341.1745 | E13: =+E14+E15 -> 7612.6732 | F13: =+F14+F15 -> 8893.1845 | G13: =+G14+G15 -> 8451.8564 | H13: =+H14+H15 -> 5236.5774 | I13: =+I14+I15 -> 1355.2931 | J13: =+J14+J15 -> 9562.8393 | ... O13: =+O14+O15 -> 63614.469
B14: CORTO PLAZO | C14: 785.5083 | D14: 1326.0559 | E14: 4429.2675 | F14: 2672.905 | G14: 2226.3677 | H14: 2364.6743 | I14: 233.74238 | J14: 1.3889645 | K14: 189.99917 | L14: 413.72402 | M14: 3853.7441 | N14: 867.3512 | O14: =+SUM(C14:N14) -> 19364.729
B15: MEDIANO Y LARGO PLAZO | C15: 659.99142 | D15: 2015.1185 | E15: 3183.4057 | F15: 6220.2794 | G15: 6225.4887 | H15: 2871.9031 | I15: 1121.5507 | J15: 9561.4503 | K15: 501.36412 | L15: 4496.1557 | M15: 2324.4859 | N15: 5068.5464 | O15: =+SUM(C15:N15) -> 44249.74
B17: PRÉSTAMOS | C17: =+C18+C24+C30+C36+C31+C22 -> 243.57335 | D17: =+D18+D24+D30+D36+D31+D22 -> 177.06057 | E17: =+E18+E24+E30+E36+E31+E22 -> 1570.2076 | F17: =+F18+F24+F30+F36+F31+F22 -> 639.59713 | G17: =+G18+G24+G30+G36+G31+G22 -> 2115.6574 | H17: =+H18+H24+H30+H36+H31+H22 -> 178.6021 | I17: =+I18+I24+I30+I36+I31+I22 -> 258.79237 | J17: =+J18+J24+J30+J36+J31+J22 -> 150.28186 | ... N17: =+N18+N24+N30+N36+N31+N22 -> 4171.1211 | O17: =+SUM(C17:N17) -> 10076.545
B18: Organismos Internacionales | C18: =SUM(C19:C21) -> 106.51255 | D18: =SUM(D19:D21) -> 139.60416 | E18: =SUM(E19:E21) -> 266.66062 | F18: =SUM(F19:F21) -> 114.67549 | G18: =SUM(G19:G21) -> 146.276 | H18: =SUM(H19:H21) -> 169.31024 | I18: =SUM(I19:I21) -> 106.51145 | J18: =SUM(J19:J21) -> 140.39548 | ... N18: =SUM(N19:N21) -> 165.68495 | O18: =+SUM(C18:N18) -> 1853.5502
B19: . BIRF | C19: 30.576801 | D19: 2.8298787 | E19: 99.807269 | F19: 55.653629 | G19: 17.595638 | H19: 33.618539 | I19: 30.576801 | J19: 2.8298787 | K19: 74.074817 | L19: 52.56496 | M19: 17.608888 | N19: 33.618539 | O19: =+SUM(C19:N19) -> 451.35564
B20: . BID | C20: 53.888565 | D20: 46.075835 | E20: 140.0008 | F20: 44.525991 | G20: 96.43696 | H20: 51.294935 | I20: 53.888565 | J20: 46.867163 | K20: 136.69913 | L20: 44.525991 | M20: 96.43696 | N20: 43.456021 | O20: =+SUM(C20:N20) -> 854.09692
B21: . Otros | C21: 22.047183 | D21: 90.698441 | E21: 26.852542 | F21: 14.495873 | G21: 32.243403 | H21: 84.396763 | I21: 22.046081 | J21: 90.698441 | K21: 28.813979 | L21: 14.861995 | M21: 32.332588 | N21: 88.610387 | O21: =+SUM(C21:N21) -> 548.09768
B22: Préstamos Garantizados | C22: =+C23 -> 0 | D22: =+D23 -> 16.812336 | E22: =+E23 -> 0 | F22: =+F23 -> 0 | G22: =+G23 -> 0 | H22: =+H23 -> 0 | I22: =+I23 -> 0 | J22: =+J23 -> 0 | ... N22: =+N23 -> 0 | O22: =+SUM(C22:N22) -> 16.812336
B23: . En moneda nacional ajustable por CER | C23: 0 | D23: 16.812336 | E23: 0 | F23: 0 | G23: 0 | H23: 0 | I23: 0 | J23: 0 | K23: 0 | L23: 0 | M23: 0 | N23: 0 | O23: =+SUM(C23:N23) -> 16.812336
B24: Banca Comercial | C24: =+C25+C28 -> 0.011551355 | D24: =+D25+D28 -> 0.76363058 | E24: =+E25+E28 -> 0.011843393 | F24: =+F25+F28 -> 500.88829 | G24: =+G25+G28 -> 16.383312 | H24: =+H25+H28 -> 0.01189378 | I24: =+I25+I28 -> 0.012034255 | J24: =+J25+J28 -> 0.78103441 | ... N24: =+N25+N28 -> 2003.5185 | O24: =+SUM(C24:N24) -> 2539.7846
B25: . En moneda nacional | C25: =+C26+C27 -> 0 | D25: =+D26+D27 -> 0.25377673 | E25: =+E26+E27 -> 0 | F25: =+F26+F27 -> 500.87653 | G25: =+G26+G27 -> 0.25377673 | H25: =+H26+H27 -> 0 | I25: =+I26+I27 -> 0 | J25: =+J26+J27 -> 0.25377673 | ... N25: =+N26+N27 -> 2003.5061 | O25: =+SUM(C25:N25) -> 2505.3978
B26: FUCO | C26: 0 | D26: 0 | E26: 0 | F26: 0 | G26: 0 | H26: 0 | I26: 0 | J26: 0 | K26: 0 | L26: 0 | M26: 0 | N26: 2003.5061 | O26: =+SUM(C26:N26) -> 2003.5061
B27: Otros | C27: 0 | D27: 0.25377673 | E27: 0 | F27: 500.87653 | G27: 0.25377673 | H27: 0 | I27: 0 | J27: 0.25377673 | K27: 0 | L27: 0 | M27: 0.25377673 | N27: 0 | O27: =+SUM(C27:N27) -> 501.89164
B28: . En moneda extranjera | C28: =+C29 -> 0.011551355 | D28: =+D29 -> 0.50985385 | E28: =+E29 -> 0.011843393 | F28: =+F29 -> 0.01175571 | G28: =+G29 -> 16.129535 | H28: =+H29 -> 0.01189378 | I28: =+I29 -> 0.012034255 | J28: =+J29 -> 0.52725769 | ... N28: =+N29 -> 0.012378887 | O28: =+SUM(C28:N28) -> 34.386816
B29: Otros | C29: 0.011551355 | D29: 0.50985385 | E29: 0.011843393 | F29: 0.01175571 | G29: 16.129535 | H29: 0.01189378 | I29: 0.012034255 | J29: 0.52725769 | K29: 0.012103665 | L29: 0.012239771 | M29: 17.124368 | N29: 0.012378887 | O29: =+SUM(C29:N29) -> 34.386816
B30: Organismos Oficiales | C30: 111.18607 | D30: 0 | E30: 1.2746468 | F30: 19.976345 | G30: 1948.8759 | H30: 0.42075657 | I30: 149.9799 | J30: 0 | K30: 0.12129997 | L30: 19.976345 | M30: 7.5957079 | N30: 0.42075657 | O30: =+SUM(C30:N30) -> 2259.8277
B31: Pagarés | C31: =+C32+C34 -> 1.3114102 | D31: =+D32+D34 -> 12.885992 | E31: =+E32+E34 -> 1290.5919 | F31: =+F32+F34 -> 0 | G31: =+G32+G34 -> 0 | H31: =+H32+H34 -> 0 | I31: =+I32+I34 -> 1.2677281 | J31: =+J32+J34 -> 0 | ... N31: =+N32+N34 -> 1.2243235 | O31: =+SUM(C31:N31) -> 1307.2813
B32: . En moneda nacional no ajustable por CER | C32: =+C33 -> 0 | D32: =+D33 -> 0 | E32: =+E33 -> 1290.5919 | F32: =+F33 -> 0 | G32: =+G33 -> 0 | H32: =+H33 -> 0 | I32: =+I33 -> 0 | J32: =+J33 -> 0 | ... N32: =+N33 -> 0 | O32: =+SUM(C32:N32) -> 1290.5919
B33: Pagaré CUT | C33: 0 | D33: 0 | E33: 1290.5919 | F33: 0 | G33: 0 | H33: 0 | I33: 0 | J33: 0 | K33: 0 | L33: 0 | M33: 0 | N33: 0 | O33: =+SUM(C33:N33) -> 1290.5919
B34: . En moneda extranjera | C34: =+C35 -> 1.3114102 | D34: =+D35 -> 12.885992 | E34: =+E35 -> 0 | F34: =+F35 -> 0 | G34: =+G35 -> 0 | H34: =+H35 -> 0 | I34: =+I35 -> 1.2677281 | J34: =+J35 -> 0 | ... N34: =+N35 -> 1.2243235 | O34: =+SUM(C34:N34) -> 16.689454
B35: Pagarés CAMMESA | C35: 1.3114102 | D35: 12.885992 | E35: 0 | F35: 0 | G35: 0 | H35: 0 | I35: 1.2677281 | J35: 0 | K35: 0 | L35: 0 | M35: 0 | N35: 1.2243235 | O35: =+SUM(C35:N35) -> 16.689454
B36: Avales | C36: =+C37+C38 -> 24.55177 | D36: =+D37+D38 -> 6.9944573 | E36: =+E37+E38 -> 11.668664 | F36: =+F37+F38 -> 4.0570071 | G36: =+G37+G38 -> 4.1222046 | H36: =+H37+H38 -> 8.8592128 | I36: =+I37+I38 -> 1.0212574 | J36: =+J37+J38 -> 9.1053434 | ... N36: =+N37+N38 -> 2000.2726 | O36: =+SUM(C36:N36) -> 2099.2893
B37: . En moneda nacional | C37: 24.419044 | D37: 0.80582735 | E37: 0.82864623 | F37: 0.83652706 | G37: 0.85608665 | H37: 0.86849447 | I37: 0.88853145 | J37: 0.90167269 | K37: 0.9187899 | L37: 0.93963909 | M37: 0.95393272 | N37: 699.94698 | O37: =+SUM(C37:N37) -> 733.16417
B38: . En moneda extranjera | C38: 0.13272592 | D38: 6.18863 | E38: 10.840018 | F38: 3.2204801 | G38: 3.2661179 | H38: 7.9907183 | I38: 0.13272592 | J38: 8.2036708 | K38: 13.387656 | L38: 6.1052072 | M38: 6.3315451 | N38: 1300.3256 | O38: =+SUM(C38:N38) -> 1366.1251
B40: ADELANTOS TRANSITORIOS BCRA | C40: 422.40588 | D40: 325.56975 | E40: 1010.101 | F40: 511.72886 | G40: 887.38626 | H40: 679.5225 | I40: 233.74238 | J40: 0 | K40: 189.99917 | L40: 413.72402 | M40: 3853.7441 | N40: 867.3512 | O40: =+SUM(C40:N40) -> 9395.2751
B42: TÍTULOS PÚBLICOS Y LETRAS DEL TESORO | C42: =SUM(C43:C57)+C60 -> 779.52049 | D42: =SUM(D43:D57)+D60 -> 2838.5441 | E42: =SUM(E43:E57)+E60 -> 5032.3645 | F42: =SUM(F43:F57)+F60 -> 7741.8585 | G42: =SUM(G43:G57)+G60 -> 5448.8128 | H42: =SUM(H43:H57)+H60 -> 4378.4528 | I42: =SUM(I43:I57)+I60 -> 862.75836 | J42: =SUM(J43:J57)+J60 -> 9412.5574 | ... N42: =SUM(N43:N57)+N60 -> 897.42526 | O42: =+SUM(C42:N42) -> 44142.648
B43: BIRAF/CHF/3,375%/12-10-2020 | C43: 0 | D43: 0 | E43: 0 | F43: 0 | G43: 0 | H43: 0 | I43: 0 | J43: 0 | K43: 0 | L43: 413.30853 | M43: 0 | N43: 0 | O43: =+SUM(C43:N43) -> 413.30853
B44: BONAR/$/BADLAR+325/01-03-2020 | C44: 0 | D44: 0 | E44: 279.28188 | F44: 0 | G44: 0 | H44: 0 | I44: 0 | J44: 0 | K44: 0 | L44: 0 | M44: 0 | N44: 0 | O44: =+SUM(C44:N44) -> 279.28188
B45: BONAR/$/BADLAR+300pb/23-12-2020 | C45: 0 | D45: 0 | E45: 0 | F45: 0 | G45: 0 | H45: 0 | I45: 0 | J45: 0 | K45: 0 | L45: 0 | M45: 0 | N45: 591.44728 | O45: =+SUM(C45:N45) -> 591.44728
B46: BONAR/U$S/8%/08-10-2020 | C46: 0 | D46: 0 | E46: 0 | F46: 0 | G46: 0 | H46: 0 | I46: 0 | J46: 0 | K46: 0 | L46: 2947.5607 | M46: 0 | N46: 0 | O46: =+SUM(C46:N46) -> 2947.5607
B47: BONAR/U$S/8,75%/07-05-2024 | C47: 0 | D47: 0 | E47: 0 | F47: 0 | G47: 1326.2057 | H47: 0 | I47: 0 | J47: 0 | K47: 0 | L47: 0 | M47: 0 | N47: 0 | O47: =+SUM(C47:N47) -> 1326.2057
B48: BONCER/$/2,25%+CER/28-04-2020 | C48: 0 | D48: 0 | E48: 0 | F48: 5238.971 | G48: 0 | H48: 0 | I48: 0 | J48: 0 | K48: 0 | L48: 0 | M48: 0 | N48: 0 | O48: =+SUM(C48:N48) -> 5238.971
B49: BONAR/$/6,72763943%/31-12-2028 | C49: 4.7663671 | D49: 4.9240523 | E49: 4.6906522 | F49: 4.8469927 | G49: 4.8741667 | H49: 4.9014931 | I49: 4.9289726 | J49: 4.9566063 | K49: 4.9843948 | L49: 5.0123392 | M49: 5.0404402 | N49: 5.0686987 | O49: =+SUM(C49:N49) -> 58.995176
B50: BONOS PGN 2021/DLK/28-06-2021 | C50: 52.688846 | D50: 52.688846 | E50: 52.688846 | F50: 52.688846 | G50: 52.688846 | H50: 52.688846 | I50: 52.688846 | J50: 52.688846 | K50: 52.84707 | L50: 52.84707 | M50: 52.84707 | N50: 52.84707 | O50: =+SUM(C50:N50) -> 632.89905
B51: BONTE/$/26%/21-11-2020 | C51: 0 | D51: 0 | E51: 0 | F51: 0 | G51: 0 | H51: 0 | I51: 0 | J51: 0 | K51: 0 | L51: 0 | M51: 2083.791 | N51: 0 | O51: =+SUM(C51:N51) -> 2083.791
B52: BOTAPO/$/TPM/21-06-2020 | C52: 0 | D52: 0 | E52: 0 | F52: 0 | G52: 0 | H52: 2377.1319 | I52: 0 | J52: 0 | K52: 0 | L52: 0 | M52: 0 | N52: 0 | O52: =+SUM(C52:N52) -> 2377.1319
B53: BONAR DUAL/DLK/4,5%/13-02-2020 | C53: 0 | D53: 1637.7715 | E53: 0 | F53: 0 | G53: 0 | H53: 0 | I53: 0 | J53: 0 | K53: 0 | L53: 0 | M53: 0 | N53: 0 | O53: =+SUM(C53:N53) -> 1637.7715
B54: BOGATO/$/1,6012%/CER+4%/6-3-20 | C54: 0 | D54: 0 | E54: 1096.7153 | F54: 0 | G54: 0 | H54: 0 | I54: 0 | J54: 0 | K54: 0 | L54: 0 | M54: 0 | N54: 0 | O54: =+SUM(C54:N54) -> 1096.7153
... B56: Letras en Garantía | C56: 0 | D56: 0 | E56: 0 | F56: 0 | G56: 0 | H56: 0 | I56: 0 | J56: 0 | K56: 0 | L56: 0 | M56: 0 | N56: 243.89263 | O56: =+SUM(C56:N56) -> 243.89263
B57: LETRAS DEL TESORO | C57: =+C58+C59 -> 692.45601 | D57: =+D58+D59 -> 1138.9902 | E57: =+E58+E59 -> 3594.8183 | F57: =+F58+F59 -> 2430.1211 | G57: =+G58+G59 -> 1940.5896 | H57: =+H58+H59 -> 1939.561 | I57: =+I58+I59 -> 789.91007 | J57: =+J58+J59 -> 9350.7424 | ... N57: =+N58+N59 -> 0 | O57: =+SUM(C57:N57) -> 22985.734
B58: . En moneda nacional | C58: 638.18144 | D58: 1085.9198 | E58: 3319.8183 | F58: 1967.2235 | G58: 1556.0914 | H58: 1939.561 | I58: 771.33033 | J58: 740.35057 | K58: 185.3353 | L58: 893.21947 | M58: 0 | N58: 0 | O58: =+SUM(C58:N58) -> 13097.031
B59: . En moneda extranjera | C59: 54.27457 | D59: 53.070325 | E59: 275 | F59: 462.89767 | G59: 384.49822 | H59: 0 | I59: 18.579735 | J59: 8610.3918 | K59: 0 | L59: 29.990796 | M59: 0 | N59: 0 | O59: =+SUM(C59:N59) -> 9888.7031
B60: OTROS (1) | C60: =+C61+C68 -> 29.609272 | D60: =+D61+D68 -> 4.1695819 | E60: =+E61+E68 -> 4.1695819 | F60: =+F61+F68 -> 15.230474 | G60: =+G61+G68 -> 4.1695819 | H60: =+H61+H68 -> 4.1695819 | I60: =+I61+I68 -> 15.230474 | J60: =+J61+J68 -> 4.1695819 | ... N60: =+N61+N68 -> 4.1695819 | O60: =+SUM(C60:N60) -> 108.65735
B61: En moneda nacional | C61: =+C62+C65 -> 16.364531 | D61: =+D62+D65 -> 4.1695819 | E61: =+E62+E65 -> 4.1695819 | F61: =+F62+F65 -> 15.230474 | G61: =+G62+G65 -> 4.1695819 | H61: =+H62+H65 -> 4.1695819 | I61: =+I62+I65 -> 15.230474 | J61: =+J62+J65 -> 4.1695819 | ... N61: =+N62+N65 -> 4.1695819 | O61: =+SUM(C61:N61) -> 95.412607
B62: · Ajustable por CER | C62: =+C63+C64 -> 5.1539556 | D62: =+D63+D64 -> 4.1695819 | E62: =+E63+E64 -> 4.1695819 | F62: =+F63+F64 -> 4.1695819 | G62: =+G63+G64 -> 4.1695819 | H62: =+H63+H64 -> 4.1695819 | I62: =+I63+I64 -> 4.1695819 | J62: =+J63+J64 -> 4.1695819 | ... N62: =+N63+N64 -> 4.1695819 | O62: =+SUM(C62:N62) -> 51.019356
B63: · Bonos de consolidación | C63: 5.0244582 | D63: 4.1695819 | E63: 4.1695819 | F63: 4.1695819 | G63: 4.1695819 | H63: 4.1695819 | I63: 4.1695819 | J63: 4.1695819 | K63: 4.1695819 | L63: 4.1695819 | M63: 4.1695819 | N63: 4.1695819 | O63: =+SUM(C63:N63) -> 50.889859
B64: · Otros | C64: 0.12949744 | D64: 0 | E64: 0 | F64: 0 | G64: 0 | H64: 0 | I64: 0 | J64: 0 | K64: 0 | L64: 0 | M64: 0 | N64: 0 | O64: =+SUM(C64:N64) -> 0.12949744
B65: · No ajustable por CER | C65: =+C66+C67 -> 11.210576 | D65: =+D66+D67 -> 0 | E65: =+E66+E67 -> 0 | F65: =+F66+F67 -> 11.060892 | G65: =+G66+G67 -> 0 | H65: =+H66+H67 -> 0 | I65: =+I66+I67 -> 11.060892 | J65: =+J66+J67 -> 0 | ... N65: =+N66+N67 -> 0 | O65: =+SUM(C65:N65) -> 44.393251
B66: · Bonos de consolidación | C66: 11.063407 | D66: 0 | E66: 0 | F66: 11.060892 | G66: 0 | H66: 0 | I66: 11.060892 | J66: 0 | K66: 0 | L66: 11.060892 | M66: 0 | N66: 0 | O66: =+SUM(C66:N66) -> 44.246083
B67: · Otros | C67: 0.14716816 | D67: 0 | E67: 0 | F67: 0 | G67: 0 | H67: 0 | I67: 0 | J67: 0 | K67: 0 | L67: 0 | M67: 0 | N67: 0 | O67: =+SUM(C67:N67) -> 0.14716816
B68: En moneda extranjera | C68: =+C69+C70 -> 13.244741 | D68: =+D69+D70 -> 0 | E68: =+E69+E70 -> 0 | F68: =+F69+F70 -> 0 | G68: =+G69+G70 -> 0 | H68: =+H69+H70 -> 0 | I68: =+I69+I70 -> 0 | J68: =+J69+J70 -> 0 | ... N68: =+N69+N70 -> 0 | O68: =+SUM(C68:N68) -> 13.244741
B69: · Bonos de consolidación | C69: 3.068763 | D69: 0 | E69: 0 | F69: 0 | G69: 0 | H69: 0 | I69: 0 | J69: 0 | K69: 0 | L69: 0 | M69: 0 | N69: 0 | O69: =+SUM(C69:N69) -> 3.068763
B70: · Otros | C70: 10.175978 | D70: 0 | E70: 0 | F70: 0 | G70: 0 | H70: 0 | I70: 0 | J70: 0 | K70: 0 | L70: 0 | M70: 0 | N70: 0 | O70: =+SUM(C70:N70) -> 10.175978
B72: TOTAL DEUDA DENOMINADA EN PESOS | C72: =+C73+C74 -> 1158.8261 | D72: =+D73+D74 -> 3128.9155 | E72: =+E73+E74 -> 7058.886 | F72: =+F73+F74 -> 8292.4027 | G72: =+G73+G74 -> 2506.3201 | H72: =+H73+H74 -> 5058.8438 | I72: =+I73+I74 -> 1078.8095 | J72: =+J73+J74 -> 803.32105 | ... N72: =+N73+N74 -> 4224.3369 | O72: =+SUM(C72:N72) -> 41130.689
B73: · Deuda ajustable por CER | C73: 5.1539556 | D73: 133.09249 | E73: 625.2009 | F73: 5243.1406 | G73: 4.1695819 | H73: 4.1695819 | I73: 4.1695819 | J73: 4.1695819 | K73: 4.1695819 | L73: 4.1695819 | M73: 4.1695819 | N73: 4.1695819 | O73: =+SUM(C73:N73) -> 6039.9446
B74: · Deuda no ajustable por CER | C74: 1153.6721 | D74: 2995.823 | E74: 6433.6851 | F74: 3049.2621 | G74: 2502.1505 | H74: 5054.6743 | I74: 1074.64 | J74: 799.15147 | K74: 434.08472 | L74: 1376.8034 | M74: 5996.6303 | N74: 4220.1674 | O74: =+SUM(C74:N74) -> 35090.744
B75: TOTAL DEUDA EN MONEDA EXTRANJERA | C75: 286.67362 | D75: 212.25896 | E75: 553.78712 | F75: 600.78174 | G75: 5945.5363 | H75: 177.73361 | I75: 276.48357 | J75: 8759.5182 | K75: 253.10898 | L75: 3528.9067 | M75: 177.43006 | N75: 1711.5606 | O75: =+SUM(C75:N75) -> 22483.78
B77: (1) Incluye bonos de consolidación, amparos y excepciones.

Sheet A.3.3
A1: Indice
B2: =+INDICE!B2 -> MINISTERIO DE ECONOMÍA
B3: SECRETARÍA DE FINANZAS
B6: PERFIL MENSUAL DE VENCIMIENTOS DE INTERÉS DE LA DEUDA BRUTA DE LA ADMINISTRACIÓN CENTRAL
B8: (En millones de U$S - Stock de deuda y tipo de cambio 31/12/19)
C9: 43831 | D9: 43862 | E9: 43891 | F9: 43922 | G9: 43952 | H9: 43983 | I9: 44013 | J9: 44044 | K9: 44075 | L9: 44105 | M9: 44136 | N9: 44166 | O9: 2020
B11: PERFIL DE VENCIMIENTOS DE LA DEUDA EN SITUACIÓN DE PAGO NORMAL
B13: TOTAL | C13: =+C14+C15 -> 1335.5651 | D13: =+D14+D15 -> 730.70172 | E13: =+E14+E15 -> 1039.757 | F13: =+F14+F15 -> 1538.3226 | G13: =+G14+G15 -> 1478.1772 | H13: =+H14+H15 -> 2740.6665 | I13: =+I14+I15 -> 945.0475 | J13: =+J14+J15 -> 571.68762 | ... O13: =+O14+O15 -> 15247.916
B14: CORTO PLAZO | C14: 125.25444 | D14: 57.042787 | E14: 92.177191 | F14: 158.28325 | G14: 43.853113 | H14: 446.33699 | I14: 0 | J14: 0.19217708 | K14: 0 | L14: 0 | M14: 0 | N14: 0 | O14: =SUM(C14:N14) -> 923.13996
B15: MEDIANO Y LARGO PLAZO | C15: 1210.3107 | D15: 673.65893 | E15: 947.57979 | F15: 1380.0394 | G15: 1434.324 | H15: 2294.3295 | I15: 945.0475 | J15: 571.49545 | K15: 492.02929 | L15: 1331.4553 | M15: 1177.1081 | N15: 1867.3982 | O15: =SUM(C15:N15) -> 14324.776
B17: PRÉSTAMOS | C17: =+C18+C23+C25+C30+C34+C31 -> 198.26914 | D17: =+D18+D23+D25+D30+D34+D31 -> 425.92235 | E17: =+E18+E23+E25+E30+E34+E31 -> 127.12431 | F17: =+F18+F23+F25+F30+F34+F31 -> 123.2979 | G17: =+G18+G23+G25+G30+G34+G31 -> 663.91154 | H17: =+H18+H23+H25+H30+H34+H31 -> 97.253486 | I17: =+I18+I23+I25+I30+I34+I31 -> 90.206093 | J17: =+J18+J23+J25+J30+J34+J31 -> 440.95364 | ... N17: =+N18+N23+N25+N30+N34+N31 -> 92.252177 | O17: =+SUM(C17:N17) -> 2929.6876
B18: Organismos Internacionales | C18: =SUM(C19:C22) -> 43.853816 | D18: =SUM(D19:D22) -> 419.93695 | E18: =SUM(E19:E22) -> 115.71496 | F18: =SUM(F19:F22) -> 49.462749 | G18: =SUM(G19:G22) -> 481.7119 | H18: =SUM(H19:H22) -> 53.408108 | I18: =SUM(I19:I22) -> 40.195775 | J18: =SUM(J19:J22) -> 435.35041 | ... N18: =SUM(N19:N22) -> 50.633859 | O18: =+SUM(C18:N18) -> 2338.9167
B19: . BIRF | C19: 2.4618101 | D19: 2.0203597 | E19: 38.053317 | F19: 19.54913 | G19: 16.828541 | H19: 27.714015 | I19: 2.0619247 | J19: 2.1966699 | K19: 36.978587 | L19: 18.673809 | M19: 16.792701 | N19: 27.286922 | O19: =+SUM(C19:N19) -> 210.61778
B20: . BID | C20: 25.717135 | D20: 18.670478 | E20: 63.492124 | F20: 25.295689 | G20: 69.102068 | H20: 8.4828444 | I20: 24.3425 | J20: 17.453539 | K20: 61.847814 | L20: 24.563163 | M20: 68.073877 | N20: 7.5181074 | O20: =+SUM(C20:N20) -> 414.55934
B21: . FMI | C21: 0 | D21: 378.87168 | E21: 0 | F21: 0 | G21: 388.74091 | H21: 0 | I21: 0 | J21: 397.37959 | K21: 0 | L21: 0 | M21: 397.37959 | N21: 0 | O21: =+SUM(C21:N21) -> 1562.3718
B22: . Otros | C22: 15.674871 | D22: 20.374428 | E22: 14.169517 | F22: 4.6179306 | G22: 7.0403883 | H22: 17.211248 | I22: 13.79135 | J22: 18.320606 | K22: 13.552334 | L22: 4.3701451 | M22: 6.4161813 | N22: 15.82883 | O22: =+SUM(C22:N22) -> 151.36783
B23: Préstamos Garantizados | C23: =+C24 -> 2.7321887 | D23: =+D24 -> 2.7321887 | E23: =+E24 -> 2.5337874 | F23: =+F24 -> 2.6621373 | G23: =+G24 -> 2.5979624 | H23: =+H24 -> 2.6621373 | I23: =+I24 -> 2.5979624 | J23: =+J24 -> 2.6621373 | ... N23: =+N24 -> 2.5979624 | O23: =+SUM(C23:N23) -> 31.700701
B24: . En moneda nacional ajustable por CER | C24: 2.7321887 | D24: 2.7321887 | E24: 2.5337874 | F24: 2.6621373 | G24: 2.5979624 | H24: 2.6621373 | I24: 2.5979624 | J24: 2.6621373 | K24: 2.6621373 | L24: 2.5979624 | M24: 2.6621373 | N24: 2.5979624 | O24: =+SUM(C24:N24) -> 31.700701
B25: Banca Comercial | C25: =+C26+C28 -> 68.647377 | D25: =+D26+D28 -> 0.18123953 | E25: =+E26+E28 -> 0.16602416 | F25: =+F26+F28 -> 68.647173 | G25: =+G26+G28 -> 1.5807713 | H25: =+H26+H28 -> 0.00325053 | I25: =+I26+I28 -> 0.0031100619 | J25: =+J26+J28 -> 0.11394388 | ... N25: =+N26+N28 -> 0.0027654226 | O25: =+SUM(C25:N25) -> 140.93668
B26: . En moneda nacional | C26: =+C27 -> 68.643784 | D26: =+D27 -> 0.13128948 | E26: =+E27 -> 0 | F26: =+F27 -> 68.643784 | G26: =+G27 -> 0.096326518 | H26: =+H27 -> 0 | I26: =+I27 -> 0 | J26: =+J27 -> 0.065644738 | ... N26: =+N27 -> 0 | O26: =+SUM(C26:N26) -> 137.61365
B27: Otros | C27: 68.643784 | D27: 0.13128948 | E27: 0 | F27: 68.643784 | G27: 0.096326518 | H27: 0 | I27: 0 | J27: 0.065644738 | K27: 0 | L27: 0 | M27: 0.032822369 | N27: 0 | O27: =+SUM(C27:N27) -> 137.61365
B28: . En moneda extranjera | C28: =+C29 -> 0.0035929549 | D28: =+D29 -> 0.049950057 | E28: =+E29 -> 0.16602416 | F28: =+F29 -> 0.0033885994 | G28: =+G29 -> 1.4844448 | H28: =+H29 -> 0.00325053 | I28: =+I29 -> 0.0031100619 | J28: =+J29 -> 0.04829914 | ... N28: =+N29 -> 0.0027654226 | O28: =+SUM(C28:N28) -> 3.3230331
B29: Otros | C29: 0.0035929549 | D29: 0.049950057 | E29: 0.16602416 | F29: 0.0033885994 | G29: 1.4844448 | H29: 0.00325053 | I29: 0.0031100619 | J29: 0.04829914 | K29: 0.0030406513 | L29: 0.0029045386 | M29: 1.5522622 | N29: 0.0027654226 | O29: =+SUM(C29:N29) -> 3.3230331
B30: Organismos Oficiales | C30: 46.900998 | D30: 0.11229725 | E30: 1.65106 | F30: 0.55707725 | G30: 176.16706 | H30: 38.12711 | I30: 46.369129 | J30: 0.11111836 | K30: 1.1549305 | L30: 0.55655566 | M30: 0.70461711 | N30: 36.361166 | O30: =+SUM(C30:N30) -> 348.77312
B31: Pagarés | C31: =+C32 -> 0 | D31: =+D32 -> 0 | E31: =+E32 -> 2.7817613 | F31: =+F32 -> 0 | G31: =+G32 -> 0 | H31: =+H32 -> 0 | I31: =+I32 -> 0 | J31: =+J32 -> 0 | ... N31: =+N32 -> 0 | O31: =+SUM(C31:N31) -> 5.5635226
B32: . En moneda nacional ajustable por CER | C32: =+C33 -> 0 | D32: =+D33 -> 0 | E32: =+E33 -> 2.7817613 | F32: =+F33 -> 0 | G32: =+G33 -> 0 | H32: =+H33 -> 0 | I32: =+I33 -> 0 | J32: =+J33 -> 0 | ... N32: =+N33 -> 0 | O32: =+SUM(C32:N32) -> 5.5635226
B33: Pagaré 2038 - B.N.A. | C33: 0 | D33: 0 | E33: 2.7817613 | F33: 0 | G33: 0 | H33: 0 | I33: 0 | J33: 0 | K33: 2.7817613 | L33: 0 | M33: 0 | N33: 0 | O33: =+SUM(C33:N33) -> 5.5635226
B34: Avales | C34: =+C35+C36 -> 36.134765 | D34: =+D35+D36 -> 2.9596762 | E34: =+E35+E36 -> 4.276716 | F34: =+F35+F36 -> 1.9687637 | G34: =+G35+G36 -> 1.8538339 | H34: =+H35+H36 -> 3.05288 | I34: =+I35+I36 -> 1.0401173 | J34: =+J35+J36 -> 2.7160375 | ... N34: =+N35+N36 -> 2.6564235 | O34: =+SUM(C34:N34) -> 63.796889
B35: . En moneda nacional | C35: 35.654012 | D35: 0.61536445 | E35: 0.60529161 | F35: 0.59493353 | G35: 0.58447694 | H35: 0.57377586 | I35: 0.56291968 | J35: 0.55181304 | K35: 0.54054213 | L35: 0.52905725 | M35: 0.51731177 | N35: 0.50538761 | O35: =+SUM(C35:N35) -> 41.834886
B36: . En moneda extranjera | C36: 0.48075238 | D36: 2.3443117 | E36: 3.6714244 | F36: 1.3738302 | G36: 1.269357 | H36: 2.4791041 | I36: 0.47719764 | J36: 2.1642244 | K36: 3.2125239 | L36: 1.2463329 | M36: 1.0919088 | N36: 2.1510359 | O36: =+SUM(C36:N36) -> 21.962003
B38: TÍTULOS PÚBLICOS Y LETRAS DEL TESORO | C38: =+C56+SUM(C73:C118)+C121+C39 -> 1137.296 | D38: =+D56+SUM(D73:D118)+D121+D39 -> 304.77937 | E38: =+E56+SUM(E73:E118)+E121+E39 -> 912.63267 | F38: =+F56+SUM(F73:F118)+F121+F39 -> 1415.0247 | G38: =+G56+SUM(G73:G118)+G121+G39 -> 814.26562 | H38: =+H56+SUM(H73:H118)+H121+H39 -> 2643.413 | I38: =+I56+SUM(I73:I118)+I121+I39 -> 854.84141 | J38: =+J56+SUM(J73:J118)+J121+J39 -> 130.73398 | ... O38: =+O56+SUM(O73:O118)+O121+O39 -> 12318.228
B39: PAR | C39: =+C40+C43+C50+C53 -> 0 | D39: =+D40+D43+D50+D53 -> 0 | E39: =+E40+E43+E50+E53 -> 254.09705 | F39: =+F40+F43+F50+F53 -> 0 | G39: =+G40+G43+G50+G53 -> 0 | H39: =+H40+H43+H50+H53 -> 0 | I39: =+I40+I43+I50+I53 -> 0 | J39: =+J40+J43+J50+J53 -> 0 | ... N39: =+N40+N43+N50+N53 -> 0 | O39: =+SUM(C39:N39) -> 508.19411
B40: Par/$+CER/T.Fija/2038 | C40: =+C41+C42 -> 0 | D40: =+D41+D42 -> 0 | E40: =+E41+E42 -> 5.3847145 | F40: =+F41+F42 -> 0 | G40: =+G41+G42 -> 0 | H40: =+H41+H42 -> 0 | I40: =+I41+I42 -> 0 | J40: =+J41+J42 -> 0 | ... N40: =+N41+N42 -> 0 | O40: =+SUM(C40:N40) -> 10.769429
B41: Emisión Canje 2005 | C41: 0 | D41: 0 | E41: 5.3633843 | F41: 0 | G41: 0 | H41: 0 | I41: 0 | J41: 0 | K41: 5.3633843 | L41: 0 | M41: 0 | N41: 0 | O41: =+SUM(C41:N41) -> 10.726769
B42: Emisión Canje 2010 | C42: 0 | D42: 0 | E42: 0.021330191 | F42: 0 | G42: 0 | H42: 0 | I42: 0 | J42: 0 | K42: 0.021330191 | L42: 0 | M42: 0 | N42: 0 | O42: =+SUM(C42:N42) -> 0.042660383
B43: Par/U$S/T.Fija/2038 | C43: =+C44+C47 -> 0 | D43: =+D44+D47 -> 0 | E43: =+E44+E47 -> 125.52433 | F43: =+F44+F47 -> 0 | G43: =+G44+G47 -> 0 | H43: =+H44+H47 -> 0 | I43: =+I44+I47 -> 0 | J43: =+J44+J47 -> 0 | ... N43: =+N44+N47 -> 0 | O43: =+SUM(C43:N43) -> 251.04866
B44: Emisión Canje 2005 | C44: =+C45+C46 -> 0 | D44: =+D45+D46 -> 0 | E44: =+E45+E46 -> 122.36723 | F44: =+F45+F46 -> 0 | G44: =+G45+G46 -> 0 | H44: =+H45+H46 -> 0 | I44: =+I45+I46 -> 0 | J44: =+J45+J46 -> 0 | ... N44: =+N45+N46 -> 0 | O44: =+SUM(C44:N44) -> 244.73445
B45: Leg. Nueva York | C45: 0 | D45: 0 | E45: 99.312922 | F45: 0 | G45: 0 | H45: 0 | I45: 0 | J45: 0 | K45: 99.312922 | L45: 0 | M45: 0 | N45: 0 | O45: =+SUM(C45:N45) -> 198.62584
B46: Leg. Argentina | C46: 0 | D46: 0 | E46: 23.054303 | F46: 0 | G46: 0 | H46: 0 | I46: 0 | J46: 0 | K46: 23.054303 | L46: 0 | M46: 0 | N46: 0 | O46: =+SUM(C46:N46) -> 46.108607
B47: Emisión Canje 2010 | C47: =+C48+C49 -> 0 | D47: =+D48+D49 -> 0 | E47: =+E48+E49 -> 3.157104 | F47: =+F48+F49 -> 0 | G47: =+G48+G49 -> 0 | H47: =+H48+H49 -> 0 | I47: =+I48+I49 -> 0 | J47: =+J48+J49 -> 0 | ... N47: =+N48+N49 -> 0 | O47: =+SUM(C47:N47) -> 6.314208
B48: Leg. Nueva York | C48: 0 | D48: 0 | E48: 1.8176096 | F48: 0 | G48: 0 | H48: 0 | I48: 0 | J48: 0 | K48: 1.8176096 | L48: 0 | M48: 0 | N48: 0 | O48: =+SUM(C48:N48) -> 3.6352192
B49: Leg. Argentina | C49: 0 | D49: 0 | E49: 1.3394944 | F49: 0 | G49: 0 | H49: 0 | I49: 0 | J49: 0 | K49: 1.3394944 | L49: 0 | M49: 0 | N49: 0 | O49: =+SUM(C49:N49) -> 2.6789888
B50: Par/EUR/T.Fija/2038 | C50: =+C51+C52 -> 0 | D50: =+D51+D52 -> 0 | E50: =+E51+E52 -> 122.62916 | F50: =+F51+F52 -> 0 | G50: =+G51+G52 -> 0 | H50: =+H51+H52 -> 0 | I50: =+I51+I52 -> 0 | J50: =+J51+J52 -> 0 | ... N50: =+N51+N52 -> 0 | O50: =+SUM(C50:N50) -> 245.25831
B51: Emisión Canje 2005 | C51: 0 | D51: 0 | E51: 95.381701 | F51: 0 | G51: 0 | H51: 0 | I51: 0 | J51: 0 | K51: 95.381701 | L51: 0 | M51: 0 | N51: 0 | O51: =+SUM(C51:N51) -> 190.7634
B52: Emisión Canje 2010 | C52: 0 | D52: 0 | E52: 27.247455 | F52: 0 | G52: 0 | H52: 0 | I52: 0 | J52: 0 | K52: 27.247455 | L52: 0 | M52: 0 | N52: 0 | O52: =+SUM(C52:N52) -> 54.49491
B53: Par/JPY/T.Fija/2038 | C53: =+C54+C55 -> 0 | D53: =+D54+D55 -> 0 | E53: =+E54+E55 -> 0.55885335 | F53: =+F54+F55 -> 0 | G53: =+G54+G55 -> 0 | H53: =+H54+H55 -> 0 | I53: =+I54+I55 -> 0 | J53: =+J54+J55 -> 0 | ... N53: =+N54+N55 -> 0 | O53: =+SUM(C53:N53) -> 1.1177067
B54: Emisión Canje 2005 | C54: 0 | D54: 0 | E54: 0.53251592 | F54: 0 | G54: 0 | H54: 0 | I54: 0 | J54: 0 | K54: 0.53251592 | L54: 0 | M54: 0 | N54: 0 | O54: =+SUM(C54:N54) -> 1.0650318
B55: Emisión Canje 2010 | C55: 0 | D55: 0 | E55: 0.026337428 | F55: 0 | G55: 0 | H55: 0 | I55: 0 | J55: 0 | K55: 0.026337428 | L55: 0 | M55: 0 | N55: 0 | O55: =+SUM(C55:N55) -> 0.052674856
B56: DESCUENTO | C56: =+C57+C60+C67+C70 -> 0 | D56: =+D57+D60+D67+D70 -> 0 | E56: =+E57+E60+E67+E70 -> 0 | F56: =+F57+F60+F67+F70 -> 0 | G56: =+G57+G60+G67+G70 -> 0 | H56: =+H57+H60+H67+H70 -> 869.67227 | I56: =+I57+I60+I67+I70 -> 0 | J56: =+J57+J60+J67+J70 -> 0 | ... N56: =+N57+N60+N67+N70 -> 869.67227 | O56: =+SUM(C56:N56) -> 1739.3445
B57: Discount/$+CER/5,83%/2033 | C57: =+C58+C59 -> 0 | D57: =+D58+D59 -> 0 | E57: =+E58+E59 -> 0 | F57: =+F58+F59 -> 0 | G57: =+G58+G59 -> 0 | H57: =+H58+H59 -> 83.836007 | I57: =+I58+I59 -> 0 | J57: =+J58+J59 -> 0 | ... N57: =+N58+N59 -> 83.836007 | O57: =+SUM(C57:N57) -> 167.67201
B58: Emisión Canje 2005 | C58: 0 | D58: 0 | E58: 0 | F58: 0 | G58: 0 | H58: 82.840207 | I58: 0 | J58: 0 | K58: 0 | L58: 0 | M58: 0 | N58: 82.840207 | O58: =+SUM(C58:N58) -> 165.68041
B59: Emisión Canje 2010 | C59: 0 | D59: 0 | E59: 0 | F59: 0 | G59: 0 | H59: 0.99580065 | I59: 0 | J59: 0 | K59: 0 | L59: 0 | M59: 0 | N59: 0.99580065 | O59: =+SUM(C59:N59) -> 1.9916013
B60: Discount/U$S/8,28%/2033 | C60: =+C61+C64 -> 0 | D60: =+D61+D64 -> 0 | E60: =+E61+E64 -> 0 | F60: =+F61+F64 -> 0 | G60: =+G61+G64 -> 0 | H60: =+H61+H64 -> 530.70813 | I60: =+I61+I64 -> 0 | J60: =+J61+J64 -> 0 | ... N60: =+N61+N64 -> 530.70813 | O60: =+SUM(C60:N60) -> 1061.4163
B61: Emisión Canje 2005 | C61: =+C62+C63 -> 0 | D61: =+D62+D63 -> 0 | E61: =+E62+E63 -> 0 | F61: =+F62+F63 -> 0 | G61: =+G62+G63 -> 0 | H61: =+H62+H63 -> 469.10147 | I61: =+I62+I63 -> 0 | J61: =+J62+J63 -> 0 | ... N61: =+N62+N63 -> 469.10147 | O61: =+SUM(C61:N61) -> 938.20294
B62: Leg. Nueva York | C62: 0 | D62: 0 | E62: 0 | F62: 0 | G62: 0 | H62: 176.42785 | I62: 0 | J62: 0 | K62: 0 | L62: 0 | M62: 0 | N62: 176.42785 | O62: =+SUM(C62:N62) -> 352.85571
B63: Leg. Argentina | C63: 0 | D63: 0 | E63: 0 | F63: 0 | G63: 0 | H63: 292.67362 | I63: 0 | J63: 0 | K63: 0 | L63: 0 | M63: 0 | N63: 292.67362 | O63: =+SUM(C63:N63) -> 585.34723
B64: Emisión Canje 2010 | C64: =+C65+C66 -> 0 | D64: =+D65+D66 -> 0 | E64: =+E65+E66 -> 0 | F64: =+F65+F66 -> 0 | G64: =+G65+G66 -> 0 | H64: =+H65+H66 -> 61.606658 | I64: =+I65+I66 -> 0 | J64: =+J65+J66 -> 0 | ... N64: =+N65+N66 -> 61.606658 | O64: =+SUM(C64:N64) -> 123.21332
B65: Leg. Nueva York | C65: 0 | D65: 0 | E65: 0 | F65: 0 | G65: 0 | H65: 53.975224 | I65: 0 | J65: 0 | K65: 0 | L65: 0 | M65: 0 | N65: 53.975224 | O65: =+SUM(C65:N65) -> 107.95045
B66: Leg. Argentina | C66: 0 | D66: 0 | E66: 0 | F66: 0 | G66: 0 | H66: 7.6314345 | I66: 0 | J66: 0 | K66: 0 | L66: 0 | M66: 0 | N66: 7.6314345 | O66: =+SUM(C66:N66) -> 15.262869
B67: Discount/EUR/7,82%/2033 | C67: =+C68+C69 -> 0 | D67: =+D68+D69 -> 0 | E67: =+E68+E69 -> 0 | F67: =+F68+F69 -> 0 | G67: =+G68+G69 -> 0 | H67: =+H68+H69 -> 253.16972 | I67: =+I68+I69 -> 0 | J67: =+J68+J69 -> 0 | ... N67: =+N68+N69 -> 253.16972 | O67: =+SUM(C67:N67) -> 506.33944
B68: Emisión Canje 2005 | C68: 0 | D68: 0 | E68: 0 | F68: 0 | G68: 0 | H68: 136.5196 | I68: 0 | J68: 0 | K68: 0 | L68: 0 | M68: 0 | N68: 136.5196 | O68: =+SUM(C68:N68) -> 273.03919
B69: Emisión Canje 2010 | C69: 0 | D69: 0 | E69: 0 | F69: 0 | G69: 0 | H69: 116.65012 | I69: 0 | J69: 0 | K69: 0 | L69: 0 | M69: 0 | N69: 116.65012 | O69: =+SUM(C69:N69) -> 233.30024
B70: Discount/JPY/4,33%/2033 | C70: =+C71+C72 -> 0 | D70: =+D71+D72 -> 0 | E70: =+E71+E72 -> 0 | F70: =+F71+F72 -> 0 | G70: =+G71+G72 -> 0 | H70: =+H71+H72 -> 1.9584134 | I70: =+I71+I72 -> 0 | J70: =+J71+J72 -> 0 | ... N70: =+N71+N72 -> 1.9584134 | O70: =+SUM(C70:N70) -> 3.9168268
B71: Emisión Canje 2005 | C71: 0 | D71: 0 | E71: 0 | F71: 0 | G71: 0 | H71: 1.3512386 | I71: 0 | J71: 0 | K71: 0 | L71: 0 | M71: 0 | N71: 1.3512386 | O71: =+SUM(C71:N71) -> 2.7024772
B72: Emisión Canje 2010 | C72: 0 | D72: 0 | E72: 0 | F72: 0 | G72: 0 | H72: 0.60717481 | I72: 0 | J72: 0 | K72: 0 | L72: 0 | M72: 0 | N72: 0.60717481 | O72: =+SUM(C72:N72) -> 1.2143496
B73: CUASIPAR/$+CER/3,31%/2045 | C73: 0 | D73: 0 | E73: 0 | F73: 0 | G73: 0 | H73: 115.42288 | I73: 0 | J73: 0 | K73: 0 | L73: 0 | M73: 0 | N73: 115.42288 | O73: =+SUM(C73:N73) -> 230.84576
B74: BONAR/$/BADLAR+300pb/23-12-2020 | C74: 0 | D74: 0 | E74: 74.993613 | F74: 0 | G74: 0 | H74: 75.817719 | I74: 0 | J74: 0 | K74: 75.817719 | L74: 0 | M74: 0 | N74: 74.993613 | O74: =+SUM(C74:N74) -> 301.62266
B75: BONAR/$/BADLAR+325/01-03-2020 | C75: 0 | D75: 0 | E75: 35.586117 | F75: 0 | G75: 0 | H75: 0 | I75: 0 | J75: 0 | K75: 0 | L75: 0 | M75: 0 | N75: 0 | O75: =+SUM(C75:N75) -> 35.586117
B76: BONAR/$/BADLAR+200/03-04-2022 | C76: 112.51441 | D76: 0 | E76: 0 | F76: 111.29143 | G76: 0 | H76: 0 | I76: 111.29143 | J76: 0 | K76: 0 | L76: 112.51441 | M76: 0 | N76: 0 | O76: =+SUM(C76:N76) -> 447.61168
B77: BONAR/$/6,72763943%/31-12-2028 | C77: 3.9556172 | D77: 3.797932 | E77: 3.9012891 | F77: 3.8749916 | G77: 3.8478176 | H77: 3.8204912 | I77: 3.7930117 | J77: 3.765378 | K77: 3.7375895 | L77: 3.7096452 | M77: 3.6815441 | N77: 3.6532856 | O77: =+SUM(C77:N77) -> 45.538593
B78: BONTE/$/15,50%/17-10-2026 | C78: 0 | D78: 0 | E78: 0 | F78: 124.95455 | G78: 0 | H78: 0 | I78: 0 | J78: 0 | K78: 0 | L78: 124.95455 | M78: 0 | N78: 0 | O78: =+SUM(C78:N78) -> 249.9091
B79: BONTE/$/16,00%/17-10-2023 | C79: 0 | D79: 0 | E79: 0 | F79: 85.683751 | G79: 0 | H79: 0 | I79: 0 | J79: 0 | K79: 0 | L79: 85.683751 | M79: 0 | N79: 0 | O79: =+SUM(C79:N79) -> 171.3675
B80: BONTE/$/18,20%/03-10-2021 | C80: 0 | D80: 0 | E80: 0 | F80: 94.957843 | G80: 0 | H80: 0 | I80: 0 | J80: 0 | K80: 0 | L80: 94.957843 | M80: 0 | N80: 0 | O80: =+SUM(C80:N80) -> 189.91569
B81: BONTE/$/26%/21-11-2020 | C81: 0 | D81: 0 | E81: 0 | F81: 0 | G81: 270.89283 | H81: 0 | I81: 0 | J81: 0 | K81: 0 | L81: 0 | M81: 270.89283 | N81: 0 | O81: =+SUM(C81:N81) -> 541.78566
B82: BONAR/U$S/8,75%/07-05-2024 | C82: 0 | D82: 0 | E82: 0 | F82: 0 | G82: 290.24681 | H82: 0 | I82: 0 | J82: 0 | K82: 0 | L82: 0 | M82: 232.22531 | N82: 0 | O82: =+SUM(C82:N82) -> 522.47212
... B117: LETRA INTRANSFERIBLE - BCRA | C117: 105.68887 | D117: 39.496581 | E117: 15.099321 | F117: 40.791735 | G117: 0 | H117: 76.54133 | I117: 105.13566 | J117: 39.067271 | K117: 15.265247 | L117: 40.791735 | M117: 0 | N117: 76.578043 | O117: =+SUM(C117:N117) -> 554.45579
B118: LETRAS DEL TESORO | C118: =+C119+C120 -> 56.61066 | D118: =+D119+D120 -> 57.042787 | E118: =+E119+E120 -> 92.177191 | F118: =+F119+F120 -> 89.639468 | G118: =+G119+G120 -> 43.853113 | H118: =+H119+H120 -> 446.33699 | I118: =+I119+I120 -> 0 | J118: =+J119+J120 -> 0.19217708 | ... N118: =+N119+N120 -> 0 | O118: =+SUM(C118:N118) -> 785.85239
B119: . En moneda nacional | C119: 56.61066 | D119: 57.042787 | E119: 92.177191 | F119: 89.639468 | G119: 43.853113 | H119: 446.33699 | I119: 0 | J119: 0.19217708 | K119: 0 | L119: 0 | M119: 0 | N119: 0 | O119: =+SUM(C119:N119) -> 785.85239
B120: . En moneda extranjera | C120: 0 | D120: 0 | E120: 0 | F120: 0 | G120: 0 | H120: 0 | I120: 0 | J120: 0 | K120: 0 | L120: 0 | M120: 0 | N120: 0 | O120: =+SUM(C120:N120) -> 0
B121: OTROS (1) | C121: =+C122+C127 -> 17.512522 | D121: =+D122+D127 -> 0.35080314 | E121: =+E122+E127 -> 0.36998383 | F121: =+F122+F127 -> 15.985441 | G121: =+G122+G127 -> 0.32995523 | H121: =+H122+H127 -> 0.32300593 | I121: =+I122+I127 -> 14.644837 | J121: =+J122+J127 -> 0.30910732 | ... N121: =+N122+N127 -> 0.28131011 | O121: =+SUM(C121:N121) -> 64.170702
B122: . En moneda nacional | C122: =+C123+C125 -> 17.512522 | D122: =+D123+D125 -> 0.35080314 | E122: =+E123+E125 -> 0.34385383 | F122: =+F123+F125 -> 15.985441 | G122: =+G123+G125 -> 0.32995523 | H122: =+H123+H125 -> 0.32300593 | I122: =+I123+I125 -> 14.644837 | J122: =+J123+J125 -> 0.30910732 | ... N122: =+N123+N125 -> 0.28131011 | O122: =+SUM(C122:N122) -> 64.118442
B123: · Ajustable por CER | C123: =+C124 -> 0.35776423 | D123: =+D124 -> 0.35080314 | E123: =+E124 -> 0.34385383 | F123: =+F124 -> 0.33690453 | G123: =+G124 -> 0.32995523 | H123: =+H124 -> 0.32300593 | I123: =+I124 -> 0.31605662 | J123: =+J124 -> 0.30910732 | ... N123: =+N124 -> 0.28131011 | O123: =+SUM(C123:N123) -> 3.8343871
B124: · Bonos de consolidación | C124: 0.35776423 | D124: 0.35080314 | E124: 0.34385383 | F124: 0.33690453 | G124: 0.32995523 | H124: 0.32300593 | I124: 0.31605662 | J124: 0.30910732 | K124: 0.30215802 | L124: 0.29520871 | M124: 0.28825941 | N124: 0.28131011 | O124: =+SUM(C124:N124) -> 3.8343871
B125: · No ajustable por CER | C125: =+C126 -> 17.154757 | D125: =+D126 -> 0 | E125: =+E126 -> 0 | F125: =+F126 -> 15.648537 | G125: =+G126 -> 0 | H125: =+H126 -> 0 | I125: =+I126 -> 14.32878 | J125: =+J126 -> 0 | ... N125: =+N126 -> 0 | O125: =+SUM(C125:N125) -> 60.284055
B126: · Bonos de consolidación | C126: 17.154757 | D126: 0 | E126: 0 | F126: 15.648537 | G126: 0 | H126: 0 | I126: 14.32878 | J126: 0 | K126: 0 | L126: 13.151981 | M126: 0 | N126: 0 | O126: =+SUM(C126:N126) -> 60.284055
B127: . En moneda extranjera | C127: =+C128 -> 0 | D127: =+D128 -> 0 | E127: =+E128 -> 0.02613 | F127: =+F128 -> 0 | G127: =+G128 -> 0 | H127: =+H128 -> 0 | I127: =+I128 -> 0 | J127: =+J128 -> 0 | ... N127: =+N128 -> 0 | O127: =+SUM(C127:N127) -> 0.05226
B128: · Otros | C128: 0 | D128: 0 | E128: 0.02613 | F128: 0 | G128: 0 | H128: 0 | I128: 0 | J128: 0 | K128: 0.02613 | L128: 0 | M128: 0 | N128: 0 | O128: =+SUM(C128:N128) -> 0.05226
B130: TOTAL DEUDA DENOMINADA EN PESOS | C130: =+C131+C132 -> 333.38091 | D130: =+D131+D132 -> 265.28819 | E130: =+E131+E132 -> 654.71572 | F130: =+F131+F132 -> 677.06571 | G130: =+G131+G132 -> 442.48619 | H130: =+H131+H132 -> 1149.7268 | I130: =+I131+I132 -> 168.64788 | J130: =+J131+J132 -> 91.472867 | ... N130: =+N131+N132 -> 281.29045 | O130: =+SUM(C130:N130) -> 5033.7675
B131: · Deuda ajustable por CER | C131: 38.847673 | D131: 3.0829918 | E131: 31.093843 | F131: 81.776419 | G131: 41.109503 | H131: 202.24403 | I131: 38.671739 | J131: 2.9712446 | K131: 31.180497 | L131: 22.732124 | M131: 41.131982 | N131: 202.13816 | O131: =+SUM(C131:N131) -> 736.98021
B132: · Deuda no ajustable por CER | C132: 294.53324 | D132: 262.2052 | E132: 623.62188 | F132: 595.28929 | G132: 401.37668 | H132: 947.48272 | I132: 129.97614 | J132: 88.501623 | K132: 80.09585 | L132: 435.50124 | M132: 359.05112 | N132: 79.152286 | O132: =+SUM(C132:N132) -> 4296.7873
B133: TOTAL DEUDA EN MONEDA EXTRANJERA | C133: 1002.1842 | D133: 465.41352 | E133: 385.04126 | F133: 861.2569 | G133: 1035.691 | H133: 1590.9397 | I133: 776.39962 | J133: 480.21476 | K133: 380.75295 | L133: 873.22193 | M133: 776.92496 | N133: 1586.1077 | O133: =+SUM(C133:N133) -> 10214.149
B135: (1) Incluye bonos de consolidación, amparos y excepciones.

Sheet A.3.4
A1: Indice
B2: MINISTERIO DE ECONOMÍA
B3: SECRETARÍA DE FINANZAS
B6: PERFIL MENSUAL DE VENCIMIENTOS DE CAPITAL DE LA DEUDA BRUTA DE LA ADMINISTRACIÓN CENTRAL
B8: (En millones de U$S - Stock de deuda y tipo de cambio 31/12/19)
C9: 44197 | D9: 44228 | E9: 44256 | F9: 44287 | G9: 44317 | H9: 44348 | I9: 44378 | J9: 44409 | K9: 44440 | L9: 44470 | M9: 44501 | N9: 44531 | O9: 2021
B11: PERFIL DE VENCIMIENTOS DE LA DEUDA EN SITUACIÓN DE PAGO NORMAL
B13: TOTAL | C13: =+C14+C15 -> 7910.2108 | D13: =+D14+D15 -> 882.63606 | E13: =+E14+E15 -> 2451.7786 | F13: =+F14+F15 -> 4776.8578 | G13: =+G14+G15 -> 1569.6536 | H13: =+H14+H15 -> 5077.6776 | I13: =+I14+I15 -> 3213.3156 | J13: =+J14+J15 -> 148.91955 | ... O13: =+O14+O15 -> 33808.448
B14: CORTO PLAZO | C14: 0 | D14: 0 | E14: 0 | F14: 0 | G14: 0 | H14: 0 | I14: 0 | J14: 0 | K14: 0 | L14: 0 | M14: 0 | N14: 0 | O14: =SUM(C14:N14) -> 0
B15: MEDIANO Y LARGO PLAZO | C15: 7910.2108 | D15: 882.63606 | E15: 2451.7786 | F15: 4776.8578 | G15: 1569.6536 | H15: 5077.6776 | I15: 3213.3156 | J15: 148.91955 | K15: 4002.5722 | L15: 1233.6402 | M15: 189.86779 | N15: 2351.3184 | O15: =SUM(C15:N15) -> 33808.448
B17: PRÉSTAMOS | C17: =+C18+C23+C25+C26+C29 -> 267.43761 | D17: =+D18+D23+D25+D26+D29 -> 152.41858 | E17: =+E18+E23+E25+E26+E29 -> 268.33856 | F17: =+F18+F23+F25+F26+F29 -> 139.50768 | G17: =+G18+G23+G25+G26+G29 -> 181.21818 | H17: =+H18+H23+H25+H26+H29 -> 173.61213 | I17: =+I18+I23+I25+I26+I29 -> 285.87647 | J17: =+J18+J23+J25+J26+J29 -> 139.44872 | ... N17: =+N18+N23+N25+N26+N29 -> 1982.3344 | O17: =+SUM(C17:N17) -> 5986.3904
B18: Organismos Internacionales | C18: =SUM(C19:C22) -> 112.76135 | D18: =SUM(D19:D22) -> 140.69686 | E18: =SUM(E19:E22) -> 251.99055 | F18: =SUM(F19:F22) -> 111.12553 | G18: =SUM(G19:G22) -> 148.39938 | H18: =SUM(H19:H22) -> 150.40717 | I18: =SUM(I19:I22) -> 131.11585 | J18: =SUM(J19:J22) -> 127.36352 | ... O18: =SUM(O19:O22) -> 5477.7924
B19: . BIRF | C19: 30.576801 | D19: 2.8298787 | E19: 72.012018 | F19: 46.871388 | G19: 17.625358 | H19: 33.618539 | I19: 30.568779 | J19: 2.8298787 | K19: 72.008569 | L19: 35.239831 | M19: 13.480842 | N19: 33.618539 | O19: =SUM(C19:N19) -> 391.28042
B20: . BID | C20: 53.888565 | D20: 46.867163 | E20: 138.62413 | F20: 49.225991 | G20: 98.409763 | H20: 43.456021 | I20: 53.888564 | J20: 33.53383 | K20: 138.62413 | L20: 51.417971 | M20: 101.39274 | N20: 26.746511 | O20: =SUM(C20:N20) -> 836.07537
B21: . FMI | C21: 0 | D21: 0 | E21: 0 | F21: 0 | G21: 0 | H21: 0 | I21: 0 | J21: 0 | K21: 1834.5046 | L21: 0 | M21: 0 | N21: 1834.5046 | O21: =SUM(C21:N21) -> 3669.0093
B22: . Otros | C22: 28.295981 | D22: 90.999814 | E22: 41.354408 | F22: 15.028149 | G22: 32.364255 | H22: 73.332609 | I22: 46.658511 | J22: 90.999814 | K22: 41.428608 | L22: 15.216325 | M22: 32.364255 | N22: 73.38466 | O22: =SUM(C22:N22) -> 581.42739
B23: Banca Comercial | C23: =+C24 -> 0.01238946 | D23: =+D24 -> 0.52768602 | E23: =+E24 -> 0.012702239 | F23: =+F24 -> 0.012608647 | G23: =+G24 -> 17.124857 | H23: =+H24 -> 0.012756564 | I23: =+I24 -> 0.012879057 | J23: =+J24 -> 0.52813043 | ... N23: =+N24 -> 0.013248373 | O23: =SUM(C23:N23) -> 35.408595
B24: . En moneda extranjera | C24: 0.01238946 | D24: 0.52768602 | E24: 0.012702239 | F24: 0.012608647 | G24: 17.124857 | H24: 0.012756564 | I24: 0.012879057 | J24: 0.52813043 | K24: 0.012981511 | L24: 0.013099315 | M24: 17.125256 | N24: 0.013248373 | O24: =SUM(C24:N24) -> 35.408595
B25: Organismos Oficiales | C25: 149.9799 | D25: 0.01279823 | E25: 0.12129997 | F25: 20.34323 | G25: 7.5957079 | H25: 0.42075657 | I25: 149.9799 | J25: 0.01279823 | K25: 0.12129997 | L25: 2.2689663 | M25: 7.5957079 | N25: 0.42075657 | O25: =SUM(C25:N25) -> 338.87312
B26: Pagarés | C26: =+C27 -> 0 | D26: =+D27 -> 0 | E26: =+E27 -> 0 | F26: =+F27 -> 0 | G26: =+G27 -> 0 | H26: =+H27 -> 1.1811965 | I26: =+I27 -> 0 | J26: =+J27 -> 0 | ... N26: =+N27 -> 0 | O26: =SUM(C26:N26) -> 1.1811965
B27: . En moneda extranjera | C27: =+C28 -> 0 | D27: =+D28 -> 0 | E27: =+E28 -> 0 | F27: =+F28 -> 0 | G27: =+G28 -> 0 | H27: =+H28 -> 1.1811965 | I27: =+I28 -> 0 | J27: =+J28 -> 0 | ... O27: =+O28 -> 1.1811965
B28: Pagarés CAMMESA | C28: 0 | D28: 0 | E28: 0 | F28: 0 | G28: 0 | H28: 1.1811965 | I28: 0 | J28: 0 | K28: 0 | L28: 0 | M28: 0 | N28: 0 | O28: =SUM(C28:N28) -> 1.1811965
B29: Avales | C29: =+C30+C31 -> 4.6839758 | D29: =+D30+D31 -> 11.181245 | E29: =+E30+E31 -> 16.214 | F29: =+F30+F31 -> 8.0263105 | G29: =+G30+G31 -> 8.0982407 | H29: =+H30+H31 -> 21.590248 | I29: =+I30+I31 -> 4.7678346 | J29: =+J30+J31 -> 11.544269 | ... O29: =+O30+O31 -> 133.13501
B30: . En moneda nacional | C30: 0.99041633 | D30: 1.0092774 | E30: 1.0376618 | F30: 1.0477388 | G30: 1.0705678 | H30: 1.0878511 | I30: 1.1113391 | J30: 1.1296004 | K30: 1.151069 | L30: 1.1754892 | M30: 1.1952516 | N30: 1.2203208 | O30: =SUM(C30:N30) -> 13.226583
B31: . En moneda extranjera | C31: 3.6935595 | D31: 10.171967 | E31: 15.176338 | F31: 6.9785717 | G31: 7.0276729 | H31: 20.502397 | I31: 3.6564955 | J31: 10.414669 | K31: 15.605452 | L31: 7.1023191 | M31: 7.1532493 | N31: 12.425735 | O31: =SUM(C31:N31) -> 119.90843
B33: ADELANTOS TRANSITORIOS BCRA | C33: 0 | D33: 0 | E33: 0 | F33: 0 | G33: 0 | H33: 4841.8065 | I33: 0 | J33: 0 | K33: 0 | L33: 0 | M33: 0 | N33: 0 | O33: =SUM(C33:N33) -> 4841.8065
B35: TÍTULOS PÚBLICOS Y LETRAS DEL TESORO | C35: =+C36+C53+SUM(C70:C118)+C121 -> 7642.7732 | D35: =+D36+D53+SUM(D70:D118)+D121 -> 730.21748 | E35: =+E36+E53+SUM(E70:E118)+E121 -> 2183.44 | F35: =+F36+F53+SUM(F70:F118)+F121 -> 4637.3501 | G35: =+G36+G53+SUM(G70:G118)+G121 -> 1388.4355 | H35: =+H36+H53+SUM(H70:H118)+H121 -> 62.258953 | I35: =+I36+I53+SUM(I70:I118)+I121 -> 2927.4391 | J35: =+J36+J53+SUM(J70:J118)+J121 -> 9.4708284 | ... O35: =+O36+O53+SUM(O70:O118)+O121 -> 22980.251
B36: PAR | C36: =+C37+C40+C47+C50 -> 0 | D36: =+D37+D40+D47+D50 -> 0 | E36: =+E37+E40+E47+E50 -> 0 | F36: =+F37+F40+F47+F50 -> 0 | G36: =+G37+G40+G47+G50 -> 0 | H36: =+H37+H40+H47+H50 -> 0 | I36: =+I37+I40+I47+I50 -> 0 | J36: =+J37+J40+J47+J50 -> 0 | ... N36: =+N37+N40+N47+N50 -> 0 | O36: =SUM(C36:N36) -> 0
B37: Par/$+CER/T.Fija/2038 | C37: =+C38+C39 -> 0 | D37: =+D38+D39 -> 0 | E37: =+E38+E39 -> 0 | F37: =+F38+F39 -> 0 | G37: =+G38+G39 -> 0 | H37: =+H38+H39 -> 0 | I37: =+I38+I39 -> 0 | J37: =+J38+J39 -> 0 | ... N37: =+N38+N39 -> 0 | O37: =SUM(C37:N37) -> 0
B38: Emisión Canje 2005 | C38: 0 | D38: 0 | E38: 0 | F38: 0 | G38: 0 | H38: 0 | I38: 0 | J38: 0 | K38: 0 | L38: 0 | M38: 0 | N38: 0 | O38: =SUM(C38:N38) -> 0
B39: Emisión Canje 2010 | C39: 0 | D39: 0 | E39: 0 | F39: 0 | G39: 0 | H39: 0 | I39: 0 | J39: 0 | K39: 0 | L39: 0 | M39: 0 | N39: 0 | O39: =SUM(C39:N39) -> 0
B40: Par/U$S/T.Fija/2038 | C40: =+C41+C44 -> 0 | D40: =+D41+D44 -> 0 | E40: =+E41+E44 -> 0 | F40: =+F41+F44 -> 0 | G40: =+G41+G44 -> 0 | H40: =+H41+H44 -> 0 | I40: =+I41+I44 -> 0 | J40: =+J41+J44 -> 0 | ... N40: =+N41+N44 -> 0 | O40: =SUM(C40:N40) -> 0
B41: Emisión Canje 2005 | C41: =+C42+C43 -> 0 | D41: =+D42+D43 -> 0 | E41: =+E42+E43 -> 0 | F41: =+F42+F43 -> 0 | G41: =+G42+G43 -> 0 | H41: =+H42+H43 -> 0 | I41: =+I42+I43 -> 0 | J41: =+J42+J43 -> 0 | ... N41: =+N42+N43 -> 0 | O41: =SUM(C41:N41) -> 0
B42: Leg. Nueva York | C42: 0 | D42: 0 | E42: 0 | F42: 0 | G42: 0 | H42: 0 | I42: 0 | J42: 0 | K42: 0 | L42: 0 | M42: 0 | N42: 0 | O42: =SUM(C42:N42) -> 0
B43: Leg. Argentina | C43: 0 | D43: 0 | E43: 0 | F43: 0 | G43: 0 | H43: 0 | I43: 0 | J43: 0 | K43: 0 | L43: 0 | M43: 0 | N43: 0 | O43: =SUM(C43:N43) -> 0
B44: Emisión Canje 2010 | C44: =+C45+C46 -> 0 | D44: =+D45+D46 -> 0 | E44: =+E45+E46 -> 0 | F44: =+F45+F46 -> 0 | G44: =+G45+G46 -> 0 | H44: =+H45+H46 -> 0 | I44: =+I45+I46 -> 0 | J44: =+J45+J46 -> 0 | ... N44: =+N45+N46 -> 0 | O44: =SUM(C44:N44) -> 0
B45: Leg. Nueva York | C45: 0 | D45: 0 | E45: 0 | F45: 0 | G45: 0 | H45: 0 | I45: 0 | J45: 0 | K45: 0 | L45: 0 | M45: 0 | N45: 0 | O45: =SUM(C45:N45) -> 0
B46: Leg. Argentina | C46: 0 | D46: 0 | E46: 0 | F46: 0 | G46: 0 | H46: 0 | I46: 0 | J46: 0 | K46: 0 | L46: 0 | M46: 0 | N46: 0 | O46: =SUM(C46:N46) -> 0
B47: Par/EUR/T.Fija/2038 | C47: =+C48+C49 -> 0 | D47: =+D48+D49 -> 0 | E47: =+E48+E49 -> 0 | F47: =+F48+F49 -> 0 | G47: =+G48+G49 -> 0 | H47: =+H48+H49 -> 0 | I47: =+I48+I49 -> 0 | J47: =+J48+J49 -> 0 | ... N47: =+N48+N49 -> 0 | O47: =SUM(C47:N47) -> 0
B48: Emisión Canje 2005 | C48: 0 | D48: 0 | E48: 0 | F48: 0 | G48: 0 | H48: 0 | I48: 0 | J48: 0 | K48: 0 | L48: 0 | M48: 0 | N48: 0 | O48: =SUM(C48:N48) -> 0
B49: Emisión Canje 2010 | C49: 0 | D49: 0 | E49: 0 | F49: 0 | G49: 0 | H49: 0 | I49: 0 | J49: 0 | K49: 0 | L49: 0 | M49: 0 | N49: 0 | O49: =SUM(C49:N49) -> 0
B50: Par/JPY/T.Fija/2038 | C50: =+C51+C52 -> 0 | D50: =+D51+D52 -> 0 | E50: =+E51+E52 -> 0 | F50: =+F51+F52 -> 0 | G50: =+G51+G52 -> 0 | H50: =+H51+H52 -> 0 | I50: =+I51+I52 -> 0 | J50: =+J51+J52 -> 0 | ... N50: =+N51+N52 -> 0 | O50: =SUM(C50:N50) -> 0
B51: Emisión Canje 2005 | C51: 0 | D51: 0 | E51: 0 | F51: 0 | G51: 0 | H51: 0 | I51: 0 | J51: 0 | K51: 0 | L51: 0 | M51: 0 | N51: 0 | O51: =SUM(C51:N51) -> 0
B52: Emisión Canje 2010 | C52: 0 | D52: 0 | E52: 0 | F52: 0 | G52: 0 | H52: 0 | I52: 0 | J52: 0 | K52: 0 | L52: 0 | M52: 0 | N52: 0 | O52: =SUM(C52:N52) -> 0
B53: DESCUENTO | C53: =+C54+C57+C64+C67 -> 0 | D53: =+D54+D57+D64+D67 -> 0 | E53: =+E54+E57+E64+E67 -> 0 | F53: =+F54+F57+F64+F67 -> 0 | G53: =+G54+G57+G64+G67 -> 0 | H53: =+H54+H57+H64+H67 -> 0 | I53: =+I54+I57+I64+I67 -> 0 | J53: =+J54+J57+J64+J67 -> 0 | ... N53: =+N54+N57+N64+N67 -> 0 | O53: =SUM(C53:N53) -> 0
B54: Discount/$+CER/5,83%/2033 | C54: =+C55+C56 -> 0 | D54: =+D55+D56 -> 0 | E54: =+E55+E56 -> 0 | F54: =+F55+F56 -> 0 | G54: =+G55+G56 -> 0 | H54: =+H55+H56 -> 0 | I54: =+I55+I56 -> 0 | J54: =+J55+J56 -> 0 | ... N54: =+N55+N56 -> 0 | O54: =SUM(C54:N54) -> 0
B55: Emisión Canje 2005 | C55: 0 | D55: 0 | E55: 0 | F55: 0 | G55: 0 | H55: 0 | I55: 0 | J55: 0 | K55: 0 | L55: 0 | M55: 0 | N55: 0 | O55: =SUM(C55:N55) -> 0
B56: Emisión Canje 2010 | C56: 0 | D56: 0 | E56: 0 | F56: 0 | G56: 0 | H56: 0 | I56: 0 | J56: 0 | K56: 0 | L56: 0 | M56: 0 | N56: 0 | O56: =SUM(C56:N56) -> 0
B57: Discount/U$S/8,28%/2033 | C57: =+C58+C61 -> 0 | D57: =+D58+D61 -> 0 | E57: =+E58+E61 -> 0 | F57: =+F58+F61 -> 0 | G57: =+G58+G61 -> 0 | H57: =+H58+H61 -> 0 | I57: =+I58+I61 -> 0 | J57: =+J58+J61 -> 0 | ... N57: =+N58+N61 -> 0 | O57: =SUM(C57:N57) -> 0
B58: Emisión Canje 2005 | C58: =+C59+C60 -> 0 | D58: =+D59+D60 -> 0 | E58: =+E59+E60 -> 0 | F58: =+F59+F60 -> 0 | G58: =+G59+G60 -> 0 | H58: =+H59+H60 -> 0 | I58: =+I59+I60 -> 0 | J58: =+J59+J60 -> 0 | ... N58: =+N59+N60 -> 0 | O58: =SUM(C58:N58) -> 0
B59: Leg. Nueva York | C59: 0 | D59: 0 | E59: 0 | F59: 0 | G59: 0 | H59: 0 | I59: 0 | J59: 0 | K59: 0 | L59: 0 | M59: 0 | N59: 0 | O59: =SUM(C59:N59) -> 0
B60: Leg. Argentina | C60: 0 | D60: 0 | E60: 0 | F60: 0 | G60: 0 | H60: 0 | I60: 0 | J60: 0 | K60: 0 | L60: 0 | M60: 0 | N60: 0 | O60: =SUM(C60:N60) -> 0
B61: Emisión Canje 2010 | C61: =+C62+C63 -> 0 | D61: =+D62+D63 -> 0 | E61: =+E62+E63 -> 0 | F61: =+F62+F63 -> 0 | G61: =+G62+G63 -> 0 | H61: =+H62+H63 -> 0 | I61: =+I62+I63 -> 0 | J61: =+J62+J63 -> 0 | ... N61: =+N62+N63 -> 0 | O61: =SUM(C61:N61) -> 0
B62: Leg. Nueva York | C62: 0 | D62: 0 | E62: 0 | F62: 0 | G62: 0 | H62: 0 | I62: 0 | J62: 0 | K62: 0 | L62: 0 | M62: 0 | N62: 0 | O62: =SUM(C62:N62) -> 0
B63: Leg. Argentina | C63: 0 | D63: 0 | E63: 0 | F63: 0 | G63: 0 | H63: 0 | I63: 0 | J63: 0 | K63: 0 | L63: 0 | M63: 0 | N63: 0 | O63: =SUM(C63:N63) -> 0
B64: Discount/EUR/7,82%/2033 | C64: =+C65+C66 -> 0 | D64: =+D65+D66 -> 0 | E64: =+E65+E66 -> 0 | F64: =+F65+F66 -> 0 | G64: =+G65+G66 -> 0 | H64: =+H65+H66 -> 0 | I64: =+I65+I66 -> 0 | J64: =+J65+J66 -> 0 | ... N64: =+N65+N66 -> 0 | O64: =SUM(C64:N64) -> 0
B65: Emisión Canje 2005 | C65: 0 | D65: 0 | E65: 0 | F65: 0 | G65: 0 | H65: 0 | I65: 0 | J65: 0 | K65: 0 | L65: 0 | M65: 0 | N65: 0 | O65: =SUM(C65:N65) -> 0
B66: Emisión Canje 2010 | C66: 0 | D66: 0 | E66: 0 | F66: 0 | G66: 0 | H66: 0 | I66: 0 | J66: 0 | K66: 0 | L66: 0 | M66: 0 | N66: 0 | O66: =SUM(C66:N66) -> 0
B67: Discount/JPY/4,33%/2033 | C67: =+C68+C69 -> 0 | D67: =+D68+D69 -> 0 | E67: =+E68+E69 -> 0 | F67: =+F68+F69 -> 0 | G67: =+G68+G69 -> 0 | H67: =+H68+H69 -> 0 | I67: =+I68+I69 -> 0 | J67: =+J68+J69 -> 0 | ... N67: =+N68+N69 -> 0 | O67: =SUM(C67:N67) -> 0
B68: Emisión Canje 2005 | C68: 0 | D68: 0 | E68: 0 | F68: 0 | G68: 0 | H68: 0 | I68: 0 | J68: 0 | K68: 0 | L68: 0 | M68: 0 | N68: 0 | O68: =SUM(C68:N68) -> 0
B69: Emisión Canje 2010 | C69: 0 | D69: 0 | E69: 0 | F69: 0 | G69: 0 | H69: 0 | I69: 0 | J69: 0 | K69: 0 | L69: 0 | M69: 0 | N69: 0 | O69: =SUM(C69:N69) -> 0
B70: CUASIPAR/$+CER/3,31%/2045 | C70: 0 | D70: 0 | E70: 0 | F70: 0 | G70: 0 | H70: 0 | I70: 0 | J70: 0 | K70: 0 | L70: 0 | M70: 0 | N70: 0 | O70: =SUM(C70:N70) -> 0
B71: BONAR/$/BADLAR+300pb/23-12-2020 | C71: 0 | D71: 0 | E71: 0 | F71: 0 | G71: 0 | H71: 0 | I71: 0 | J71: 0 | K71: 0 | L71: 0 | M71: 0 | N71: 0 | O71: =SUM(C71:N71) -> 0
B72: BONAR/$/BADLAR+325/01-03-2020 | C72: 0 | D72: 0 | E72: 0 | F72: 0 | G72: 0 | H72: 0 | I72: 0 | J72: 0 | K72: 0 | L72: 0 | M72: 0 | N72: 0 | O72: =SUM(C72:N72) -> 0
B73: BONAR/$/BADLAR+200/03-04-2022 | C73: 0 | D73: 0 | E73: 0 | F73: 0 | G73: 0 | H73: 0 | I73: 0 | J73: 0 | K73: 0 | L73: 0 | M73: 0 | N73: 0 | O73: =SUM(C73:N73) -> 0
B74: BONAR/$/6,72763943%/31-12-2028 | C74: 5.0971157 | D74: 5.3654448 | E74: 5.0368989 | F74: 5.1840113 | G74: 5.2130748 | H74: 5.2423012 | I74: 5.2716915 | J74: 5.3012465 | K74: 5.3309672 | L74: 5.3608546 | M74: 5.3909095 | N74: 5.4211329 | O74: =SUM(C74:N74) -> 63.215649
B75: BONTE/$/15,50%/17-10-2026 | C75: 0 | D75: 0 | E75: 0 | F75: 0 | G75: 0 | H75: 0 | I75: 0 | J75: 0 | K75: 0 | L75: 0 | M75: 0 | N75: 0 | O75: =SUM(C75:N75) -> 0
B76: BONTE/$/16,00%/17-10-2023 | C76: 0 | D76: 0 | E76: 0 | F76: 0 | G76: 0 | H76: 0 | I76: 0 | J76: 0 | K76: 0 | L76: 0 | M76: 0 | N76: 0 | O76: =SUM(C76:N76) -> 0
B77: BONTE/$/18,20%/03-10-2021 | C77: 0 | D77: 0 | E77: 0 | F77: 0 | G77: 0 | H77: 0 | I77: 0 | J77: 0 | K77: 0 | L77: 1043.4928 | M77: 0 | N77: 0 | O77: =SUM(C77:N77) -> 1043.4928
B78: BONTE/$/26%/21-11-2020 | C78: 0 | D78: 0 | E78: 0 | F78: 0 | G78: 0 | H78: 0 | I78: 0 | J78: 0 | K78: 0 | L78: 0 | M78: 0 | N78: 0 | O78: =SUM(C78:N78) -> 0
B79: BONAR/U$S/8,75%/07-05-2024 | C79: 0 | D79: 0 | E79: 0 | F79: 0 | G79: 1326.2057 | H79: 0 | I79: 0 | J79: 0 | K79: 0 | L79: 0 | M79: 0 | N79: 0 | O79: =SUM(C79:N79) -> 1326.2057
... B117: Letras en Garantía | C117: 0 | D117: 0 | E117: 0 | F117: 0 | G117: 0 | H117: 0 | I117: 0 | J117: 0 | K117: 0 | L117: 0 | M117: 0 | N117: 359.39327 | O117: =SUM(C117:N117) -> 359.39327
B118: LETRAS DEL TESORO | C118: =+C119+C120 -> 65.451392 | D118: =+D119+D120 -> 0 | E118: =+E119+E120 -> 0 | F118: =+F119+F120 -> 64.088534 | G118: =+G119+G120 -> 0 | H118: =+H119+H120 -> 0 | I118: =+I119+I120 -> 46.319402 | J118: =+J119+J120 -> 0 | ... N118: =+N119+N120 -> 0 | O118: =SUM(C118:N118) -> 232.98139
B119: . En moneda nacional | C119: 0 | D119: 0 | E119: 0 | F119: 0 | G119: 0 | H119: 0 | I119: 0 | J119: 0 | K119: 0 | L119: 0 | M119: 0 | N119: 0 | O119: =SUM(C119:N119) -> 0
B120: . En moneda extranjera | C120: 65.451392 | D120: 0 | E120: 0 | F120: 64.088534 | G120: 0 | H120: 0 | I120: 46.319402 | J120: 0 | K120: 0 | L120: 57.122065 | M120: 0 | N120: 0 | O120: =SUM(C120:N120) -> 232.98139
B121: OTROS (1) | C121: =+C122+C129 -> 15.377642 | D121: =+D122+D129 -> 4.1695819 | E121: =+E122+E129 -> 4.1695819 | F121: =+F122+F129 -> 15.230474 | G121: =+G122+G129 -> 4.1695819 | H121: =+H122+H129 -> 4.1695819 | I121: =+I122+I129 -> 15.230474 | J121: =+J122+J129 -> 4.1695819 | ... N121: =+N122+N129 -> 4.1695819 | O121: =SUM(C121:N121) -> 94.425717
B122: En moneda nacional | C122: =+C123+C126 -> 15.377642 | D122: =+D123+D126 -> 4.1695819 | E122: =+E123+E126 -> 4.1695819 | F122: =+F123+F126 -> 15.230474 | G122: =+G123+G126 -> 4.1695819 | H122: =+H123+H126 -> 4.1695819 | I122: =+I123+I126 -> 15.230474 | J122: =+J123+J126 -> 4.1695819 | ... N122: =+N123+N126 -> 4.1695819 | O122: =SUM(C122:N122) -> 94.425717
B123: · Ajustable por CER | C123: =+C124+C125 -> 4.1695819 | D123: =+D124 -> 4.1695819 | E123: =+E124 -> 4.1695819 | F123: =+F124 -> 4.1695819 | G123: =+G124 -> 4.1695819 | H123: =+H124 -> 4.1695819 | I123: =+I124 -> 4.1695819 | J123: =+J124 -> 4.1695819 | K123: =+K124 -> 4.1695819 | ... N123: =+N124 -> 4.1695819 | O123: =SUM(C123:N123) -> 50.034982
B124: · Bonos de consolidación | C124: 4.1695819 | D124: 4.1695819 | E124: 4.1695819 | F124: 4.1695819 | G124: 4.1695819 | H124: 4.1695819 | I124: 4.1695819 | J124: 4.1695819 | K124: 4.1695819 | L124: 4.1695819 | M124: 4.1695819 | N124: 4.1695819 | O124: =SUM(C124:N124) -> 50.034982
B125: · Otros | C125: 0 | D125: 0 | E125: 0 | F125: 0 | G125: 0 | H125: 0 | I125: 0 | J125: 0 | K125: 0 | L125: 0 | M125: 0 | N125: 0 | O125: =SUM(C125:N125) -> 0
B126: · No ajustable por CER | C126: =+C127+C128 -> 11.20806 | D126: =+D127+D128 -> 0 | E126: =+E127+E128 -> 0 | F126: =+F127+F128 -> 11.060892 | G126: =+G127+G128 -> 0 | H126: =+H127+H128 -> 0 | I126: =+I127+I128 -> 11.060892 | J126: =+J127+J128 -> 0 | ... N126: =+N127+N128 -> 0 | O126: =SUM(C126:N126) -> 44.390735
B127: · Bonos de consolidación | C127: 11.060892 | D127: 0 | E127: 0 | F127: 11.060892 | G127: 0 | H127: 0 | I127: 11.060892 | J127: 0 | K127: 0 | L127: 11.060892 | M127: 0 | N127: 0 | O127: =SUM(C127:N127) -> 44.243567
B128: · Otros | C128: 0.14716816 | D128: 0 | E128: 0 | F128: 0 | G128: 0 | H128: 0 | I128: 0 | J128: 0 | K128: 0 | L128: 0 | M128: 0 | N128: 0 | O128: =SUM(C128:N128) -> 0.14716816
B129: . En moneda extranjera | C129: =+C130+C131 -> 0 | D129: =+D130+D131 -> 0 | E129: =+E130+E131 -> 0 | F129: =+F130+F131 -> 0 | G129: =+G130+G131 -> 0 | H129: =+H130+H131 -> 0 | I129: =+I130+I131 -> 0 | J129: =+J130+J131 -> 0 | ... N129: =+N130+N131 -> 0 | O129: =SUM(C129:N129) -> 0
B130: · Bonos de Consolidación | C130: 0 | D130: 0 | E130: 0 | F130: 0 | G130: 0 | H130: 0 | I130: 0 | J130: 0 | K130: 0 | L130: 0 | M130: 0 | N130: 0 | O130: =SUM(C130:N130) -> 0
B131: · Otros | C131: 0 | D131: 0 | E131: 0 | F131: 0 | G131: 0 | H131: 0 | I131: 0 | J131: 0 | K131: 0 | L131: 0 | M131: 0 | N131: 0 | O131: =SUM(C131:N131) -> 0
B134: TOTAL DEUDA DENOMINADA EN PESOS | C134: =+C135+C136 -> 74.312244 | D134: =+D135+D136 -> 731.22675 | E134: =+E135+E136 -> 63.091213 | F134: =+F135+F136 -> 74.309294 | G134: =+G135+G136 -> 63.300295 | H134: =+H135+H136 -> 4905.1533 | I134: =+I135+I136 -> 2882.2311 | J134: =+J135+J136 -> 10.600429 | ... N134: =+N135+N136 -> 10.811036 | O134: =SUM(C134:N134) -> 11791.318
B135: · Deuda ajustable por CER | C135: 4.1695819 | D135: 4.1695819 | E135: 4.1695819 | F135: 4.1695819 | G135: 4.1695819 | H135: 4.1695819 | I135: 2864.7872 | J135: 4.1695819 | K135: 4.1695819 | L135: 4.1695819 | M135: 4.1695819 | N135: 4.1695819 | O135: =SUM(C135:N135) -> 2910.6526
B136: · Deuda no ajustable por CER | C136: 70.142662 | D136: 727.05717 | E136: 58.921631 | F136: 70.139712 | G136: 59.130713 | H136: 4900.9837 | I136: 17.443922 | J136: 6.4308469 | K136: 1896.097 | L136: 1061.09 | M136: 6.5861612 | N136: 6.6414537 | O136: =SUM(C136:N136) -> 8880.665
B137: TOTAL DEUDA EN MONEDA EXTRANJERA | C137: 7835.8986 | D137: 151.40931 | E137: 2388.6874 | F137: 4702.5485 | G137: 1506.3533 | H137: 172.52428 | I137: 331.08453 | J137: 138.31912 | K137: 2102.3057 | L137: 168.38058 | M137: 179.11205 | N137: 2340.5074 | O137: =SUM(C137:N137) -> 22017.131
B139: (1) Incluye bonos de consolidación, amparos y excepciones.

Sheet A.3.5
A1: Indice
B2: =+INDICE!B2 -> MINISTERIO DE ECONOMÍA
B3: SECRETARÍA DE FINANZAS
B6: PERFIL MENSUAL DE VENCIMIENTOS DE INTERÉS DE LA DEUDA BRUTA DE LA ADMINISTRACIÓN CENTRAL
B8: (En millones de U$S - Stock de deuda y tipo de cambio 31/12/19)
C9: 44197 | D9: 44228 | E9: 44256 | F9: 44287 | G9: 44317 | H9: 44348 | I9: 44378 | J9: 44409 | K9: 44440 | L9: 44470 | M9: 44501 | N9: 44531 | O9: 2021
B11: PERFIL DE VENCIMIENTOS DE LA DEUDA EN SITUACIÓN DE PAGO NORMAL
B13: TOTAL | C13: =SUM(C14:C15) -> 1163.4141 | D13: =SUM(D14:D15) -> 568.97766 | E13: =SUM(E14:E15) -> 408.62606 | F13: =SUM(F14:F15) -> 1191.5111 | G13: =SUM(G14:G15) -> 751.66605 | H13: =SUM(H14:H15) -> 1786.9735 | I13: =SUM(I14:I15) -> 893.82429 | J13: =SUM(J14:J15) -> 523.67424 | ... N13: =SUM(N14:N15) -> 1782.7547 | O13: =SUM(C13:N13) -> 11299.959
B14: CORTO PLAZO | C14: 0 | D14: 0 | E14: 0 | F14: 0 | G14: 0 | H14: 0 | I14: 0 | J14: 0 | K14: 0 | L14: 0 | M14: 0 | N14: 0 | O14: =SUM(C14:N14) -> 0
B15: MEDIANO Y LARGO PLAZO | C15: 1163.4141 | D15: 568.97766 | E15: 408.62606 | F15: 1191.5111 | G15: 751.66605 | H15: 1786.9735 | I15: 893.82429 | J15: 523.67424 | K15: 389.76589 | L15: 1034.9552 | M15: 803.81671 | N15: 1782.7547 | O15: =SUM(C15:N15) -> 11299.959
B17: PRÉSTAMOS | C17: =+C18+C23+C25+C28+C29+C34 -> 87.272282 | D17: =+D18+D23+D25+D28+D29+D34 -> 438.45709 | E17: =+E18+E23+E25+E28+E29+E34 -> 115.61012 | F17: =+F18+F23+F25+F28+F29+F34 -> 50.225967 | G17: =+G18+G23+G25+G28+G29+G34 -> 477.50369 | H17: =+H18+H23+H25+H28+H29+H34 -> 87.528091 | I17: =+I18+I23+I25+I28+I29+I34 -> 81.590894 | J17: =+J18+J23+J25+J28+J29+J34 -> 477.70174 | ... N17: =+N18+N23+N25+N28+N29+N34 -> 83.038136 | O17: =SUM(C17:N17) -> 2594.6099
B18: Organismos Internacionales | C18: =+SUM(C19:C22) -> 38.880551 | D18: =+SUM(D19:D22) -> 433.31396 | E18: =+SUM(E19:E22) -> 106.54312 | F18: =+SUM(F19:F22) -> 45.545588 | G18: =+SUM(G19:G22) -> 471.56395 | H18: =+SUM(H19:H22) -> 48.545966 | I18: =+SUM(I19:I22) -> 36.402335 | J18: =+SUM(J19:J22) -> 473.01527 | ... N18: =+SUM(N19:N22) -> 46.470178 | O18: =SUM(C18:N18) -> 2378.0181
B19: . BIRF | C19: 1.7598747 | D19: 2.1801108 | E19: 35.452804 | F19: 17.870169 | G19: 16.2965 | H19: 26.746563 | I19: 1.4303119 | J19: 2.1075272 | K19: 34.975165 | L19: 17.325351 | M19: 16.339899 | N19: 26.430363 | O19: =SUM(C19:N19) -> 198.91464
B20: . BID | C20: 23.684049 | D20: 16.649918 | E20: 58.324898 | F20: 23.684787 | G20: 65.163855 | H20: 6.7024708 | I20: 22.387071 | J20: 15.399263 | K20: 56.694991 | L20: 22.990334 | M20: 64.379291 | N20: 5.9604704 | O20: =SUM(C20:N20) -> 382.0214
B21: . FMI | C21: 0 | D21: 397.37959 | E21: 0 | F21: 0 | G21: 384.42156 | H21: 0 | I21: 0 | J21: 440.15893 | K21: 0 | L21: 0 | M21: 444.00081 | N21: 0 | O21: =SUM(C21:N21) -> 1665.9609
B22: . Otros | C22: 13.436628 | D22: 17.104334 | E22: 12.765421 | F22: 3.9906321 | G22: 5.6820343 | H22: 15.096932 | I22: 12.584952 | J22: 15.349547 | K22: 12.155915 | L22: 3.7705045 | M22: 5.1048857 | N22: 14.079344 | O22: =SUM(C22:N22) -> 131.12113
B23: Préstamos Garantizados | C23: =SUM(C24:C24) -> 2.6621373 | D23: =SUM(D24:D24) -> 2.6621373 | E23: =SUM(E24:E24) -> 2.4696125 | F23: =SUM(F24:F24) -> 2.6621373 | G23: =SUM(G24:G24) -> 2.5979624 | H23: =SUM(H24:H24) -> 2.6621373 | I23: =SUM(I24:I24) -> 2.5979624 | J23: =SUM(J24:J24) -> 2.6621373 | ... N23: =SUM(N24:N24) -> 2.5979624 | O23: =SUM(C23:N23) -> 31.496423
B24: . En moneda nacional ajustable por CER | C24: 2.6621373 | D24: 2.6621373 | E24: 2.4696125 | F24: 2.6621373 | G24: 2.5979624 | H24: 2.6621373 | I24: 2.5979624 | J24: 2.6621373 | K24: 2.6621373 | L24: 2.5979624 | M24: 2.6621373 | N24: 2.5979624 | O24: =SUM(C24:N24) -> 31.496423
B25: Banca Comercial | C25: =+C26+C27 -> 0.0027548493 | D25: =+D26+D27 -> 0.044733318 | E25: =+E26+E27 -> 0.0024420709 | F25: =+F26+F27 -> 0.002535663 | G25: =+G26+G27 -> 1.4234704 | H25: =+H26+H27 -> 0.0023877453 | I25: =+I26+I27 -> 0.0022652526 | J25: =+J26+J27 -> 0.040028515 | ... N25: =+N26+N27 -> 0.0018959439 | O25: =SUM(C25:N25) -> 2.8685961
B26: . En moneda nacional | C26: 0 | D26: 0 | E26: 0 | F26: 0 | G26: 0 | H26: 0 | I26: 0 | J26: 0 | K26: 0 | L26: 0 | M26: 0 | N26: 0 | O26: =SUM(C26:N26) -> 0
B27: . En moneda extranjera | C27: 0.0027548493 | D27: 0.044733318 | E27: 0.0024420709 | F27: 0.002535663 | G27: 1.4234704 | H27: 0.0023877453 | I27: 0.0022652526 | J27: 0.040028515 | K27: 0.0021627986 | L27: 0.0020449943 | M27: 1.3418746 | N27: 0.0018959439 | O27: =SUM(C27:N27) -> 2.8685961
B28: Organismos Oficiales | C28: 44.838333 | D28: 0.11229725 | E28: 0.6642949 | F28: 0.53512397 | G28: 0.61551871 | H28: 34.178971 | I28: 41.877389 | J28: 0.11040093 | K28: 0.18951534 | L28: 0.51911546 | M28: 0.5436512 | N28: 32.34739 | O28: =SUM(C28:N28) -> 156.532
B29: Pagarés | C29: =+C30+C32 -> 0 | D29: =+D30 -> 0 | E29: =+E30 -> 2.7817613 | F29: =+F30 -> 0 | G29: =+G30 -> 0 | H29: =+H30 -> 0 | I29: =+I30 -> 0 | J29: =+J30 -> 0 | K29: =+K30 -> 2.7817613 | ... N29: =+N30 -> 0 | O29: =SUM(C29:N29) -> 5.5635226
B30: . En moneda nacional ajustable por CER | C30: =+C31 -> 0 | D30: =+D31 -> 0 | E30: =+E31 -> 2.7817613 | F30: =+F31 -> 0 | G30: =+G31 -> 0 | H30: =+H31 -> 0 | I30: =+I31 -> 0 | J30: =+J31 -> 0 | ... N30: =+N31 -> 0 | O30: =SUM(C30:N30) -> 5.5635226
B31: Pagaré 2038 - B.N.A. | C31: 0 | D31: 0 | E31: 2.7817613 | F31: 0 | G31: 0 | H31: 0 | I31: 0 | J31: 0 | K31: 2.7817613 | L31: 0 | M31: 0 | N31: 0 | O31: =SUM(C31:N31) -> 5.5635226
B32: . En moneda nacional no ajustable por CER | C32: =+C33 -> 0 | D32: =+D33 -> 0 | E32: =+E33 -> 0 | F32: =+F33 -> 0 | G32: =+G33 -> 0 | H32: =+H33 -> 0 | I32: =+I33 -> 0 | J32: =+J33 -> 0 | ... N32: =+N33 -> 0 | O32: =SUM(C32:N32) -> 0
B33: Pagaré CUT | C33: 0 | D33: 0 | E33: 0 | F33: 0 | G33: 0 | H33: 0 | I33: 0 | J33: 0 | K33: 0 | L33: 0 | M33: 0 | N33: 0 | O33: =SUM(C33:N33) -> 0
B34: Avales | C34: =C35+C36 -> 0.88850581 | D34: =D35+D36 -> 2.3239632 | E34: =E35+E36 -> 3.1488864 | F34: =F35+F36 -> 1.4805826 | G34: =G35+G36 -> 1.3027824 | H34: =H35+H36 -> 2.1386287 | I34: =I35+I36 -> 0.71094248 | J34: =J35+J36 -> 1.8739005 | ... N34: =N35+N36 -> 1.6207103 | O34: =SUM(C34:N34) -> 20.131243
B35: . En moneda nacional | C35: 0.49319633 | D35: 0.48081612 | E35: 0.46820015 | F35: 0.45522938 | G35: 0.44213265 | H35: 0.42875055 | I35: 0.41515241 | J35: 0.40126067 | K35: 0.38714067 | L35: 0.3727523 | M35: 0.35805869 | N35: 0.34311804 | O35: =SUM(C35:N35) -> 5.045808
B36: . En moneda extranjera | C36: 0.39530948 | D36: 1.8431471 | E36: 2.6806863 | F36: 1.0253532 | G36: 0.86064974 | H36: 1.7098781 | I36: 0.29579007 | J36: 1.4726398 | K36: 2.1344047 | L36: 0.76978057 | M36: 0.62020421 | N36: 1.2775922 | O36: =SUM(C36:N36) -> 15.085436
B38: TÍTULOS PÚBLICOS Y LETRAS DEL TESORO | C38: =+C39+C56+SUM(C73:C119)+C122 -> 1076.1419 | D38: =+D39+D56+SUM(D73:D119)+D122 -> 130.52058 | E38: =+E39+E56+SUM(E73:E119)+E122 -> 293.01594 | F38: =+F39+F56+SUM(F73:F119)+F122 -> 1141.2851 | G38: =+G39+G56+SUM(G73:G119)+G122 -> 274.16237 | H38: =+H39+H56+SUM(H73:H119)+H122 -> 1699.4454 | I38: =+I39+I56+SUM(I73:I119)+I122 -> 812.23339 | J38: =+J39+J56+SUM(J73:J119)+J122 -> 45.972505 | ... O38: =+O39+O56+SUM(O73:O119)+O122 -> 8705.3496
B39: PAR | C39: =+C40+C43+C50+C53 -> 0 | D39: =+D40+D43+D50+D53 -> 0 | E39: =+E40+E43+E50+E53 -> 254.09705 | F39: =+F40+F43+F50+F53 -> 0 | G39: =+G40+G43+G50+G53 -> 0 | H39: =+H40+H43+H50+H53 -> 0 | I39: =+I40+I43+I50+I53 -> 0 | J39: =+J40+J43+J50+J53 -> 0 | ... N39: =+N40+N43+N50+N53 -> 0 | O39: =SUM(C39:N39) -> 508.19411
B40: Par/$+CER/T.Fija/2038 | C40: =+C41+C42 -> 0 | D40: =+D41+D42 -> 0 | E40: =+E41+E42 -> 5.3847145 | F40: =+F41+F42 -> 0 | G40: =+G41+G42 -> 0 | H40: =+H41+H42 -> 0 | I40: =+I41+I42 -> 0 | J40: =+J41+J42 -> 0 | ... N40: =+N41+N42 -> 0 | O40: =SUM(C40:N40) -> 10.769429
B41: Emisión Canje 2005 | C41: 0 | D41: 0 | E41: 5.3633843 | F41: 0 | G41: 0 | H41: 0 | I41: 0 | J41: 0 | K41: 5.3633843 | L41: 0 | M41: 0 | N41: 0 | O41: =SUM(C41:N41) -> 10.726769
B42: Emisión Canje 2010 | C42: 0 | D42: 0 | E42: 0.021330191 | F42: 0 | G42: 0 | H42: 0 | I42: 0 | J42: 0 | K42: 0.021330191 | L42: 0 | M42: 0 | N42: 0 | O42: =SUM(C42:N42) -> 0.042660383
B43: Par/U$S/T.Fija/2038 | C43: =+C44+C47 -> 0 | D43: =+D44+D47 -> 0 | E43: =+E44+E47 -> 125.52433 | F43: =+F44+F47 -> 0 | G43: =+G44+G47 -> 0 | H43: =+H44+H47 -> 0 | I43: =+I44+I47 -> 0 | J43: =+J44+J47 -> 0 | ... N43: =+N44+N47 -> 0 | O43: =SUM(C43:N43) -> 251.04866
B44: Emisión Canje 2005 | C44: =+C45+C46 -> 0 | D44: =+D45+D46 -> 0 | E44: =+E45+E46 -> 122.36723 | F44: =+F45+F46 -> 0 | G44: =+G45+G46 -> 0 | H44: =+H45+H46 -> 0 | I44: =+I45+I46 -> 0 | J44: =+J45+J46 -> 0 | ... N44: =+N45+N46 -> 0 | O44: =SUM(C44:N44) -> 244.73445
B45: Leg. Nueva York | C45: 0 | D45: 0 | E45: 99.312922 | F45: 0 | G45: 0 | H45: 0 | I45: 0 | J45: 0 | K45: 99.312922 | L45: 0 | M45: 0 | N45: 0 | O45: =SUM(C45:N45) -> 198.62584
B46: Leg. Argentina | C46: 0 | D46: 0 | E46: 23.054303 | F46: 0 | G46: 0 | H46: 0 | I46: 0 | J46: 0 | K46: 23.054303 | L46: 0 | M46: 0 | N46: 0 | O46: =SUM(C46:N46) -> 46.108607
B47: Emisión Canje 2010 | C47: =+C48+C49 -> 0 | D47: =+D48+D49 -> 0 | E47: =+E48+E49 -> 3.157104 | F47: =+F48+F49 -> 0 | G47: =+G48+G49 -> 0 | H47: =+H48+H49 -> 0 | I47: =+I48+I49 -> 0 | J47: =+J48+J49 -> 0 | ... N47: =+N48+N49 -> 0 | O47: =SUM(C47:N47) -> 6.314208
B48: Leg. Nueva York | C48: 0 | D48: 0 | E48: 1.8176096 | F48: 0 | G48: 0 | H48: 0 | I48: 0 | J48: 0 | K48: 1.8176096 | L48: 0 | M48: 0 | N48: 0 | O48: =SUM(C48:N48) -> 3.6352192
B49: Leg. Argentina | C49: 0 | D49: 0 | E49: 1.3394944 | F49: 0 | G49: 0 | H49: 0 | I49: 0 | J49: 0 | K49: 1.3394944 | L49: 0 | M49: 0 | N49: 0 | O49: =SUM(C49:N49) -> 2.6789888
B50: Par/EUR/T.Fija/2038 | C50: =+C51+C52 -> 0 | D50: =+D51+D52 -> 0 | E50: =+E51+E52 -> 122.62916 | F50: =+F51+F52 -> 0 | G50: =+G51+G52 -> 0 | H50: =+H51+H52 -> 0 | I50: =+I51+I52 -> 0 | J50: =+J51+J52 -> 0 | ... N50: =+N51+N52 -> 0 | O50: =SUM(C50:N50) -> 245.25831
B51: Emisión Canje 2005 | C51: 0 | D51: 0 | E51: 95.381701 | F51: 0 | G51: 0 | H51: 0 | I51: 0 | J51: 0 | K51: 95.381701 | L51: 0 | M51: 0 | N51: 0 | O51: =SUM(C51:N51) -> 190.7634
B52: Emisión Canje 2010 | C52: 0 | D52: 0 | E52: 27.247455 | F52: 0 | G52: 0 | H52: 0 | I52: 0 | J52: 0 | K52: 27.247455 | L52: 0 | M52: 0 | N52: 0 | O52: =SUM(C52:N52) -> 54.49491
B53: Par/JPY/T.Fija/2038 | C53: =+C54+C55 -> 0 | D53: =+D54+D55 -> 0 | E53: =+E54+E55 -> 0.55885335 | F53: =+F54+F55 -> 0 | G53: =+G54+G55 -> 0 | H53: =+H54+H55 -> 0 | I53: =+I54+I55 -> 0 | J53: =+J54+J55 -> 0 | ... N53: =+N54+N55 -> 0 | O53: =SUM(C53:N53) -> 1.1177067
B54: Emisión Canje 2005 | C54: 0 | D54: 0 | E54: 0.53251592 | F54: 0 | G54: 0 | H54: 0 | I54: 0 | J54: 0 | K54: 0.53251592 | L54: 0 | M54: 0 | N54: 0 | O54: =SUM(C54:N54) -> 1.0650318
B55: Emisión Canje 2010 | C55: 0 | D55: 0 | E55: 0.026337428 | F55: 0 | G55: 0 | H55: 0 | I55: 0 | J55: 0 | K55: 0.026337428 | L55: 0 | M55: 0 | N55: 0 | O55: =SUM(C55:N55) -> 0.052674856
B56: DESCUENTO | C56: =+C57+C60+C67+C70 -> 0 | D56: =+D57+D60+D67+D70 -> 0 | E56: =+E57+E60+E67+E70 -> 0 | F56: =+F57+F60+F67+F70 -> 0 | G56: =+G57+G60+G67+G70 -> 0 | H56: =+H57+H60+H67+H70 -> 869.67227 | I56: =+I57+I60+I67+I70 -> 0 | J56: =+J57+J60+J67+J70 -> 0 | ... N56: =+N57+N60+N67+N70 -> 869.67227 | O56: =SUM(C56:N56) -> 1739.3445
B57: Discount/$+CER/5,83%/2033 | C57: =+C58+C59 -> 0 | D57: =+D58+D59 -> 0 | E57: =+E58+E59 -> 0 | F57: =+F58+F59 -> 0 | G57: =+G58+G59 -> 0 | H57: =+H58+H59 -> 83.836007 | I57: =+I58+I59 -> 0 | J57: =+J58+J59 -> 0 | ... N57: =+N58+N59 -> 83.836007 | O57: =SUM(C57:N57) -> 167.67201
B58: Emisión Canje 2005 | C58: 0 | D58: 0 | E58: 0 | F58: 0 | G58: 0 | H58: 82.840207 | I58: 0 | J58: 0 | K58: 0 | L58: 0 | M58: 0 | N58: 82.840207 | O58: =SUM(C58:N58) -> 165.68041
B59: Emisión Canje 2010 | C59: 0 | D59: 0 | E59: 0 | F59: 0 | G59: 0 | H59: 0.99580065 | I59: 0 | J59: 0 | K59: 0 | L59: 0 | M59: 0 | N59: 0.99580065 | O59: =SUM(C59:N59) -> 1.9916013
B60: Discount/U$S/8,28%/2033 | C60: =+C61+C64 -> 0 | D60: =+D61+D64 -> 0 | E60: =+E61+E64 -> 0 | F60: =+F61+F64 -> 0 | G60: =+G61+G64 -> 0 | H60: =+H61+H64 -> 530.70813 | I60: =+I61+I64 -> 0 | J60: =+J61+J64 -> 0 | ... N60: =+N61+N64 -> 530.70813 | O60: =SUM(C60:N60) -> 1061.4163
B61: Emisión Canje 2005 | C61: =+C62+C63 -> 0 | D61: =+D62+D63 -> 0 | E61: =+E62+E63 -> 0 | F61: =+F62+F63 -> 0 | G61: =+G62+G63 -> 0 | H61: =+H62+H63 -> 469.10147 | I61: =+I62+I63 -> 0 | J61: =+J62+J63 -> 0 | ... N61: =+N62+N63 -> 469.10147 | O61: =SUM(C61:N61) -> 938.20294
B62: Leg. Nueva York | C62: 0 | D62: 0 | E62: 0 | F62: 0 | G62: 0 | H62: 176.42785 | I62: 0 | J62: 0 | K62: 0 | L62: 0 | M62: 0 | N62: 176.42785 | O62: =SUM(C62:N62) -> 352.85571
B63: Leg. Argentina | C63: 0 | D63: 0 | E63: 0 | F63: 0 | G63: 0 | H63: 292.67362 | I63: 0 | J63: 0 | K63: 0 | L63: 0 | M63: 0 | N63: 292.67362 | O63: =SUM(C63:N63) -> 585.34723
B64: Emisión Canje 2010 | C64: =+C65+C66 -> 0 | D64: =+D65+D66 -> 0 | E64: =+E65+E66 -> 0 | F64: =+F65+F66 -> 0 | G64: =+G65+G66 -> 0 | H64: =+H65+H66 -> 61.606658 | I64: =+I65+I66 -> 0 | J64: =+J65+J66 -> 0 | ... N64: =+N65+N66 -> 61.606658 | O64: =SUM(C64:N64) -> 123.21332
B65: Leg. Nueva York | C65: 0 | D65: 0 | E65: 0 | F65: 0 | G65: 0 | H65: 53.975224 | I65: 0 | J65: 0 | K65: 0 | L65: 0 | M65: 0 | N65: 53.975224 | O65: =SUM(C65:N65) -> 107.95045
B66: Leg. Argentina | C66: 0 | D66: 0 | E66: 0 | F66: 0 | G66: 0 | H66: 7.6314345 | I66: 0 | J66: 0 | K66: 0 | L66: 0 | M66: 0 | N66: 7.6314345 | O66: =SUM(C66:N66) -> 15.262869
B67: Discount/EUR/7,82%/2033 | C67: =+C68+C69 -> 0 | D67: =+D68+D69 -> 0 | E67: =+E68+E69 -> 0 | F67: =+F68+F69 -> 0 | G67: =+G68+G69 -> 0 | H67: =+H68+H69 -> 253.16972 | I67: =+I68+I69 -> 0 | J67: =+J68+J69 -> 0 | ... N67: =+N68+N69 -> 253.16972 | O67: =SUM(C67:N67) -> 506.33944
B68: Emisión Canje 2005 | C68: 0 | D68: 0 | E68: 0 | F68: 0 | G68: 0 | H68: 136.5196 | I68: 0 | J68: 0 | K68: 0 | L68: 0 | M68: 0 | N68: 136.5196 | O68: =SUM(C68:N68) -> 273.03919
B69: Emisión Canje 2010 | C69: 0 | D69: 0 | E69: 0 | F69: 0 | G69: 0 | H69: 116.65012 | I69: 0 | J69: 0 | K69: 0 | L69: 0 | M69: 0 | N69: 116.65012 | O69: =SUM(C69:N69) -> 233.30024
B70: Discount/JPY/4,33%/2033 | C70: =+C71+C72 -> 0 | D70: =+D71+D72 -> 0 | E70: =+E71+E72 -> 0 | F70: =+F71+F72 -> 0 | G70: =+G71+G72 -> 0 | H70: =+H71+H72 -> 1.9584134 | I70: =+I71+I72 -> 0 | J70: =+J71+J72 -> 0 | ... N70: =+N71+N72 -> 1.9584134 | O70: =SUM(C70:N70) -> 3.9168268
B71: Emisión Canje 2005 | C71: 0 | D71: 0 | E71: 0 | F71: 0 | G71: 0 | H71: 1.3512386 | I71: 0 | J71: 0 | K71: 0 | L71: 0 | M71: 0 | N71: 1.3512386 | O71: =SUM(C71:N71) -> 2.7024772
B72: Emisión Canje 2010 | C72: 0 | D72: 0 | E72: 0 | F72: 0 | G72: 0 | H72: 0.60717481 | I72: 0 | J72: 0 | K72: 0 | L72: 0 | M72: 0 | N72: 0.60717481 | O72: =SUM(C72:N72) -> 1.2143496
B73: CUASIPAR/$+CER/3,31%/2045 | C73: 0 | D73: 0 | E73: 0 | F73: 0 | G73: 0 | H73: 115.42288 | I73: 0 | J73: 0 | K73: 0 | L73: 0 | M73: 0 | N73: 115.42288 | O73: =SUM(C73:N73) -> 230.84576
B74: BONAR/$/BADLAR+300pb/23-12-2020 | C74: 0 | D74: 0 | E74: 0 | F74: 0 | G74: 0 | H74: 0 | I74: 0 | J74: 0 | K74: 0 | L74: 0 | M74: 0 | N74: 0 | O74: =SUM(C74:N74) -> 0
B75: BONAR/$/BADLAR+325/01-03-2020 | C75: 0 | D75: 0 | E75: 0 | F75: 0 | G75: 0 | H75: 0 | I75: 0 | J75: 0 | K75: 0 | L75: 0 | M75: 0 | N75: 0 | O75: =SUM(C75:N75) -> 0
B76: BONAR/$/BADLAR+200/03-04-2022 | C76: 112.51441 | D76: 0 | E76: 0 | F76: 110.06845 | G76: 0 | H76: 0 | I76: 111.29143 | J76: 0 | K76: 0 | L76: 112.51441 | M76: 0 | N76: 0 | O76: =SUM(C76:N76) -> 446.3887
B77: BONAR/$/6,72763943%/31-12-2028 | C77: 3.6248686 | D77: 3.3565395 | E77: 3.5662116 | F77: 3.5379729 | G77: 3.5089095 | H77: 3.4796831 | I77: 3.4502928 | J77: 3.4207378 | K77: 3.391017 | L77: 3.3611297 | M77: 3.3310748 | N77: 3.3008514 | O77: =SUM(C77:N77) -> 41.329289
B78: BONTE/$/15,50%/17-10-2026 | C78: 0 | D78: 0 | E78: 0 | F78: 124.95455 | G78: 0 | H78: 0 | I78: 0 | J78: 0 | K78: 0 | L78: 124.95455 | M78: 0 | N78: 0 | O78: =SUM(C78:N78) -> 249.9091
B79: BONTE/$/16,00%/17-10-2023 | C79: 0 | D79: 0 | E79: 0 | F79: 85.683751 | G79: 0 | H79: 0 | I79: 0 | J79: 0 | K79: 0 | L79: 85.683751 | M79: 0 | N79: 0 | O79: =SUM(C79:N79) -> 171.3675
B80: BONTE/$/18,20%/03-10-2021 | C80: 0 | D80: 0 | E80: 0 | F80: 94.957843 | G80: 0 | H80: 0 | I80: 0 | J80: 0 | K80: 0 | L80: 94.957843 | M80: 0 | N80: 0 | O80: =SUM(C80:N80) -> 189.91569
B81: BONTE/$/26%/21-11-2020 | C81: 0 | D81: 0 | E81: 0 | F81: 0 | G81: 0 | H81: 0 | I81: 0 | J81: 0 | K81: 0 | L81: 0 | M81: 0 | N81: 0 | O81: =SUM(C81:N81) -> 0
B82: BONAR/U$S/8,75%/07-05-2024 | C82: 0 | D82: 0 | E82: 0 | F82: 0 | G82: 232.22531 | H82: 0 | I82: 0 | J82: 0 | K82: 0 | L82: 0 | M82: 174.20381 | N82: 0 | O82: =SUM(C82:N82) -> 406.42912
... B118: LETRA INTRANSFERIBLE - BCRA | C118: 106.291 | D118: 39.496581 | E118: 15.016357 | F118: 40.568829 | G118: 0 | H118: 76.086358 | I118: 68.23278 | J118: 38.852615 | K118: 0 | L118: 40.791735 | M118: 0 | N118: 76.578043 | O118: =SUM(C118:N118) -> 501.9143
B119: LETRAS DEL TESORO | C119: =+C120+C121 -> 0 | D119: =+D120+D121 -> 0 | E119: =+E120+E121 -> 0 | F119: =+F120+F121 -> 0 | G119: =+G120+G121 -> 0 | H119: =+H120+H121 -> 0 | I119: =+I120+I121 -> 0 | J119: =+J120+J121 -> 0 | ... N119: =+N120+N121 -> 0 | O119: =SUM(C119:N119) -> 0
B120: . En moneda nacional | C120: 0 | D120: 0 | E120: 0 | F120: 0 | G120: 0 | H120: 0 | I120: 0 | J120: 0 | K120: 0 | L120: 0 | M120: 0 | N120: 0 | O120: =SUM(C120:N120) -> 0
B121: . En moneda extranjera | C121: 0 | D121: 0 | E121: 0 | F121: 0 | G121: 0 | H121: 0 | I121: 0 | J121: 0 | K121: 0 | L121: 0 | M121: 0 | N121: 0 | O121: =SUM(C121:N121) -> 0
B122: OTROS (1) | C122: =+C123+C128 -> 12.092083 | D122: =+D123+D128 -> 0.2674115 | E122: =+E123+E128 -> 0.2865922 | F122: =+F123+F128 -> 10.509074 | G122: =+G123+G128 -> 0.24656359 | H122: =+H123+H128 -> 0.23961429 | I122: =+I123+I128 -> 9.2824211 | J122: =+J123+J128 -> 0.22571568 | ... N122: =+N123+N128 -> 0.19791847 | O122: =SUM(C122:N122) -> 41.82392
B123: . En moneda nacional | C123: =+C124+C126 -> 12.092083 | D123: =+D124+D126 -> 0.2674115 | E123: =+E124+E126 -> 0.2604622 | F123: =+F124+F126 -> 10.509074 | G123: =+G124+G126 -> 0.24656359 | H123: =+H124+H126 -> 0.23961429 | I123: =+I124+I126 -> 9.2824211 | J123: =+J124+J126 -> 0.22571568 | ... N123: =+N124+N126 -> 0.19791847 | O123: =SUM(C123:N123) -> 41.77166
B124: · Ajustable por CER | C124: =+C125 -> 0.2743608 | D124: =+D125 -> 0.2674115 | E124: =+E125 -> 0.2604622 | F124: =+F125 -> 0.25351289 | G124: =+G125 -> 0.24656359 | H124: =+H125 -> 0.23961429 | I124: =+I125 -> 0.23266499 | J124: =+J125 -> 0.22571568 | ... N124: =+N125 -> 0.19791847 | O124: =SUM(C124:N124) -> 2.8336756
B125: · Bonos de consolidación | C125: 0.2743608 | D125: 0.2674115 | E125: 0.2604622 | F125: 0.25351289 | G125: 0.24656359 | H125: 0.23961429 | I125: 0.23266499 | J125: 0.22571568 | K125: 0.21876638 | L125: 0.21181708 | M125: 0.20486777 | N125: 0.19791847 | O125: =SUM(C125:N125) -> 2.8336756
B126: · No ajustable por CER | C126: =+C127 -> 11.817722 | D126: =+D127 -> 0 | E126: =+E127 -> 0 | F126: =+F127 -> 10.255561 | G126: =+G127 -> 0 | H126: =+H127 -> 0 | I126: =+I127 -> 9.0497561 | J126: =+J127 -> 0 | ... N126: =+N127 -> 0 | O126: =SUM(C126:N126) -> 38.937984
B127: · Bonos de consolidación | C127: 11.817722 | D127: 0 | E127: 0 | F127: 10.255561 | G127: 0 | H127: 0 | I127: 9.0497561 | J127: 0 | K127: 0 | L127: 7.814945 | M127: 0 | N127: 0 | O127: =SUM(C127:N127) -> 38.937984
B128: . En moneda extranjera | C128: =+C129 -> 0 | D128: =+D129 -> 0 | E128: =+E129 -> 0.02613 | F128: =+F129 -> 0 | G128: =+G129 -> 0 | H128: =+H129 -> 0 | I128: =+I129 -> 0 | J128: =+J129 -> 0 | ... N128: =+N129 -> 0 | O128: =SUM(C128:N128) -> 0.05226
B129: · Otros | C129: 0 | D129: 0 | E129: 0.02613 | F129: 0 | G129: 0 | H129: 0 | I129: 0 | J129: 0 | K129: 0.02613 | L129: 0 | M129: 0 | N129: 0 | O129: =SUM(C129:N129) -> 0.05226
B131: TOTAL DEUDA DENOMINADA EN PESOS | C131: =+C132+C133 -> 167.14442 | D131: =+D132+D133 -> 90.693514 | E131: =+E132+E133 -> 34.980688 | F131: =+F132+F133 -> 452.66796 | G131: =+G132+G133 -> 44.977154 | H131: =+H132+H133 -> 206.06907 | I131: =+I132+I133 -> 162.79498 | J131: =+J132+J133 -> 6.7098514 | ... N131: =+N132+N133 -> 205.69874 | O131: =SUM(C131:N131) -> 1903.6575
B132: · Deuda ajustable por CER | C132: 38.694218 | D132: 2.9295488 | E132: 30.946276 | F132: 22.754603 | G132: 41.026111 | H132: 202.16064 | I132: 38.588347 | J132: 2.887853 | K132: 31.097105 | L132: 22.648732 | M132: 41.048591 | N132: 202.05477 | O132: =SUM(C132:N132) -> 676.83679
B133: · Deuda no ajustable por CER | C133: 128.4502 | D133: 87.763966 | E133: 4.0344118 | F133: 429.91335 | G133: 3.9510421 | H133: 3.9084336 | I133: 124.20663 | J133: 3.8219984 | K133: 3.7781577 | L133: 429.65938 | M133: 3.6891335 | N133: 3.6439694 | O133: =SUM(C133:N133) -> 1226.8207
B134: TOTAL DEUDA EN MONEDA EXTRANJERA | C134: 996.26972 | D134: 478.28415 | E134: 373.64537 | F134: 738.84313 | G134: 706.6889 | H134: 1580.9044 | I134: 731.02931 | J134: 516.96439 | K134: 354.89062 | L134: 582.64706 | M134: 759.07899 | N134: 1577.0559 | O134: =SUM(C134:N134) -> 9396.302
B136: (1) Incluye bonos de consolidación, amparos y excepciones.

Sheet A.3.6
A1: Indice
B2: =+INDICE!B2 -> MINISTERIO DE ECONOMÍA
B3: =+A.3.5!B3 -> SECRETARÍA DE FINANZAS
B6: PERFIL ANUAL DE VENCIMIENTOS DE CAPITAL E INTERÉS DE LA DEUDA BRUTA DE LA ADMINISTRACIÓN CENTRAL
B7: DEUDA EN SITUACIÓN DE PAGO NORMAL (1)
B9: (En miles de U$S - Tipo de cambio 31/12/2019)
B10: TIPO DE ACREEDOR | C10: 2020 | D10: 2021 | E10: 2022 | F10: 2023 | G10: 2024 | H10: 2025 | I10: 2026 | J10: 2027 | K10: 2028 | L10: 2029 | M10: 2030/2117 (3) | N10: TOTAL
B13: TÍTULOS PÚBLICOS | C13: =+C15+C16 -> 32445397 | D13: =+D15+D16 -> 31093226 | E13: =+E15+E16 -> 27844028 | F13: =+F15+F16 -> 23576025 | G13: =+G15+G16 -> 21077395 | H13: =+H15+H16 -> 24452500 | I13: =+I15+I16 -> 15484563 | J13: =+J15+J16 -> 16039292 | ... N13: =+N15+N16 -> 2.8949663e+08
B14: Como % del total de servicios (2) | C14: =+C13/$N$70 -> 0.075337465 | D14: =+D13/$N$70 -> 0.072197755 | E14: =+E13/$N$70 -> 0.064653191 | F14: =+F13/$N$70 -> 0.054742987 | G14: =+G13/$N$70 -> 0.048941226 | H14: =+H13/$N$70 -> 0.056778142 | I14: =+I13/$N$70 -> 0.035954799 | J14: =+J13/$N$70 -> 0.037242867 | ... N14: =+N13/$N$70 -> 0.6722045
B15: CAPITAL | C15: 20913021 | D15: 22387877 | E15: 20198001 | F15: 17019595 | G15: 15093857 | H15: 18895925 | I15: 10803131 | J15: 12162849 | K15: 8698091.2 | L15: 4289070.4 | M15: 43691393 | N15: =SUM(C15:M15) -> 1.9415281e+08
B16: INTERÉS | C16: 11532376 | D16: 8705349.6 | E16: 7646026.9 | F16: 6556429.8 | G16: 5983538.8 | H16: 5556575.3 | I16: 4681432.7 | J16: 3876443.4 | K16: 3002953.3 | L16: 2677095.7 | M16: 35125598 | N16: =SUM(C16:M16) -> 95343819
B18: LETRAS DEL TESORO | C18: =+C20+C21 -> 23771587 | D18: =+D20+D21 -> 232981.39 | E18: =+E20+E21 -> 211223.48 | F18: =+F20+F21 -> 448025.78 | G18: =+G20+G21 -> 45310.327 | H18: =+H20+H21 -> 0 | I18: =+I20+I21 -> 0 | J18: =+J20+J21 -> 0 | ... N18: =+N20+N21 -> 24709128
B19: Como % del total de servicios (2) | C19: =+C18/$N$70 -> 0.055197076 | D19: =+D18/$N$70 -> 0.00054097742 | E19: =+E18/$N$70 -> 0.00049045606 | F19: =+F18/$N$70 -> 0.0010403055 | G19: =+G18/$N$70 -> 0.00010520954 | H19: =+H18/$N$70 -> 0 | I19: =+I18/$N$70 -> 0 | J19: =+J18/$N$70 -> 0 | ... N19: =+N18/$N$70 -> 0.057374025
B20: CAPITAL | C20: 22985734 | D20: 232981.39 | E20: 211223.48 | F20: 448025.78 | G20: 45310.327 | H20: 0 | I20: 0 | J20: 0 | K20: 0 | L20: 0 | M20: 0 | N20: =SUM(C20:M20) -> 23923275
B21: INTERÉS | C21: 785852.39 | D21: 0 | E21: 0 | F21: 0 | G21: 0 | H21: 0 | I21: 0 | J21: 0 | K21: 0 | L21: 0 | M21: 0 | N21: =SUM(C21:M21) -> 785852.39
B23: LETRAS EN GARANTÍA | C23: =+C25+C26 -> 243892.62 | D23: =+D25+D26 -> 359393.28 | E23: =+E25+E26 -> 365231.28 | F23: =+F25+F26 -> 370856.28 | G23: =+G25+G26 -> 370856.28 | H23: =+H25+H26 -> 370856.28 | I23: =+I25+I26 -> 370856.28 | J23: =+J25+J26 -> 370856.28 | ... N23: =+N25+N26 -> 7368439.4
B24: Como % del total de servicios (2) | C24: =+C23/$N$70 -> 0.00056631305 | D24: =+D23/$N$70 -> 0.0008345029 | E24: =+E23/$N$70 -> 0.0008480586 | F24: =+F23/$N$70 -> 0.00086111972 | G24: =+G23/$N$70 -> 0.00086111972 | H24: =+H23/$N$70 -> 0.00086111972 | I24: =+I23/$N$70 -> 0.00086111972 | J24: =+J23/$N$70 -> 0.00086111972 | ... N24: =+N23/$N$70 -> 0.017109347
B25: CAPITAL | C25: 243892.62 | D25: 359393.28 | E25: 365231.28 | F25: 370856.28 | G25: 370856.28 | H25: 370856.28 | I25: 370856.28 | J25: 370856.28 | K25: 370856.28 | L25: 370856.28 | M25: 3803928.3 | N25: =SUM(C25:M25) -> 7368439.4
B26: INTERÉS | C26: 0 | D26: 0 | E26: 0 | F26: 0 | G26: 0 | H26: 0 | I26: 0 | J26: 0 | K26: 0 | L26: 0 | M26: 0 | N26: =SUM(C26:M26) -> 0
B28: PRÉSTAMOS | C28: =+C30+C31 -> 13006233 | D28: =+D30+D31 -> 8581000.2 | E28: =+E30+E31 -> 21744006 | F28: =+F30+F31 -> 21749086 | G28: =+G30+G31 -> 7475556.6 | H28: =+H30+H31 -> 2520919.3 | I28: =+I30+I31 -> 2262242.6 | J28: =+J30+J31 -> 2242473.8 | ... N28: =+N30+N31 -> 94856218
B29: Como % del total de servicios (2) | C29: =+C28/$N$70 -> 0.030200174 | D29: =+D28/$N$70 -> 0.019924885 | E29: =+E28/$N$70 -> 0.050489081 | F29: =+F28/$N$70 -> 0.050500877 | G29: =+G28/$N$70 -> 0.01735807 | H29: =+H28/$N$70 -> 0.0058535166 | I29: =+I28/$N$70 -> 0.0052528752 | J29: =+J28/$N$70 -> 0.0052069724 | ... N29: =+N28/$N$70 -> 0.22025395
B30: CAPITAL | C30: =+C35+C40+C45+C50+C55+C60 -> 10076545 | D30: =+D35+D40+D45+D50+D55+D60 -> 5986390.4 | E30: =+E35+E40+E45+E50+E55+E60 -> 19460072 | F30: =+F35+F40+F45+F50+F55+F60 -> 20364462 | G30: =+G35+G40+G45+G50+G55+G60 -> 6716596.4 | H30: =+H35+H40+H45+H50+H55+H60 -> 1907798.4 | I30: =+I35+I40+I45+I50+I55+I60 -> 1718727 | J30: =+J35+J40+J45+J50+J55+J60 -> 1764014.1 | ... M30: =+M35+M40+M45+M50+M55+M60 -> 9781531.6 | N30: =SUM(C30:M30) -> 80843847
B31: INTERÉS | C31: =+C36+C41+C46+C51+C56+C61 -> 2929687.6 | D31: =+D36+D41+D46+D51+D56+D61 -> 2594609.9 | E31: =+E36+E41+E46+E51+E56+E61 -> 2283933.6 | F31: =+F36+F41+F46+F51+F56+F61 -> 1384624.4 | G31: =+G36+G41+G46+G51+G56+G61 -> 758960.16 | H31: =+H36+H41+H46+H51+H56+H61 -> 613120.93 | I31: =+I36+I41+I46+I51+I56+I61 -> 543515.61 | J31: =+J36+J41+J46+J51+J56+J61 -> 478459.68 | ... M31: =+M36+M41+M46+M51+M56+M61 -> 1656895 | N31: =SUM(C31:M31) -> 14012371
B34: ORGANISMOS INTERNACIONALES | C34: =+C35+C36 -> 4192467 | D34: =+D35+D36 -> 7855810.5 | E34: =+E35+E36 -> 21083759 | F34: =+F35+F36 -> 21172459 | G34: =+G35+G36 -> 6969177.9 | H34: =+H35+H36 -> 2035840.3 | I34: =+I35+I36 -> 1804372.8 | J34: =+J35+J36 -> 1678924 | ... N34: =+N35+N36 -> 80194335
B35: CAPITAL | C35: 1853550.2 | D35: 5477792.4 | E35: 18987875 | F35: 19950088 | G35: 6352899.1 | H35: 1547273.7 | I35: 1367701.3 | J35: 1288091.5 | K35: 1233722.7 | L35: 1179511.7 | M35: 8762283.2 | N35: =SUM(C35:M35) -> 68000788
B36: INTERÉS | C36: 2338916.7 | D36: 2378018.1 | E36: 2095884.6 | F36: 1222371.7 | G36: 616278.78 | H36: 488566.61 | I36: 436671.54 | J36: 390832.45 | K36: 348149.12 | L36: 305743.5 | M36: 1572113.7 | N36: =SUM(C36:M36) -> 12193547
B39: ORGANISMOS OFICIALES | C39: =+C40+C41 -> 2608600.9 | D39: =+D40+D41 -> 495405.12 | E39: =+E40+E41 -> 454911.53 | F39: =+F40+F41 -> 458949.46 | G39: =+G40+G41 -> 431258.88 | H39: =+H40+H41 -> 412420.47 | I39: =+I40+I41 -> 386522.8 | J39: =+J40+J41 -> 369171.03 | ... N39: =+N40+N41 -> 6537933.3
B40: CAPITAL | C40: 2259827.7 | D40: 338873.12 | E40: 316380.32 | F40: 337669.82 | G40: 327260.49 | H40: 326058.99 | I40: 317483.92 | J40: 317390.71 | K40: 317390.71 | L40: 317390.71 | M40: 222345.78 | N40: =SUM(C40:M40) -> 5398072.3
B41: INTERÉS | C41: 348773.12 | D41: 156532 | E41: 138531.21 | F41: 121279.64 | G41: 103998.38 | H41: 86361.477 | I41: 69038.876 | J41: 51780.328 | K41: 34612.43 | L41: 17264.128 | M41: 11689.4 | N41: =SUM(C41:M41) -> 1139861
B44: PRÉSTAMOS GARANTIZADOS | C44: =+C45+C46 -> 48513.037 | D44: =+D45+D46 -> 31496.423 | E44: =+E45+E46 -> 31496.423 | F44: =+F45+F46 -> 31496.423 | G44: =+G45+G46 -> 31560.598 | H44: =+H45+H46 -> 31496.423 | I44: =+I45+I46 -> 31496.423 | J44: =+J45+J46 -> 156195.91 | ... N44: =+N45+N46 -> 977568.34
B45: CAPITAL | C45: 16812.336 | D45: 0 | E45: 0 | F45: 0 | G45: 0 | H45: 0 | I45: 0 | J45: 126277.96 | K45: 0 | L45: 0 | M45: 497234.75 | N45: =SUM(C45:M45) -> 640325.05
B46: INTERÉS | C46: 31700.701 | D46: 31496.423 | E46: 31496.423 | F46: 31496.423 | G46: 31560.598 | H46: 31496.423 | I46: 31496.423 | J46: 29917.949 | K46: 25246.7 | L46: 25182.525 | M46: 36152.701 | N46: =SUM(C46:M46) -> 337243.29
B49: BANCA COMERCIAL | C49: =+C50+C51 -> 2680721.3 | D49: =+D50+D51 -> 38277.191 | E49: =+E50+E51 -> 37847.19 | F49: =+F50+F51 -> 37309.189 | G49: =+G50+G51 -> 36847.713 | H49: =+H50+H51 -> 34450.679 | I49: =+I50+I51 -> 33808.731 | J49: =+J50+J51 -> 32619.327 | ... N49: =+N50+N51 -> 2937052
B50: CAPITAL | C50: 2539784.6 | D50: 35408.595 | E50: 35419.549 | F50: 35321.816 | G50: 35288.83 | H50: 33317.785 | I50: 33063.482 | J50: 32253.893 | K50: 1988.9729 | L50: 1988.9729 | M50: 1060.7069 | N50: =SUM(C50:M50) -> 2784897.2
B51: INTERÉS | C51: 140936.68 | D51: 2868.5961 | E51: 2427.6409 | F51: 1987.3729 | G51: 1558.8831 | H51: 1132.8945 | I51: 745.24979 | J51: 365.43423 | K51: 78.688196 | L51: 43.924493 | M51: 9.3995404 | N51: =SUM(C51:M51) -> 152154.77
B54: AVALES | C54: =+C55+C56 -> 2163086.1 | D54: =+D55+D56 -> 153266.25 | E54: =+E55+E56 -> 130428.09 | F54: =+F55+F56 -> 43307.996 | G54: =+G55+G56 -> 1147.9456 | H54: =+H55+H56 -> 1147.9456 | I54: =+I55+I56 -> 478.31081 | J54: =+J55+J56 -> 0 | ... N54: =+N55+N56 -> 2492862.7
B55: CAPITAL | C55: 2099289.3 | D55: 133135.01 | E55: 120397.85 | F55: 41382.269 | G55: 1147.9456 | H55: 1147.9456 | I55: 478.31081 | J55: 0 | K55: 0 | L55: 0 | M55: 0 | N55: =SUM(C55:M55) -> 2396978.6
B56: INTERÉS | C56: 63796.889 | D56: 20131.243 | E56: 10030.233 | F56: 1925.7267 | G56: 0 | H56: 0 | I56: 0 | J56: 0 | K56: 0 | L56: 0 | M56: 0 | N56: =SUM(C56:M56) -> 95884.093
B59: PAGARÉS | C59: =+C60+C61 -> 1312844.8 | D59: =+D60+D61 -> 6744.7191 | E59: =+E60+E61 -> 5563.5226 | F59: =+F60+F61 -> 5563.5226 | G59: =+G60+G61 -> 5563.5226 | H59: =+H60+H61 -> 5563.5226 | I59: =+I60+I61 -> 5563.5226 | J59: =+J60+J61 -> 5563.5226 | ... N59: =+N60+N61 -> 1716466.7
B60: CAPITAL | C60: 1307281.3 | D60: 1181.1965 | E60: 0 | F60: 0 | G60: 0 | H60: 0 | I60: 0 | J60: 0 | K60: 0 | L60: 15716.165 | M60: 298607.14 | N60: =SUM(C60:M60) -> 1622785.8
B61: INTERÉS | C61: 5563.5226 | D61: 5563.5226 | E61: 5563.5226 | F61: 5563.5226 | G61: 5563.5226 | H61: 5563.5226 | I61: 5563.5226 | J61: 5563.5226 | K61: 5563.5226 | L61: 6679.3703 | M61: 36929.846 | N61: =SUM(C61:M61) -> 93680.919
B64: ADELANTOS TRANSITORIOS BCRA | C64: =+C66+C67 -> 9395275.1 | D64: =+D66+D67 -> 4841806.5 | E64: =+E66+E67 -> 0 | F64: =+F66+F67 -> 0 | G64: =+G66+G67 -> 0 | H64: =+H66+H67 -> 0 | I64: =+I66+I67 -> 0 | J64: =+J66+J67 -> 0 | ... N64: =+N66+N67 -> 14237082
B65: Como % del total de servicios (2) | C65: =+C64/$N$70 -> 0.021815612 | D65: =+D64/$N$70 -> 0.011242563 | E65: =+E64/$N$70 -> 0 | F65: =+F64/$N$70 -> 0 | G65: =+G64/$N$70 -> 0 | H65: =+H64/$N$70 -> 0 | I65: =+I64/$N$70 -> 0 | J65: =+J64/$N$70 -> 0 | ... N65: =+N64/$N$70 -> 0.033058175
B66: CAPITAL | C66: 9395275.1 | D66: 4841806.5 | E66: 0 | F66: 0 | G66: 0 | H66: 0 | I66: 0 | J66: 0 | K66: 0 | L66: 0 | M66: 0 | N66: =SUM(C66:M66) -> 14237082
B67: INTERÉS | C67: 0 | D67: 0 | E67: 0 | F67: 0 | G67: 0 | H67: 0 | I67: 0 | J67: 0 | K67: 0 | L67: 0 | M67: 0 | N67: =SUM(C67:M67) -> 0
B70: TOTAL | C70: =+C72+C73 -> 78862385 | D70: =+D72+D73 -> 45108408 | E70: =+E72+E73 -> 50164489 | F70: =+F72+F73 -> 46143993 | G70: =+G72+G73 -> 28969119 | H70: =+H72+H73 -> 27344276 | I70: =+I72+I73 -> 18117662 | J70: =+J72+J73 -> 18652622 | ... N70: =+N72+N73 -> 4.306675e+08
B71: Como % del total de servicios (2) | C71: =+C70/$N$70 -> 0.18311664 | D71: =+D70/$N$70 -> 0.10474068 | E71: =+E70/$N$70 -> 0.11648079 | F71: =+F70/$N$70 -> 0.10714529 | G71: =+G70/$N$70 -> 0.067265626 | H71: =+H70/$N$70 -> 0.063492778 | I71: =+I70/$N$70 -> 0.042068794 | J71: =+J70/$N$70 -> 0.043310959 | ... N71: =+N70/$N$70 -> 1
B72: CAPITAL | C72: =+C15+C20+C25+C30+C66 -> 63614469 | D72: =+D15+D20+D25+D30+D66 -> 33808448 | E72: =+E15+E20+E25+E30+E66 -> 40234528 | F72: =+F15+F20+F25+F30+F66 -> 38202939 | G72: =+G15+G20+G25+G30+G66 -> 22226620 | H72: =+H15+H20+H25+H30+H66 -> 21174580 | I72: =+I15+I20+I25+I30+I66 -> 12892714 | J72: =+J15+J20+J25+J30+J66 -> 14297719 | ... M72: =+M15+M20+M25+M30+M66 -> 57276853 | N72: =SUM(C72:M72) -> 3.2052545e+08
B73: INTERÉS | C73: =+C67+C31+C26+C21+C16 -> 15247916 | D73: =+D67+D31+D26+D21+D16 -> 11299959 | E73: =+E67+E31+E26+E21+E16 -> 9929960.5 | F73: =+F67+F31+F26+F21+F16 -> 7941054.2 | G73: =+G67+G31+G26+G21+G16 -> 6742499 | H73: =+H67+H31+H26+H21+H16 -> 6169696.2 | I73: =+I67+I31+I26+I21+I16 -> 5224948.3 | J73: =+J67+J31+J26+J21+J16 -> 4354903 | ... M73: =+M67+M31+M26+M21+M16 -> 36782493 | N73: =SUM(C73:M73) -> 1.1014204e+08
B76: (1) No incluye estimación del pago eventual por los Valores Negociables Vinculadas al PBI.
B77: (2) Como porcentaje del total de los servicios proyectados (capital mas interés) para el período 01/01/2020 - 31/12/2117.
B78: (3) A partir del año 2050 el total de servicios corresponde al Bono del Tesoro Consolidado 2089 y al Bono Internacional U$S 2117.

Sheet A.3.7
A1: Indice
B2: =+INDICE!B2 -> MINISTERIO DE ECONOMÍA
B3: =+A.3.6!B3 -> SECRETARÍA DE FINANZAS
B6: PERFIL ANUAL DE VENCIMIENTOS DE CAPITAL DE LA DEUDA BRUTA DE LA ADMINISTRACIÓN CENTRAL
B8: (En millones de U$S - Stock de deuda y tipo de cambio 31/12/19)
C9: 2020 | D9: 2021 | E9: 2022 | F9: 2023 | G9: 2024 | H9: 2025 | I9: 2026 | J9: 2027 | K9: 2028 | L9: 2029 | M9: 2030 | N9: 2031 | O9: 2032 | P9: 2033 | Q9: 2034 | R9: 2035 | S9: 2036 | T9: 2037 | U9: 2038 | V9: 2039 | W9: 2040 | X9: 2041 | Y9: 2042 | Z9: 2043 | AA9: 2044 | AB9: 2045 | AC9: 2046 | AD9: 2047 | AE9: 2048 | AF9: 2049 | AG9: 2050 | AH9: 2051-2117 (2) | AI9: Total
B11: PERFIL DE VENCIMIENTOS DE LA DEUDA EN SITUACIÓN DE PAGO NORMAL
B13: TOTAL | C13: =+C14+C15 -> 63614.469 | D13: =+D14+D15 -> 33808.448 | E13: =+E14+E15 -> 40234.528 | F13: =+F14+F15 -> 38202.939 | G13: =+G14+G15 -> 22226.62 | H13: =+H14+H15 -> 21174.58 | I13: =+I14+I15 -> 12892.714 | J13: =+J14+J15 -> 14297.719 | ... AH13: =+AH14+AH15 -> 2759.8587 | AI13: =SUM(C13:AH13) -> 320525.45
B14: CORTO PLAZO | C14: 19364.729 | D14: 0 | E14: 0 | F14: 0 | G14: 0 | H14: 0 | I14: 0 | J14: 0 | K14: 0 | L14: 0 | M14: 0 | N14: 0 | O14: 0 | P14: 0 | Q14: 0 | R14: 0 | S14: 0 | T14: 0 | U14: 0 | V14: 0 | W14: 0 | X14: 0 | Y14: 0 | Z14: 0 | AA14: 0 | AB14: 0 | AC14: 0 | AD14: 0 | AE14: 0 | AF14: 0 | AG14: 0 | AH14: 0 | AI14: =SUM(C14:AH14) -> 19364.729
B15: MEDIANO Y LARGO PLAZO | C15: 44249.74 | D15: 33808.448 | E15: 40234.528 | F15: 38202.939 | G15: 22226.62 | H15: 21174.58 | I15: 12892.714 | J15: 14297.719 | K15: 10622.05 | L15: 6174.5342 | M15: 5387.7437 | N15: 5680.7373 | O15: 5057.0403 | P15: 4922.035 | Q15: 2653.0653 | R15: 3495.4007 | S15: 5908.8928 | T15: 4105.1856 | U15: 3758.532 | V15: 1297.9735 | W15: 1041.2926 | X15: 906.33291 | Y15: 892.19905 | Z15: 868.67051 | AA15: 808.43955 | AB15: 807.68881 | AC15: 2854.2748 | AD15: 929.45018 | AE15: 3068.2909 | AF15: 40.713913 | AG15: 33.035027 | AH15: 2759.8587 | AI15: =SUM(C15:AH15) -> 301160.72
B17: PRÉSTAMOS | C17: =+C18+C23+C25+C31+C32+C39 -> 10076.545 | D17: =+D18+D23+D25+D31+D32+D39 -> 5986.3904 | E17: =+E18+E23+E25+E31+E32+E39 -> 19460.072 | F17: =+F18+F23+F25+F31+F32+F39 -> 20364.462 | G17: =+G18+G23+G25+G31+G32+G39 -> 6716.5964 | H17: =+H18+H23+H25+H31+H32+H39 -> 1907.7984 | I17: =+I18+I23+I25+I31+I32+I39 -> 1718.727 | J17: =+J18+J23+J25+J31+J32+J39 -> 1764.0141 | ... AH17: =+AH18+AH23+AH25+AH31+AH32+AH39 -> 1.1758144 | AI17: =SUM(C17:AH17) -> 80843.847
B18: Organismos Internacionales | C18: =SUM(C19:C22) -> 1853.5502 | D18: =SUM(D19:D22) -> 5477.7924 | E18: =SUM(E19:E22) -> 18987.875 | F18: =SUM(F19:F22) -> 19950.088 | G18: =SUM(G19:G22) -> 6352.8991 | H18: =SUM(H19:H22) -> 1547.2737 | I18: =SUM(I19:I22) -> 1367.7013 | J18: =SUM(J19:J22) -> 1288.0915 | ... AH18: =SUM(AH19:AH22) -> 1.1758144 | AI18: =SUM(C18:AH18) -> 68000.788
B19: . BIRF | C19: 451.35564 | D19: 391.28042 | E19: 291.12943 | F19: 264.38689 | G19: 284.91763 | H19: 287.78871 | I19: 320.52219 | J19: 320.56424 | K19: 320.56424 | L19: 320.56424 | M19: 320.56424 | N19: 320.56424 | O19: 320.56424 | P19: 320.56424 | Q19: 320.56424 | R19: 320.56424 | S19: 320.71944 | T19: 287.50088 | U19: 204.19016 | V19: 141.40401 | W19: 112.26384 | X19: 109.9245 | Y19: 109.9245 | Z19: 109.9245 | AA19: 109.9245 | AB19: 110.12243 | AC19: 104.12761 | AD19: 88.590091 | AE19: 68.143688 | AF19: 40.566744 | AG19: 32.887859 | AH19: 1.1758144 | AI19: =SUM(C19:AH19) -> 7127.8496
B20: . BID | C20: 854.09692 | D20: 836.07537 | E20: 772.16482 | F20: 781.25913 | G20: 855.61984 | H20: 821.83522 | I20: 796.60582 | J20: 755.66815 | K20: 755.66815 | L20: 724.51868 | M20: 724.51868 | N20: 708.60695 | O20: 577.1979 | P20: 490.55377 | Q20: 448.33317 | R20: 393.31876 | S20: 359.984 | T20: 312.82817 | U20: 222.53187 | V20: 132.28338 | W20: 101.0697 | X20: 83.950001 | Y20: 77.160307 | Z20: 60.201233 | AA20: 0.94866924 | AB20: 0 | AC20: 0 | AD20: 0 | AE20: 0 | AF20: 0 | AG20: 0 | AH20: 0 | AI20: =SUM(C20:AH20) -> 12646.999
B21: . FMI | C21: 0 | D21: 3669.0093 | E21: 17345.624 | F21: 18395.226 | G21: 4718.6117 | H21: 0 | I21: 0 | J21: 0 | K21: 0 | L21: 0 | M21: 0 | N21: 0 | O21: 0 | P21: 0 | Q21: 0 | R21: 0 | S21: 0 | T21: 0 | U21: 0 | V21: 0 | W21: 0 | X21: 0 | Y21: 0 | Z21: 0 | AA21: 0 | AB21: 0 | AC21: 0 | AD21: 0 | AE21: 0 | AF21: 0 | AG21: 0 | AH21: 0 | AI21: =SUM(C21:AH21) -> 44128.471
B22: . Otros | C22: 548.09768 | D22: 581.42739 | E22: 578.95686 | F22: 509.21568 | G22: 493.74994 | H22: 437.64973 | I22: 250.57328 | J22: 211.85915 | K22: 157.49036 | L22: 134.42876 | M22: 102.00666 | N22: 50.735264 | O22: 21.433437 | P22: 4.435064 | Q22: 4.0736193 | R22: 3.5655094 | S22: 2.8436006 | T22: 2.3030062 | U22: 2.3030062 | V22: 0.32150312 | W22: 0 | X22: 0 | Y22: 0 | Z22: 0 | AA22: 0 | AB22: 0 | AC22: 0 | AD22: 0 | AE22: 0 | AF22: 0 | AG22: 0 | AH22: 0 | AI22: =SUM(C22:AH22) -> 4097.4695
B23: Préstamos Garantizados | C23: =SUM(C24:C24) -> 16.812336 | D23: =SUM(D24:D24) -> 0 | E23: =SUM(E24:E24) -> 0 | F23: =SUM(F24:F24) -> 0 | G23: =SUM(G24:G24) -> 0 | H23: =SUM(H24:H24) -> 0 | I23: =SUM(I24:I24) -> 0 | J23: =SUM(J24:J24) -> 126.27796 | ... AH23: =SUM(AH24:AH24) -> 0 | AI23: =SUM(C23:AH23) -> 640.32505
B24: . En moneda nacional ajustable por CER | C24: 16.812336 | D24: 0 | E24: 0 | F24: 0 | G24: 0 | H24: 0 | I24: 0 | J24: 126.27796 | K24: 0 | L24: 0 | M24: 34.248668 | N24: 462.98608 | O24: 0 | P24: 0 | Q24: 0 | R24: 0 | S24: 0 | T24: 0 | U24: 0 | V24: 0 | W24: 0 | X24: 0 | Y24: 0 | Z24: 0 | AA24: 0 | AB24: 0 | AC24: 0 | AD24: 0 | AE24: 0 | AF24: 0 | AG24: 0 | AH24: 0 | AI24: =SUM(C24:AH24) -> 640.32505
B25: Banca Comercial | C25: =+C26+C29 -> 2539.7846 | D25: =+D26+D29 -> 35.408595 | E25: =+E26+E29 -> 35.419549 | F25: =+F26+F29 -> 35.321816 | G25: =+G26+G29 -> 35.28883 | H25: =+H26+H29 -> 33.317785 | I25: =+I26+I29 -> 33.063482 | J25: =+J26+J29 -> 32.253893 | ... AH25: =+AH26+AH29 -> 0 | AI25: =SUM(C25:AH25) -> 2784.8972
B26: . En moneda nacional | C26: =+C27+C28 -> 2505.3978 | D26: =+D27+D28 -> 0 | E26: =+E27+E28 -> 0 | F26: =+F27+F28 -> 0 | G26: =+G27+G28 -> 0 | H26: =+H27+H28 -> 0 | I26: =+I27+I28 -> 0 | J26: =+J27+J28 -> 0 | ... AH26: =+AH27+AH28 -> 0 | AI26: =SUM(C26:AH26) -> 2505.3978
B27: FUCO | C27: 2003.5061 | D27: 0 | E27: 0 | F27: 0 | G27: 0 | H27: 0 | I27: 0 | J27: 0 | K27: 0 | L27: 0 | M27: 0 | N27: 0 | O27: 0 | P27: 0 | Q27: 0 | R27: 0 | S27: 0 | T27: 0 | U27: 0 | V27: 0 | W27: 0 | X27: 0 | Y27: 0 | Z27: 0 | AA27: 0 | AB27: 0 | AC27: 0 | AD27: 0 | AE27: 0 | AF27: 0 | AG27: 0 | AH27: 0 | AI27: =SUM(C27:AH27) -> 2003.5061
B28: Otros | C28: 501.89164 | D28: 0 | E28: 0 | F28: 0 | G28: 0 | H28: 0 | I28: 0 | J28: 0 | K28: 0 | L28: 0 | M28: 0 | N28: 0 | O28: 0 | P28: 0 | Q28: 0 | R28: 0 | S28: 0 | T28: 0 | U28: 0 | V28: 0 | W28: 0 | X28: 0 | Y28: 0 | Z28: 0 | AA28: 0 | AB28: 0 | AC28: 0 | AD28: 0 | AE28: 0 | AF28: 0 | AG28: 0 | AH28: 0 | AI28: =SUM(C28:AH28) -> 501.89164
B29: . En moneda extranjera | C29: =+C30 -> 34.386816 | D29: =+D30 -> 35.408595 | E29: =+E30 -> 35.419549 | F29: =+F30 -> 35.321816 | G29: =+G30 -> 35.28883 | H29: =+H30 -> 33.317785 | I29: =+I30 -> 33.063482 | J29: =+J30 -> 32.253893 | ... AH29: =+AH30 -> 0 | AI29: =SUM(C29:AH29) -> 279.49942
B30: Otros | C30: 34.386816 | D30: 35.408595 | E30: 35.419549 | F30: 35.321816 | G30: 35.28883 | H30: 33.317785 | I30: 33.063482 | J30: 32.253893 | K30: 1.9889729 | L30: 1.9889729 | M30: 1.0607069 | N30: 0 | O30: 0 | P30: 0 | Q30: 0 | R30: 0 | S30: 0 | T30: 0 | U30: 0 | V30: 0 | W30: 0 | X30: 0 | Y30: 0 | Z30: 0 | AA30: 0 | AB30: 0 | AC30: 0 | AD30: 0 | AE30: 0 | AF30: 0 | AG30: 0 | AH30: 0 | AI30: =SUM(C30:AH30) -> 279.49942
B31: Organismos Oficiales | C31: 2259.8277 | D31: 338.87312 | E31: 316.38032 | F31: 337.66982 | G31: 327.26049 | H31: 326.05899 | I31: 317.48392 | J31: 317.39071 | K31: 317.39071 | L31: 317.39071 | M31: 104.25869 | N31: 36.758693 | O31: 36.758693 | P31: 5.3958587 | Q31: 5.0526518 | R31: 5.0526518 | S31: 5.0270553 | T31: 5.0270553 | U31: 5.0270553 | V31: 4.2280443 | W31: 3.4290332 | X31: 3.429033 | Y31: 1.9228651 | Z31: 0.97839489 | AA31: 0 | AB31: 0 | AC31: 0 | AD31: 0 | AE31: 0 | AF31: 0 | AG31: 0 | AH31: 0 | AI31: =SUM(C31:AH31) -> 5398.0723
B32: Pagarés | C32: =+C33+C35+C37 -> 1307.2813 | D32: =+D33+D35+D37 -> 1.1811965 | E32: =+E33+E35+E37 -> 0 | F32: =+F33+F35+F37 -> 0 | G32: =+G33+G35+G37 -> 0 | H32: =+H33+H35+H37 -> 0 | I32: =+I33+I35+I37 -> 0 | J32: =+J33+J35+J37 -> 0 | ... AH32: =+AH33+AH35+AH37 -> 0 | AI32: =SUM(C32:AH32) -> 1622.7858
B33: . En moneda nacional ajustable por CER | C33: =+C34 -> 0 | D33: =+D34 -> 0 | E33: =+E34 -> 0 | F33: =+F34 -> 0 | G33: =+G34 -> 0 | H33: =+H34 -> 0 | I33: =+I34 -> 0 | J33: =+J34 -> 0 | ... AH33: =+AH34 -> 0 | AI33: =SUM(C33:AH33) -> 314.32331
B34: Pagaré 2038 - B.N.A. | C34: 0 | D34: 0 | E34: 0 | F34: 0 | G34: 0 | H34: 0 | I34: 0 | J34: 0 | K34: 0 | L34: 15.716165 | M34: 31.432331 | N34: 31.432331 | O34: 31.432331 | P34: 31.432331 | Q34: 31.432331 | R34: 31.432331 | S34: 31.432331 | T34: 31.432331 | U34: 47.148496 | V34: 0 | W34: 0 | X34: 0 | Y34: 0 | Z34: 0 | AA34: 0 | AB34: 0 | AC34: 0 | AD34: 0 | AE34: 0 | AF34: 0 | AG34: 0 | AH34: 0 | AI34: =SUM(C34:AH34) -> 314.32331
B35: . En moneda nacional no ajustable por CER | C35: =+C36 -> 1290.5919 | D35: =+D36 -> 0 | E35: =+E36 -> 0 | F35: =+F36 -> 0 | G35: =+G36 -> 0 | H35: =+H36 -> 0 | I35: =+I36 -> 0 | J35: =+J36 -> 0 | ... AH35: =+AH36 -> 0 | AI35: =SUM(C35:AH35) -> 1290.5919
B36: Pagaré CUT | C36: 1290.5919 | D36: 0 | E36: 0 | F36: 0 | G36: 0 | H36: 0 | I36: 0 | J36: 0 | K36: 0 | L36: 0 | M36: 0 | N36: 0 | O36: 0 | P36: 0 | Q36: 0 | R36: 0 | S36: 0 | T36: 0 | U36: 0 | V36: 0 | W36: 0 | X36: 0 | Y36: 0 | Z36: 0 | AA36: 0 | AB36: 0 | AC36: 0 | AD36: 0 | AE36: 0 | AF36: 0 | AG36: 0 | AH36: 0 | AI36: =SUM(C36:AH36) -> 1290.5919
B37: . En moneda extranjera | C37: =+C38 -> 16.689454 | D37: =+D38 -> 1.1811965 | E37: =+E38 -> 0 | F37: =+F38 -> 0 | G37: =+G38 -> 0 | H37: =+H38 -> 0 | I37: =+I38 -> 0 | J37: =+J38 -> 0 | ... AH37: =+AH38 -> 0 | AI37: =SUM(C37:AH37) -> 17.87065
B38: Pagarés CAMMESA | C38: 16.689454 | D38: 1.1811965 | E38: 0 | F38: 0 | G38: 0 | H38: 0 | I38: 0 | J38: 0 | K38: 0 | L38: 0 | M38: 0 | N38: 0 | O38: 0 | P38: 0 | Q38: 0 | R38: 0 | S38: 0 | T38: 0 | U38: 0 | V38: 0 | W38: 0 | X38: 0 | Y38: 0 | Z38: 0 | AA38: 0 | AB38: 0 | AC38: 0 | AD38: 0 | AE38: 0 | AF38: 0 | AG38: 0 | AH38: 0 | AI38: =SUM(C38:AH38) -> 17.87065
B39: Avales | C39: =+C40+C41 -> 2099.2893 | D39: =+D40+D41 -> 133.13501 | E39: =+E40+E41 -> 120.39785 | F39: =+F40+F41 -> 41.382269 | G39: =+G40+G41 -> 1.1479456 | H39: =+H40+H41 -> 1.1479456 | I39: =+I40+I41 -> 0.47831081 | J39: =+J40+J41 -> 0 | ... AH39: =+AH40+AH41 -> 0 | AI39: =SUM(C39:AH39) -> 2396.9786
B40: . En moneda nacional | C40: 733.16417 | D40: 13.226583 | E40: 16.566647 | F40: 9.6624755 | G40: 0 | H40: 0 | I40: 0 | J40: 0 | K40: 0 | L40: 0 | M40: 0 | N40: 0 | O40: 0 | P40: 0 | Q40: 0 | R40: 0 | S40: 0 | T40: 0 | U40: 0 | V40: 0 | W40: 0 | X40: 0 | Y40: 0 | Z40: 0 | AA40: 0 | AB40: 0 | AC40: 0 | AD40: 0 | AE40: 0 | AF40: 0 | AG40: 0 | AH40: 0 | AI40: =SUM(C40:AH40) -> 772.61988
B41: . En moneda extranjera | C41: 1366.1251 | D41: 119.90843 | E41: 103.83121 | F41: 31.719793 | G41: 1.1479456 | H41: 1.1479456 | I41: 0.47831081 | J41: 0 | K41: 0 | L41: 0 | M41: 0 | N41: 0 | O41: 0 | P41: 0 | Q41: 0 | R41: 0 | S41: 0 | T41: 0 | U41: 0 | V41: 0 | W41: 0 | X41: 0 | Y41: 0 | Z41: 0 | AA41: 0 | AB41: 0 | AC41: 0 | AD41: 0 | AE41: 0 | AF41: 0 | AG41: 0 | AH41: 0 | AI41: =SUM(C41:AH41) -> 1624.3587
B43: ADELANTOS TRANSITORIOS BCRA | C43: 9395.2751 | D43: 4841.8065 | E43: 0 | F43: 0 | G43: 0 | H43: 0 | I43: 0 | J43: 0 | K43: 0 | L43: 0 | M43: 0 | N43: 0 | O43: 0 | P43: 0 | Q43: 0 | R43: 0 | S43: 0 | T43: 0 | U43: 0 | V43: 0 | W43: 0 | X43: 0 | Y43: 0 | Z43: 0 | AA43: 0 | AB43: 0 | AC43: 0 | AD43: 0 | AE43: 0 | AF43: 0 | AG43: 0 | AH43: 0 | AI43: =SUM(C43:AH43) -> 14237.082
B45: TÍTULOS PÚBLICOS Y LETRAS DEL TESORO | C45: =+C46+C63+SUM(C80:C129)+C132 -> 44142.648 | D45: =+D46+D63+SUM(D80:D129)+D132 -> 22980.251 | E45: =+E46+E63+SUM(E80:E129)+E132 -> 20774.456 | F45: =+F46+F63+SUM(F80:F129)+F132 -> 17838.478 | G45: =+G46+G63+SUM(G80:G129)+G132 -> 15510.023 | H45: =+H46+H63+SUM(H80:H129)+H132 -> 19266.781 | I45: =+I46+I63+SUM(I80:I129)+I132 -> 11173.987 | J45: =+J46+J63+SUM(J80:J129)+J132 -> 12533.705 | ... AH45: =+AH46+AH63+SUM(AH80:AH129)+AH132 -> 2758.6829 | AI45: =SUM(C45:AH45) -> 225444.52
B46: PAR | C46: =+C47+C50+C57+C60 -> 0 | D46: =+D47+D50+D57+D60 -> 0 | E46: =+E47+E50+E57+E60 -> 0 | F46: =+F47+F50+F57+F60 -> 0 | G46: =+G47+G50+G57+G60 -> 0 | H46: =+H47+H50+H57+H60 -> 0 | I46: =+I47+I50+I57+I60 -> 0 | J46: =+J47+J50+J57+J60 -> 0 | ... AH46: =+AH47+AH50+AH57+AH60 -> 0 | AI46: =SUM(C46:AH46) -> 14726.058
B47: Par/$+CER/T.Fija/2038 | C47: =+C48+C49 -> 0 | D47: =+D48+D49 -> 0 | E47: =+E48+E49 -> 0 | F47: =+F48+F49 -> 0 | G47: =+G48+G49 -> 0 | H47: =+H48+H49 -> 0 | I47: =+I48+I49 -> 0 | J47: =+J48+J49 -> 0 | ... AH47: =+AH48+AH49 -> 0 | AI47: =SUM(C47:AH47) -> 608.44231
B48: Emisión Canje 2005 | C48: 0 | D48: 0 | E48: 0 | F48: 0 | G48: 0 | H48: 0 | I48: 0 | J48: 0 | K48: 0 | L48: 30.301606 | M48: 60.603212 | N48: 60.603212 | O48: 60.603212 | P48: 60.603212 | Q48: 60.603212 | R48: 60.603212 | S48: 60.603212 | T48: 60.603212 | U48: 90.904818 | V48: 0 | W48: 0 | X48: 0 | Y48: 0 | Z48: 0 | AA48: 0 | AB48: 0 | AC48: 0 | AD48: 0 | AE48: 0 | AF48: 0 | AG48: 0 | AH48: 0 | AI48: =SUM(C48:AH48) -> 606.03212
B49: Emisión Canje 2010 | C49: 0 | D49: 0 | E49: 0 | F49: 0 | G49: 0 | H49: 0 | I49: 0 | J49: 0 | K49: 0 | L49: 0.12050955 | M49: 0.24101911 | N49: 0.24101911 | O49: 0.24101911 | P49: 0.24101911 | Q49: 0.24101911 | R49: 0.24101911 | S49: 0.24101911 | T49: 0.24101911 | U49: 0.36152866 | V49: 0 | W49: 0 | X49: 0 | Y49: 0 | Z49: 0 | AA49: 0 | AB49: 0 | AC49: 0 | AD49: 0 | AE49: 0 | AF49: 0 | AG49: 0 | AH49: 0 | AI49: =SUM(C49:AH49) -> 2.4101911
B50: Par/U$S/T.Fija/2038 | C50: =+C51+C54 -> 0 | D50: =+D51+D54 -> 0 | E50: =+E51+E54 -> 0 | F50: =+F51+F54 -> 0 | G50: =+G51+G54 -> 0 | H50: =+H51+H54 -> 0 | I50: =+I51+I54 -> 0 | J50: =+J51+J54 -> 0 | ... AH50: =+AH51+AH54 -> 0 | AI50: =SUM(C50:AH50) -> 6694.6309
B51: Emisión Canje 2005 | C51: =+C52+C53 -> 0 | D51: =+D52+D53 -> 0 | E51: =+E52+E53 -> 0 | F51: =+F52+F53 -> 0 | G51: =+G52+G53 -> 0 | H51: =+H52+H53 -> 0 | I51: =+I52+I53 -> 0 | J51: =+J52+J53 -> 0 | ... AH51: =+AH52+AH53 -> 0 | AI51: =SUM(C51:AH51) -> 6526.252
B52: Leg. Nueva York | C52: 0 | D52: 0 | E52: 0 | F52: 0 | G52: 0 | H52: 0 | I52: 0 | J52: 0 | K52: 0 | L52: 264.83446 | M52: 529.66892 | N52: 529.66892 | O52: 529.66892 | P52: 529.66892 | Q52: 529.66892 | R52: 529.66892 | S52: 529.66892 | T52: 529.66892 | U52: 794.50338 | V52: 0 | W52: 0 | X52: 0 | Y52: 0 | Z52: 0 | AA52: 0 | AB52: 0 | AC52: 0 | AD52: 0 | AE52: 0 | AF52: 0 | AG52: 0 | AH52: 0 | AI52: =SUM(C52:AH52) -> 5296.6892
B53: Leg. Argentina | C53: 0 | D53: 0 | E53: 0 | F53: 0 | G53: 0 | H53: 0 | I53: 0 | J53: 0 | K53: 0 | L53: 61.478142 | M53: 122.95628 | N53: 122.95628 | O53: 122.95628 | P53: 122.95628 | Q53: 122.95628 | R53: 122.95628 | S53: 122.95628 | T53: 122.95628 | U53: 184.43443 | V53: 0 | W53: 0 | X53: 0 | Y53: 0 | Z53: 0 | AA53: 0 | AB53: 0 | AC53: 0 | AD53: 0 | AE53: 0 | AF53: 0 | AG53: 0 | AH53: 0 | AI53: =SUM(C53:AH53) -> 1229.5628
B54: Emisión Canje 2010 | C54: =+C55+C56 -> 0 | D54: =+D55+D56 -> 0 | E54: =+E55+E56 -> 0 | F54: =+F55+F56 -> 0 | G54: =+G55+G56 -> 0 | H54: =+H55+H56 -> 0 | I54: =+I55+I56 -> 0 | J54: =+J55+J56 -> 0 | ... AH54: =+AH55+AH56 -> 0 | AI54: =SUM(C54:AH54) -> 168.37888
B55: Leg. Nueva York | C55: 0 | D55: 0 | E55: 0 | F55: 0 | G55: 0 | H55: 0 | I55: 0 | J55: 0 | K55: 0 | L55: 4.846959 | M55: 9.6939179 | N55: 9.6939179 | O55: 9.6939179 | P55: 9.6939179 | Q55: 9.6939179 | R55: 9.6939179 | S55: 9.6939179 | T55: 9.6939179 | U55: 14.540877 | V55: 0 | W55: 0 | X55: 0 | Y55: 0 | Z55: 0 | AA55: 0 | AB55: 0 | AC55: 0 | AD55: 0 | AE55: 0 | AF55: 0 | AG55: 0 | AH55: 0 | AI55: =SUM(C55:AH55) -> 96.939179
B56: Leg. Argentina | C56: 0 | D56: 0 | E56: 0 | F56: 0 | G56: 0 | H56: 0 | I56: 0 | J56: 0 | K56: 0 | L56: 3.5719851 | M56: 7.1439702 | N56: 7.1439702 | O56: 7.1439702 | P56: 7.1439702 | Q56: 7.1439702 | R56: 7.1439702 | S56: 7.1439702 | T56: 7.1439702 | U56: 10.715955 | V56: 0 | W56: 0 | X56: 0 | Y56: 0 | Z56: 0 | AA56: 0 | AB56: 0 | AC56: 0 | AD56: 0 | AE56: 0 | AF56: 0 | AG56: 0 | AH56: 0 | AI56: =SUM(C56:AH56) -> 71.439702
B57: Par/EUR/T.Fija/2038 | C57: =+C58+C59 -> 0 | D57: =+D58+D59 -> 0 | E57: =+E58+E59 -> 0 | F57: =+F58+F59 -> 0 | G57: =+G58+G59 -> 0 | H57: =+H58+H59 -> 0 | I57: =+I58+I59 -> 0 | J57: =+J58+J59 -> 0 | ... AH57: =+AH58+AH59 -> 0 | AI57: =SUM(C57:AH57) -> 7256.1631
B58: Emisión Canje 2005 | C58: 0 | D58: 0 | E58: 0 | F58: 0 | G58: 0 | H58: 0 | I58: 0 | J58: 0 | K58: 0 | L58: 282.19438 | M58: 564.38876 | N58: 564.38876 | O58: 564.38876 | P58: 564.38876 | Q58: 564.38876 | R58: 564.38876 | S58: 564.38876 | T58: 564.38876 | U58: 846.58315 | V58: 0 | W58: 0 | X58: 0 | Y58: 0 | Z58: 0 | AA58: 0 | AB58: 0 | AC58: 0 | AD58: 0 | AE58: 0 | AF58: 0 | AG58: 0 | AH58: 0 | AI58: =SUM(C58:AH58) -> 5643.8876
B59: Emisión Canje 2010 | C59: 0 | D59: 0 | E59: 0 | F59: 0 | G59: 0 | H59: 0 | I59: 0 | J59: 0 | K59: 0 | L59: 80.613773 | M59: 161.22755 | N59: 161.22755 | O59: 161.22755 | P59: 161.22755 | Q59: 161.22755 | R59: 161.22755 | S59: 161.22755 | T59: 161.22755 | U59: 241.84132 | V59: 0 | W59: 0 | X59: 0 | Y59: 0 | Z59: 0 | AA59: 0 | AB59: 0 | AC59: 0 | AD59: 0 | AE59: 0 | AF59: 0 | AG59: 0 | AH59: 0 | AI59: =SUM(C59:AH59) -> 1612.2755
B60: Par/JPY/T.Fija/2038 | C60: =+C61+C62 -> 0 | D60: =+D61+D62 -> 0 | E60: =+E61+E62 -> 0 | F60: =+F61+F62 -> 0 | G60: =+G61+G62 -> 0 | H60: =+H61+H62 -> 0 | I60: =+I61+I62 -> 0 | J60: =+J61+J62 -> 0 | ... AH60: =+AH61+AH62 -> 0 | AI60: =SUM(C60:AH60) -> 166.82189
B61: Emisión Canje 2005 | C61: 0 | D61: 0 | E61: 0 | F61: 0 | G61: 0 | H61: 0 | I61: 0 | J61: 0 | K61: 0 | L61: 7.9479988 | M61: 15.895998 | N61: 15.895998 | O61: 15.895998 | P61: 15.895998 | Q61: 15.895998 | R61: 15.895998 | S61: 15.895998 | T61: 15.895998 | U61: 23.843996 | V61: 0 | W61: 0 | X61: 0 | Y61: 0 | Z61: 0 | AA61: 0 | AB61: 0 | AC61: 0 | AD61: 0 | AE61: 0 | AF61: 0 | AG61: 0 | AH61: 0 | AI61: =SUM(C61:AH61) -> 158.95998
B62: Emisión Canje 2010 | C62: 0 | D62: 0 | E62: 0 | F62: 0 | G62: 0 | H62: 0 | I62: 0 | J62: 0 | K62: 0 | L62: 0.39309594 | M62: 0.78619188 | N62: 0.78619188 | O62: 0.78619188 | P62: 0.78619188 | Q62: 0.78619188 | R62: 0.78619188 | S62: 0.78619188 | T62: 0.78619188 | U62: 1.1792878 | V62: 0 | W62: 0 | X62: 0 | Y62: 0 | Z62: 0 | AA62: 0 | AB62: 0 | AC62: 0 | AD62: 0 | AE62: 0 | AF62: 0 | AG62: 0 | AH62: 0 | AI62: =SUM(C62:AH62) -> 7.8619188
B63: DESCUENTO | C63: =+C64+C67+C74+C77 -> 0 | D63: =+D64+D67+D74+D77 -> 0 | E63: =+E64+E67+E74+E77 -> 0 | F63: =+F64+F67+F74+F77 -> 0 | G63: =+G64+G67+G74+G77 -> 2226.0445 | H63: =+H64+H67+H74+H77 -> 2226.0445 | I63: =+I64+I67+I74+I77 -> 2226.0445 | J63: =+J64+J67+J74+J77 -> 2226.0445 | ... AH63: =+AH64+AH67+AH74+AH77 -> 0 | AI63: =SUM(C63:AH63) -> 22260.445
B64: Discount/$+CER/5,83%/2033 | C64: =+C65+C66 -> 0 | D64: =+D65+D66 -> 0 | E64: =+E65+E66 -> 0 | F64: =+F65+F66 -> 0 | G64: =+G65+G66 -> 287.60208 | H64: =+H65+H66 -> 287.60208 | I64: =+I65+I66 -> 287.60208 | J64: =+J65+J66 -> 287.60208 | ... AH64: =+AH65+AH66 -> 0 | AI64: =SUM(C64:AH64) -> 2876.0208
B65: Emisión Canje 2005 | C65: 0 | D65: 0 | E65: 0 | F65: 0 | G65: 284.18596 | H65: 284.18596 | I65: 284.18596 | J65: 284.18596 | K65: 284.18596 | L65: 284.18596 | M65: 284.18596 | N65: 284.18596 | O65: 284.18596 | P65: 284.18596 | Q65: 0 | R65: 0 | S65: 0 | T65: 0 | U65: 0 | V65: 0 | W65: 0 | X65: 0 | Y65: 0 | Z65: 0 | AA65: 0 | AB65: 0 | AC65: 0 | AD65: 0 | AE65: 0 | AF65: 0 | AG65: 0 | AH65: 0 | AI65: =SUM(C65:AH65) -> 2841.8596
B66: Emisión Canje 2010 | C66: 0 | D66: 0 | E66: 0 | F66: 0 | G66: 3.4161257 | H66: 3.4161257 | I66: 3.4161257 | J66: 3.4161257 | K66: 3.4161257 | L66: 3.4161257 | M66: 3.4161257 | N66: 3.4161257 | O66: 3.4161257 | P66: 3.4161257 | Q66: 0 | R66: 0 | S66: 0 | T66: 0 | U66: 0 | V66: 0 | W66: 0 | X66: 0 | Y66: 0 | Z66: 0 | AA66: 0 | AB66: 0 | AC66: 0 | AD66: 0 | AE66: 0 | AF66: 0 | AG66: 0 | AH66: 0 | AI66: =SUM(C66:AH66) -> 34.161257
B67: Discount/U$S/8,28%/2033 | C67: =+C68+C71 -> 0 | D67: =+D68+D71 -> 0 | E67: =+E68+E71 -> 0 | F67: =+F68+F71 -> 0 | G67: =+G68+G71 -> 1281.9037 | H67: =+H68+H71 -> 1281.9037 | I67: =+I68+I71 -> 1281.9037 | J67: =+J68+J71 -> 1281.9037 | ... AH67: =+AH68+AH71 -> 0 | AI67: =SUM(C67:AH67) -> 12819.037
B68: Emisión Canje 2005 | C68: =+C69+C70 -> 0 | D68: =+D69+D70 -> 0 | E68: =+E69+E70 -> 0 | F68: =+F69+F70 -> 0 | G68: =+G69+G70 -> 1133.0953 | H68: =+H69+H70 -> 1133.0953 | I68: =+I69+I70 -> 1133.0953 | J68: =+J69+J70 -> 1133.0953 | ... AH68: =+AH69+AH70 -> 0 | AI68: =SUM(C68:AH68) -> 11330.953
B69: Leg. Nueva York | C69: 0 | D69: 0 | E69: 0 | F69: 0 | G69: 426.15424 | H69: 426.15424 | I69: 426.15424 | J69: 426.15424 | K69: 426.15424 | L69: 426.15424 | M69: 426.15424 | N69: 426.15424 | O69: 426.15424 | P69: 426.15424 | Q69: 0 | R69: 0 | S69: 0 | T69: 0 | U69: 0 | V69: 0 | W69: 0 | X69: 0 | Y69: 0 | Z69: 0 | AA69: 0 | AB69: 0 | AC69: 0 | AD69: 0 | AE69: 0 | AF69: 0 | AG69: 0 | AH69: 0 | AI69: =SUM(C69:AH69) -> 4261.5424
B70: Leg. Argentina | C70: 0 | D70: 0 | E70: 0 | F70: 0 | G70: 706.9411 | H70: 706.9411 | I70: 706.9411 | J70: 706.9411 | K70: 706.9411 | L70: 706.9411 | M70: 706.9411 | N70: 706.9411 | O70: 706.9411 | P70: 706.9411 | Q70: 0 | R70: 0 | S70: 0 | T70: 0 | U70: 0 | V70: 0 | W70: 0 | X70: 0 | Y70: 0 | Z70: 0 | AA70: 0 | AB70: 0 | AC70: 0 | AD70: 0 | AE70: 0 | AF70: 0 | AG70: 0 | AH70: 0 | AI70: =SUM(C70:AH70) -> 7069.411
B71: Emisión Canje 2010 | C71: =+C72+C73 -> 0 | D71: =+D72+D73 -> 0 | E71: =+E72+E73 -> 0 | F71: =+F72+F73 -> 0 | G71: =+G72+G73 -> 148.80835 | H71: =+H72+H73 -> 148.80835 | I71: =+I72+I73 -> 148.80835 | J71: =+J72+J73 -> 148.80835 | ... AH71: =+AH72+AH73 -> 0 | AI71: =SUM(C71:AH71) -> 1488.0835
B72: Leg. Nueva York | C72: 0 | D72: 0 | E72: 0 | F72: 0 | G72: 130.37494 | H72: 130.37494 | I72: 130.37494 | J72: 130.37494 | K72: 130.37494 | L72: 130.37494 | M72: 130.37494 | N72: 130.37494 | O72: 130.37494 | P72: 130.37494 | Q72: 0 | R72: 0 | S72: 0 | T72: 0 | U72: 0 | V72: 0 | W72: 0 | X72: 0 | Y72: 0 | Z72: 0 | AA72: 0 | AB72: 0 | AC72: 0 | AD72: 0 | AE72: 0 | AF72: 0 | AG72: 0 | AH72: 0 | AI72: =SUM(C72:AH72) -> 1303.7494
B73: Leg. Argentina | C73: 0 | D73: 0 | E73: 0 | F73: 0 | G73: 18.433417 | H73: 18.433417 | I73: 18.433417 | J73: 18.433417 | K73: 18.433417 | L73: 18.433417 | M73: 18.433417 | N73: 18.433417 | O73: 18.433417 | P73: 18.433417 | Q73: 0 | R73: 0 | S73: 0 | T73: 0 | U73: 0 | V73: 0 | W73: 0 | X73: 0 | Y73: 0 | Z73: 0 | AA73: 0 | AB73: 0 | AC73: 0 | AD73: 0 | AE73: 0 | AF73: 0 | AG73: 0 | AH73: 0 | AI73: =SUM(C73:AH73) -> 184.33417
B74: Discount/EUR/7,82%/2033 | C74: =+C75+C76 -> 0 | D74: =+D75+D76 -> 0 | E74: =+E75+E76 -> 0 | F74: =+F75+F76 -> 0 | G74: =+G75+G76 -> 647.49288 | H74: =+H75+H76 -> 647.49288 | I74: =+I75+I76 -> 647.49288 | J74: =+J75+J76 -> 647.49288 | ... AH74: =+AH75+AH76 -> 0 | AI74: =SUM(C74:AH74) -> 6474.9288
B75: Emisión Canje 2005 | C75: 0 | D75: 0 | E75: 0 | F75: 0 | G75: 349.15498 | H75: 349.15498 | I75: 349.15498 | J75: 349.15498 | K75: 349.15498 | L75: 349.15498 | M75: 349.15498 | N75: 349.15498 | O75: 349.15498 | P75: 349.15498 | Q75: 0 | R75: 0 | S75: 0 | T75: 0 | U75: 0 | V75: 0 | W75: 0 | X75: 0 | Y75: 0 | Z75: 0 | AA75: 0 | AB75: 0 | AC75: 0 | AD75: 0 | AE75: 0 | AF75: 0 | AG75: 0 | AH75: 0 | AI75: =SUM(C75:AH75) -> 3491.5498
B76: Emisión Canje 2010 | C76: 0 | D76: 0 | E76: 0 | F76: 0 | G76: 298.3379 | H76: 298.3379 | I76: 298.3379 | J76: 298.3379 | K76: 298.3379 | L76: 298.3379 | M76: 298.3379 | N76: 298.3379 | O76: 298.3379 | P76: 298.3379 | Q76: 0 | R76: 0 | S76: 0 | T76: 0 | U76: 0 | V76: 0 | W76: 0 | X76: 0 | Y76: 0 | Z76: 0 | AA76: 0 | AB76: 0 | AC76: 0 | AD76: 0 | AE76: 0 | AF76: 0 | AG76: 0 | AH76: 0 | AI76: =SUM(C76:AH76) -> 2983.379
B77: Discount/JPY/4,33%/2033 | C77: =+C78+C79 -> 0 | D77: =+D78+D79 -> 0 | E77: =+E78+E79 -> 0 | F77: =+F78+F79 -> 0 | G77: =+G78+G79 -> 9.0457894 | H77: =+H78+H79 -> 9.0457894 | I77: =+I78+I79 -> 9.0457894 | J77: =+J78+J79 -> 9.0457894 | ... AH77: =+AH78+AH79 -> 0 | AI77: =SUM(C77:AH77) -> 90.457894
B78: Emisión Canje 2005 | C78: 0 | D78: 0 | E78: 0 | F78: 0 | G78: 6.2412868 | H78: 6.2412868 | I78: 6.2412868 | J78: 6.2412868 | K78: 6.2412868 | L78: 6.2412868 | M78: 6.2412868 | N78: 6.2412868 | O78: 6.2412868 | P78: 6.2412868 | Q78: 0 | R78: 0 | S78: 0 | T78: 0 | U78: 0 | V78: 0 | W78: 0 | X78: 0 | Y78: 0 | Z78: 0 | AA78: 0 | AB78: 0 | AC78: 0 | AD78: 0 | AE78: 0 | AF78: 0 | AG78: 0 | AH78: 0 | AI78: =SUM(C78:AH78) -> 62.412868
